Workbook

Sheet Config
A1: Config — cost model & capital assumptions
A2: Edit BLUE / yellow-filled cells only. Every other sheet reads from here.
A3: CAPITAL & PERIOD
A4: Deployed capital (₹) | B4: 1000000 | C4: MTF capital base. Sizing is capital/4 if n<=4 else capital/n.
A5: Tracking start date | B5: 46235 | C5: Day 1 of the Daily PnL calendar. Change it and every dated sheet re-bases.
A6: Trading days per year | B6: 252 | C6: Annualisation factor for Sharpe.
A7: Risk-free rate (annual) | B7: 0.065 | C7: Sharpe numerator.
A8: MTF funded fraction of position | B8: 0.75 | C8: Portion the broker funds and charges interest on. 0.75 = you post 25% margin.
A10: COST MODEL — per product
A11: Seeded with typical Indian equity rates. VERIFY EVERY NUMBER against a real Dhan contract note before trusting the net column — statutory rates change and broker plans differ.
A12: Product | B12: Brokerage % (per order) | C12: Brokerage cap (₹/order) | D12: STT % on buy | E12: STT % on sell | F12: Exch txn % (per side) | G12: SEBI % (per side) | H12: Stamp duty % (buy side) | I12: GST % on charges | J12: DP charge (₹ per sell) | K12: MTF interest (% p.a.)
A13: MTF | B13: 0.0003 | C13: 20 | D13: 0.001 | E13: 0.001 | F13: 2.97e-05 | G13: 1e-06 | H13: 0.00015 | I13: 0.18 | J13: 15.34 | K13: 0.15
A14: CNC | B14: 0 | C14: 0 | D14: 0.001 | E14: 0.001 | F14: 2.97e-05 | G14: 1e-06 | H14: 0.00015 | I14: 0.18 | J14: 15.34 | K14: 0
A15: INTRADAY | B15: 0.0003 | C15: 20 | D15: 0 | E15: 0.00025 | F15: 2.97e-05 | G15: 1e-06 | H15: 3e-05 | I15: 0.18 | J15: 0 | K15: 0
A17: ASSUMPTIONS BAKED INTO THE COST FORMULAS
A18: 1. Brokerage = MIN(cap, pct x order value), charged on BOTH entry and exit orders. Set cap huge if your plan is pure-percentage.
A19: 2. STT on delivery (MTF/CNC) hits both legs; on INTRADAY it is sell-side only. A short's 'sell' is its ENTRY — the formula handles that.
A20: 3. Stamp duty is buy-side only. For a short, the buy is the COVER.
A21: 4. GST applies to brokerage + exchange txn + SEBI fees. Not to STT or stamp duty.
A22: 5. MTF interest = rate/365 x holding days x entry value x funded fraction (B8). Real MTF interest varies by scrip margin, so this is an approximation.
A23: 6. DP/demat charge is added once per closed trade on delivery products; ₹0 on INTRADAY, so short legs are unaffected.
A24: 7. Slippage is NOT a modelled cost — it is measured directly as (fill price vs 15:20 reference price) in the Trade Log.
A26: HOW TO USE THE TRADE LOG
A27: Type only into BLUE columns: Trade ID, Signal Date, Symbol, Leg, Product, Ref Price, Entry Date, Entry Price, Qty, Exit Date, Exit Stage, Exit Price, Last Price, Broker Actual Net, Notes.
A28: Everything else is a formula. Do not overwrite it.
A29: ONE ROW PER LEG. A long that gets shorted on exit is two rows. Use the same Trade ID stem with -L and -S suffixes — the Signal ID column strips the suffix and pairs them automatically.
... A33: Grey columns at the far right are internal cost-lookup helpers. Ignore them, don't delete them.

Sheet Summary
A1: Key P&L statistics — gross and net
A2: Fully derived from the Trade Log and Daily PnL. Nothing on this sheet is typed by hand.
A3: PERIOD & CAPITAL
A4: Deployed capital | B4: =Config!$B$4 -> 1000000
A5: First entry date | B5: =IFERROR(MIN('Trade Log'!$H$4:$H$503),"") -> 46251
A6: Last exit date | B6: =IFERROR(MAX('Trade Log'!$L$4:$L$503),"") -> 46252
A7: Calendar days elapsed | B7: =IF(OR($B$5="",$B$6=""),"",$B$6-$B$5+1) -> 2
A8: Active trading days | B8: =COUNTIFS('Daily PnL'!$C$4:$C$403,">0") -> 1 | G8: Days on which at least one leg closed.
A10: HEADLINE P&L
A11: Gross P&L | B11: =SUM('Trade Log'!$Q$4:$Q$503) -> 24775.5
A12: Total costs | B12: =SUM('Trade Log'!$Y$4:$Y$503) -> 856.94781
A13: Net P&L | B13: =SUM('Trade Log'!$Z$4:$Z$503) -> 23918.552 | G13: The anchor number for the whole workbook.
A14: Gross return on capital | B14: =IF(Config!$B$4=0,"",$B$11/Config!$B$4) -> 0.0247755
A15: Net return on capital | B15: =IF(Config!$B$4=0,"",$B$13/Config!$B$4) -> 0.023918552
A16: Cost drag (% of gross) | B16: =IF($B$11=0,"",$B$12/$B$11) -> 0.034588517 | G16: How much of the gross edge the cost model eats.
A17: Total turnover (both sides) | B17: =SUM('Trade Log'!$K$4:$K$503)+SUM('Trade Log'!$O$4:$O$503) -> 1052896.5
A18: Costs as bp of turnover | B18: =IF($B$17=0,"",$B$12/$B$17*10000) -> 8.1389558 | G18: Compare against your ~25bp/side assumption.
A19: Annualised net return (CAGR-style) | B19: =IF(OR($B$7="",$B$7<=0,Config!$B$4=0),"",$B$13/Config!$B$4*365/$B$7) -> 4.3651358 | G19: Simple scaling, not compounded. Meaningless until you have a few months of data.
A21: SPLIT BY LEG
B22: Gross P&L | C22: Total Costs | D22: Net P&L | E22: Legs | F22: Net / Leg | G22: Win Rate
A23: LONG | B23: =SUMIF('Trade Log'!$E$4:$E$503,$A23,'Trade Log'!$Q$4:$Q$503) -> 19546.5 | C23: =SUMIF('Trade Log'!$E$4:$E$503,$A23,'Trade Log'!$Y$4:$Y$503) -> 715.13719 | D23: =SUMIF('Trade Log'!$E$4:$E$503,$A23,'Trade Log'!$Z$4:$Z$503) -> 18831.363 | E23: =COUNTIFS('Trade Log'!$E$4:$E$503,$A23,'Trade Log'!$Z$4:$Z$503,"<>") -> 1 | F23: =IF($E23=0,"",$D23/$E23) -> 18831.363 | G23: =IF($E23=0,"",COUNTIFS('Trade Log'!$E$4:$E$503,$A23,'Trade Log'!$Z$4:$Z$503,">0")/$E23) -> 1
A24: SHORT | B24: =SUMIF('Trade Log'!$E$4:$E$503,$A24,'Trade Log'!$Q$4:$Q$503) -> 5229 | C24: =SUMIF('Trade Log'!$E$4:$E$503,$A24,'Trade Log'!$Y$4:$Y$503) -> 141.81062 | D24: =SUMIF('Trade Log'!$E$4:$E$503,$A24,'Trade Log'!$Z$4:$Z$503) -> 5087.1894 | E24: =COUNTIFS('Trade Log'!$E$4:$E$503,$A24,'Trade Log'!$Z$4:$Z$503,"<>") -> 1 | F24: =IF($E24=0,"",$D24/$E24) -> 5087.1894 | G24: =IF($E24=0,"",COUNTIFS('Trade Log'!$E$4:$E$503,$A24,'Trade Log'!$Z$4:$Z$503,">0")/$E24) -> 1
A25: TOTAL | B25: =SUM(B23:B24) -> 24775.5 | C25: =SUM(C23:C24) -> 856.94781 | D25: =SUM(D23:D24) -> 23918.552 | E25: =SUM(E23:E24) -> 2 | F25: =IF($E$25=0,"",$D$25/$E$25) -> 11959.276
A26: If the SHORT row is net-negative, the short-on-exit overlay is not paying for itself once real fills and INTRADAY costs are applied.
A28: FULL-CYCLE (SIGNAL-LEVEL) RESULTS
A29: One signal = the long plus its paired short overlay leg, matched on Signal ID. This is the number that actually reflects a day's decision.
A30: Signals completed | B30: =COUNT('Trade Log'!$AF$4:$AF$503) -> 1
A31: Total cycle net P&L | B31: =SUM('Trade Log'!$AF$4:$AF$503) -> 23918.552
A32: Average net per signal | B32: =IFERROR($B$31/$B$30,"") -> 23918.552
A33: Cycle win rate | B33: =IFERROR(COUNTIF('Trade Log'!$AF$4:$AF$503,">0")/$B$30,"") -> 1
A34: Best signal | B34: =IFERROR(MAX('Trade Log'!$AF$4:$AF$503),"") -> 23918.552
A35: Worst signal | B35: =IFERROR(MIN('Trade Log'!$AF$4:$AF$503),"") -> 23918.552
A36: Cycle profit factor | B36: =IFERROR(SUMIF('Trade Log'!$AF$4:$AF$503,">0")/ABS(SUMIF('Trade Log'!$AF$4:$AF$503,"<0")),"")
A38: COST BREAKDOWN
A39: Component | B39: Total (₹) | C39: bp of Turnover | D39: % of All Costs
A40: Brokerage | B40: =SUM('Trade Log'!$S$4:$S$503) -> 80 | C40: =IF($B$17=0,"",$B40/$B$17*10000) -> 0.75980878 | D40: =IF($B$12=0,"",$B40/$B$12) -> 0.093354576
A41: STT | B41: =SUM('Trade Log'!$T$4:$T$503) -> 586.644 | C41: =IF($B$17=0,"",$B41/$B$17*10000) -> 5.5717157 | D41: =IF($B$12=0,"",$B41/$B$12) -> 0.68457378
A42: Exchange txn | B42: =SUM('Trade Log'!$U$4:$U$503) -> 31.271026 | C42: =IF($B$17=0,"",$B42/$B$17*10000) -> 0.297 | D42: =IF($B$12=0,"",$B42/$B$12) -> 0.036491167
A43: SEBI + Stamp + DP | B43: =SUM('Trade Log'!$V$4:$V$503) -> 61.799292 | C43: =IF($B$17=0,"",$B43/$B$17*10000) -> 0.58694555 | D43: =IF($B$12=0,"",$B43/$B$12) -> 0.072115584
A44: GST | B44: =SUM('Trade Log'!$W$4:$W$503) -> 20.218306 | C44: =IF($B$17=0,"",$B44/$B$17*10000) -> 0.19202558 | D44: =IF($B$12=0,"",$B44/$B$12) -> 0.023593392
A45: MTF interest | B45: =SUM('Trade Log'!$X$4:$X$503) -> 77.015188 | C45: =IF($B$17=0,"",$B45/$B$17*10000) -> 0.7314602 | D45: =IF($B$12=0,"",$B45/$B$12) -> 0.089871504
A46: TOTAL | B46: =SUM(B40:B45) -> 856.94781 | C46: =SUM(C40:C45) -> 8.1389558 | D46: =SUM(D40:D45) -> 1
A47: MTF interest is the one line that scales with holding time rather than turnover — watch it if longs start surviving past 11:59 more often.
A49: TRADE STATISTICS (per leg, net of costs)
A50: Legs entered | B50: =COUNTA('Trade Log'!$D$4:$D$503) -> 2
A51: Legs closed | B51: =COUNT('Trade Log'!$Z$4:$Z$503) -> 2
A52: Legs still open | B52: =IF(OR($B$50="",$B$51=""),"",$B$50-$B$51) -> 0
A53: Gross win rate | B53: =IFERROR(COUNTIF('Trade Log'!$Q$4:$Q$503,">0")/COUNT('Trade Log'!$Q$4:$Q$503),"") -> 1
A54: Net win rate | B54: =IFERROR(COUNTIF('Trade Log'!$Z$4:$Z$503,">0")/COUNT('Trade Log'!$Z$4:$Z$503),"") -> 1 | G54: The gap vs gross is trades that costs flipped from winners into losers.
A55: Average net win | B55: =IFERROR(AVERAGEIF('Trade Log'!$Z$4:$Z$503,">0"),"") -> 11959.276
A56: Average net loss | B56: =IFERROR(AVERAGEIF('Trade Log'!$Z$4:$Z$503,"<0"),"")
A57: Payoff ratio (win/loss) | B57: =IFERROR($B$55/ABS($B$56),"")
A58: Expectancy per leg (net) | B58: =IFERROR($B$13/$B$51,"") -> 11959.276
A59: Profit factor (net) | B59: =IFERROR(SUMIF('Trade Log'!$Z$4:$Z$503,">0")/ABS(SUMIF('Trade Log'!$Z$4:$Z$503,"<0")),"")
A60: Best leg (net) | B60: =IFERROR(MAX('Trade Log'!$Z$4:$Z$503),"") -> 18831.363
A61: Worst leg (net) | B61: =IFERROR(MIN('Trade Log'!$Z$4:$Z$503),"") -> 5087.1894
A62: Average holding days | B62: =IFERROR(AVERAGE('Trade Log'!$P$4:$P$503),"") -> 0.5
A63: Average leg size (₹) | B63: =IFERROR(AVERAGE('Trade Log'!$K$4:$K$503),"") -> 259644.75
A64: Legs per active day | B64: =IFERROR($B$51/$B$8,"") -> 2
A66: DAILY & RISK STATISTICS
A67: Average daily net P&L | B67: =IFERROR(AVERAGE('Daily PnL'!$H$4:$H$403),"") -> 23918.552 | G67: Active days only.
A68: Daily net P&L std dev | B68: =IFERROR(STDEV('Daily PnL'!$H$4:$H$403),"")
A69: Average daily return | B69: =IFERROR(AVERAGE('Daily PnL'!$O$4:$O$403),"") -> 0.023918552
A70: Daily return std dev | B70: =IFERROR(STDEV('Daily PnL'!$O$4:$O$403),"")
A71: Sharpe ratio (annualised, net) | B71: =IFERROR(($B$69-Config!$B$7/Config!$B$6)/$B$70*SQRT(Config!$B$6),"") | G71: Active days only, so it is not flattered by flat days.
A72: Sortino ratio (annualised) | B72: ='Distribution & Risk'!$B$24
A73: Best day (net) | B73: =IFERROR(MAX('Daily PnL'!$H$4:$H$403),"") -> 23918.552
A74: Worst day (net) | B74: =IFERROR(MIN('Daily PnL'!$H$4:$H$403),"") -> 23918.552
A75: % profitable days | B75: =IFERROR(COUNTIF('Daily PnL'!$H$4:$H$403,">0")/COUNT('Daily PnL'!$H$4:$H$403),"") -> 1
A76: Max consecutive winning days | B76: =IFERROR(MAX('Daily PnL'!$S$4:$S$403),"") -> 1
A77: Max consecutive losing days | B77: =IFERROR(MAX('Daily PnL'!$T$4:$T$403),"") -> 0
A78: Max drawdown (₹) | B78: =IFERROR(MIN('Daily PnL'!$L$4:$L$403),"") -> 0
A79: Max drawdown (%) | B79: =IFERROR(MIN('Daily PnL'!$M$4:$M$403),"") -> 0
A80: Net P&L / max drawdown | B80: =IFERROR($B$13/ABS($B$78),"")
A81: Current drawdown (%) | B81: =IFERROR(INDEX('Daily PnL'!$M$4:$M$403,MATCH($B$6,'Daily PnL'!$A$4:$A$403,0)),"") -> 0
A82: Peak capital deployed | B82: =IFERROR(MAX('Daily PnL'!$N$4:$N$403),"") -> 269418 | G82: Largest single-day notional entered — sanity-check against your MTF limit.
A84: EXIT-STAGE ATTRIBUTION
A85: Exit Stage | B85: Legs | C85: Gross P&L | D85: Net P&L | E85: Net / Leg | F85: % of Net P&L | G85: Win Rate
A86: TARGET_17 | B86: =COUNTIF('Trade Log'!$M$4:$M$503,$A86) -> 0 | C86: =SUMIF('Trade Log'!$M$4:$M$503,$A86,'Trade Log'!$Q$4:$Q$503) -> 0 | D86: =SUMIF('Trade Log'!$M$4:$M$503,$A86,'Trade Log'!$Z$4:$Z$503) -> 0 | E86: =IF($B86=0,"",$D86/$B86) | F86: =IF($B$13=0,"",$D86/$B$13) -> 0 | G86: =IF($B86=0,"",COUNTIFS('Trade Log'!$M$4:$M$503,$A86,'Trade Log'!$Z$4:$Z$503,">0")/$B86)
A87: EXIT_925 | B87: =COUNTIF('Trade Log'!$M$4:$M$503,$A87) -> 1 | C87: =SUMIF('Trade Log'!$M$4:$M$503,$A87,'Trade Log'!$Q$4:$Q$503) -> 19546.5 | D87: =SUMIF('Trade Log'!$M$4:$M$503,$A87,'Trade Log'!$Z$4:$Z$503) -> 18831.363 | E87: =IF($B87=0,"",$D87/$B87) -> 18831.363 | F87: =IF($B$13=0,"",$D87/$B$13) -> 0.78731199 | G87: =IF($B87=0,"",COUNTIFS('Trade Log'!$M$4:$M$503,$A87,'Trade Log'!$Z$4:$Z$503,">0")/$B87) -> 1
A88: PARTIAL_925_NODATA | B88: =COUNTIF('Trade Log'!$M$4:$M$503,$A88) -> 0 | C88: =SUMIF('Trade Log'!$M$4:$M$503,$A88,'Trade Log'!$Q$4:$Q$503) -> 0 | D88: =SUMIF('Trade Log'!$M$4:$M$503,$A88,'Trade Log'!$Z$4:$Z$503) -> 0 | E88: =IF($B88=0,"",$D88/$B88) | F88: =IF($B$13=0,"",$D88/$B$13) -> 0 | G88: =IF($B88=0,"",COUNTIFS('Trade Log'!$M$4:$M$503,$A88,'Trade Log'!$Z$4:$Z$503,">0")/$B88)
A89: FORCE_1159 | B89: =COUNTIF('Trade Log'!$M$4:$M$503,$A89) -> 0 | C89: =SUMIF('Trade Log'!$M$4:$M$503,$A89,'Trade Log'!$Q$4:$Q$503) -> 0 | D89: =SUMIF('Trade Log'!$M$4:$M$503,$A89,'Trade Log'!$Z$4:$Z$503) -> 0 | E89: =IF($B89=0,"",$D89/$B89) | F89: =IF($B$13=0,"",$D89/$B$13) -> 0 | G89: =IF($B89=0,"",COUNTIFS('Trade Log'!$M$4:$M$503,$A89,'Trade Log'!$Z$4:$Z$503,">0")/$B89)
A90: COVER_TARGET_5 | B90: =COUNTIF('Trade Log'!$M$4:$M$503,$A90) -> 0 | C90: =SUMIF('Trade Log'!$M$4:$M$503,$A90,'Trade Log'!$Q$4:$Q$503) -> 0 | D90: =SUMIF('Trade Log'!$M$4:$M$503,$A90,'Trade Log'!$Z$4:$Z$503) -> 0 | E90: =IF($B90=0,"",$D90/$B90) | F90: =IF($B$13=0,"",$D90/$B$13) -> 0 | G90: =IF($B90=0,"",COUNTIFS('Trade Log'!$M$4:$M$503,$A90,'Trade Log'!$Z$4:$Z$503,">0")/$B90)
A91: UC_STOP | B91: =COUNTIF('Trade Log'!$M$4:$M$503,$A91) -> 0 | C91: =SUMIF('Trade Log'!$M$4:$M$503,$A91,'Trade Log'!$Q$4:$Q$503) -> 0 | D91: =SUMIF('Trade Log'!$M$4:$M$503,$A91,'Trade Log'!$Z$4:$Z$503) -> 0 | E91: =IF($B91=0,"",$D91/$B91) | F91: =IF($B$13=0,"",$D91/$B$13) -> 0 | G91: =IF($B91=0,"",COUNTIFS('Trade Log'!$M$4:$M$503,$A91,'Trade Log'!$Z$4:$Z$503,">0")/$B91)
A92: SQUAREOFF_239 | B92: =COUNTIF('Trade Log'!$M$4:$M$503,$A92) -> 1 | C92: =SUMIF('Trade Log'!$M$4:$M$503,$A92,'Trade Log'!$Q$4:$Q$503) -> 5229 | D92: =SUMIF('Trade Log'!$M$4:$M$503,$A92,'Trade Log'!$Z$4:$Z$503) -> 5087.1894 | E92: =IF($B92=0,"",$D92/$B92) -> 5087.1894 | F92: =IF($B$13=0,"",$D92/$B$13) -> 0.21268801 | G92: =IF($B92=0,"",COUNTIFS('Trade Log'!$M$4:$M$503,$A92,'Trade Log'!$Z$4:$Z$503,">0")/$B92) -> 1
A93: MANUAL | B93: =COUNTIF('Trade Log'!$M$4:$M$503,$A93) -> 0 | C93: =SUMIF('Trade Log'!$M$4:$M$503,$A93,'Trade Log'!$Q$4:$Q$503) -> 0 | D93: =SUMIF('Trade Log'!$M$4:$M$503,$A93,'Trade Log'!$Z$4:$Z$503) -> 0 | E93: =IF($B93=0,"",$D93/$B93) | F93: =IF($B$13=0,"",$D93/$B$13) -> 0 | G93: =IF($B93=0,"",COUNTIFS('Trade Log'!$M$4:$M$503,$A93,'Trade Log'!$Z$4:$Z$503,">0")/$B93)
A94: TARGET_17, COVER_TARGET_5 and UC_STOP are the features shipped on 17 Aug. If their rows stay at zero legs, the orders are not filling; if their Net/Leg is worse than EXIT_925, they are costing you.
A96: EXECUTION QUALITY & COST RECONCILIATION
A97: Break-even slippage in the backtest was ~44bp/side against a ~25bp/side realistic cost, leaving ~18-19bp of budget that has never been checked against real fills. This block checks it.
A98: Avg entry slippage, LONG legs (bp) | B98: =IFERROR(AVERAGEIFS('Trade Log'!$AC$4:$AC$503,'Trade Log'!$E$4:$E$503,"LONG"),"") -> 35 | G98: Positive = filled worse than the 15:20 reference price.
A99: Avg entry slippage, SHORT legs (bp) | B99: =IFERROR(AVERAGEIFS('Trade Log'!$AC$4:$AC$503,'Trade Log'!$E$4:$E$503,"SHORT"),"") -> 0
A100: Median entry slippage (bp) | B100: =IFERROR(MEDIAN('Trade Log'!$AC$4:$AC$503),"") -> 17.5 | G100: Compare to the mean — a big gap means a few bad fills dominate.
A101: Worst entry slippage (bp) | B101: =IFERROR(MAX('Trade Log'!$AC$4:$AC$503),"") -> 35
A102: Legs slipping worse than 50bp | B102: =COUNTIF('Trade Log'!$AC$4:$AC$503,">50") -> 0
A103: Avg modelled cost per leg (bp) | B103: =IFERROR(AVERAGE('Trade Log'!$AB$4:$AB$503),"") -> 16.941895
A104: All-in friction (bp of turnover) | B104: =IF($B$17=0,"",$B$12/$B$17*10000+$B$98) -> 43.138956 | G104: Costs plus average long slippage. Compare to the 44bp/side break-even.
A105: Slippage budget remaining (bp) | B105: =IF($B$104="","",44-$B$104) -> 0.86104416 | G105: Negative means the live strategy is running past the backtest's break-even.
A106: Legs reconciled to contract note | B106: =COUNT('Trade Log'!$AH$4:$AH$503) -> 0 | G106: Fill 'Broker Actual Net' from your Dhan P&L statement.
A107: Model vs broker, total variance | B107: =SUM('Trade Log'!$AI$4:$AI$503) -> 0 | G107: Should trend to zero. A persistent gap means the Config cost model is wrong.
A108: Model vs broker, avg per leg | B108: =IFERROR($B$107/$B$106,"")
...

Sheet Trade Log
A1: Trade Log — one row per leg
A2: BLUE header = you type it. Dark header = formula. Grey header = internal helper.
A3: Trade ID | B3: Signal ID | C3: Signal Date | D3: Symbol | E3: Leg | F3: Product | G3: Ref Price | H3: Entry Date | I3: Entry Price | J3: Qty | K3: Entry Value | L3: Exit Date | M3: Exit Stage | N3: Exit Price | O3: Exit Value | P3: Holding Days | Q3: Gross P&L | R3: Gross Ret % | S3: Brokerage | T3: STT | U3: Exch Txn | V3: SEBI+Stamp+DP | W3: GST | X3: MTF Interest | Y3: Total Costs | Z3: Net P&L | AA3: Net Ret % | AB3: Cost (bp) | AC3: Entry Slip (bp) | AD3: Last Price | AE3: Unrealised Gross | AF3: Cycle Net (L+S) | AG3: Cycle Ret % | AH3: Broker Actual Net | AI3: Model - Broker | AJ3: Notes | AK3: hlp:prod | AL3: hlp:buy | AM3: hlp:sell
A4: 2026-08-17-TVSSRICHAK-L | B4: =IF($D4="","",IF(OR(RIGHT($A4,2)="-L",RIGHT($A4,2)="-S"),LEFT($A4,LEN($A4)-2),$A4)) -> 2026-08-17-TVSSRICHAK | C4: 46251 | D4: TVSSRICHAK | E4: LONG | F4: MTF | G4: 100 | H4: 46251 | I4: 100.35 | J4: 2490 | K4: =IF($D4="","",$I4*$J4) -> 249871.5 | L4: 46252 | M4: EXIT_925 | N4: 108.2 | O4: =IF(OR($D4="",$N4=""),"",$N4*$J4) -> 269418 | P4: =IF(OR($D4="",$L4=""),"",MAX($L4-$H4,0)) -> 1 | Q4: =IF(OR($D4="",$N4=""),"",IF($E4="LONG",($N4-$I4)*$J4,($I4-$N4)*$J4)) -> 19546.5 | R4: =IF(OR($D4="",$Q4="",$K4=0),"",$Q4/$K4) -> 0.078226208 | S4: =IF(OR($D4="",$N4=""),"",MIN(INDEX(Config!$C$13:$C$15,$AK4),INDEX(Config!$B$13:$B$15,$AK4)*$K4)+MIN(INDEX(Config!$C$13:$C$15,$AK4),INDEX(Config!$B$13:$B$15,$AK4)*$O4)) -> 40 | T4: =IF(OR($D4="",$N4=""),"",INDEX(Config!$D$13:$D$15,$AK4)*$AL4+INDEX(Config!$E$13:$E$15,$AK4)*$AM4) -> 519.2895 | U4: =IF(OR($D4="",$N4=""),"",INDEX(Config!$F$13:$F$15,$AK4)*($K4+$O4)) -> 15.422898 | V4: =IF(OR($D4="",$N4=""),"",INDEX(Config!$G$13:$G$15,$AK4)*($K4+$O4)+INDEX(Config!$H$13:$H$15,$AK4)*$AL4+INDEX(Config!$J$13:$J$15,$AK4)) -> 53.340015 | W4: =IF(OR($D4="",$N4=""),"",INDEX(Config!$I$13:$I$15,$AK4)*($S4+$U4+INDEX(Config!$G$13:$G$15,$AK4)*($K4+$O4))) -> 10.069594 | X4: =IF(OR($D4="",$N4=""),"",INDEX(Config!$K$13:$K$15,$AK4)/365*$P4*$K4*Config!$B$8) -> 77.015188 | Y4: =IF(OR($D4="",$N4=""),"",SUM($S4:$X4)) -> 715.13719 | Z4: =IF(OR($D4="",$Q4=""),"",$Q4-$Y4) -> 18831.363 | AA4: =IF(OR($D4="",$Z4="",$K4=0),"",$Z4/$K4) -> 0.075364188 | AB4: =IF(OR($D4="",$Y4="",$K4=0),"",$Y4/$K4*10000) -> 28.620199 | AC4: =IF(OR($D4="",$G4="",$G4=0,$I4=""),"",IF($E4="LONG",($I4-$G4)/$G4,($G4-$I4)/$G4)*10000) -> 35 | AE4: =IF(OR($D4="",$N4<>"",$AD4=""),"",IF($E4="LONG",($AD4-$I4)*$J4,($I4-$AD4)*$J4)) | AF4: =IF(OR($D4="",$E4<>"LONG",$Z4=""),"",$Z4+SUMIFS($Z$4:$Z$503,$B$4:$B$503,$B4,$E$4:$E$503,"SHORT")) -> 23918.552 | AG4: =IF(OR($AF4="",$K4=0),"",$AF4/$K4) -> 0.095723411 | AI4: =IF(OR($D4="",$AH4="",$Z4=""),"",$Z4-$AH4) | AJ4: EXAMPLE — delete. Entered 15:21, exited profitably at 9:25. | AK4: =IF($D4="","",IFERROR(MATCH($F4,Config!$A$13:$A$15,0),1)) -> 1 | AL4: =IF(OR($D4="",$N4=""),"",IF($E4="LONG",$K4,$O4)) -> 249871.5 | AM4: =IF(OR($D4="",$N4=""),"",IF($E4="LONG",$O4,$K4)) -> 269418
A5: 2026-08-17-TVSSRICHAK-S | B5: =IF($D5="","",IF(OR(RIGHT($A5,2)="-L",RIGHT($A5,2)="-S"),LEFT($A5,LEN($A5)-2),$A5)) -> 2026-08-17-TVSSRICHAK | C5: 46251 | D5: TVSSRICHAK | E5: SHORT | F5: INTRADAY | G5: 108.2 | H5: 46252 | I5: 108.2 | J5: 2490 | K5: =IF($D5="","",$I5*$J5) -> 269418 | L5: 46252 | M5: SQUAREOFF_239 | N5: 106.1 | O5: =IF(OR($D5="",$N5=""),"",$N5*$J5) -> 264189 | P5: =IF(OR($D5="",$L5=""),"",MAX($L5-$H5,0)) -> 0 | Q5: =IF(OR($D5="",$N5=""),"",IF($E5="LONG",($N5-$I5)*$J5,($I5-$N5)*$J5)) -> 5229 | R5: =IF(OR($D5="",$Q5="",$K5=0),"",$Q5/$K5) -> 0.019408503 | S5: =IF(OR($D5="",$N5=""),"",MIN(INDEX(Config!$C$13:$C$15,$AK5),INDEX(Config!$B$13:$B$15,$AK5)*$K5)+MIN(INDEX(Config!$C$13:$C$15,$AK5),INDEX(Config!$B$13:$B$15,$AK5)*$O5)) -> 40 | T5: =IF(OR($D5="",$N5=""),"",INDEX(Config!$D$13:$D$15,$AK5)*$AL5+INDEX(Config!$E$13:$E$15,$AK5)*$AM5) -> 67.3545 | U5: =IF(OR($D5="",$N5=""),"",INDEX(Config!$F$13:$F$15,$AK5)*($K5+$O5)) -> 15.848128 | V5: =IF(OR($D5="",$N5=""),"",INDEX(Config!$G$13:$G$15,$AK5)*($K5+$O5)+INDEX(Config!$H$13:$H$15,$AK5)*$AL5+INDEX(Config!$J$13:$J$15,$AK5)) -> 8.459277 | W5: =IF(OR($D5="",$N5=""),"",INDEX(Config!$I$13:$I$15,$AK5)*($S5+$U5+INDEX(Config!$G$13:$G$15,$AK5)*($K5+$O5))) -> 10.148712 | X5: =IF(OR($D5="",$N5=""),"",INDEX(Config!$K$13:$K$15,$AK5)/365*$P5*$K5*Config!$B$8) -> 0 | Y5: =IF(OR($D5="",$N5=""),"",SUM($S5:$X5)) -> 141.81062 | Z5: =IF(OR($D5="",$Q5=""),"",$Q5-$Y5) -> 5087.1894 | AA5: =IF(OR($D5="",$Z5="",$K5=0),"",$Z5/$K5) -> 0.018882144 | AB5: =IF(OR($D5="",$Y5="",$K5=0),"",$Y5/$K5*10000) -> 5.263591 | AC5: =IF(OR($D5="",$G5="",$G5=0,$I5=""),"",IF($E5="LONG",($I5-$G5)/$G5,($G5-$I5)/$G5)*10000) -> 0 | AE5: =IF(OR($D5="",$N5<>"",$AD5=""),"",IF($E5="LONG",($AD5-$I5)*$J5,($I5-$AD5)*$J5)) | AF5: =IF(OR($D5="",$E5<>"LONG",$Z5=""),"",$Z5+SUMIFS($Z$4:$Z$503,$B$4:$B$503,$B5,$E$4:$E$503,"SHORT")) | AG5: =IF(OR($AF5="",$K5=0),"",$AF5/$K5) | AI5: =IF(OR($D5="",$AH5="",$Z5=""),"",$Z5-$AH5) | AJ5: EXAMPLE — delete. Short-on-exit overlay, covered at 2:39pm. | AK5: =IF($D5="","",IFERROR(MATCH($F5,Config!$A$13:$A$15,0),1)) -> 3 | AL5: =IF(OR($D5="",$N5=""),"",IF($E5="LONG",$K5,$O5)) -> 264189 | AM5: =IF(OR($D5="",$N5=""),"",IF($E5="LONG",$O5,$K5)) -> 269418
B6: =IF($D6="","",IF(OR(RIGHT($A6,2)="-L",RIGHT($A6,2)="-S"),LEFT($A6,LEN($A6)-2),$A6)) | K6: =IF($D6="","",$I6*$J6) | O6: =IF(OR($D6="",$N6=""),"",$N6*$J6) | P6: =IF(OR($D6="",$L6=""),"",MAX($L6-$H6,0)) | Q6: =IF(OR($D6="",$N6=""),"",IF($E6="LONG",($N6-$I6)*$J6,($I6-$N6)*$J6)) | R6: =IF(OR($D6="",$Q6="",$K6=0),"",$Q6/$K6) | S6: =IF(OR($D6="",$N6=""),"",MIN(INDEX(Config!$C$13:$C$15,$AK6),INDEX(Config!$B$13:$B$15,$AK6)*$K6)+MIN(INDEX(Config!$C$13:$C$15,$AK6),INDEX(Config!$B$13:$B$15,$AK6)*$O6)) | T6: =IF(OR($D6="",$N6=""),"",INDEX(Config!$D$13:$D$15,$AK6)*$AL6+INDEX(Config!$E$13:$E$15,$AK6)*$AM6) | U6: =IF(OR($D6="",$N6=""),"",INDEX(Config!$F$13:$F$15,$AK6)*($K6+$O6)) | V6: =IF(OR($D6="",$N6=""),"",INDEX(Config!$G$13:$G$15,$AK6)*($K6+$O6)+INDEX(Config!$H$13:$H$15,$AK6)*$AL6+INDEX(Config!$J$13:$J$15,$AK6)) | W6: =IF(OR($D6="",$N6=""),"",INDEX(Config!$I$13:$I$15,$AK6)*($S6+$U6+INDEX(Config!$G$13:$G$15,$AK6)*($K6+$O6))) | X6: =IF(OR($D6="",$N6=""),"",INDEX(Config!$K$13:$K$15,$AK6)/365*$P6*$K6*Config!$B$8) | Y6: =IF(OR($D6="",$N6=""),"",SUM($S6:$X6)) | Z6: =IF(OR($D6="",$Q6=""),"",$Q6-$Y6) | AA6: =IF(OR($D6="",$Z6="",$K6=0),"",$Z6/$K6) | AB6: =IF(OR($D6="",$Y6="",$K6=0),"",$Y6/$K6*10000) | AC6: =IF(OR($D6="",$G6="",$G6=0,$I6=""),"",IF($E6="LONG",($I6-$G6)/$G6,($G6-$I6)/$G6)*10000) | AE6: =IF(OR($D6="",$N6<>"",$AD6=""),"",IF($E6="LONG",($AD6-$I6)*$J6,($I6-$AD6)*$J6)) | AF6: =IF(OR($D6="",$E6<>"LONG",$Z6=""),"",$Z6+SUMIFS($Z$4:$Z$503,$B$4:$B$503,$B6,$E$4:$E$503,"SHORT")) | AG6: =IF(OR($AF6="",$K6=0),"",$AF6/$K6) | AI6: =IF(OR($D6="",$AH6="",$Z6=""),"",$Z6-$AH6) | AK6: =IF($D6="","",IFERROR(MATCH($F6,Config!$A$13:$A$15,0),1)) | AL6: =IF(OR($D6="",$N6=""),"",IF($E6="LONG",$K6,$O6)) | AM6: =IF(OR($D6="",$N6=""),"",IF($E6="LONG",$O6,$K6))
B7: =IF($D7="","",IF(OR(RIGHT($A7,2)="-L",RIGHT($A7,2)="-S"),LEFT($A7,LEN($A7)-2),$A7)) | K7: =IF($D7="","",$I7*$J7) | O7: =IF(OR($D7="",$N7=""),"",$N7*$J7) | P7: =IF(OR($D7="",$L7=""),"",MAX($L7-$H7,0)) | Q7: =IF(OR($D7="",$N7=""),"",IF($E7="LONG",($N7-$I7)*$J7,($I7-$N7)*$J7)) | R7: =IF(OR($D7="",$Q7="",$K7=0),"",$Q7/$K7) | S7: =IF(OR($D7="",$N7=""),"",MIN(INDEX(Config!$C$13:$C$15,$AK7),INDEX(Config!$B$13:$B$15,$AK7)*$K7)+MIN(INDEX(Config!$C$13:$C$15,$AK7),INDEX(Config!$B$13:$B$15,$AK7)*$O7)) | T7: =IF(OR($D7="",$N7=""),"",INDEX(Config!$D$13:$D$15,$AK7)*$AL7+INDEX(Config!$E$13:$E$15,$AK7)*$AM7) | U7: =IF(OR($D7="",$N7=""),"",INDEX(Config!$F$13:$F$15,$AK7)*($K7+$O7)) | V7: =IF(OR($D7="",$N7=""),"",INDEX(Config!$G$13:$G$15,$AK7)*($K7+$O7)+INDEX(Config!$H$13:$H$15,$AK7)*$AL7+INDEX(Config!$J$13:$J$15,$AK7)) | W7: =IF(OR($D7="",$N7=""),"",INDEX(Config!$I$13:$I$15,$AK7)*($S7+$U7+INDEX(Config!$G$13:$G$15,$AK7)*($K7+$O7))) | X7: =IF(OR($D7="",$N7=""),"",INDEX(Config!$K$13:$K$15,$AK7)/365*$P7*$K7*Config!$B$8) | Y7: =IF(OR($D7="",$N7=""),"",SUM($S7:$X7)) | Z7: =IF(OR($D7="",$Q7=""),"",$Q7-$Y7) | AA7: =IF(OR($D7="",$Z7="",$K7=0),"",$Z7/$K7) | AB7: =IF(OR($D7="",$Y7="",$K7=0),"",$Y7/$K7*10000) | AC7: =IF(OR($D7="",$G7="",$G7=0,$I7=""),"",IF($E7="LONG",($I7-$G7)/$G7,($G7-$I7)/$G7)*10000) | AE7: =IF(OR($D7="",$N7<>"",$AD7=""),"",IF($E7="LONG",($AD7-$I7)*$J7,($I7-$AD7)*$J7)) | AF7: =IF(OR($D7="",$E7<>"LONG",$Z7=""),"",$Z7+SUMIFS($Z$4:$Z$503,$B$4:$B$503,$B7,$E$4:$E$503,"SHORT")) | AG7: =IF(OR($AF7="",$K7=0),"",$AF7/$K7) | AI7: =IF(OR($D7="",$AH7="",$Z7=""),"",$Z7-$AH7) | AK7: =IF($D7="","",IFERROR(MATCH($F7,Config!$A$13:$A$15,0),1)) | AL7: =IF(OR($D7="",$N7=""),"",IF($E7="LONG",$K7,$O7)) | AM7: =IF(OR($D7="",$N7=""),"",IF($E7="LONG",$O7,$K7))
B8: =IF($D8="","",IF(OR(RIGHT($A8,2)="-L",RIGHT($A8,2)="-S"),LEFT($A8,LEN($A8)-2),$A8)) | K8: =IF($D8="","",$I8*$J8) | O8: =IF(OR($D8="",$N8=""),"",$N8*$J8) | P8: =IF(OR($D8="",$L8=""),"",MAX($L8-$H8,0)) | Q8: =IF(OR($D8="",$N8=""),"",IF($E8="LONG",($N8-$I8)*$J8,($I8-$N8)*$J8)) | R8: =IF(OR($D8="",$Q8="",$K8=0),"",$Q8/$K8) | S8: =IF(OR($D8="",$N8=""),"",MIN(INDEX(Config!$C$13:$C$15,$AK8),INDEX(Config!$B$13:$B$15,$AK8)*$K8)+MIN(INDEX(Config!$C$13:$C$15,$AK8),INDEX(Config!$B$13:$B$15,$AK8)*$O8)) | T8: =IF(OR($D8="",$N8=""),"",INDEX(Config!$D$13:$D$15,$AK8)*$AL8+INDEX(Config!$E$13:$E$15,$AK8)*$AM8) | U8: =IF(OR($D8="",$N8=""),"",INDEX(Config!$F$13:$F$15,$AK8)*($K8+$O8)) | V8: =IF(OR($D8="",$N8=""),"",INDEX(Config!$G$13:$G$15,$AK8)*($K8+$O8)+INDEX(Config!$H$13:$H$15,$AK8)*$AL8+INDEX(Config!$J$13:$J$15,$AK8)) | W8: =IF(OR($D8="",$N8=""),"",INDEX(Config!$I$13:$I$15,$AK8)*($S8+$U8+INDEX(Config!$G$13:$G$15,$AK8)*($K8+$O8))) | X8: =IF(OR($D8="",$N8=""),"",INDEX(Config!$K$13:$K$15,$AK8)/365*$P8*$K8*Config!$B$8) | Y8: =IF(OR($D8="",$N8=""),"",SUM($S8:$X8)) | Z8: =IF(OR($D8="",$Q8=""),"",$Q8-$Y8) | AA8: =IF(OR($D8="",$Z8="",$K8=0),"",$Z8/$K8) | AB8: =IF(OR($D8="",$Y8="",$K8=0),"",$Y8/$K8*10000) | AC8: =IF(OR($D8="",$G8="",$G8=0,$I8=""),"",IF($E8="LONG",($I8-$G8)/$G8,($G8-$I8)/$G8)*10000) | AE8: =IF(OR($D8="",$N8<>"",$AD8=""),"",IF($E8="LONG",($AD8-$I8)*$J8,($I8-$AD8)*$J8)) | AF8: =IF(OR($D8="",$E8<>"LONG",$Z8=""),"",$Z8+SUMIFS($Z$4:$Z$503,$B$4:$B$503,$B8,$E$4:$E$503,"SHORT")) | AG8: =IF(OR($AF8="",$K8=0),"",$AF8/$K8) | AI8: =IF(OR($D8="",$AH8="",$Z8=""),"",$Z8-$AH8) | AK8: =IF($D8="","",IFERROR(MATCH($F8,Config!$A$13:$A$15,0),1)) | AL8: =IF(OR($D8="",$N8=""),"",IF($E8="LONG",$K8,$O8)) | AM8: =IF(OR($D8="",$N8=""),"",IF($E8="LONG",$O8,$K8))
B9: =IF($D9="","",IF(OR(RIGHT($A9,2)="-L",RIGHT($A9,2)="-S"),LEFT($A9,LEN($A9)-2),$A9)) | K9: =IF($D9="","",$I9*$J9) | O9: =IF(OR($D9="",$N9=""),"",$N9*$J9) | P9: =IF(OR($D9="",$L9=""),"",MAX($L9-$H9,0)) | Q9: =IF(OR($D9="",$N9=""),"",IF($E9="LONG",($N9-$I9)*$J9,($I9-$N9)*$J9)) | R9: =IF(OR($D9="",$Q9="",$K9=0),"",$Q9/$K9) | S9: =IF(OR($D9="",$N9=""),"",MIN(INDEX(Config!$C$13:$C$15,$AK9),INDEX(Config!$B$13:$B$15,$AK9)*$K9)+MIN(INDEX(Config!$C$13:$C$15,$AK9),INDEX(Config!$B$13:$B$15,$AK9)*$O9)) | T9: =IF(OR($D9="",$N9=""),"",INDEX(Config!$D$13:$D$15,$AK9)*$AL9+INDEX(Config!$E$13:$E$15,$AK9)*$AM9) | U9: =IF(OR($D9="",$N9=""),"",INDEX(Config!$F$13:$F$15,$AK9)*($K9+$O9)) | V9: =IF(OR($D9="",$N9=""),"",INDEX(Config!$G$13:$G$15,$AK9)*($K9+$O9)+INDEX(Config!$H$13:$H$15,$AK9)*$AL9+INDEX(Config!$J$13:$J$15,$AK9)) | W9: =IF(OR($D9="",$N9=""),"",INDEX(Config!$I$13:$I$15,$AK9)*($S9+$U9+INDEX(Config!$G$13:$G$15,$AK9)*($K9+$O9))) | X9: =IF(OR($D9="",$N9=""),"",INDEX(Config!$K$13:$K$15,$AK9)/365*$P9*$K9*Config!$B$8) | Y9: =IF(OR($D9="",$N9=""),"",SUM($S9:$X9)) | Z9: =IF(OR($D9="",$Q9=""),"",$Q9-$Y9) | AA9: =IF(OR($D9="",$Z9="",$K9=0),"",$Z9/$K9) | AB9: =IF(OR($D9="",$Y9="",$K9=0),"",$Y9/$K9*10000) | AC9: =IF(OR($D9="",$G9="",$G9=0,$I9=""),"",IF($E9="LONG",($I9-$G9)/$G9,($G9-$I9)/$G9)*10000) | AE9: =IF(OR($D9="",$N9<>"",$AD9=""),"",IF($E9="LONG",($AD9-$I9)*$J9,($I9-$AD9)*$J9)) | AF9: =IF(OR($D9="",$E9<>"LONG",$Z9=""),"",$Z9+SUMIFS($Z$4:$Z$503,$B$4:$B$503,$B9,$E$4:$E$503,"SHORT")) | AG9: =IF(OR($AF9="",$K9=0),"",$AF9/$K9) | AI9: =IF(OR($D9="",$AH9="",$Z9=""),"",$Z9-$AH9) | AK9: =IF($D9="","",IFERROR(MATCH($F9,Config!$A$13:$A$15,0),1)) | AL9: =IF(OR($D9="",$N9=""),"",IF($E9="LONG",$K9,$O9)) | AM9: =IF(OR($D9="",$N9=""),"",IF($E9="LONG",$O9,$K9))
B10: =IF($D10="","",IF(OR(RIGHT($A10,2)="-L",RIGHT($A10,2)="-S"),LEFT($A10,LEN($A10)-2),$A10)) | K10: =IF($D10="","",$I10*$J10) | O10: =IF(OR($D10="",$N10=""),"",$N10*$J10) | P10: =IF(OR($D10="",$L10=""),"",MAX($L10-$H10,0)) | Q10: =IF(OR($D10="",$N10=""),"",IF($E10="LONG",($N10-$I10)*$J10,($I10-$N10)*$J10)) | R10: =IF(OR($D10="",$Q10="",$K10=0),"",$Q10/$K10) | S10: =IF(OR($D10="",$N10=""),"",MIN(INDEX(Config!$C$13:$C$15,$AK10),INDEX(Config!$B$13:$B$15,$AK10)*$K10)+MIN(INDEX(Config!$C$13:$C$15,$AK10),INDEX(Config!$B$13:$B$15,$AK10)*$O10)) | T10: =IF(OR($D10="",$N10=""),"",INDEX(Config!$D$13:$D$15,$AK10)*$AL10+INDEX(Config!$E$13:$E$15,$AK10)*$AM10) | U10: =IF(OR($D10="",$N10=""),"",INDEX(Config!$F$13:$F$15,$AK10)*($K10+$O10)) | V10: =IF(OR($D10="",$N10=""),"",INDEX(Config!$G$13:$G$15,$AK10)*($K10+$O10)+INDEX(Config!$H$13:$H$15,$AK10)*$AL10+INDEX(Config!$J$13:$J$15,$AK10)) | W10: =IF(OR($D10="",$N10=""),"",INDEX(Config!$I$13:$I$15,$AK10)*($S10+$U10+INDEX(Config!$G$13:$G$15,$AK10)*($K10+$O10))) | X10: =IF(OR($D10="",$N10=""),"",INDEX(Config!$K$13:$K$15,$AK10)/365*$P10*$K10*Config!$B$8) | Y10: =IF(OR($D10="",$N10=""),"",SUM($S10:$X10)) | Z10: =IF(OR($D10="",$Q10=""),"",$Q10-$Y10) | AA10: =IF(OR($D10="",$Z10="",$K10=0),"",$Z10/$K10) | AB10: =IF(OR($D10="",$Y10="",$K10=0),"",$Y10/$K10*10000) | AC10: =IF(OR($D10="",$G10="",$G10=0,$I10=""),"",IF($E10="LONG",($I10-$G10)/$G10,($G10-$I10)/$G10)*10000) | AE10: =IF(OR($D10="",$N10<>"",$AD10=""),"",IF($E10="LONG",($AD10-$I10)*$J10,($I10-$AD10)*$J10)) | AF10: =IF(OR($D10="",$E10<>"LONG",$Z10=""),"",$Z10+SUMIFS($Z$4:$Z$503,$B$4:$B$503,$B10,$E$4:$E$503,"SHORT")) | AG10: =IF(OR($AF10="",$K10=0),"",$AF10/$K10) | AI10: =IF(OR($D10="",$AH10="",$Z10=""),"",$Z10-$AH10) | AK10: =IF($D10="","",IFERROR(MATCH($F10,Config!$A$13:$A$15,0),1)) | AL10: =IF(OR($D10="",$N10=""),"",IF($E10="LONG",$K10,$O10)) | AM10: =IF(OR($D10="",$N10=""),"",IF($E10="LONG",$O10,$K10))
B11: =IF($D11="","",IF(OR(RIGHT($A11,2)="-L",RIGHT($A11,2)="-S"),LEFT($A11,LEN($A11)-2),$A11)) | K11: =IF($D11="","",$I11*$J11) | O11: =IF(OR($D11="",$N11=""),"",$N11*$J11) | P11: =IF(OR($D11="",$L11=""),"",MAX($L11-$H11,0)) | Q11: =IF(OR($D11="",$N11=""),"",IF($E11="LONG",($N11-$I11)*$J11,($I11-$N11)*$J11)) | R11: =IF(OR($D11="",$Q11="",$K11=0),"",$Q11/$K11) | S11: =IF(OR($D11="",$N11=""),"",MIN(INDEX(Config!$C$13:$C$15,$AK11),INDEX(Config!$B$13:$B$15,$AK11)*$K11)+MIN(INDEX(Config!$C$13:$C$15,$AK11),INDEX(Config!$B$13:$B$15,$AK11)*$O11)) | T11: =IF(OR($D11="",$N11=""),"",INDEX(Config!$D$13:$D$15,$AK11)*$AL11+INDEX(Config!$E$13:$E$15,$AK11)*$AM11) | U11: =IF(OR($D11="",$N11=""),"",INDEX(Config!$F$13:$F$15,$AK11)*($K11+$O11)) | V11: =IF(OR($D11="",$N11=""),"",INDEX(Config!$G$13:$G$15,$AK11)*($K11+$O11)+INDEX(Config!$H$13:$H$15,$AK11)*$AL11+INDEX(Config!$J$13:$J$15,$AK11)) | W11: =IF(OR($D11="",$N11=""),"",INDEX(Config!$I$13:$I$15,$AK11)*($S11+$U11+INDEX(Config!$G$13:$G$15,$AK11)*($K11+$O11))) | X11: =IF(OR($D11="",$N11=""),"",INDEX(Config!$K$13:$K$15,$AK11)/365*$P11*$K11*Config!$B$8) | Y11: =IF(OR($D11="",$N11=""),"",SUM($S11:$X11)) | Z11: =IF(OR($D11="",$Q11=""),"",$Q11-$Y11) | AA11: =IF(OR($D11="",$Z11="",$K11=0),"",$Z11/$K11) | AB11: =IF(OR($D11="",$Y11="",$K11=0),"",$Y11/$K11*10000) | AC11: =IF(OR($D11="",$G11="",$G11=0,$I11=""),"",IF($E11="LONG",($I11-$G11)/$G11,($G11-$I11)/$G11)*10000) | AE11: =IF(OR($D11="",$N11<>"",$AD11=""),"",IF($E11="LONG",($AD11-$I11)*$J11,($I11-$AD11)*$J11)) | AF11: =IF(OR($D11="",$E11<>"LONG",$Z11=""),"",$Z11+SUMIFS($Z$4:$Z$503,$B$4:$B$503,$B11,$E$4:$E$503,"SHORT")) | AG11: =IF(OR($AF11="",$K11=0),"",$AF11/$K11) | AI11: =IF(OR($D11="",$AH11="",$Z11=""),"",$Z11-$AH11) | AK11: =IF($D11="","",IFERROR(MATCH($F11,Config!$A$13:$A$15,0),1)) | AL11: =IF(OR($D11="",$N11=""),"",IF($E11="LONG",$K11,$O11)) | AM11: =IF(OR($D11="",$N11=""),"",IF($E11="LONG",$O11,$K11))
B12: =IF($D12="","",IF(OR(RIGHT($A12,2)="-L",RIGHT($A12,2)="-S"),LEFT($A12,LEN($A12)-2),$A12)) | K12: =IF($D12="","",$I12*$J12) | O12: =IF(OR($D12="",$N12=""),"",$N12*$J12) | P12: =IF(OR($D12="",$L12=""),"",MAX($L12-$H12,0)) | Q12: =IF(OR($D12="",$N12=""),"",IF($E12="LONG",($N12-$I12)*$J12,($I12-$N12)*$J12)) | R12: =IF(OR($D12="",$Q12="",$K12=0),"",$Q12/$K12) | S12: =IF(OR($D12="",$N12=""),"",MIN(INDEX(Config!$C$13:$C$15,$AK12),INDEX(Config!$B$13:$B$15,$AK12)*$K12)+MIN(INDEX(Config!$C$13:$C$15,$AK12),INDEX(Config!$B$13:$B$15,$AK12)*$O12)) | T12: =IF(OR($D12="",$N12=""),"",INDEX(Config!$D$13:$D$15,$AK12)*$AL12+INDEX(Config!$E$13:$E$15,$AK12)*$AM12) | U12: =IF(OR($D12="",$N12=""),"",INDEX(Config!$F$13:$F$15,$AK12)*($K12+$O12)) | V12: =IF(OR($D12="",$N12=""),"",INDEX(Config!$G$13:$G$15,$AK12)*($K12+$O12)+INDEX(Config!$H$13:$H$15,$AK12)*$AL12+INDEX(Config!$J$13:$J$15,$AK12)) | W12: =IF(OR($D12="",$N12=""),"",INDEX(Config!$I$13:$I$15,$AK12)*($S12+$U12+INDEX(Config!$G$13:$G$15,$AK12)*($K12+$O12))) | X12: =IF(OR($D12="",$N12=""),"",INDEX(Config!$K$13:$K$15,$AK12)/365*$P12*$K12*Config!$B$8) | Y12: =IF(OR($D12="",$N12=""),"",SUM($S12:$X12)) | Z12: =IF(OR($D12="",$Q12=""),"",$Q12-$Y12) | AA12: =IF(OR($D12="",$Z12="",$K12=0),"",$Z12/$K12) | AB12: =IF(OR($D12="",$Y12="",$K12=0),"",$Y12/$K12*10000) | AC12: =IF(OR($D12="",$G12="",$G12=0,$I12=""),"",IF($E12="LONG",($I12-$G12)/$G12,($G12-$I12)/$G12)*10000) | AE12: =IF(OR($D12="",$N12<>"",$AD12=""),"",IF($E12="LONG",($AD12-$I12)*$J12,($I12-$AD12)*$J12)) | AF12: =IF(OR($D12="",$E12<>"LONG",$Z12=""),"",$Z12+SUMIFS($Z$4:$Z$503,$B$4:$B$503,$B12,$E$4:$E$503,"SHORT")) | AG12: =IF(OR($AF12="",$K12=0),"",$AF12/$K12) | AI12: =IF(OR($D12="",$AH12="",$Z12=""),"",$Z12-$AH12) | AK12: =IF($D12="","",IFERROR(MATCH($F12,Config!$A$13:$A$15,0),1)) | AL12: =IF(OR($D12="",$N12=""),"",IF($E12="LONG",$K12,$O12)) | AM12: =IF(OR($D12="",$N12=""),"",IF($E12="LONG",$O12,$K12))
B13: =IF($D13="","",IF(OR(RIGHT($A13,2)="-L",RIGHT($A13,2)="-S"),LEFT($A13,LEN($A13)-2),$A13)) | K13: =IF($D13="","",$I13*$J13) | O13: =IF(OR($D13="",$N13=""),"",$N13*$J13) | P13: =IF(OR($D13="",$L13=""),"",MAX($L13-$H13,0)) | Q13: =IF(OR($D13="",$N13=""),"",IF($E13="LONG",($N13-$I13)*$J13,($I13-$N13)*$J13)) | R13: =IF(OR($D13="",$Q13="",$K13=0),"",$Q13/$K13) | S13: =IF(OR($D13="",$N13=""),"",MIN(INDEX(Config!$C$13:$C$15,$AK13),INDEX(Config!$B$13:$B$15,$AK13)*$K13)+MIN(INDEX(Config!$C$13:$C$15,$AK13),INDEX(Config!$B$13:$B$15,$AK13)*$O13)) | T13: =IF(OR($D13="",$N13=""),"",INDEX(Config!$D$13:$D$15,$AK13)*$AL13+INDEX(Config!$E$13:$E$15,$AK13)*$AM13) | U13: =IF(OR($D13="",$N13=""),"",INDEX(Config!$F$13:$F$15,$AK13)*($K13+$O13)) | V13: =IF(OR($D13="",$N13=""),"",INDEX(Config!$G$13:$G$15,$AK13)*($K13+$O13)+INDEX(Config!$H$13:$H$15,$AK13)*$AL13+INDEX(Config!$J$13:$J$15,$AK13)) | W13: =IF(OR($D13="",$N13=""),"",INDEX(Config!$I$13:$I$15,$AK13)*($S13+$U13+INDEX(Config!$G$13:$G$15,$AK13)*($K13+$O13))) | X13: =IF(OR($D13="",$N13=""),"",INDEX(Config!$K$13:$K$15,$AK13)/365*$P13*$K13*Config!$B$8) | Y13: =IF(OR($D13="",$N13=""),"",SUM($S13:$X13)) | Z13: =IF(OR($D13="",$Q13=""),"",$Q13-$Y13) | AA13: =IF(OR($D13="",$Z13="",$K13=0),"",$Z13/$K13) | AB13: =IF(OR($D13="",$Y13="",$K13=0),"",$Y13/$K13*10000) | AC13: =IF(OR($D13="",$G13="",$G13=0,$I13=""),"",IF($E13="LONG",($I13-$G13)/$G13,($G13-$I13)/$G13)*10000) | AE13: =IF(OR($D13="",$N13<>"",$AD13=""),"",IF($E13="LONG",($AD13-$I13)*$J13,($I13-$AD13)*$J13)) | AF13: =IF(OR($D13="",$E13<>"LONG",$Z13=""),"",$Z13+SUMIFS($Z$4:$Z$503,$B$4:$B$503,$B13,$E$4:$E$503,"SHORT")) | AG13: =IF(OR($AF13="",$K13=0),"",$AF13/$K13) | AI13: =IF(OR($D13="",$AH13="",$Z13=""),"",$Z13-$AH13) | AK13: =IF($D13="","",IFERROR(MATCH($F13,Config!$A$13:$A$15,0),1)) | AL13: =IF(OR($D13="",$N13=""),"",IF($E13="LONG",$K13,$O13)) | AM13: =IF(OR($D13="",$N13=""),"",IF($E13="LONG",$O13,$K13))
B14: =IF($D14="","",IF(OR(RIGHT($A14,2)="-L",RIGHT($A14,2)="-S"),LEFT($A14,LEN($A14)-2),$A14)) | K14: =IF($D14="","",$I14*$J14) | O14: =IF(OR($D14="",$N14=""),"",$N14*$J14) | P14: =IF(OR($D14="",$L14=""),"",MAX($L14-$H14,0)) | Q14: =IF(OR($D14="",$N14=""),"",IF($E14="LONG",($N14-$I14)*$J14,($I14-$N14)*$J14)) | R14: =IF(OR($D14="",$Q14="",$K14=0),"",$Q14/$K14) | S14: =IF(OR($D14="",$N14=""),"",MIN(INDEX(Config!$C$13:$C$15,$AK14),INDEX(Config!$B$13:$B$15,$AK14)*$K14)+MIN(INDEX(Config!$C$13:$C$15,$AK14),INDEX(Config!$B$13:$B$15,$AK14)*$O14)) | T14: =IF(OR($D14="",$N14=""),"",INDEX(Config!$D$13:$D$15,$AK14)*$AL14+INDEX(Config!$E$13:$E$15,$AK14)*$AM14) | U14: =IF(OR($D14="",$N14=""),"",INDEX(Config!$F$13:$F$15,$AK14)*($K14+$O14)) | V14: =IF(OR($D14="",$N14=""),"",INDEX(Config!$G$13:$G$15,$AK14)*($K14+$O14)+INDEX(Config!$H$13:$H$15,$AK14)*$AL14+INDEX(Config!$J$13:$J$15,$AK14)) | W14: =IF(OR($D14="",$N14=""),"",INDEX(Config!$I$13:$I$15,$AK14)*($S14+$U14+INDEX(Config!$G$13:$G$15,$AK14)*($K14+$O14))) | X14: =IF(OR($D14="",$N14=""),"",INDEX(Config!$K$13:$K$15,$AK14)/365*$P14*$K14*Config!$B$8) | Y14: =IF(OR($D14="",$N14=""),"",SUM($S14:$X14)) | Z14: =IF(OR($D14="",$Q14=""),"",$Q14-$Y14) | AA14: =IF(OR($D14="",$Z14="",$K14=0),"",$Z14/$K14) | AB14: =IF(OR($D14="",$Y14="",$K14=0),"",$Y14/$K14*10000) | AC14: =IF(OR($D14="",$G14="",$G14=0,$I14=""),"",IF($E14="LONG",($I14-$G14)/$G14,($G14-$I14)/$G14)*10000) | AE14: =IF(OR($D14="",$N14<>"",$AD14=""),"",IF($E14="LONG",($AD14-$I14)*$J14,($I14-$AD14)*$J14)) | AF14: =IF(OR($D14="",$E14<>"LONG",$Z14=""),"",$Z14+SUMIFS($Z$4:$Z$503,$B$4:$B$503,$B14,$E$4:$E$503,"SHORT")) | AG14: =IF(OR($AF14="",$K14=0),"",$AF14/$K14) | AI14: =IF(OR($D14="",$AH14="",$Z14=""),"",$Z14-$AH14) | AK14: =IF($D14="","",IFERROR(MATCH($F14,Config!$A$13:$A$15,0),1)) | AL14: =IF(OR($D14="",$N14=""),"",IF($E14="LONG",$K14,$O14)) | AM14: =IF(OR($D14="",$N14=""),"",IF($E14="LONG",$O14,$K14))
B15: =IF($D15="","",IF(OR(RIGHT($A15,2)="-L",RIGHT($A15,2)="-S"),LEFT($A15,LEN($A15)-2),$A15)) | K15: =IF($D15="","",$I15*$J15) | O15: =IF(OR($D15="",$N15=""),"",$N15*$J15) | P15: =IF(OR($D15="",$L15=""),"",MAX($L15-$H15,0)) | Q15: =IF(OR($D15="",$N15=""),"",IF($E15="LONG",($N15-$I15)*$J15,($I15-$N15)*$J15)) | R15: =IF(OR($D15="",$Q15="",$K15=0),"",$Q15/$K15) | S15: =IF(OR($D15="",$N15=""),"",MIN(INDEX(Config!$C$13:$C$15,$AK15),INDEX(Config!$B$13:$B$15,$AK15)*$K15)+MIN(INDEX(Config!$C$13:$C$15,$AK15),INDEX(Config!$B$13:$B$15,$AK15)*$O15)) | T15: =IF(OR($D15="",$N15=""),"",INDEX(Config!$D$13:$D$15,$AK15)*$AL15+INDEX(Config!$E$13:$E$15,$AK15)*$AM15) | U15: =IF(OR($D15="",$N15=""),"",INDEX(Config!$F$13:$F$15,$AK15)*($K15+$O15)) | V15: =IF(OR($D15="",$N15=""),"",INDEX(Config!$G$13:$G$15,$AK15)*($K15+$O15)+INDEX(Config!$H$13:$H$15,$AK15)*$AL15+INDEX(Config!$J$13:$J$15,$AK15)) | W15: =IF(OR($D15="",$N15=""),"",INDEX(Config!$I$13:$I$15,$AK15)*($S15+$U15+INDEX(Config!$G$13:$G$15,$AK15)*($K15+$O15))) | X15: =IF(OR($D15="",$N15=""),"",INDEX(Config!$K$13:$K$15,$AK15)/365*$P15*$K15*Config!$B$8) | Y15: =IF(OR($D15="",$N15=""),"",SUM($S15:$X15)) | Z15: =IF(OR($D15="",$Q15=""),"",$Q15-$Y15) | AA15: =IF(OR($D15="",$Z15="",$K15=0),"",$Z15/$K15) | AB15: =IF(OR($D15="",$Y15="",$K15=0),"",$Y15/$K15*10000) | AC15: =IF(OR($D15="",$G15="",$G15=0,$I15=""),"",IF($E15="LONG",($I15-$G15)/$G15,($G15-$I15)/$G15)*10000) | AE15: =IF(OR($D15="",$N15<>"",$AD15=""),"",IF($E15="LONG",($AD15-$I15)*$J15,($I15-$AD15)*$J15)) | AF15: =IF(OR($D15="",$E15<>"LONG",$Z15=""),"",$Z15+SUMIFS($Z$4:$Z$503,$B$4:$B$503,$B15,$E$4:$E$503,"SHORT")) | AG15: =IF(OR($AF15="",$K15=0),"",$AF15/$K15) | AI15: =IF(OR($D15="",$AH15="",$Z15=""),"",$Z15-$AH15) | AK15: =IF($D15="","",IFERROR(MATCH($F15,Config!$A$13:$A$15,0),1)) | AL15: =IF(OR($D15="",$N15=""),"",IF($E15="LONG",$K15,$O15)) | AM15: =IF(OR($D15="",$N15=""),"",IF($E15="LONG",$O15,$K15))
B16: =IF($D16="","",IF(OR(RIGHT($A16,2)="-L",RIGHT($A16,2)="-S"),LEFT($A16,LEN($A16)-2),$A16)) | K16: =IF($D16="","",$I16*$J16) | O16: =IF(OR($D16="",$N16=""),"",$N16*$J16) | P16: =IF(OR($D16="",$L16=""),"",MAX($L16-$H16,0)) | Q16: =IF(OR($D16="",$N16=""),"",IF($E16="LONG",($N16-$I16)*$J16,($I16-$N16)*$J16)) | R16: =IF(OR($D16="",$Q16="",$K16=0),"",$Q16/$K16) | S16: =IF(OR($D16="",$N16=""),"",MIN(INDEX(Config!$C$13:$C$15,$AK16),INDEX(Config!$B$13:$B$15,$AK16)*$K16)+MIN(INDEX(Config!$C$13:$C$15,$AK16),INDEX(Config!$B$13:$B$15,$AK16)*$O16)) | T16: =IF(OR($D16="",$N16=""),"",INDEX(Config!$D$13:$D$15,$AK16)*$AL16+INDEX(Config!$E$13:$E$15,$AK16)*$AM16) | U16: =IF(OR($D16="",$N16=""),"",INDEX(Config!$F$13:$F$15,$AK16)*($K16+$O16)) | V16: =IF(OR($D16="",$N16=""),"",INDEX(Config!$G$13:$G$15,$AK16)*($K16+$O16)+INDEX(Config!$H$13:$H$15,$AK16)*$AL16+INDEX(Config!$J$13:$J$15,$AK16)) | W16: =IF(OR($D16="",$N16=""),"",INDEX(Config!$I$13:$I$15,$AK16)*($S16+$U16+INDEX(Config!$G$13:$G$15,$AK16)*($K16+$O16))) | X16: =IF(OR($D16="",$N16=""),"",INDEX(Config!$K$13:$K$15,$AK16)/365*$P16*$K16*Config!$B$8) | Y16: =IF(OR($D16="",$N16=""),"",SUM($S16:$X16)) | Z16: =IF(OR($D16="",$Q16=""),"",$Q16-$Y16) | AA16: =IF(OR($D16="",$Z16="",$K16=0),"",$Z16/$K16) | AB16: =IF(OR($D16="",$Y16="",$K16=0),"",$Y16/$K16*10000) | AC16: =IF(OR($D16="",$G16="",$G16=0,$I16=""),"",IF($E16="LONG",($I16-$G16)/$G16,($G16-$I16)/$G16)*10000) | AE16: =IF(OR($D16="",$N16<>"",$AD16=""),"",IF($E16="LONG",($AD16-$I16)*$J16,($I16-$AD16)*$J16)) | AF16: =IF(OR($D16="",$E16<>"LONG",$Z16=""),"",$Z16+SUMIFS($Z$4:$Z$503,$B$4:$B$503,$B16,$E$4:$E$503,"SHORT")) | AG16: =IF(OR($AF16="",$K16=0),"",$AF16/$K16) | AI16: =IF(OR($D16="",$AH16="",$Z16=""),"",$Z16-$AH16) | AK16: =IF($D16="","",IFERROR(MATCH($F16,Config!$A$13:$A$15,0),1)) | AL16: =IF(OR($D16="",$N16=""),"",IF($E16="LONG",$K16,$O16)) | AM16: =IF(OR($D16="",$N16=""),"",IF($E16="LONG",$O16,$K16))
B17: =IF($D17="","",IF(OR(RIGHT($A17,2)="-L",RIGHT($A17,2)="-S"),LEFT($A17,LEN($A17)-2),$A17)) | K17: =IF($D17="","",$I17*$J17) | O17: =IF(OR($D17="",$N17=""),"",$N17*$J17) | P17: =IF(OR($D17="",$L17=""),"",MAX($L17-$H17,0)) | Q17: =IF(OR($D17="",$N17=""),"",IF($E17="LONG",($N17-$I17)*$J17,($I17-$N17)*$J17)) | R17: =IF(OR($D17="",$Q17="",$K17=0),"",$Q17/$K17) | S17: =IF(OR($D17="",$N17=""),"",MIN(INDEX(Config!$C$13:$C$15,$AK17),INDEX(Config!$B$13:$B$15,$AK17)*$K17)+MIN(INDEX(Config!$C$13:$C$15,$AK17),INDEX(Config!$B$13:$B$15,$AK17)*$O17)) | T17: =IF(OR($D17="",$N17=""),"",INDEX(Config!$D$13:$D$15,$AK17)*$AL17+INDEX(Config!$E$13:$E$15,$AK17)*$AM17) | U17: =IF(OR($D17="",$N17=""),"",INDEX(Config!$F$13:$F$15,$AK17)*($K17+$O17)) | V17: =IF(OR($D17="",$N17=""),"",INDEX(Config!$G$13:$G$15,$AK17)*($K17+$O17)+INDEX(Config!$H$13:$H$15,$AK17)*$AL17+INDEX(Config!$J$13:$J$15,$AK17)) | W17: =IF(OR($D17="",$N17=""),"",INDEX(Config!$I$13:$I$15,$AK17)*($S17+$U17+INDEX(Config!$G$13:$G$15,$AK17)*($K17+$O17))) | X17: =IF(OR($D17="",$N17=""),"",INDEX(Config!$K$13:$K$15,$AK17)/365*$P17*$K17*Config!$B$8) | Y17: =IF(OR($D17="",$N17=""),"",SUM($S17:$X17)) | Z17: =IF(OR($D17="",$Q17=""),"",$Q17-$Y17) | AA17: =IF(OR($D17="",$Z17="",$K17=0),"",$Z17/$K17) | AB17: =IF(OR($D17="",$Y17="",$K17=0),"",$Y17/$K17*10000) | AC17: =IF(OR($D17="",$G17="",$G17=0,$I17=""),"",IF($E17="LONG",($I17-$G17)/$G17,($G17-$I17)/$G17)*10000) | AE17: =IF(OR($D17="",$N17<>"",$AD17=""),"",IF($E17="LONG",($AD17-$I17)*$J17,($I17-$AD17)*$J17)) | AF17: =IF(OR($D17="",$E17<>"LONG",$Z17=""),"",$Z17+SUMIFS($Z$4:$Z$503,$B$4:$B$503,$B17,$E$4:$E$503,"SHORT")) | AG17: =IF(OR($AF17="",$K17=0),"",$AF17/$K17) | AI17: =IF(OR($D17="",$AH17="",$Z17=""),"",$Z17-$AH17) | AK17: =IF($D17="","",IFERROR(MATCH($F17,Config!$A$13:$A$15,0),1)) | AL17: =IF(OR($D17="",$N17=""),"",IF($E17="LONG",$K17,$O17)) | AM17: =IF(OR($D17="",$N17=""),"",IF($E17="LONG",$O17,$K17))
... B503: =IF($D503="","",IF(OR(RIGHT($A503,2)="-L",RIGHT($A503,2)="-S"),LEFT($A503,LEN($A503)-2),$A503)) | K503: =IF($D503="","",$I503*$J503) | O503: =IF(OR($D503="",$N503=""),"",$N503*$J503) | P503: =IF(OR($D503="",$L503=""),"",MAX($L503-$H503,0)) | Q503: =IF(OR($D503="",$N503=""),"",IF($E503="LONG",($N503-$I503)*$J503,($I503-$N503)*$J503)) | R503: =IF(OR($D503="",$Q503="",$K503=0),"",$Q503/$K503) | S503: =IF(OR($D503="",$N503=""),"",MIN(INDEX(Config!$C$13:$C$15,$AK503),INDEX(Config!$B$13:$B$15,$AK503)*$K503)+MIN(INDEX(Config!$C$13:$C$15,$AK503),INDEX(Config!$B$13:$B$15,$AK503)*$O503)) | T503: =IF(OR($D503="",$N503=""),"",INDEX(Config!$D$13:$D$15,$AK503)*$AL503+INDEX(Config!$E$13:$E$15,$AK503)*$AM503) | U503: =IF(OR($D503="",$N503=""),"",INDEX(Config!$F$13:$F$15,$AK503)*($K503+$O503)) | V503: =IF(OR($D503="",$N503=""),"",INDEX(Config!$G$13:$G$15,$AK503)*($K503+$O503)+INDEX(Config!$H$13:$H$15,$AK503)*$AL503+INDEX(Config!$J$13:$J$15,$AK503)) | W503: =IF(OR($D503="",$N503=""),"",INDEX(Config!$I$13:$I$15,$AK503)*($S503+$U503+INDEX(Config!$G$13:$G$15,$AK503)*($K503+$O503))) | X503: =IF(OR($D503="",$N503=""),"",INDEX(Config!$K$13:$K$15,$AK503)/365*$P503*$K503*Config!$B$8) | Y503: =IF(OR($D503="",$N503=""),"",SUM($S503:$X503)) | Z503: =IF(OR($D503="",$Q503=""),"",$Q503-$Y503) | AA503: =IF(OR($D503="",$Z503="",$K503=0),"",$Z503/$K503) | AB503: =IF(OR($D503="",$Y503="",$K503=0),"",$Y503/$K503*10000) | AC503: =IF(OR($D503="",$G503="",$G503=0,$I503=""),"",IF($E503="LONG",($I503-$G503)/$G503,($G503-$I503)/$G503)*10000) | AE503: =IF(OR($D503="",$N503<>"",$AD503=""),"",IF($E503="LONG",($AD503-$I503)*$J503,($I503-$AD503)*$J503)) | AF503: =IF(OR($D503="",$E503<>"LONG",$Z503=""),"",$Z503+SUMIFS($Z$4:$Z$503,$B$4:$B$503,$B503,$E$4:$E$503,"SHORT")) | AG503: =IF(OR($AF503="",$K503=0),"",$AF503/$K503) | AI503: =IF(OR($D503="",$AH503="",$Z503=""),"",$Z503-$AH503) | AK503: =IF($D503="","",IFERROR(MATCH($F503,Config!$A$13:$A$15,0),1)) | AL503: =IF(OR($D503="",$N503=""),"",IF($E503="LONG",$K503,$O503)) | AM503: =IF(OR($D503="",$N503=""),"",IF($E503="LONG",$O503,$K503))

Sheet Daily PnL
A1: Daily P&L, equity curve, drawdown & rolling risk
A2: P&L is attributed to the EXIT date. Calendar starts at Config!B5. Blank Net = no trades closed that day.
A3: Date | B3: Day | C3: Legs Closed | D3: Long Gross | E3: Short Gross | F3: Total Gross | G3: Total Costs | H3: Net P&L | I3: Cumulative Net | J3: Equity | K3: Peak Equity | L3: Drawdown (₹) | M3: Drawdown % | N3: Capital Deployed | O3: Daily Ret | P3: Roll 20d Net | Q3: Roll 20d Sharpe | R3: Roll 60d Sharpe | S3: hlp:winstk | T3: hlp:losstk
A4: =Config!$B$5 -> 46235 | B4: =IF($A4="","",TEXT($A4,"ddd")) -> Sat | C4: =IF($A4="","",COUNTIFS('Trade Log'!$L$4:$L$503,$A4)) -> 0 | D4: =IF($A4="","",SUMIFS('Trade Log'!$Q$4:$Q$503,'Trade Log'!$L$4:$L$503,$A4,'Trade Log'!$E$4:$E$503,"LONG")) -> 0 | E4: =IF($A4="","",SUMIFS('Trade Log'!$Q$4:$Q$503,'Trade Log'!$L$4:$L$503,$A4,'Trade Log'!$E$4:$E$503,"SHORT")) -> 0 | F4: =IF($A4="","",$D4+$E4) -> 0 | G4: =IF($A4="","",SUMIFS('Trade Log'!$Y$4:$Y$503,'Trade Log'!$L$4:$L$503,$A4)) -> 0 | H4: =IF($A4="","",IF($C4=0,"",$F4-$G4)) | I4: =IF($A4="","",0+IF($H4="",0,$H4)) -> 0 | J4: =IF($A4="","",Config!$B$4+$I4) -> 1000000 | K4: =IF($A4="","",MAX($J$4:$J4)) -> 1000000 | L4: =IF($A4="","",$J4-$K4) -> 0 | M4: =IF(OR($A4="",$K4=0),"",$L4/$K4) -> 0 | N4: =IF($A4="","",SUMIFS('Trade Log'!$K$4:$K$503,'Trade Log'!$H$4:$H$503,$A4)) -> 0 | O4: =IF(OR($A4="",$H4="",Config!$B$4=0),"",$H4/Config!$B$4) | P4: =IF($A4="","",SUM($H$4:$H4)) -> 0 | Q4: =IF($A4="","",IFERROR((AVERAGE($O$4:$O4)-Config!$B$7/Config!$B$6)/STDEV($O$4:$O4)*SQRT(Config!$B$6),"")) | R4: =IF($A4="","",IFERROR((AVERAGE($O$4:$O4)-Config!$B$7/Config!$B$6)/STDEV($O$4:$O4)*SQRT(Config!$B$6),"")) | S4: =IF($H4="",0,IF($H4>0,1,0)) -> 0 | T4: =IF($H4="",0,IF($H4<0,1,0)) -> 0
A5: =IF($A4="","",$A4+1) -> 46236 | B5: =IF($A5="","",TEXT($A5,"ddd")) -> Sun | C5: =IF($A5="","",COUNTIFS('Trade Log'!$L$4:$L$503,$A5)) -> 0 | D5: =IF($A5="","",SUMIFS('Trade Log'!$Q$4:$Q$503,'Trade Log'!$L$4:$L$503,$A5,'Trade Log'!$E$4:$E$503,"LONG")) -> 0 | E5: =IF($A5="","",SUMIFS('Trade Log'!$Q$4:$Q$503,'Trade Log'!$L$4:$L$503,$A5,'Trade Log'!$E$4:$E$503,"SHORT")) -> 0 | F5: =IF($A5="","",$D5+$E5) -> 0 | G5: =IF($A5="","",SUMIFS('Trade Log'!$Y$4:$Y$503,'Trade Log'!$L$4:$L$503,$A5)) -> 0 | H5: =IF($A5="","",IF($C5=0,"",$F5-$G5)) | I5: =IF($A5="","",$I4+IF($H5="",0,$H5)) -> 0 | J5: =IF($A5="","",Config!$B$4+$I5) -> 1000000 | K5: =IF($A5="","",MAX($J$4:$J5)) -> 1000000 | L5: =IF($A5="","",$J5-$K5) -> 0 | M5: =IF(OR($A5="",$K5=0),"",$L5/$K5) -> 0 | N5: =IF($A5="","",SUMIFS('Trade Log'!$K$4:$K$503,'Trade Log'!$H$4:$H$503,$A5)) -> 0 | O5: =IF(OR($A5="",$H5="",Config!$B$4=0),"",$H5/Config!$B$4) | P5: =IF($A5="","",SUM($H$4:$H5)) -> 0 | Q5: =IF($A5="","",IFERROR((AVERAGE($O$4:$O5)-Config!$B$7/Config!$B$6)/STDEV($O$4:$O5)*SQRT(Config!$B$6),"")) | R5: =IF($A5="","",IFERROR((AVERAGE($O$4:$O5)-Config!$B$7/Config!$B$6)/STDEV($O$4:$O5)*SQRT(Config!$B$6),"")) | S5: =IF($H5="",$S4,IF($H5>0,$S4+1,0)) -> 0 | T5: =IF($H5="",$T4,IF($H5<0,$T4+1,0)) -> 0
A6: =IF($A5="","",$A5+1) -> 46237 | B6: =IF($A6="","",TEXT($A6,"ddd")) -> Mon | C6: =IF($A6="","",COUNTIFS('Trade Log'!$L$4:$L$503,$A6)) -> 0 | D6: =IF($A6="","",SUMIFS('Trade Log'!$Q$4:$Q$503,'Trade Log'!$L$4:$L$503,$A6,'Trade Log'!$E$4:$E$503,"LONG")) -> 0 | E6: =IF($A6="","",SUMIFS('Trade Log'!$Q$4:$Q$503,'Trade Log'!$L$4:$L$503,$A6,'Trade Log'!$E$4:$E$503,"SHORT")) -> 0 | F6: =IF($A6="","",$D6+$E6) -> 0 | G6: =IF($A6="","",SUMIFS('Trade Log'!$Y$4:$Y$503,'Trade Log'!$L$4:$L$503,$A6)) -> 0 | H6: =IF($A6="","",IF($C6=0,"",$F6-$G6)) | I6: =IF($A6="","",$I5+IF($H6="",0,$H6)) -> 0 | J6: =IF($A6="","",Config!$B$4+$I6) -> 1000000 | K6: =IF($A6="","",MAX($J$4:$J6)) -> 1000000 | L6: =IF($A6="","",$J6-$K6) -> 0 | M6: =IF(OR($A6="",$K6=0),"",$L6/$K6) -> 0 | N6: =IF($A6="","",SUMIFS('Trade Log'!$K$4:$K$503,'Trade Log'!$H$4:$H$503,$A6)) -> 0 | O6: =IF(OR($A6="",$H6="",Config!$B$4=0),"",$H6/Config!$B$4) | P6: =IF($A6="","",SUM($H$4:$H6)) -> 0 | Q6: =IF($A6="","",IFERROR((AVERAGE($O$4:$O6)-Config!$B$7/Config!$B$6)/STDEV($O$4:$O6)*SQRT(Config!$B$6),"")) | R6: =IF($A6="","",IFERROR((AVERAGE($O$4:$O6)-Config!$B$7/Config!$B$6)/STDEV($O$4:$O6)*SQRT(Config!$B$6),"")) | S6: =IF($H6="",$S5,IF($H6>0,$S5+1,0)) -> 0 | T6: =IF($H6="",$T5,IF($H6<0,$T5+1,0)) -> 0
A7: =IF($A6="","",$A6+1) -> 46238 | B7: =IF($A7="","",TEXT($A7,"ddd")) -> Tue | C7: =IF($A7="","",COUNTIFS('Trade Log'!$L$4:$L$503,$A7)) -> 0 | D7: =IF($A7="","",SUMIFS('Trade Log'!$Q$4:$Q$503,'Trade Log'!$L$4:$L$503,$A7,'Trade Log'!$E$4:$E$503,"LONG")) -> 0 | E7: =IF($A7="","",SUMIFS('Trade Log'!$Q$4:$Q$503,'Trade Log'!$L$4:$L$503,$A7,'Trade Log'!$E$4:$E$503,"SHORT")) -> 0 | F7: =IF($A7="","",$D7+$E7) -> 0 | G7: =IF($A7="","",SUMIFS('Trade Log'!$Y$4:$Y$503,'Trade Log'!$L$4:$L$503,$A7)) -> 0 | H7: =IF($A7="","",IF($C7=0,"",$F7-$G7)) | I7: =IF($A7="","",$I6+IF($H7="",0,$H7)) -> 0 | J7: =IF($A7="","",Config!$B$4+$I7) -> 1000000 | K7: =IF($A7="","",MAX($J$4:$J7)) -> 1000000 | L7: =IF($A7="","",$J7-$K7) -> 0 | M7: =IF(OR($A7="",$K7=0),"",$L7/$K7) -> 0 | N7: =IF($A7="","",SUMIFS('Trade Log'!$K$4:$K$503,'Trade Log'!$H$4:$H$503,$A7)) -> 0 | O7: =IF(OR($A7="",$H7="",Config!$B$4=0),"",$H7/Config!$B$4) | P7: =IF($A7="","",SUM($H$4:$H7)) -> 0 | Q7: =IF($A7="","",IFERROR((AVERAGE($O$4:$O7)-Config!$B$7/Config!$B$6)/STDEV($O$4:$O7)*SQRT(Config!$B$6),"")) | R7: =IF($A7="","",IFERROR((AVERAGE($O$4:$O7)-Config!$B$7/Config!$B$6)/STDEV($O$4:$O7)*SQRT(Config!$B$6),"")) | S7: =IF($H7="",$S6,IF($H7>0,$S6+1,0)) -> 0 | T7: =IF($H7="",$T6,IF($H7<0,$T6+1,0)) -> 0
A8: =IF($A7="","",$A7+1) -> 46239 | B8: =IF($A8="","",TEXT($A8,"ddd")) -> Wed | C8: =IF($A8="","",COUNTIFS('Trade Log'!$L$4:$L$503,$A8)) -> 0 | D8: =IF($A8="","",SUMIFS('Trade Log'!$Q$4:$Q$503,'Trade Log'!$L$4:$L$503,$A8,'Trade Log'!$E$4:$E$503,"LONG")) -> 0 | E8: =IF($A8="","",SUMIFS('Trade Log'!$Q$4:$Q$503,'Trade Log'!$L$4:$L$503,$A8,'Trade Log'!$E$4:$E$503,"SHORT")) -> 0 | F8: =IF($A8="","",$D8+$E8) -> 0 | G8: =IF($A8="","",SUMIFS('Trade Log'!$Y$4:$Y$503,'Trade Log'!$L$4:$L$503,$A8)) -> 0 | H8: =IF($A8="","",IF($C8=0,"",$F8-$G8)) | I8: =IF($A8="","",$I7+IF($H8="",0,$H8)) -> 0 | J8: =IF($A8="","",Config!$B$4+$I8) -> 1000000 | K8: =IF($A8="","",MAX($J$4:$J8)) -> 1000000 | L8: =IF($A8="","",$J8-$K8) -> 0 | M8: =IF(OR($A8="",$K8=0),"",$L8/$K8) -> 0 | N8: =IF($A8="","",SUMIFS('Trade Log'!$K$4:$K$503,'Trade Log'!$H$4:$H$503,$A8)) -> 0 | O8: =IF(OR($A8="",$H8="",Config!$B$4=0),"",$H8/Config!$B$4) | P8: =IF($A8="","",SUM($H$4:$H8)) -> 0 | Q8: =IF($A8="","",IFERROR((AVERAGE($O$4:$O8)-Config!$B$7/Config!$B$6)/STDEV($O$4:$O8)*SQRT(Config!$B$6),"")) | R8: =IF($A8="","",IFERROR((AVERAGE($O$4:$O8)-Config!$B$7/Config!$B$6)/STDEV($O$4:$O8)*SQRT(Config!$B$6),"")) | S8: =IF($H8="",$S7,IF($H8>0,$S7+1,0)) -> 0 | T8: =IF($H8="",$T7,IF($H8<0,$T7+1,0)) -> 0
A9: =IF($A8="","",$A8+1) -> 46240 | B9: =IF($A9="","",TEXT($A9,"ddd")) -> Thu | C9: =IF($A9="","",COUNTIFS('Trade Log'!$L$4:$L$503,$A9)) -> 0 | D9: =IF($A9="","",SUMIFS('Trade Log'!$Q$4:$Q$503,'Trade Log'!$L$4:$L$503,$A9,'Trade Log'!$E$4:$E$503,"LONG")) -> 0 | E9: =IF($A9="","",SUMIFS('Trade Log'!$Q$4:$Q$503,'Trade Log'!$L$4:$L$503,$A9,'Trade Log'!$E$4:$E$503,"SHORT")) -> 0 | F9: =IF($A9="","",$D9+$E9) -> 0 | G9: =IF($A9="","",SUMIFS('Trade Log'!$Y$4:$Y$503,'Trade Log'!$L$4:$L$503,$A9)) -> 0 | H9: =IF($A9="","",IF($C9=0,"",$F9-$G9)) | I9: =IF($A9="","",$I8+IF($H9="",0,$H9)) -> 0 | J9: =IF($A9="","",Config!$B$4+$I9) -> 1000000 | K9: =IF($A9="","",MAX($J$4:$J9)) -> 1000000 | L9: =IF($A9="","",$J9-$K9) -> 0 | M9: =IF(OR($A9="",$K9=0),"",$L9/$K9) -> 0 | N9: =IF($A9="","",SUMIFS('Trade Log'!$K$4:$K$503,'Trade Log'!$H$4:$H$503,$A9)) -> 0 | O9: =IF(OR($A9="",$H9="",Config!$B$4=0),"",$H9/Config!$B$4) | P9: =IF($A9="","",SUM($H$4:$H9)) -> 0 | Q9: =IF($A9="","",IFERROR((AVERAGE($O$4:$O9)-Config!$B$7/Config!$B$6)/STDEV($O$4:$O9)*SQRT(Config!$B$6),"")) | R9: =IF($A9="","",IFERROR((AVERAGE($O$4:$O9)-Config!$B$7/Config!$B$6)/STDEV($O$4:$O9)*SQRT(Config!$B$6),"")) | S9: =IF($H9="",$S8,IF($H9>0,$S8+1,0)) -> 0 | T9: =IF($H9="",$T8,IF($H9<0,$T8+1,0)) -> 0
A10: =IF($A9="","",$A9+1) -> 46241 | B10: =IF($A10="","",TEXT($A10,"ddd")) -> Fri | C10: =IF($A10="","",COUNTIFS('Trade Log'!$L$4:$L$503,$A10)) -> 0 | D10: =IF($A10="","",SUMIFS('Trade Log'!$Q$4:$Q$503,'Trade Log'!$L$4:$L$503,$A10,'Trade Log'!$E$4:$E$503,"LONG")) -> 0 | E10: =IF($A10="","",SUMIFS('Trade Log'!$Q$4:$Q$503,'Trade Log'!$L$4:$L$503,$A10,'Trade Log'!$E$4:$E$503,"SHORT")) -> 0 | F10: =IF($A10="","",$D10+$E10) -> 0 | G10: =IF($A10="","",SUMIFS('Trade Log'!$Y$4:$Y$503,'Trade Log'!$L$4:$L$503,$A10)) -> 0 | H10: =IF($A10="","",IF($C10=0,"",$F10-$G10)) | I10: =IF($A10="","",$I9+IF($H10="",0,$H10)) -> 0 | J10: =IF($A10="","",Config!$B$4+$I10) -> 1000000 | K10: =IF($A10="","",MAX($J$4:$J10)) -> 1000000 | L10: =IF($A10="","",$J10-$K10) -> 0 | M10: =IF(OR($A10="",$K10=0),"",$L10/$K10) -> 0 | N10: =IF($A10="","",SUMIFS('Trade Log'!$K$4:$K$503,'Trade Log'!$H$4:$H$503,$A10)) -> 0 | O10: =IF(OR($A10="",$H10="",Config!$B$4=0),"",$H10/Config!$B$4) | P10: =IF($A10="","",SUM($H$4:$H10)) -> 0 | Q10: =IF($A10="","",IFERROR((AVERAGE($O$4:$O10)-Config!$B$7/Config!$B$6)/STDEV($O$4:$O10)*SQRT(Config!$B$6),"")) | R10: =IF($A10="","",IFERROR((AVERAGE($O$4:$O10)-Config!$B$7/Config!$B$6)/STDEV($O$4:$O10)*SQRT(Config!$B$6),"")) | S10: =IF($H10="",$S9,IF($H10>0,$S9+1,0)) -> 0 | T10: =IF($H10="",$T9,IF($H10<0,$T9+1,0)) -> 0
A11: =IF($A10="","",$A10+1) -> 46242 | B11: =IF($A11="","",TEXT($A11,"ddd")) -> Sat | C11: =IF($A11="","",COUNTIFS('Trade Log'!$L$4:$L$503,$A11)) -> 0 | D11: =IF($A11="","",SUMIFS('Trade Log'!$Q$4:$Q$503,'Trade Log'!$L$4:$L$503,$A11,'Trade Log'!$E$4:$E$503,"LONG")) -> 0 | E11: =IF($A11="","",SUMIFS('Trade Log'!$Q$4:$Q$503,'Trade Log'!$L$4:$L$503,$A11,'Trade Log'!$E$4:$E$503,"SHORT")) -> 0 | F11: =IF($A11="","",$D11+$E11) -> 0 | G11: =IF($A11="","",SUMIFS('Trade Log'!$Y$4:$Y$503,'Trade Log'!$L$4:$L$503,$A11)) -> 0 | H11: =IF($A11="","",IF($C11=0,"",$F11-$G11)) | I11: =IF($A11="","",$I10+IF($H11="",0,$H11)) -> 0 | J11: =IF($A11="","",Config!$B$4+$I11) -> 1000000 | K11: =IF($A11="","",MAX($J$4:$J11)) -> 1000000 | L11: =IF($A11="","",$J11-$K11) -> 0 | M11: =IF(OR($A11="",$K11=0),"",$L11/$K11) -> 0 | N11: =IF($A11="","",SUMIFS('Trade Log'!$K$4:$K$503,'Trade Log'!$H$4:$H$503,$A11)) -> 0 | O11: =IF(OR($A11="",$H11="",Config!$B$4=0),"",$H11/Config!$B$4) | P11: =IF($A11="","",SUM($H$4:$H11)) -> 0 | Q11: =IF($A11="","",IFERROR((AVERAGE($O$4:$O11)-Config!$B$7/Config!$B$6)/STDEV($O$4:$O11)*SQRT(Config!$B$6),"")) | R11: =IF($A11="","",IFERROR((AVERAGE($O$4:$O11)-Config!$B$7/Config!$B$6)/STDEV($O$4:$O11)*SQRT(Config!$B$6),"")) | S11: =IF($H11="",$S10,IF($H11>0,$S10+1,0)) -> 0 | T11: =IF($H11="",$T10,IF($H11<0,$T10+1,0)) -> 0
A12: =IF($A11="","",$A11+1) -> 46243 | B12: =IF($A12="","",TEXT($A12,"ddd")) -> Sun | C12: =IF($A12="","",COUNTIFS('Trade Log'!$L$4:$L$503,$A12)) -> 0 | D12: =IF($A12="","",SUMIFS('Trade Log'!$Q$4:$Q$503,'Trade Log'!$L$4:$L$503,$A12,'Trade Log'!$E$4:$E$503,"LONG")) -> 0 | E12: =IF($A12="","",SUMIFS('Trade Log'!$Q$4:$Q$503,'Trade Log'!$L$4:$L$503,$A12,'Trade Log'!$E$4:$E$503,"SHORT")) -> 0 | F12: =IF($A12="","",$D12+$E12) -> 0 | G12: =IF($A12="","",SUMIFS('Trade Log'!$Y$4:$Y$503,'Trade Log'!$L$4:$L$503,$A12)) -> 0 | H12: =IF($A12="","",IF($C12=0,"",$F12-$G12)) | I12: =IF($A12="","",$I11+IF($H12="",0,$H12)) -> 0 | J12: =IF($A12="","",Config!$B$4+$I12) -> 1000000 | K12: =IF($A12="","",MAX($J$4:$J12)) -> 1000000 | L12: =IF($A12="","",$J12-$K12) -> 0 | M12: =IF(OR($A12="",$K12=0),"",$L12/$K12) -> 0 | N12: =IF($A12="","",SUMIFS('Trade Log'!$K$4:$K$503,'Trade Log'!$H$4:$H$503,$A12)) -> 0 | O12: =IF(OR($A12="",$H12="",Config!$B$4=0),"",$H12/Config!$B$4) | P12: =IF($A12="","",SUM($H$4:$H12)) -> 0 | Q12: =IF($A12="","",IFERROR((AVERAGE($O$4:$O12)-Config!$B$7/Config!$B$6)/STDEV($O$4:$O12)*SQRT(Config!$B$6),"")) | R12: =IF($A12="","",IFERROR((AVERAGE($O$4:$O12)-Config!$B$7/Config!$B$6)/STDEV($O$4:$O12)*SQRT(Config!$B$6),"")) | S12: =IF($H12="",$S11,IF($H12>0,$S11+1,0)) -> 0 | T12: =IF($H12="",$T11,IF($H12<0,$T11+1,0)) -> 0
A13: =IF($A12="","",$A12+1) -> 46244 | B13: =IF($A13="","",TEXT($A13,"ddd")) -> Mon | C13: =IF($A13="","",COUNTIFS('Trade Log'!$L$4:$L$503,$A13)) -> 0 | D13: =IF($A13="","",SUMIFS('Trade Log'!$Q$4:$Q$503,'Trade Log'!$L$4:$L$503,$A13,'Trade Log'!$E$4:$E$503,"LONG")) -> 0 | E13: =IF($A13="","",SUMIFS('Trade Log'!$Q$4:$Q$503,'Trade Log'!$L$4:$L$503,$A13,'Trade Log'!$E$4:$E$503,"SHORT")) -> 0 | F13: =IF($A13="","",$D13+$E13) -> 0 | G13: =IF($A13="","",SUMIFS('Trade Log'!$Y$4:$Y$503,'Trade Log'!$L$4:$L$503,$A13)) -> 0 | H13: =IF($A13="","",IF($C13=0,"",$F13-$G13)) | I13: =IF($A13="","",$I12+IF($H13="",0,$H13)) -> 0 | J13: =IF($A13="","",Config!$B$4+$I13) -> 1000000 | K13: =IF($A13="","",MAX($J$4:$J13)) -> 1000000 | L13: =IF($A13="","",$J13-$K13) -> 0 | M13: =IF(OR($A13="",$K13=0),"",$L13/$K13) -> 0 | N13: =IF($A13="","",SUMIFS('Trade Log'!$K$4:$K$503,'Trade Log'!$H$4:$H$503,$A13)) -> 0 | O13: =IF(OR($A13="",$H13="",Config!$B$4=0),"",$H13/Config!$B$4) | P13: =IF($A13="","",SUM($H$4:$H13)) -> 0 | Q13: =IF($A13="","",IFERROR((AVERAGE($O$4:$O13)-Config!$B$7/Config!$B$6)/STDEV($O$4:$O13)*SQRT(Config!$B$6),"")) | R13: =IF($A13="","",IFERROR((AVERAGE($O$4:$O13)-Config!$B$7/Config!$B$6)/STDEV($O$4:$O13)*SQRT(Config!$B$6),"")) | S13: =IF($H13="",$S12,IF($H13>0,$S12+1,0)) -> 0 | T13: =IF($H13="",$T12,IF($H13<0,$T12+1,0)) -> 0
A14: =IF($A13="","",$A13+1) -> 46245 | B14: =IF($A14="","",TEXT($A14,"ddd")) -> Tue | C14: =IF($A14="","",COUNTIFS('Trade Log'!$L$4:$L$503,$A14)) -> 0 | D14: =IF($A14="","",SUMIFS('Trade Log'!$Q$4:$Q$503,'Trade Log'!$L$4:$L$503,$A14,'Trade Log'!$E$4:$E$503,"LONG")) -> 0 | E14: =IF($A14="","",SUMIFS('Trade Log'!$Q$4:$Q$503,'Trade Log'!$L$4:$L$503,$A14,'Trade Log'!$E$4:$E$503,"SHORT")) -> 0 | F14: =IF($A14="","",$D14+$E14) -> 0 | G14: =IF($A14="","",SUMIFS('Trade Log'!$Y$4:$Y$503,'Trade Log'!$L$4:$L$503,$A14)) -> 0 | H14: =IF($A14="","",IF($C14=0,"",$F14-$G14)) | I14: =IF($A14="","",$I13+IF($H14="",0,$H14)) -> 0 | J14: =IF($A14="","",Config!$B$4+$I14) -> 1000000 | K14: =IF($A14="","",MAX($J$4:$J14)) -> 1000000 | L14: =IF($A14="","",$J14-$K14) -> 0 | M14: =IF(OR($A14="",$K14=0),"",$L14/$K14) -> 0 | N14: =IF($A14="","",SUMIFS('Trade Log'!$K$4:$K$503,'Trade Log'!$H$4:$H$503,$A14)) -> 0 | O14: =IF(OR($A14="",$H14="",Config!$B$4=0),"",$H14/Config!$B$4) | P14: =IF($A14="","",SUM($H$4:$H14)) -> 0 | Q14: =IF($A14="","",IFERROR((AVERAGE($O$4:$O14)-Config!$B$7/Config!$B$6)/STDEV($O$4:$O14)*SQRT(Config!$B$6),"")) | R14: =IF($A14="","",IFERROR((AVERAGE($O$4:$O14)-Config!$B$7/Config!$B$6)/STDEV($O$4:$O14)*SQRT(Config!$B$6),"")) | S14: =IF($H14="",$S13,IF($H14>0,$S13+1,0)) -> 0 | T14: =IF($H14="",$T13,IF($H14<0,$T13+1,0)) -> 0
A15: =IF($A14="","",$A14+1) -> 46246 | B15: =IF($A15="","",TEXT($A15,"ddd")) -> Wed | C15: =IF($A15="","",COUNTIFS('Trade Log'!$L$4:$L$503,$A15)) -> 0 | D15: =IF($A15="","",SUMIFS('Trade Log'!$Q$4:$Q$503,'Trade Log'!$L$4:$L$503,$A15,'Trade Log'!$E$4:$E$503,"LONG")) -> 0 | E15: =IF($A15="","",SUMIFS('Trade Log'!$Q$4:$Q$503,'Trade Log'!$L$4:$L$503,$A15,'Trade Log'!$E$4:$E$503,"SHORT")) -> 0 | F15: =IF($A15="","",$D15+$E15) -> 0 | G15: =IF($A15="","",SUMIFS('Trade Log'!$Y$4:$Y$503,'Trade Log'!$L$4:$L$503,$A15)) -> 0 | H15: =IF($A15="","",IF($C15=0,"",$F15-$G15)) | I15: =IF($A15="","",$I14+IF($H15="",0,$H15)) -> 0 | J15: =IF($A15="","",Config!$B$4+$I15) -> 1000000 | K15: =IF($A15="","",MAX($J$4:$J15)) -> 1000000 | L15: =IF($A15="","",$J15-$K15) -> 0 | M15: =IF(OR($A15="",$K15=0),"",$L15/$K15) -> 0 | N15: =IF($A15="","",SUMIFS('Trade Log'!$K$4:$K$503,'Trade Log'!$H$4:$H$503,$A15)) -> 0 | O15: =IF(OR($A15="",$H15="",Config!$B$4=0),"",$H15/Config!$B$4) | P15: =IF($A15="","",SUM($H$4:$H15)) -> 0 | Q15: =IF($A15="","",IFERROR((AVERAGE($O$4:$O15)-Config!$B$7/Config!$B$6)/STDEV($O$4:$O15)*SQRT(Config!$B$6),"")) | R15: =IF($A15="","",IFERROR((AVERAGE($O$4:$O15)-Config!$B$7/Config!$B$6)/STDEV($O$4:$O15)*SQRT(Config!$B$6),"")) | S15: =IF($H15="",$S14,IF($H15>0,$S14+1,0)) -> 0 | T15: =IF($H15="",$T14,IF($H15<0,$T14+1,0)) -> 0
A16: =IF($A15="","",$A15+1) -> 46247 | B16: =IF($A16="","",TEXT($A16,"ddd")) -> Thu | C16: =IF($A16="","",COUNTIFS('Trade Log'!$L$4:$L$503,$A16)) -> 0 | D16: =IF($A16="","",SUMIFS('Trade Log'!$Q$4:$Q$503,'Trade Log'!$L$4:$L$503,$A16,'Trade Log'!$E$4:$E$503,"LONG")) -> 0 | E16: =IF($A16="","",SUMIFS('Trade Log'!$Q$4:$Q$503,'Trade Log'!$L$4:$L$503,$A16,'Trade Log'!$E$4:$E$503,"SHORT")) -> 0 | F16: =IF($A16="","",$D16+$E16) -> 0 | G16: =IF($A16="","",SUMIFS('Trade Log'!$Y$4:$Y$503,'Trade Log'!$L$4:$L$503,$A16)) -> 0 | H16: =IF($A16="","",IF($C16=0,"",$F16-$G16)) | I16: =IF($A16="","",$I15+IF($H16="",0,$H16)) -> 0 | J16: =IF($A16="","",Config!$B$4+$I16) -> 1000000 | K16: =IF($A16="","",MAX($J$4:$J16)) -> 1000000 | L16: =IF($A16="","",$J16-$K16) -> 0 | M16: =IF(OR($A16="",$K16=0),"",$L16/$K16) -> 0 | N16: =IF($A16="","",SUMIFS('Trade Log'!$K$4:$K$503,'Trade Log'!$H$4:$H$503,$A16)) -> 0 | O16: =IF(OR($A16="",$H16="",Config!$B$4=0),"",$H16/Config!$B$4) | P16: =IF($A16="","",SUM($H$4:$H16)) -> 0 | Q16: =IF($A16="","",IFERROR((AVERAGE($O$4:$O16)-Config!$B$7/Config!$B$6)/STDEV($O$4:$O16)*SQRT(Config!$B$6),"")) | R16: =IF($A16="","",IFERROR((AVERAGE($O$4:$O16)-Config!$B$7/Config!$B$6)/STDEV($O$4:$O16)*SQRT(Config!$B$6),"")) | S16: =IF($H16="",$S15,IF($H16>0,$S15+1,0)) -> 0 | T16: =IF($H16="",$T15,IF($H16<0,$T15+1,0)) -> 0
... A23: =IF($A22="","",$A22+1) -> 46254 | B23: =IF($A23="","",TEXT($A23,"ddd")) -> Thu | C23: =IF($A23="","",COUNTIFS('Trade Log'!$L$4:$L$503,$A23)) -> 0 | D23: =IF($A23="","",SUMIFS('Trade Log'!$Q$4:$Q$503,'Trade Log'!$L$4:$L$503,$A23,'Trade Log'!$E$4:$E$503,"LONG")) -> 0 | E23: =IF($A23="","",SUMIFS('Trade Log'!$Q$4:$Q$503,'Trade Log'!$L$4:$L$503,$A23,'Trade Log'!$E$4:$E$503,"SHORT")) -> 0 | F23: =IF($A23="","",$D23+$E23) -> 0 | G23: =IF($A23="","",SUMIFS('Trade Log'!$Y$4:$Y$503,'Trade Log'!$L$4:$L$503,$A23)) -> 0 | H23: =IF($A23="","",IF($C23=0,"",$F23-$G23)) | I23: =IF($A23="","",$I22+IF($H23="",0,$H23)) -> 23918.552 | J23: =IF($A23="","",Config!$B$4+$I23) -> 1023918.6 | K23: =IF($A23="","",MAX($J$4:$J23)) -> 1023918.6 | L23: =IF($A23="","",$J23-$K23) -> 0 | M23: =IF(OR($A23="",$K23=0),"",$L23/$K23) -> 0 | N23: =IF($A23="","",SUMIFS('Trade Log'!$K$4:$K$503,'Trade Log'!$H$4:$H$503,$A23)) -> 0 | O23: =IF(OR($A23="",$H23="",Config!$B$4=0),"",$H23/Config!$B$4) | P23: =IF($A23="","",SUM($H$4:$H23)) -> 23918.552 | Q23: =IF($A23="","",IFERROR((AVERAGE($O$4:$O23)-Config!$B$7/Config!$B$6)/STDEV($O$4:$O23)*SQRT(Config!$B$6),"")) | R23: =IF($A23="","",IFERROR((AVERAGE($O$4:$O23)-Config!$B$7/Config!$B$6)/STDEV($O$4:$O23)*SQRT(Config!$B$6),"")) | S23: =IF($H23="",$S22,IF($H23>0,$S22+1,0)) -> 1 | T23: =IF($H23="",$T22,IF($H23<0,$T22+1,0)) -> 0
A24: =IF($A23="","",$A23+1) -> 46255 | B24: =IF($A24="","",TEXT($A24,"ddd")) -> Fri | C24: =IF($A24="","",COUNTIFS('Trade Log'!$L$4:$L$503,$A24)) -> 0 | D24: =IF($A24="","",SUMIFS('Trade Log'!$Q$4:$Q$503,'Trade Log'!$L$4:$L$503,$A24,'Trade Log'!$E$4:$E$503,"LONG")) -> 0 | E24: =IF($A24="","",SUMIFS('Trade Log'!$Q$4:$Q$503,'Trade Log'!$L$4:$L$503,$A24,'Trade Log'!$E$4:$E$503,"SHORT")) -> 0 | F24: =IF($A24="","",$D24+$E24) -> 0 | G24: =IF($A24="","",SUMIFS('Trade Log'!$Y$4:$Y$503,'Trade Log'!$L$4:$L$503,$A24)) -> 0 | H24: =IF($A24="","",IF($C24=0,"",$F24-$G24)) | I24: =IF($A24="","",$I23+IF($H24="",0,$H24)) -> 23918.552 | J24: =IF($A24="","",Config!$B$4+$I24) -> 1023918.6 | K24: =IF($A24="","",MAX($J$4:$J24)) -> 1023918.6 | L24: =IF($A24="","",$J24-$K24) -> 0 | M24: =IF(OR($A24="",$K24=0),"",$L24/$K24) -> 0 | N24: =IF($A24="","",SUMIFS('Trade Log'!$K$4:$K$503,'Trade Log'!$H$4:$H$503,$A24)) -> 0 | O24: =IF(OR($A24="",$H24="",Config!$B$4=0),"",$H24/Config!$B$4) | P24: =IF($A24="","",SUM($H$5:$H24)) -> 23918.552 | Q24: =IF($A24="","",IFERROR((AVERAGE($O$5:$O24)-Config!$B$7/Config!$B$6)/STDEV($O$5:$O24)*SQRT(Config!$B$6),"")) | R24: =IF($A24="","",IFERROR((AVERAGE($O$4:$O24)-Config!$B$7/Config!$B$6)/STDEV($O$4:$O24)*SQRT(Config!$B$6),"")) | S24: =IF($H24="",$S23,IF($H24>0,$S23+1,0)) -> 1 | T24: =IF($H24="",$T23,IF($H24<0,$T23+1,0)) -> 0
A25: =IF($A24="","",$A24+1) -> 46256 | B25: =IF($A25="","",TEXT($A25,"ddd")) -> Sat | C25: =IF($A25="","",COUNTIFS('Trade Log'!$L$4:$L$503,$A25)) -> 0 | D25: =IF($A25="","",SUMIFS('Trade Log'!$Q$4:$Q$503,'Trade Log'!$L$4:$L$503,$A25,'Trade Log'!$E$4:$E$503,"LONG")) -> 0 | E25: =IF($A25="","",SUMIFS('Trade Log'!$Q$4:$Q$503,'Trade Log'!$L$4:$L$503,$A25,'Trade Log'!$E$4:$E$503,"SHORT")) -> 0 | F25: =IF($A25="","",$D25+$E25) -> 0 | G25: =IF($A25="","",SUMIFS('Trade Log'!$Y$4:$Y$503,'Trade Log'!$L$4:$L$503,$A25)) -> 0 | H25: =IF($A25="","",IF($C25=0,"",$F25-$G25)) | I25: =IF($A25="","",$I24+IF($H25="",0,$H25)) -> 23918.552 | J25: =IF($A25="","",Config!$B$4+$I25) -> 1023918.6 | K25: =IF($A25="","",MAX($J$4:$J25)) -> 1023918.6 | L25: =IF($A25="","",$J25-$K25) -> 0 | M25: =IF(OR($A25="",$K25=0),"",$L25/$K25) -> 0 | N25: =IF($A25="","",SUMIFS('Trade Log'!$K$4:$K$503,'Trade Log'!$H$4:$H$503,$A25)) -> 0 | O25: =IF(OR($A25="",$H25="",Config!$B$4=0),"",$H25/Config!$B$4) | P25: =IF($A25="","",SUM($H$6:$H25)) -> 23918.552 | Q25: =IF($A25="","",IFERROR((AVERAGE($O$6:$O25)-Config!$B$7/Config!$B$6)/STDEV($O$6:$O25)*SQRT(Config!$B$6),"")) | R25: =IF($A25="","",IFERROR((AVERAGE($O$4:$O25)-Config!$B$7/Config!$B$6)/STDEV($O$4:$O25)*SQRT(Config!$B$6),"")) | S25: =IF($H25="",$S24,IF($H25>0,$S24+1,0)) -> 1 | T25: =IF($H25="",$T24,IF($H25<0,$T24+1,0)) -> 0
A26: =IF($A25="","",$A25+1) -> 46257 | B26: =IF($A26="","",TEXT($A26,"ddd")) -> Sun | C26: =IF($A26="","",COUNTIFS('Trade Log'!$L$4:$L$503,$A26)) -> 0 | D26: =IF($A26="","",SUMIFS('Trade Log'!$Q$4:$Q$503,'Trade Log'!$L$4:$L$503,$A26,'Trade Log'!$E$4:$E$503,"LONG")) -> 0 | E26: =IF($A26="","",SUMIFS('Trade Log'!$Q$4:$Q$503,'Trade Log'!$L$4:$L$503,$A26,'Trade Log'!$E$4:$E$503,"SHORT")) -> 0 | F26: =IF($A26="","",$D26+$E26) -> 0 | G26: =IF($A26="","",SUMIFS('Trade Log'!$Y$4:$Y$503,'Trade Log'!$L$4:$L$503,$A26)) -> 0 | H26: =IF($A26="","",IF($C26=0,"",$F26-$G26)) | I26: =IF($A26="","",$I25+IF($H26="",0,$H26)) -> 23918.552 | J26: =IF($A26="","",Config!$B$4+$I26) -> 1023918.6 | K26: =IF($A26="","",MAX($J$4:$J26)) -> 1023918.6 | L26: =IF($A26="","",$J26-$K26) -> 0 | M26: =IF(OR($A26="",$K26=0),"",$L26/$K26) -> 0 | N26: =IF($A26="","",SUMIFS('Trade Log'!$K$4:$K$503,'Trade Log'!$H$4:$H$503,$A26)) -> 0 | O26: =IF(OR($A26="",$H26="",Config!$B$4=0),"",$H26/Config!$B$4) | P26: =IF($A26="","",SUM($H$7:$H26)) -> 23918.552 | Q26: =IF($A26="","",IFERROR((AVERAGE($O$7:$O26)-Config!$B$7/Config!$B$6)/STDEV($O$7:$O26)*SQRT(Config!$B$6),"")) | R26: =IF($A26="","",IFERROR((AVERAGE($O$4:$O26)-Config!$B$7/Config!$B$6)/STDEV($O$4:$O26)*SQRT(Config!$B$6),"")) | S26: =IF($H26="",$S25,IF($H26>0,$S25+1,0)) -> 1 | T26: =IF($H26="",$T25,IF($H26<0,$T25+1,0)) -> 0
A27: =IF($A26="","",$A26+1) -> 46258 | B27: =IF($A27="","",TEXT($A27,"ddd")) -> Mon | C27: =IF($A27="","",COUNTIFS('Trade Log'!$L$4:$L$503,$A27)) -> 0 | D27: =IF($A27="","",SUMIFS('Trade Log'!$Q$4:$Q$503,'Trade Log'!$L$4:$L$503,$A27,'Trade Log'!$E$4:$E$503,"LONG")) -> 0 | E27: =IF($A27="","",SUMIFS('Trade Log'!$Q$4:$Q$503,'Trade Log'!$L$4:$L$503,$A27,'Trade Log'!$E$4:$E$503,"SHORT")) -> 0 | F27: =IF($A27="","",$D27+$E27) -> 0 | G27: =IF($A27="","",SUMIFS('Trade Log'!$Y$4:$Y$503,'Trade Log'!$L$4:$L$503,$A27)) -> 0 | H27: =IF($A27="","",IF($C27=0,"",$F27-$G27)) | I27: =IF($A27="","",$I26+IF($H27="",0,$H27)) -> 23918.552 | J27: =IF($A27="","",Config!$B$4+$I27) -> 1023918.6 | K27: =IF($A27="","",MAX($J$4:$J27)) -> 1023918.6 | L27: =IF($A27="","",$J27-$K27) -> 0 | M27: =IF(OR($A27="",$K27=0),"",$L27/$K27) -> 0 | N27: =IF($A27="","",SUMIFS('Trade Log'!$K$4:$K$503,'Trade Log'!$H$4:$H$503,$A27)) -> 0 | O27: =IF(OR($A27="",$H27="",Config!$B$4=0),"",$H27/Config!$B$4) | P27: =IF($A27="","",SUM($H$8:$H27)) -> 23918.552 | Q27: =IF($A27="","",IFERROR((AVERAGE($O$8:$O27)-Config!$B$7/Config!$B$6)/STDEV($O$8:$O27)*SQRT(Config!$B$6),"")) | R27: =IF($A27="","",IFERROR((AVERAGE($O$4:$O27)-Config!$B$7/Config!$B$6)/STDEV($O$4:$O27)*SQRT(Config!$B$6),"")) | S27: =IF($H27="",$S26,IF($H27>0,$S26+1,0)) -> 1 | T27: =IF($H27="",$T26,IF($H27<0,$T26+1,0)) -> 0
A28: =IF($A27="","",$A27+1) -> 46259 | B28: =IF($A28="","",TEXT($A28,"ddd")) -> Tue | C28: =IF($A28="","",COUNTIFS('Trade Log'!$L$4:$L$503,$A28)) -> 0 | D28: =IF($A28="","",SUMIFS('Trade Log'!$Q$4:$Q$503,'Trade Log'!$L$4:$L$503,$A28,'Trade Log'!$E$4:$E$503,"LONG")) -> 0 | E28: =IF($A28="","",SUMIFS('Trade Log'!$Q$4:$Q$503,'Trade Log'!$L$4:$L$503,$A28,'Trade Log'!$E$4:$E$503,"SHORT")) -> 0 | F28: =IF($A28="","",$D28+$E28) -> 0 | G28: =IF($A28="","",SUMIFS('Trade Log'!$Y$4:$Y$503,'Trade Log'!$L$4:$L$503,$A28)) -> 0 | H28: =IF($A28="","",IF($C28=0,"",$F28-$G28)) | I28: =IF($A28="","",$I27+IF($H28="",0,$H28)) -> 23918.552 | J28: =IF($A28="","",Config!$B$4+$I28) -> 1023918.6 | K28: =IF($A28="","",MAX($J$4:$J28)) -> 1023918.6 | L28: =IF($A28="","",$J28-$K28) -> 0 | M28: =IF(OR($A28="",$K28=0),"",$L28/$K28) -> 0 | N28: =IF($A28="","",SUMIFS('Trade Log'!$K$4:$K$503,'Trade Log'!$H$4:$H$503,$A28)) -> 0 | O28: =IF(OR($A28="",$H28="",Config!$B$4=0),"",$H28/Config!$B$4) | P28: =IF($A28="","",SUM($H$9:$H28)) -> 23918.552 | Q28: =IF($A28="","",IFERROR((AVERAGE($O$9:$O28)-Config!$B$7/Config!$B$6)/STDEV($O$9:$O28)*SQRT(Config!$B$6),"")) | R28: =IF($A28="","",IFERROR((AVERAGE($O$4:$O28)-Config!$B$7/Config!$B$6)/STDEV($O$4:$O28)*SQRT(Config!$B$6),"")) | S28: =IF($H28="",$S27,IF($H28>0,$S27+1,0)) -> 1 | T28: =IF($H28="",$T27,IF($H28<0,$T27+1,0)) -> 0
A29: =IF($A28="","",$A28+1) -> 46260 | B29: =IF($A29="","",TEXT($A29,"ddd")) -> Wed | C29: =IF($A29="","",COUNTIFS('Trade Log'!$L$4:$L$503,$A29)) -> 0 | D29: =IF($A29="","",SUMIFS('Trade Log'!$Q$4:$Q$503,'Trade Log'!$L$4:$L$503,$A29,'Trade Log'!$E$4:$E$503,"LONG")) -> 0 | E29: =IF($A29="","",SUMIFS('Trade Log'!$Q$4:$Q$503,'Trade Log'!$L$4:$L$503,$A29,'Trade Log'!$E$4:$E$503,"SHORT")) -> 0 | F29: =IF($A29="","",$D29+$E29) -> 0 | G29: =IF($A29="","",SUMIFS('Trade Log'!$Y$4:$Y$503,'Trade Log'!$L$4:$L$503,$A29)) -> 0 | H29: =IF($A29="","",IF($C29=0,"",$F29-$G29)) | I29: =IF($A29="","",$I28+IF($H29="",0,$H29)) -> 23918.552 | J29: =IF($A29="","",Config!$B$4+$I29) -> 1023918.6 | K29: =IF($A29="","",MAX($J$4:$J29)) -> 1023918.6 | L29: =IF($A29="","",$J29-$K29) -> 0 | M29: =IF(OR($A29="",$K29=0),"",$L29/$K29) -> 0 | N29: =IF($A29="","",SUMIFS('Trade Log'!$K$4:$K$503,'Trade Log'!$H$4:$H$503,$A29)) -> 0 | O29: =IF(OR($A29="",$H29="",Config!$B$4=0),"",$H29/Config!$B$4) | P29: =IF($A29="","",SUM($H$10:$H29)) -> 23918.552 | Q29: =IF($A29="","",IFERROR((AVERAGE($O$10:$O29)-Config!$B$7/Config!$B$6)/STDEV($O$10:$O29)*SQRT(Config!$B$6),"")) | R29: =IF($A29="","",IFERROR((AVERAGE($O$4:$O29)-Config!$B$7/Config!$B$6)/STDEV($O$4:$O29)*SQRT(Config!$B$6),"")) | S29: =IF($H29="",$S28,IF($H29>0,$S28+1,0)) -> 1 | T29: =IF($H29="",$T28,IF($H29<0,$T28+1,0)) -> 0
A30: =IF($A29="","",$A29+1) -> 46261 | B30: =IF($A30="","",TEXT($A30,"ddd")) -> Thu | C30: =IF($A30="","",COUNTIFS('Trade Log'!$L$4:$L$503,$A30)) -> 0 | D30: =IF($A30="","",SUMIFS('Trade Log'!$Q$4:$Q$503,'Trade Log'!$L$4:$L$503,$A30,'Trade Log'!$E$4:$E$503,"LONG")) -> 0 | E30: =IF($A30="","",SUMIFS('Trade Log'!$Q$4:$Q$503,'Trade Log'!$L$4:$L$503,$A30,'Trade Log'!$E$4:$E$503,"SHORT")) -> 0 | F30: =IF($A30="","",$D30+$E30) -> 0 | G30: =IF($A30="","",SUMIFS('Trade Log'!$Y$4:$Y$503,'Trade Log'!$L$4:$L$503,$A30)) -> 0 | H30: =IF($A30="","",IF($C30=0,"",$F30-$G30)) | I30: =IF($A30="","",$I29+IF($H30="",0,$H30)) -> 23918.552 | J30: =IF($A30="","",Config!$B$4+$I30) -> 1023918.6 | K30: =IF($A30="","",MAX($J$4:$J30)) -> 1023918.6 | L30: =IF($A30="","",$J30-$K30) -> 0 | M30: =IF(OR($A30="",$K30=0),"",$L30/$K30) -> 0 | N30: =IF($A30="","",SUMIFS('Trade Log'!$K$4:$K$503,'Trade Log'!$H$4:$H$503,$A30)) -> 0 | O30: =IF(OR($A30="",$H30="",Config!$B$4=0),"",$H30/Config!$B$4) | P30: =IF($A30="","",SUM($H$11:$H30)) -> 23918.552 | Q30: =IF($A30="","",IFERROR((AVERAGE($O$11:$O30)-Config!$B$7/Config!$B$6)/STDEV($O$11:$O30)*SQRT(Config!$B$6),"")) | R30: =IF($A30="","",IFERROR((AVERAGE($O$4:$O30)-Config!$B$7/Config!$B$6)/STDEV($O$4:$O30)*SQRT(Config!$B$6),"")) | S30: =IF($H30="",$S29,IF($H30>0,$S29+1,0)) -> 1 | T30: =IF($H30="",$T29,IF($H30<0,$T29+1,0)) -> 0
A31: =IF($A30="","",$A30+1) -> 46262 | B31: =IF($A31="","",TEXT($A31,"ddd")) -> Fri | C31: =IF($A31="","",COUNTIFS('Trade Log'!$L$4:$L$503,$A31)) -> 0 | D31: =IF($A31="","",SUMIFS('Trade Log'!$Q$4:$Q$503,'Trade Log'!$L$4:$L$503,$A31,'Trade Log'!$E$4:$E$503,"LONG")) -> 0 | E31: =IF($A31="","",SUMIFS('Trade Log'!$Q$4:$Q$503,'Trade Log'!$L$4:$L$503,$A31,'Trade Log'!$E$4:$E$503,"SHORT")) -> 0 | F31: =IF($A31="","",$D31+$E31) -> 0 | G31: =IF($A31="","",SUMIFS('Trade Log'!$Y$4:$Y$503,'Trade Log'!$L$4:$L$503,$A31)) -> 0 | H31: =IF($A31="","",IF($C31=0,"",$F31-$G31)) | I31: =IF($A31="","",$I30+IF($H31="",0,$H31)) -> 23918.552 | J31: =IF($A31="","",Config!$B$4+$I31) -> 1023918.6 | K31: =IF($A31="","",MAX($J$4:$J31)) -> 1023918.6 | L31: =IF($A31="","",$J31-$K31) -> 0 | M31: =IF(OR($A31="",$K31=0),"",$L31/$K31) -> 0 | N31: =IF($A31="","",SUMIFS('Trade Log'!$K$4:$K$503,'Trade Log'!$H$4:$H$503,$A31)) -> 0 | O31: =IF(OR($A31="",$H31="",Config!$B$4=0),"",$H31/Config!$B$4) | P31: =IF($A31="","",SUM($H$12:$H31)) -> 23918.552 | Q31: =IF($A31="","",IFERROR((AVERAGE($O$12:$O31)-Config!$B$7/Config!$B$6)/STDEV($O$12:$O31)*SQRT(Config!$B$6),"")) | R31: =IF($A31="","",IFERROR((AVERAGE($O$4:$O31)-Config!$B$7/Config!$B$6)/STDEV($O$4:$O31)*SQRT(Config!$B$6),"")) | S31: =IF($H31="",$S30,IF($H31>0,$S30+1,0)) -> 1 | T31: =IF($H31="",$T30,IF($H31<0,$T30+1,0)) -> 0
A32: =IF($A31="","",$A31+1) -> 46263 | B32: =IF($A32="","",TEXT($A32,"ddd")) -> Sat | C32: =IF($A32="","",COUNTIFS('Trade Log'!$L$4:$L$503,$A32)) -> 0 | D32: =IF($A32="","",SUMIFS('Trade Log'!$Q$4:$Q$503,'Trade Log'!$L$4:$L$503,$A32,'Trade Log'!$E$4:$E$503,"LONG")) -> 0 | E32: =IF($A32="","",SUMIFS('Trade Log'!$Q$4:$Q$503,'Trade Log'!$L$4:$L$503,$A32,'Trade Log'!$E$4:$E$503,"SHORT")) -> 0 | F32: =IF($A32="","",$D32+$E32) -> 0 | G32: =IF($A32="","",SUMIFS('Trade Log'!$Y$4:$Y$503,'Trade Log'!$L$4:$L$503,$A32)) -> 0 | H32: =IF($A32="","",IF($C32=0,"",$F32-$G32)) | I32: =IF($A32="","",$I31+IF($H32="",0,$H32)) -> 23918.552 | J32: =IF($A32="","",Config!$B$4+$I32) -> 1023918.6 | K32: =IF($A32="","",MAX($J$4:$J32)) -> 1023918.6 | L32: =IF($A32="","",$J32-$K32) -> 0 | M32: =IF(OR($A32="",$K32=0),"",$L32/$K32) -> 0 | N32: =IF($A32="","",SUMIFS('Trade Log'!$K$4:$K$503,'Trade Log'!$H$4:$H$503,$A32)) -> 0 | O32: =IF(OR($A32="",$H32="",Config!$B$4=0),"",$H32/Config!$B$4) | P32: =IF($A32="","",SUM($H$13:$H32)) -> 23918.552 | Q32: =IF($A32="","",IFERROR((AVERAGE($O$13:$O32)-Config!$B$7/Config!$B$6)/STDEV($O$13:$O32)*SQRT(Config!$B$6),"")) | R32: =IF($A32="","",IFERROR((AVERAGE($O$4:$O32)-Config!$B$7/Config!$B$6)/STDEV($O$4:$O32)*SQRT(Config!$B$6),"")) | S32: =IF($H32="",$S31,IF($H32>0,$S31+1,0)) -> 1 | T32: =IF($H32="",$T31,IF($H32<0,$T31+1,0)) -> 0
A33: =IF($A32="","",$A32+1) -> 46264 | B33: =IF($A33="","",TEXT($A33,"ddd")) -> Sun | C33: =IF($A33="","",COUNTIFS('Trade Log'!$L$4:$L$503,$A33)) -> 0 | D33: =IF($A33="","",SUMIFS('Trade Log'!$Q$4:$Q$503,'Trade Log'!$L$4:$L$503,$A33,'Trade Log'!$E$4:$E$503,"LONG")) -> 0 | E33: =IF($A33="","",SUMIFS('Trade Log'!$Q$4:$Q$503,'Trade Log'!$L$4:$L$503,$A33,'Trade Log'!$E$4:$E$503,"SHORT")) -> 0 | F33: =IF($A33="","",$D33+$E33) -> 0 | G33: =IF($A33="","",SUMIFS('Trade Log'!$Y$4:$Y$503,'Trade Log'!$L$4:$L$503,$A33)) -> 0 | H33: =IF($A33="","",IF($C33=0,"",$F33-$G33)) | I33: =IF($A33="","",$I32+IF($H33="",0,$H33)) -> 23918.552 | J33: =IF($A33="","",Config!$B$4+$I33) -> 1023918.6 | K33: =IF($A33="","",MAX($J$4:$J33)) -> 1023918.6 | L33: =IF($A33="","",$J33-$K33) -> 0 | M33: =IF(OR($A33="",$K33=0),"",$L33/$K33) -> 0 | N33: =IF($A33="","",SUMIFS('Trade Log'!$K$4:$K$503,'Trade Log'!$H$4:$H$503,$A33)) -> 0 | O33: =IF(OR($A33="",$H33="",Config!$B$4=0),"",$H33/Config!$B$4) | P33: =IF($A33="","",SUM($H$14:$H33)) -> 23918.552 | Q33: =IF($A33="","",IFERROR((AVERAGE($O$14:$O33)-Config!$B$7/Config!$B$6)/STDEV($O$14:$O33)*SQRT(Config!$B$6),"")) | R33: =IF($A33="","",IFERROR((AVERAGE($O$4:$O33)-Config!$B$7/Config!$B$6)/STDEV($O$4:$O33)*SQRT(Config!$B$6),"")) | S33: =IF($H33="",$S32,IF($H33>0,$S32+1,0)) -> 1 | T33: =IF($H33="",$T32,IF($H33<0,$T32+1,0)) -> 0
A34: =IF($A33="","",$A33+1) -> 46265 | B34: =IF($A34="","",TEXT($A34,"ddd")) -> Mon | C34: =IF($A34="","",COUNTIFS('Trade Log'!$L$4:$L$503,$A34)) -> 0 | D34: =IF($A34="","",SUMIFS('Trade Log'!$Q$4:$Q$503,'Trade Log'!$L$4:$L$503,$A34,'Trade Log'!$E$4:$E$503,"LONG")) -> 0 | E34: =IF($A34="","",SUMIFS('Trade Log'!$Q$4:$Q$503,'Trade Log'!$L$4:$L$503,$A34,'Trade Log'!$E$4:$E$503,"SHORT")) -> 0 | F34: =IF($A34="","",$D34+$E34) -> 0 | G34: =IF($A34="","",SUMIFS('Trade Log'!$Y$4:$Y$503,'Trade Log'!$L$4:$L$503,$A34)) -> 0 | H34: =IF($A34="","",IF($C34=0,"",$F34-$G34)) | I34: =IF($A34="","",$I33+IF($H34="",0,$H34)) -> 23918.552 | J34: =IF($A34="","",Config!$B$4+$I34) -> 1023918.6 | K34: =IF($A34="","",MAX($J$4:$J34)) -> 1023918.6 | L34: =IF($A34="","",$J34-$K34) -> 0 | M34: =IF(OR($A34="",$K34=0),"",$L34/$K34) -> 0 | N34: =IF($A34="","",SUMIFS('Trade Log'!$K$4:$K$503,'Trade Log'!$H$4:$H$503,$A34)) -> 0 | O34: =IF(OR($A34="",$H34="",Config!$B$4=0),"",$H34/Config!$B$4) | P34: =IF($A34="","",SUM($H$15:$H34)) -> 23918.552 | Q34: =IF($A34="","",IFERROR((AVERAGE($O$15:$O34)-Config!$B$7/Config!$B$6)/STDEV($O$15:$O34)*SQRT(Config!$B$6),"")) | R34: =IF($A34="","",IFERROR((AVERAGE($O$4:$O34)-Config!$B$7/Config!$B$6)/STDEV($O$4:$O34)*SQRT(Config!$B$6),"")) | S34: =IF($H34="",$S33,IF($H34>0,$S33+1,0)) -> 1 | T34: =IF($H34="",$T33,IF($H34<0,$T33+1,0)) -> 0
A35: =IF($A34="","",$A34+1) -> 46266 | B35: =IF($A35="","",TEXT($A35,"ddd")) -> Tue | C35: =IF($A35="","",COUNTIFS('Trade Log'!$L$4:$L$503,$A35)) -> 0 | D35: =IF($A35="","",SUMIFS('Trade Log'!$Q$4:$Q$503,'Trade Log'!$L$4:$L$503,$A35,'Trade Log'!$E$4:$E$503,"LONG")) -> 0 | E35: =IF($A35="","",SUMIFS('Trade Log'!$Q$4:$Q$503,'Trade Log'!$L$4:$L$503,$A35,'Trade Log'!$E$4:$E$503,"SHORT")) -> 0 | F35: =IF($A35="","",$D35+$E35) -> 0 | G35: =IF($A35="","",SUMIFS('Trade Log'!$Y$4:$Y$503,'Trade Log'!$L$4:$L$503,$A35)) -> 0 | H35: =IF($A35="","",IF($C35=0,"",$F35-$G35)) | I35: =IF($A35="","",$I34+IF($H35="",0,$H35)) -> 23918.552 | J35: =IF($A35="","",Config!$B$4+$I35) -> 1023918.6 | K35: =IF($A35="","",MAX($J$4:$J35)) -> 1023918.6 | L35: =IF($A35="","",$J35-$K35) -> 0 | M35: =IF(OR($A35="",$K35=0),"",$L35/$K35) -> 0 | N35: =IF($A35="","",SUMIFS('Trade Log'!$K$4:$K$503,'Trade Log'!$H$4:$H$503,$A35)) -> 0 | O35: =IF(OR($A35="",$H35="",Config!$B$4=0),"",$H35/Config!$B$4) | P35: =IF($A35="","",SUM($H$16:$H35)) -> 23918.552 | Q35: =IF($A35="","",IFERROR((AVERAGE($O$16:$O35)-Config!$B$7/Config!$B$6)/STDEV($O$16:$O35)*SQRT(Config!$B$6),"")) | R35: =IF($A35="","",IFERROR((AVERAGE($O$4:$O35)-Config!$B$7/Config!$B$6)/STDEV($O$4:$O35)*SQRT(Config!$B$6),"")) | S35: =IF($H35="",$S34,IF($H35>0,$S34+1,0)) -> 1 | T35: =IF($H35="",$T34,IF($H35<0,$T34+1,0)) -> 0
A36: =IF($A35="","",$A35+1) -> 46267 | B36: =IF($A36="","",TEXT($A36,"ddd")) -> Wed | C36: =IF($A36="","",COUNTIFS('Trade Log'!$L$4:$L$503,$A36)) -> 0 | D36: =IF($A36="","",SUMIFS('Trade Log'!$Q$4:$Q$503,'Trade Log'!$L$4:$L$503,$A36,'Trade Log'!$E$4:$E$503,"LONG")) -> 0 | E36: =IF($A36="","",SUMIFS('Trade Log'!$Q$4:$Q$503,'Trade Log'!$L$4:$L$503,$A36,'Trade Log'!$E$4:$E$503,"SHORT")) -> 0 | F36: =IF($A36="","",$D36+$E36) -> 0 | G36: =IF($A36="","",SUMIFS('Trade Log'!$Y$4:$Y$503,'Trade Log'!$L$4:$L$503,$A36)) -> 0 | H36: =IF($A36="","",IF($C36=0,"",$F36-$G36)) | I36: =IF($A36="","",$I35+IF($H36="",0,$H36)) -> 23918.552 | J36: =IF($A36="","",Config!$B$4+$I36) -> 1023918.6 | K36: =IF($A36="","",MAX($J$4:$J36)) -> 1023918.6 | L36: =IF($A36="","",$J36-$K36) -> 0 | M36: =IF(OR($A36="",$K36=0),"",$L36/$K36) -> 0 | N36: =IF($A36="","",SUMIFS('Trade Log'!$K$4:$K$503,'Trade Log'!$H$4:$H$503,$A36)) -> 0 | O36: =IF(OR($A36="",$H36="",Config!$B$4=0),"",$H36/Config!$B$4) | P36: =IF($A36="","",SUM($H$17:$H36)) -> 23918.552 | Q36: =IF($A36="","",IFERROR((AVERAGE($O$17:$O36)-Config!$B$7/Config!$B$6)/STDEV($O$17:$O36)*SQRT(Config!$B$6),"")) | R36: =IF($A36="","",IFERROR((AVERAGE($O$4:$O36)-Config!$B$7/Config!$B$6)/STDEV($O$4:$O36)*SQRT(Config!$B$6),"")) | S36: =IF($H36="",$S35,IF($H36>0,$S35+1,0)) -> 1 | T36: =IF($H36="",$T35,IF($H36<0,$T35+1,0)) -> 0
A37: =IF($A36="","",$A36+1) -> 46268 | B37: =IF($A37="","",TEXT($A37,"ddd")) -> Thu | C37: =IF($A37="","",COUNTIFS('Trade Log'!$L$4:$L$503,$A37)) -> 0 | D37: =IF($A37="","",SUMIFS('Trade Log'!$Q$4:$Q$503,'Trade Log'!$L$4:$L$503,$A37,'Trade Log'!$E$4:$E$503,"LONG")) -> 0 | E37: =IF($A37="","",SUMIFS('Trade Log'!$Q$4:$Q$503,'Trade Log'!$L$4:$L$503,$A37,'Trade Log'!$E$4:$E$503,"SHORT")) -> 0 | F37: =IF($A37="","",$D37+$E37) -> 0 | G37: =IF($A37="","",SUMIFS('Trade Log'!$Y$4:$Y$503,'Trade Log'!$L$4:$L$503,$A37)) -> 0 | H37: =IF($A37="","",IF($C37=0,"",$F37-$G37)) | I37: =IF($A37="","",$I36+IF($H37="",0,$H37)) -> 23918.552 | J37: =IF($A37="","",Config!$B$4+$I37) -> 1023918.6 | K37: =IF($A37="","",MAX($J$4:$J37)) -> 1023918.6 | L37: =IF($A37="","",$J37-$K37) -> 0 | M37: =IF(OR($A37="",$K37=0),"",$L37/$K37) -> 0 | N37: =IF($A37="","",SUMIFS('Trade Log'!$K$4:$K$503,'Trade Log'!$H$4:$H$503,$A37)) -> 0 | O37: =IF(OR($A37="",$H37="",Config!$B$4=0),"",$H37/Config!$B$4) | P37: =IF($A37="","",SUM($H$18:$H37)) -> 23918.552 | Q37: =IF($A37="","",IFERROR((AVERAGE($O$18:$O37)-Config!$B$7/Config!$B$6)/STDEV($O$18:$O37)*SQRT(Config!$B$6),"")) | R37: =IF($A37="","",IFERROR((AVERAGE($O$4:$O37)-Config!$B$7/Config!$B$6)/STDEV($O$4:$O37)*SQRT(Config!$B$6),"")) | S37: =IF($H37="",$S36,IF($H37>0,$S36+1,0)) -> 1 | T37: =IF($H37="",$T36,IF($H37<0,$T36+1,0)) -> 0
A38: =IF($A37="","",$A37+1) -> 46269 | B38: =IF($A38="","",TEXT($A38,"ddd")) -> Fri | C38: =IF($A38="","",COUNTIFS('Trade Log'!$L$4:$L$503,$A38)) -> 0 | D38: =IF($A38="","",SUMIFS('Trade Log'!$Q$4:$Q$503,'Trade Log'!$L$4:$L$503,$A38,'Trade Log'!$E$4:$E$503,"LONG")) -> 0 | E38: =IF($A38="","",SUMIFS('Trade Log'!$Q$4:$Q$503,'Trade Log'!$L$4:$L$503,$A38,'Trade Log'!$E$4:$E$503,"SHORT")) -> 0 | F38: =IF($A38="","",$D38+$E38) -> 0 | G38: =IF($A38="","",SUMIFS('Trade Log'!$Y$4:$Y$503,'Trade Log'!$L$4:$L$503,$A38)) -> 0 | H38: =IF($A38="","",IF($C38=0,"",$F38-$G38)) | I38: =IF($A38="","",$I37+IF($H38="",0,$H38)) -> 23918.552 | J38: =IF($A38="","",Config!$B$4+$I38) -> 1023918.6 | K38: =IF($A38="","",MAX($J$4:$J38)) -> 1023918.6 | L38: =IF($A38="","",$J38-$K38) -> 0 | M38: =IF(OR($A38="",$K38=0),"",$L38/$K38) -> 0 | N38: =IF($A38="","",SUMIFS('Trade Log'!$K$4:$K$503,'Trade Log'!$H$4:$H$503,$A38)) -> 0 | O38: =IF(OR($A38="",$H38="",Config!$B$4=0),"",$H38/Config!$B$4) | P38: =IF($A38="","",SUM($H$19:$H38)) -> 23918.552 | Q38: =IF($A38="","",IFERROR((AVERAGE($O$19:$O38)-Config!$B$7/Config!$B$6)/STDEV($O$19:$O38)*SQRT(Config!$B$6),"")) | R38: =IF($A38="","",IFERROR((AVERAGE($O$4:$O38)-Config!$B$7/Config!$B$6)/STDEV($O$4:$O38)*SQRT(Config!$B$6),"")) | S38: =IF($H38="",$S37,IF($H38>0,$S37+1,0)) -> 1 | T38: =IF($H38="",$T37,IF($H38<0,$T37+1,0)) -> 0
A39: =IF($A38="","",$A38+1) -> 46270 | B39: =IF($A39="","",TEXT($A39,"ddd")) -> Sat | C39: =IF($A39="","",COUNTIFS('Trade Log'!$L$4:$L$503,$A39)) -> 0 | D39: =IF($A39="","",SUMIFS('Trade Log'!$Q$4:$Q$503,'Trade Log'!$L$4:$L$503,$A39,'Trade Log'!$E$4:$E$503,"LONG")) -> 0 | E39: =IF($A39="","",SUMIFS('Trade Log'!$Q$4:$Q$503,'Trade Log'!$L$4:$L$503,$A39,'Trade Log'!$E$4:$E$503,"SHORT")) -> 0 | F39: =IF($A39="","",$D39+$E39) -> 0 | G39: =IF($A39="","",SUMIFS('Trade Log'!$Y$4:$Y$503,'Trade Log'!$L$4:$L$503,$A39)) -> 0 | H39: =IF($A39="","",IF($C39=0,"",$F39-$G39)) | I39: =IF($A39="","",$I38+IF($H39="",0,$H39)) -> 23918.552 | J39: =IF($A39="","",Config!$B$4+$I39) -> 1023918.6 | K39: =IF($A39="","",MAX($J$4:$J39)) -> 1023918.6 | L39: =IF($A39="","",$J39-$K39) -> 0 | M39: =IF(OR($A39="",$K39=0),"",$L39/$K39) -> 0 | N39: =IF($A39="","",SUMIFS('Trade Log'!$K$4:$K$503,'Trade Log'!$H$4:$H$503,$A39)) -> 0 | O39: =IF(OR($A39="",$H39="",Config!$B$4=0),"",$H39/Config!$B$4) | P39: =IF($A39="","",SUM($H$20:$H39)) -> 23918.552 | Q39: =IF($A39="","",IFERROR((AVERAGE($O$20:$O39)-Config!$B$7/Config!$B$6)/STDEV($O$20:$O39)*SQRT(Config!$B$6),"")) | R39: =IF($A39="","",IFERROR((AVERAGE($O$4:$O39)-Config!$B$7/Config!$B$6)/STDEV($O$4:$O39)*SQRT(Config!$B$6),"")) | S39: =IF($H39="",$S38,IF($H39>0,$S38+1,0)) -> 1 | T39: =IF($H39="",$T38,IF($H39<0,$T38+1,0)) -> 0
A40: =IF($A39="","",$A39+1) -> 46271 | B40: =IF($A40="","",TEXT($A40,"ddd")) -> Sun | C40: =IF($A40="","",COUNTIFS('Trade Log'!$L$4:$L$503,$A40)) -> 0 | D40: =IF($A40="","",SUMIFS('Trade Log'!$Q$4:$Q$503,'Trade Log'!$L$4:$L$503,$A40,'Trade Log'!$E$4:$E$503,"LONG")) -> 0 | E40: =IF($A40="","",SUMIFS('Trade Log'!$Q$4:$Q$503,'Trade Log'!$L$4:$L$503,$A40,'Trade Log'!$E$4:$E$503,"SHORT")) -> 0 | F40: =IF($A40="","",$D40+$E40) -> 0 | G40: =IF($A40="","",SUMIFS('Trade Log'!$Y$4:$Y$503,'Trade Log'!$L$4:$L$503,$A40)) -> 0 | H40: =IF($A40="","",IF($C40=0,"",$F40-$G40)) | I40: =IF($A40="","",$I39+IF($H40="",0,$H40)) -> 23918.552 | J40: =IF($A40="","",Config!$B$4+$I40) -> 1023918.6 | K40: =IF($A40="","",MAX($J$4:$J40)) -> 1023918.6 | L40: =IF($A40="","",$J40-$K40) -> 0 | M40: =IF(OR($A40="",$K40=0),"",$L40/$K40) -> 0 | N40: =IF($A40="","",SUMIFS('Trade Log'!$K$4:$K$503,'Trade Log'!$H$4:$H$503,$A40)) -> 0 | O40: =IF(OR($A40="",$H40="",Config!$B$4=0),"",$H40/Config!$B$4) | P40: =IF($A40="","",SUM($H$21:$H40)) -> 23918.552 | Q40: =IF($A40="","",IFERROR((AVERAGE($O$21:$O40)-Config!$B$7/Config!$B$6)/STDEV($O$21:$O40)*SQRT(Config!$B$6),"")) | R40: =IF($A40="","",IFERROR((AVERAGE($O$4:$O40)-Config!$B$7/Config!$B$6)/STDEV($O$4:$O40)*SQRT(Config!$B$6),"")) | S40: =IF($H40="",$S39,IF($H40>0,$S39+1,0)) -> 1 | T40: =IF($H40="",$T39,IF($H40<0,$T39+1,0)) -> 0
A41: =IF($A40="","",$A40+1) -> 46272 | B41: =IF($A41="","",TEXT($A41,"ddd")) -> Mon | C41: =IF($A41="","",COUNTIFS('Trade Log'!$L$4:$L$503,$A41)) -> 0 | D41: =IF($A41="","",SUMIFS('Trade Log'!$Q$4:$Q$503,'Trade Log'!$L$4:$L$503,$A41,'Trade Log'!$E$4:$E$503,"LONG")) -> 0 | E41: =IF($A41="","",SUMIFS('Trade Log'!$Q$4:$Q$503,'Trade Log'!$L$4:$L$503,$A41,'Trade Log'!$E$4:$E$503,"SHORT")) -> 0 | F41: =IF($A41="","",$D41+$E41) -> 0 | G41: =IF($A41="","",SUMIFS('Trade Log'!$Y$4:$Y$503,'Trade Log'!$L$4:$L$503,$A41)) -> 0 | H41: =IF($A41="","",IF($C41=0,"",$F41-$G41)) | I41: =IF($A41="","",$I40+IF($H41="",0,$H41)) -> 23918.552 | J41: =IF($A41="","",Config!$B$4+$I41) -> 1023918.6 | K41: =IF($A41="","",MAX($J$4:$J41)) -> 1023918.6 | L41: =IF($A41="","",$J41-$K41) -> 0 | M41: =IF(OR($A41="",$K41=0),"",$L41/$K41) -> 0 | N41: =IF($A41="","",SUMIFS('Trade Log'!$K$4:$K$503,'Trade Log'!$H$4:$H$503,$A41)) -> 0 | O41: =IF(OR($A41="",$H41="",Config!$B$4=0),"",$H41/Config!$B$4) | P41: =IF($A41="","",SUM($H$22:$H41)) -> 0 | Q41: =IF($A41="","",IFERROR((AVERAGE($O$22:$O41)-Config!$B$7/Config!$B$6)/STDEV($O$22:$O41)*SQRT(Config!$B$6),"")) | R41: =IF($A41="","",IFERROR((AVERAGE($O$4:$O41)-Config!$B$7/Config!$B$6)/STDEV($O$4:$O41)*SQRT(Config!$B$6),"")) | S41: =IF($H41="",$S40,IF($H41>0,$S40+1,0)) -> 1 | T41: =IF($H41="",$T40,IF($H41<0,$T40+1,0)) -> 0
A42: =IF($A41="","",$A41+1) -> 46273 | B42: =IF($A42="","",TEXT($A42,"ddd")) -> Tue | C42: =IF($A42="","",COUNTIFS('Trade Log'!$L$4:$L$503,$A42)) -> 0 | D42: =IF($A42="","",SUMIFS('Trade Log'!$Q$4:$Q$503,'Trade Log'!$L$4:$L$503,$A42,'Trade Log'!$E$4:$E$503,"LONG")) -> 0 | E42: =IF($A42="","",SUMIFS('Trade Log'!$Q$4:$Q$503,'Trade Log'!$L$4:$L$503,$A42,'Trade Log'!$E$4:$E$503,"SHORT")) -> 0 | F42: =IF($A42="","",$D42+$E42) -> 0 | G42: =IF($A42="","",SUMIFS('Trade Log'!$Y$4:$Y$503,'Trade Log'!$L$4:$L$503,$A42)) -> 0 | H42: =IF($A42="","",IF($C42=0,"",$F42-$G42)) | I42: =IF($A42="","",$I41+IF($H42="",0,$H42)) -> 23918.552 | J42: =IF($A42="","",Config!$B$4+$I42) -> 1023918.6 | K42: =IF($A42="","",MAX($J$4:$J42)) -> 1023918.6 | L42: =IF($A42="","",$J42-$K42) -> 0 | M42: =IF(OR($A42="",$K42=0),"",$L42/$K42) -> 0 | N42: =IF($A42="","",SUMIFS('Trade Log'!$K$4:$K$503,'Trade Log'!$H$4:$H$503,$A42)) -> 0 | O42: =IF(OR($A42="",$H42="",Config!$B$4=0),"",$H42/Config!$B$4) | P42: =IF($A42="","",SUM($H$23:$H42)) -> 0 | Q42: =IF($A42="","",IFERROR((AVERAGE($O$23:$O42)-Config!$B$7/Config!$B$6)/STDEV($O$23:$O42)*SQRT(Config!$B$6),"")) | R42: =IF($A42="","",IFERROR((AVERAGE($O$4:$O42)-Config!$B$7/Config!$B$6)/STDEV($O$4:$O42)*SQRT(Config!$B$6),"")) | S42: =IF($H42="",$S41,IF($H42>0,$S41+1,0)) -> 1 | T42: =IF($H42="",$T41,IF($H42<0,$T41+1,0)) -> 0
A43: =IF($A42="","",$A42+1) -> 46274 | B43: =IF($A43="","",TEXT($A43,"ddd")) -> Wed | C43: =IF($A43="","",COUNTIFS('Trade Log'!$L$4:$L$503,$A43)) -> 0 | D43: =IF($A43="","",SUMIFS('Trade Log'!$Q$4:$Q$503,'Trade Log'!$L$4:$L$503,$A43,'Trade Log'!$E$4:$E$503,"LONG")) -> 0 | E43: =IF($A43="","",SUMIFS('Trade Log'!$Q$4:$Q$503,'Trade Log'!$L$4:$L$503,$A43,'Trade Log'!$E$4:$E$503,"SHORT")) -> 0 | F43: =IF($A43="","",$D43+$E43) -> 0 | G43: =IF($A43="","",SUMIFS('Trade Log'!$Y$4:$Y$503,'Trade Log'!$L$4:$L$503,$A43)) -> 0 | H43: =IF($A43="","",IF($C43=0,"",$F43-$G43)) | I43: =IF($A43="","",$I42+IF($H43="",0,$H43)) -> 23918.552 | J43: =IF($A43="","",Config!$B$4+$I43) -> 1023918.6 | K43: =IF($A43="","",MAX($J$4:$J43)) -> 1023918.6 | L43: =IF($A43="","",$J43-$K43) -> 0 | M43: =IF(OR($A43="",$K43=0),"",$L43/$K43) -> 0 | N43: =IF($A43="","",SUMIFS('Trade Log'!$K$4:$K$503,'Trade Log'!$H$4:$H$503,$A43)) -> 0 | O43: =IF(OR($A43="",$H43="",Config!$B$4=0),"",$H43/Config!$B$4) | P43: =IF($A43="","",SUM($H$24:$H43)) -> 0 | Q43: =IF($A43="","",IFERROR((AVERAGE($O$24:$O43)-Config!$B$7/Config!$B$6)/STDEV($O$24:$O43)*SQRT(Config!$B$6),"")) | R43: =IF($A43="","",IFERROR((AVERAGE($O$4:$O43)-Config!$B$7/Config!$B$6)/STDEV($O$4:$O43)*SQRT(Config!$B$6),"")) | S43: =IF($H43="",$S42,IF($H43>0,$S42+1,0)) -> 1 | T43: =IF($H43="",$T42,IF($H43<0,$T42+1,0)) -> 0
A44: =IF($A43="","",$A43+1) -> 46275 | B44: =IF($A44="","",TEXT($A44,"ddd")) -> Thu | C44: =IF($A44="","",COUNTIFS('Trade Log'!$L$4:$L$503,$A44)) -> 0 | D44: =IF($A44="","",SUMIFS('Trade Log'!$Q$4:$Q$503,'Trade Log'!$L$4:$L$503,$A44,'Trade Log'!$E$4:$E$503,"LONG")) -> 0 | E44: =IF($A44="","",SUMIFS('Trade Log'!$Q$4:$Q$503,'Trade Log'!$L$4:$L$503,$A44,'Trade Log'!$E$4:$E$503,"SHORT")) -> 0 | F44: =IF($A44="","",$D44+$E44) -> 0 | G44: =IF($A44="","",SUMIFS('Trade Log'!$Y$4:$Y$503,'Trade Log'!$L$4:$L$503,$A44)) -> 0 | H44: =IF($A44="","",IF($C44=0,"",$F44-$G44)) | I44: =IF($A44="","",$I43+IF($H44="",0,$H44)) -> 23918.552 | J44: =IF($A44="","",Config!$B$4+$I44) -> 1023918.6 | K44: =IF($A44="","",MAX($J$4:$J44)) -> 1023918.6 | L44: =IF($A44="","",$J44-$K44) -> 0 | M44: =IF(OR($A44="",$K44=0),"",$L44/$K44) -> 0 | N44: =IF($A44="","",SUMIFS('Trade Log'!$K$4:$K$503,'Trade Log'!$H$4:$H$503,$A44)) -> 0 | O44: =IF(OR($A44="",$H44="",Config!$B$4=0),"",$H44/Config!$B$4) | P44: =IF($A44="","",SUM($H$25:$H44)) -> 0 | Q44: =IF($A44="","",IFERROR((AVERAGE($O$25:$O44)-Config!$B$7/Config!$B$6)/STDEV($O$25:$O44)*SQRT(Config!$B$6),"")) | R44: =IF($A44="","",IFERROR((AVERAGE($O$4:$O44)-Config!$B$7/Config!$B$6)/STDEV($O$4:$O44)*SQRT(Config!$B$6),"")) | S44: =IF($H44="",$S43,IF($H44>0,$S43+1,0)) -> 1 | T44: =IF($H44="",$T43,IF($H44<0,$T43+1,0)) -> 0
A45: =IF($A44="","",$A44+1) -> 46276 | B45: =IF($A45="","",TEXT($A45,"ddd")) -> Fri | C45: =IF($A45="","",COUNTIFS('Trade Log'!$L$4:$L$503,$A45)) -> 0 | D45: =IF($A45="","",SUMIFS('Trade Log'!$Q$4:$Q$503,'Trade Log'!$L$4:$L$503,$A45,'Trade Log'!$E$4:$E$503,"LONG")) -> 0 | E45: =IF($A45="","",SUMIFS('Trade Log'!$Q$4:$Q$503,'Trade Log'!$L$4:$L$503,$A45,'Trade Log'!$E$4:$E$503,"SHORT")) -> 0 | F45: =IF($A45="","",$D45+$E45) -> 0 | G45: =IF($A45="","",SUMIFS('Trade Log'!$Y$4:$Y$503,'Trade Log'!$L$4:$L$503,$A45)) -> 0 | H45: =IF($A45="","",IF($C45=0,"",$F45-$G45)) | I45: =IF($A45="","",$I44+IF($H45="",0,$H45)) -> 23918.552 | J45: =IF($A45="","",Config!$B$4+$I45) -> 1023918.6 | K45: =IF($A45="","",MAX($J$4:$J45)) -> 1023918.6 | L45: =IF($A45="","",$J45-$K45) -> 0 | M45: =IF(OR($A45="",$K45=0),"",$L45/$K45) -> 0 | N45: =IF($A45="","",SUMIFS('Trade Log'!$K$4:$K$503,'Trade Log'!$H$4:$H$503,$A45)) -> 0 | O45: =IF(OR($A45="",$H45="",Config!$B$4=0),"",$H45/Config!$B$4) | P45: =IF($A45="","",SUM($H$26:$H45)) -> 0 | Q45: =IF($A45="","",IFERROR((AVERAGE($O$26:$O45)-Config!$B$7/Config!$B$6)/STDEV($O$26:$O45)*SQRT(Config!$B$6),"")) | R45: =IF($A45="","",IFERROR((AVERAGE($O$4:$O45)-Config!$B$7/Config!$B$6)/STDEV($O$4:$O45)*SQRT(Config!$B$6),"")) | S45: =IF($H45="",$S44,IF($H45>0,$S44+1,0)) -> 1 | T45: =IF($H45="",$T44,IF($H45<0,$T44+1,0)) -> 0
A46: =IF($A45="","",$A45+1) -> 46277 | B46: =IF($A46="","",TEXT($A46,"ddd")) -> Sat | C46: =IF($A46="","",COUNTIFS('Trade Log'!$L$4:$L$503,$A46)) -> 0 | D46: =IF($A46="","",SUMIFS('Trade Log'!$Q$4:$Q$503,'Trade Log'!$L$4:$L$503,$A46,'Trade Log'!$E$4:$E$503,"LONG")) -> 0 | E46: =IF($A46="","",SUMIFS('Trade Log'!$Q$4:$Q$503,'Trade Log'!$L$4:$L$503,$A46,'Trade Log'!$E$4:$E$503,"SHORT")) -> 0 | F46: =IF($A46="","",$D46+$E46) -> 0 | G46: =IF($A46="","",SUMIFS('Trade Log'!$Y$4:$Y$503,'Trade Log'!$L$4:$L$503,$A46)) -> 0 | H46: =IF($A46="","",IF($C46=0,"",$F46-$G46)) | I46: =IF($A46="","",$I45+IF($H46="",0,$H46)) -> 23918.552 | J46: =IF($A46="","",Config!$B$4+$I46) -> 1023918.6 | K46: =IF($A46="","",MAX($J$4:$J46)) -> 1023918.6 | L46: =IF($A46="","",$J46-$K46) -> 0 | M46: =IF(OR($A46="",$K46=0),"",$L46/$K46) -> 0 | N46: =IF($A46="","",SUMIFS('Trade Log'!$K$4:$K$503,'Trade Log'!$H$4:$H$503,$A46)) -> 0 | O46: =IF(OR($A46="",$H46="",Config!$B$4=0),"",$H46/Config!$B$4) | P46: =IF($A46="","",SUM($H$27:$H46)) -> 0 | Q46: =IF($A46="","",IFERROR((AVERAGE($O$27:$O46)-Config!$B$7/Config!$B$6)/STDEV($O$27:$O46)*SQRT(Config!$B$6),"")) | R46: =IF($A46="","",IFERROR((AVERAGE($O$4:$O46)-Config!$B$7/Config!$B$6)/STDEV($O$4:$O46)*SQRT(Config!$B$6),"")) | S46: =IF($H46="",$S45,IF($H46>0,$S45+1,0)) -> 1 | T46: =IF($H46="",$T45,IF($H46<0,$T45+1,0)) -> 0
A47: =IF($A46="","",$A46+1) -> 46278 | B47: =IF($A47="","",TEXT($A47,"ddd")) -> Sun | C47: =IF($A47="","",COUNTIFS('Trade Log'!$L$4:$L$503,$A47)) -> 0 | D47: =IF($A47="","",SUMIFS('Trade Log'!$Q$4:$Q$503,'Trade Log'!$L$4:$L$503,$A47,'Trade Log'!$E$4:$E$503,"LONG")) -> 0 | E47: =IF($A47="","",SUMIFS('Trade Log'!$Q$4:$Q$503,'Trade Log'!$L$4:$L$503,$A47,'Trade Log'!$E$4:$E$503,"SHORT")) -> 0 | F47: =IF($A47="","",$D47+$E47) -> 0 | G47: =IF($A47="","",SUMIFS('Trade Log'!$Y$4:$Y$503,'Trade Log'!$L$4:$L$503,$A47)) -> 0 | H47: =IF($A47="","",IF($C47=0,"",$F47-$G47)) | I47: =IF($A47="","",$I46+IF($H47="",0,$H47)) -> 23918.552 | J47: =IF($A47="","",Config!$B$4+$I47) -> 1023918.6 | K47: =IF($A47="","",MAX($J$4:$J47)) -> 1023918.6 | L47: =IF($A47="","",$J47-$K47) -> 0 | M47: =IF(OR($A47="",$K47=0),"",$L47/$K47) -> 0 | N47: =IF($A47="","",SUMIFS('Trade Log'!$K$4:$K$503,'Trade Log'!$H$4:$H$503,$A47)) -> 0 | O47: =IF(OR($A47="",$H47="",Config!$B$4=0),"",$H47/Config!$B$4) | P47: =IF($A47="","",SUM($H$28:$H47)) -> 0 | Q47: =IF($A47="","",IFERROR((AVERAGE($O$28:$O47)-Config!$B$7/Config!$B$6)/STDEV($O$28:$O47)*SQRT(Config!$B$6),"")) | R47: =IF($A47="","",IFERROR((AVERAGE($O$4:$O47)-Config!$B$7/Config!$B$6)/STDEV($O$4:$O47)*SQRT(Config!$B$6),"")) | S47: =IF($H47="",$S46,IF($H47>0,$S46+1,0)) -> 1 | T47: =IF($H47="",$T46,IF($H47<0,$T46+1,0)) -> 0
A48: =IF($A47="","",$A47+1) -> 46279 | B48: =IF($A48="","",TEXT($A48,"ddd")) -> Mon | C48: =IF($A48="","",COUNTIFS('Trade Log'!$L$4:$L$503,$A48)) -> 0 | D48: =IF($A48="","",SUMIFS('Trade Log'!$Q$4:$Q$503,'Trade Log'!$L$4:$L$503,$A48,'Trade Log'!$E$4:$E$503,"LONG")) -> 0 | E48: =IF($A48="","",SUMIFS('Trade Log'!$Q$4:$Q$503,'Trade Log'!$L$4:$L$503,$A48,'Trade Log'!$E$4:$E$503,"SHORT")) -> 0 | F48: =IF($A48="","",$D48+$E48) -> 0 | G48: =IF($A48="","",SUMIFS('Trade Log'!$Y$4:$Y$503,'Trade Log'!$L$4:$L$503,$A48)) -> 0 | H48: =IF($A48="","",IF($C48=0,"",$F48-$G48)) | I48: =IF($A48="","",$I47+IF($H48="",0,$H48)) -> 23918.552 | J48: =IF($A48="","",Config!$B$4+$I48) -> 1023918.6 | K48: =IF($A48="","",MAX($J$4:$J48)) -> 1023918.6 | L48: =IF($A48="","",$J48-$K48) -> 0 | M48: =IF(OR($A48="",$K48=0),"",$L48/$K48) -> 0 | N48: =IF($A48="","",SUMIFS('Trade Log'!$K$4:$K$503,'Trade Log'!$H$4:$H$503,$A48)) -> 0 | O48: =IF(OR($A48="",$H48="",Config!$B$4=0),"",$H48/Config!$B$4) | P48: =IF($A48="","",SUM($H$29:$H48)) -> 0 | Q48: =IF($A48="","",IFERROR((AVERAGE($O$29:$O48)-Config!$B$7/Config!$B$6)/STDEV($O$29:$O48)*SQRT(Config!$B$6),"")) | R48: =IF($A48="","",IFERROR((AVERAGE($O$4:$O48)-Config!$B$7/Config!$B$6)/STDEV($O$4:$O48)*SQRT(Config!$B$6),"")) | S48: =IF($H48="",$S47,IF($H48>0,$S47+1,0)) -> 1 | T48: =IF($H48="",$T47,IF($H48<0,$T47+1,0)) -> 0
A49: =IF($A48="","",$A48+1) -> 46280 | B49: =IF($A49="","",TEXT($A49,"ddd")) -> Tue | C49: =IF($A49="","",COUNTIFS('Trade Log'!$L$4:$L$503,$A49)) -> 0 | D49: =IF($A49="","",SUMIFS('Trade Log'!$Q$4:$Q$503,'Trade Log'!$L$4:$L$503,$A49,'Trade Log'!$E$4:$E$503,"LONG")) -> 0 | E49: =IF($A49="","",SUMIFS('Trade Log'!$Q$4:$Q$503,'Trade Log'!$L$4:$L$503,$A49,'Trade Log'!$E$4:$E$503,"SHORT")) -> 0 | F49: =IF($A49="","",$D49+$E49) -> 0 | G49: =IF($A49="","",SUMIFS('Trade Log'!$Y$4:$Y$503,'Trade Log'!$L$4:$L$503,$A49)) -> 0 | H49: =IF($A49="","",IF($C49=0,"",$F49-$G49)) | I49: =IF($A49="","",$I48+IF($H49="",0,$H49)) -> 23918.552 | J49: =IF($A49="","",Config!$B$4+$I49) -> 1023918.6 | K49: =IF($A49="","",MAX($J$4:$J49)) -> 1023918.6 | L49: =IF($A49="","",$J49-$K49) -> 0 | M49: =IF(OR($A49="",$K49=0),"",$L49/$K49) -> 0 | N49: =IF($A49="","",SUMIFS('Trade Log'!$K$4:$K$503,'Trade Log'!$H$4:$H$503,$A49)) -> 0 | O49: =IF(OR($A49="",$H49="",Config!$B$4=0),"",$H49/Config!$B$4) | P49: =IF($A49="","",SUM($H$30:$H49)) -> 0 | Q49: =IF($A49="","",IFERROR((AVERAGE($O$30:$O49)-Config!$B$7/Config!$B$6)/STDEV($O$30:$O49)*SQRT(Config!$B$6),"")) | R49: =IF($A49="","",IFERROR((AVERAGE($O$4:$O49)-Config!$B$7/Config!$B$6)/STDEV($O$4:$O49)*SQRT(Config!$B$6),"")) | S49: =IF($H49="",$S48,IF($H49>0,$S48+1,0)) -> 1 | T49: =IF($H49="",$T48,IF($H49<0,$T48+1,0)) -> 0
A50: =IF($A49="","",$A49+1) -> 46281 | B50: =IF($A50="","",TEXT($A50,"ddd")) -> Wed | C50: =IF($A50="","",COUNTIFS('Trade Log'!$L$4:$L$503,$A50)) -> 0 | D50: =IF($A50="","",SUMIFS('Trade Log'!$Q$4:$Q$503,'Trade Log'!$L$4:$L$503,$A50,'Trade Log'!$E$4:$E$503,"LONG")) -> 0 | E50: =IF($A50="","",SUMIFS('Trade Log'!$Q$4:$Q$503,'Trade Log'!$L$4:$L$503,$A50,'Trade Log'!$E$4:$E$503,"SHORT")) -> 0 | F50: =IF($A50="","",$D50+$E50) -> 0 | G50: =IF($A50="","",SUMIFS('Trade Log'!$Y$4:$Y$503,'Trade Log'!$L$4:$L$503,$A50)) -> 0 | H50: =IF($A50="","",IF($C50=0,"",$F50-$G50)) | I50: =IF($A50="","",$I49+IF($H50="",0,$H50)) -> 23918.552 | J50: =IF($A50="","",Config!$B$4+$I50) -> 1023918.6 | K50: =IF($A50="","",MAX($J$4:$J50)) -> 1023918.6 | L50: =IF($A50="","",$J50-$K50) -> 0 | M50: =IF(OR($A50="",$K50=0),"",$L50/$K50) -> 0 | N50: =IF($A50="","",SUMIFS('Trade Log'!$K$4:$K$503,'Trade Log'!$H$4:$H$503,$A50)) -> 0 | O50: =IF(OR($A50="",$H50="",Config!$B$4=0),"",$H50/Config!$B$4) | P50: =IF($A50="","",SUM($H$31:$H50)) -> 0 | Q50: =IF($A50="","",IFERROR((AVERAGE($O$31:$O50)-Config!$B$7/Config!$B$6)/STDEV($O$31:$O50)*SQRT(Config!$B$6),"")) | R50: =IF($A50="","",IFERROR((AVERAGE($O$4:$O50)-Config!$B$7/Config!$B$6)/STDEV($O$4:$O50)*SQRT(Config!$B$6),"")) | S50: =IF($H50="",$S49,IF($H50>0,$S49+1,0)) -> 1 | T50: =IF($H50="",$T49,IF($H50<0,$T49+1,0)) -> 0
A51: =IF($A50="","",$A50+1) -> 46282 | B51: =IF($A51="","",TEXT($A51,"ddd")) -> Thu | C51: =IF($A51="","",COUNTIFS('Trade Log'!$L$4:$L$503,$A51)) -> 0 | D51: =IF($A51="","",SUMIFS('Trade Log'!$Q$4:$Q$503,'Trade Log'!$L$4:$L$503,$A51,'Trade Log'!$E$4:$E$503,"LONG")) -> 0 | E51: =IF($A51="","",SUMIFS('Trade Log'!$Q$4:$Q$503,'Trade Log'!$L$4:$L$503,$A51,'Trade Log'!$E$4:$E$503,"SHORT")) -> 0 | F51: =IF($A51="","",$D51+$E51) -> 0 | G51: =IF($A51="","",SUMIFS('Trade Log'!$Y$4:$Y$503,'Trade Log'!$L$4:$L$503,$A51)) -> 0 | H51: =IF($A51="","",IF($C51=0,"",$F51-$G51)) | I51: =IF($A51="","",$I50+IF($H51="",0,$H51)) -> 23918.552 | J51: =IF($A51="","",Config!$B$4+$I51) -> 1023918.6 | K51: =IF($A51="","",MAX($J$4:$J51)) -> 1023918.6 | L51: =IF($A51="","",$J51-$K51) -> 0 | M51: =IF(OR($A51="",$K51=0),"",$L51/$K51) -> 0 | N51: =IF($A51="","",SUMIFS('Trade Log'!$K$4:$K$503,'Trade Log'!$H$4:$H$503,$A51)) -> 0 | O51: =IF(OR($A51="",$H51="",Config!$B$4=0),"",$H51/Config!$B$4) | P51: =IF($A51="","",SUM($H$32:$H51)) -> 0 | Q51: =IF($A51="","",IFERROR((AVERAGE($O$32:$O51)-Config!$B$7/Config!$B$6)/STDEV($O$32:$O51)*SQRT(Config!$B$6),"")) | R51: =IF($A51="","",IFERROR((AVERAGE($O$4:$O51)-Config!$B$7/Config!$B$6)/STDEV($O$4:$O51)*SQRT(Config!$B$6),"")) | S51: =IF($H51="",$S50,IF($H51>0,$S50+1,0)) -> 1 | T51: =IF($H51="",$T50,IF($H51<0,$T50+1,0)) -> 0
A52: =IF($A51="","",$A51+1) -> 46283 | B52: =IF($A52="","",TEXT($A52,"ddd")) -> Fri | C52: =IF($A52="","",COUNTIFS('Trade Log'!$L$4:$L$503,$A52)) -> 0 | D52: =IF($A52="","",SUMIFS('Trade Log'!$Q$4:$Q$503,'Trade Log'!$L$4:$L$503,$A52,'Trade Log'!$E$4:$E$503,"LONG")) -> 0 | E52: =IF($A52="","",SUMIFS('Trade Log'!$Q$4:$Q$503,'Trade Log'!$L$4:$L$503,$A52,'Trade Log'!$E$4:$E$503,"SHORT")) -> 0 | F52: =IF($A52="","",$D52+$E52) -> 0 | G52: =IF($A52="","",SUMIFS('Trade Log'!$Y$4:$Y$503,'Trade Log'!$L$4:$L$503,$A52)) -> 0 | H52: =IF($A52="","",IF($C52=0,"",$F52-$G52)) | I52: =IF($A52="","",$I51+IF($H52="",0,$H52)) -> 23918.552 | J52: =IF($A52="","",Config!$B$4+$I52) -> 1023918.6 | K52: =IF($A52="","",MAX($J$4:$J52)) -> 1023918.6 | L52: =IF($A52="","",$J52-$K52) -> 0 | M52: =IF(OR($A52="",$K52=0),"",$L52/$K52) -> 0 | N52: =IF($A52="","",SUMIFS('Trade Log'!$K$4:$K$503,'Trade Log'!$H$4:$H$503,$A52)) -> 0 | O52: =IF(OR($A52="",$H52="",Config!$B$4=0),"",$H52/Config!$B$4) | P52: =IF($A52="","",SUM($H$33:$H52)) -> 0 | Q52: =IF($A52="","",IFERROR((AVERAGE($O$33:$O52)-Config!$B$7/Config!$B$6)/STDEV($O$33:$O52)*SQRT(Config!$B$6),"")) | R52: =IF($A52="","",IFERROR((AVERAGE($O$4:$O52)-Config!$B$7/Config!$B$6)/STDEV($O$4:$O52)*SQRT(Config!$B$6),"")) | S52: =IF($H52="",$S51,IF($H52>0,$S51+1,0)) -> 1 | T52: =IF($H52="",$T51,IF($H52<0,$T51+1,0)) -> 0
A53: =IF($A52="","",$A52+1) -> 46284 | B53: =IF($A53="","",TEXT($A53,"ddd")) -> Sat | C53: =IF($A53="","",COUNTIFS('Trade Log'!$L$4:$L$503,$A53)) -> 0 | D53: =IF($A53="","",SUMIFS('Trade Log'!$Q$4:$Q$503,'Trade Log'!$L$4:$L$503,$A53,'Trade Log'!$E$4:$E$503,"LONG")) -> 0 | E53: =IF($A53="","",SUMIFS('Trade Log'!$Q$4:$Q$503,'Trade Log'!$L$4:$L$503,$A53,'Trade Log'!$E$4:$E$503,"SHORT")) -> 0 | F53: =IF($A53="","",$D53+$E53) -> 0 | G53: =IF($A53="","",SUMIFS('Trade Log'!$Y$4:$Y$503,'Trade Log'!$L$4:$L$503,$A53)) -> 0 | H53: =IF($A53="","",IF($C53=0,"",$F53-$G53)) | I53: =IF($A53="","",$I52+IF($H53="",0,$H53)) -> 23918.552 | J53: =IF($A53="","",Config!$B$4+$I53) -> 1023918.6 | K53: =IF($A53="","",MAX($J$4:$J53)) -> 1023918.6 | L53: =IF($A53="","",$J53-$K53) -> 0 | M53: =IF(OR($A53="",$K53=0),"",$L53/$K53) -> 0 | N53: =IF($A53="","",SUMIFS('Trade Log'!$K$4:$K$503,'Trade Log'!$H$4:$H$503,$A53)) -> 0 | O53: =IF(OR($A53="",$H53="",Config!$B$4=0),"",$H53/Config!$B$4) | P53: =IF($A53="","",SUM($H$34:$H53)) -> 0 | Q53: =IF($A53="","",IFERROR((AVERAGE($O$34:$O53)-Config!$B$7/Config!$B$6)/STDEV($O$34:$O53)*SQRT(Config!$B$6),"")) | R53: =IF($A53="","",IFERROR((AVERAGE($O$4:$O53)-Config!$B$7/Config!$B$6)/STDEV($O$4:$O53)*SQRT(Config!$B$6),"")) | S53: =IF($H53="",$S52,IF($H53>0,$S52+1,0)) -> 1 | T53: =IF($H53="",$T52,IF($H53<0,$T52+1,0)) -> 0
A54: =IF($A53="","",$A53+1) -> 46285 | B54: =IF($A54="","",TEXT($A54,"ddd")) -> Sun | C54: =IF($A54="","",COUNTIFS('Trade Log'!$L$4:$L$503,$A54)) -> 0 | D54: =IF($A54="","",SUMIFS('Trade Log'!$Q$4:$Q$503,'Trade Log'!$L$4:$L$503,$A54,'Trade Log'!$E$4:$E$503,"LONG")) -> 0 | E54: =IF($A54="","",SUMIFS('Trade Log'!$Q$4:$Q$503,'Trade Log'!$L$4:$L$503,$A54,'Trade Log'!$E$4:$E$503,"SHORT")) -> 0 | F54: =IF($A54="","",$D54+$E54) -> 0 | G54: =IF($A54="","",SUMIFS('Trade Log'!$Y$4:$Y$503,'Trade Log'!$L$4:$L$503,$A54)) -> 0 | H54: =IF($A54="","",IF($C54=0,"",$F54-$G54)) | I54: =IF($A54="","",$I53+IF($H54="",0,$H54)) -> 23918.552 | J54: =IF($A54="","",Config!$B$4+$I54) -> 1023918.6 | K54: =IF($A54="","",MAX($J$4:$J54)) -> 1023918.6 | L54: =IF($A54="","",$J54-$K54) -> 0 | M54: =IF(OR($A54="",$K54=0),"",$L54/$K54) -> 0 | N54: =IF($A54="","",SUMIFS('Trade Log'!$K$4:$K$503,'Trade Log'!$H$4:$H$503,$A54)) -> 0 | O54: =IF(OR($A54="",$H54="",Config!$B$4=0),"",$H54/Config!$B$4) | P54: =IF($A54="","",SUM($H$35:$H54)) -> 0 | Q54: =IF($A54="","",IFERROR((AVERAGE($O$35:$O54)-Config!$B$7/Config!$B$6)/STDEV($O$35:$O54)*SQRT(Config!$B$6),"")) | R54: =IF($A54="","",IFERROR((AVERAGE($O$4:$O54)-Config!$B$7/Config!$B$6)/STDEV($O$4:$O54)*SQRT(Config!$B$6),"")) | S54: =IF($H54="",$S53,IF($H54>0,$S53+1,0)) -> 1 | T54: =IF($H54="",$T53,IF($H54<0,$T53+1,0)) -> 0
A55: =IF($A54="","",$A54+1) -> 46286 | B55: =IF($A55="","",TEXT($A55,"ddd")) -> Mon | C55: =IF($A55="","",COUNTIFS('Trade Log'!$L$4:$L$503,$A55)) -> 0 | D55: =IF($A55="","",SUMIFS('Trade Log'!$Q$4:$Q$503,'Trade Log'!$L$4:$L$503,$A55,'Trade Log'!$E$4:$E$503,"LONG")) -> 0 | E55: =IF($A55="","",SUMIFS('Trade Log'!$Q$4:$Q$503,'Trade Log'!$L$4:$L$503,$A55,'Trade Log'!$E$4:$E$503,"SHORT")) -> 0 | F55: =IF($A55="","",$D55+$E55) -> 0 | G55: =IF($A55="","",SUMIFS('Trade Log'!$Y$4:$Y$503,'Trade Log'!$L$4:$L$503,$A55)) -> 0 | H55: =IF($A55="","",IF($C55=0,"",$F55-$G55)) | I55: =IF($A55="","",$I54+IF($H55="",0,$H55)) -> 23918.552 | J55: =IF($A55="","",Config!$B$4+$I55) -> 1023918.6 | K55: =IF($A55="","",MAX($J$4:$J55)) -> 1023918.6 | L55: =IF($A55="","",$J55-$K55) -> 0 | M55: =IF(OR($A55="",$K55=0),"",$L55/$K55) -> 0 | N55: =IF($A55="","",SUMIFS('Trade Log'!$K$4:$K$503,'Trade Log'!$H$4:$H$503,$A55)) -> 0 | O55: =IF(OR($A55="",$H55="",Config!$B$4=0),"",$H55/Config!$B$4) | P55: =IF($A55="","",SUM($H$36:$H55)) -> 0 | Q55: =IF($A55="","",IFERROR((AVERAGE($O$36:$O55)-Config!$B$7/Config!$B$6)/STDEV($O$36:$O55)*SQRT(Config!$B$6),"")) | R55: =IF($A55="","",IFERROR((AVERAGE($O$4:$O55)-Config!$B$7/Config!$B$6)/STDEV($O$4:$O55)*SQRT(Config!$B$6),"")) | S55: =IF($H55="",$S54,IF($H55>0,$S54+1,0)) -> 1 | T55: =IF($H55="",$T54,IF($H55<0,$T54+1,0)) -> 0
A56: =IF($A55="","",$A55+1) -> 46287 | B56: =IF($A56="","",TEXT($A56,"ddd")) -> Tue | C56: =IF($A56="","",COUNTIFS('Trade Log'!$L$4:$L$503,$A56)) -> 0 | D56: =IF($A56="","",SUMIFS('Trade Log'!$Q$4:$Q$503,'Trade Log'!$L$4:$L$503,$A56,'Trade Log'!$E$4:$E$503,"LONG")) -> 0 | E56: =IF($A56="","",SUMIFS('Trade Log'!$Q$4:$Q$503,'Trade Log'!$L$4:$L$503,$A56,'Trade Log'!$E$4:$E$503,"SHORT")) -> 0 | F56: =IF($A56="","",$D56+$E56) -> 0 | G56: =IF($A56="","",SUMIFS('Trade Log'!$Y$4:$Y$503,'Trade Log'!$L$4:$L$503,$A56)) -> 0 | H56: =IF($A56="","",IF($C56=0,"",$F56-$G56)) | I56: =IF($A56="","",$I55+IF($H56="",0,$H56)) -> 23918.552 | J56: =IF($A56="","",Config!$B$4+$I56) -> 1023918.6 | K56: =IF($A56="","",MAX($J$4:$J56)) -> 1023918.6 | L56: =IF($A56="","",$J56-$K56) -> 0 | M56: =IF(OR($A56="",$K56=0),"",$L56/$K56) -> 0 | N56: =IF($A56="","",SUMIFS('Trade Log'!$K$4:$K$503,'Trade Log'!$H$4:$H$503,$A56)) -> 0 | O56: =IF(OR($A56="",$H56="",Config!$B$4=0),"",$H56/Config!$B$4) | P56: =IF($A56="","",SUM($H$37:$H56)) -> 0 | Q56: =IF($A56="","",IFERROR((AVERAGE($O$37:$O56)-Config!$B$7/Config!$B$6)/STDEV($O$37:$O56)*SQRT(Config!$B$6),"")) | R56: =IF($A56="","",IFERROR((AVERAGE($O$4:$O56)-Config!$B$7/Config!$B$6)/STDEV($O$4:$O56)*SQRT(Config!$B$6),"")) | S56: =IF($H56="",$S55,IF($H56>0,$S55+1,0)) -> 1 | T56: =IF($H56="",$T55,IF($H56<0,$T55+1,0)) -> 0
A57: =IF($A56="","",$A56+1) -> 46288 | B57: =IF($A57="","",TEXT($A57,"ddd")) -> Wed | C57: =IF($A57="","",COUNTIFS('Trade Log'!$L$4:$L$503,$A57)) -> 0 | D57: =IF($A57="","",SUMIFS('Trade Log'!$Q$4:$Q$503,'Trade Log'!$L$4:$L$503,$A57,'Trade Log'!$E$4:$E$503,"LONG")) -> 0 | E57: =IF($A57="","",SUMIFS('Trade Log'!$Q$4:$Q$503,'Trade Log'!$L$4:$L$503,$A57,'Trade Log'!$E$4:$E$503,"SHORT")) -> 0 | F57: =IF($A57="","",$D57+$E57) -> 0 | G57: =IF($A57="","",SUMIFS('Trade Log'!$Y$4:$Y$503,'Trade Log'!$L$4:$L$503,$A57)) -> 0 | H57: =IF($A57="","",IF($C57=0,"",$F57-$G57)) | I57: =IF($A57="","",$I56+IF($H57="",0,$H57)) -> 23918.552 | J57: =IF($A57="","",Config!$B$4+$I57) -> 1023918.6 | K57: =IF($A57="","",MAX($J$4:$J57)) -> 1023918.6 | L57: =IF($A57="","",$J57-$K57) -> 0 | M57: =IF(OR($A57="",$K57=0),"",$L57/$K57) -> 0 | N57: =IF($A57="","",SUMIFS('Trade Log'!$K$4:$K$503,'Trade Log'!$H$4:$H$503,$A57)) -> 0 | O57: =IF(OR($A57="",$H57="",Config!$B$4=0),"",$H57/Config!$B$4) | P57: =IF($A57="","",SUM($H$38:$H57)) -> 0 | Q57: =IF($A57="","",IFERROR((AVERAGE($O$38:$O57)-Config!$B$7/Config!$B$6)/STDEV($O$38:$O57)*SQRT(Config!$B$6),"")) | R57: =IF($A57="","",IFERROR((AVERAGE($O$4:$O57)-Config!$B$7/Config!$B$6)/STDEV($O$4:$O57)*SQRT(Config!$B$6),"")) | S57: =IF($H57="",$S56,IF($H57>0,$S56+1,0)) -> 1 | T57: =IF($H57="",$T56,IF($H57<0,$T56+1,0)) -> 0
A58: =IF($A57="","",$A57+1) -> 46289 | B58: =IF($A58="","",TEXT($A58,"ddd")) -> Thu | C58: =IF($A58="","",COUNTIFS('Trade Log'!$L$4:$L$503,$A58)) -> 0 | D58: =IF($A58="","",SUMIFS('Trade Log'!$Q$4:$Q$503,'Trade Log'!$L$4:$L$503,$A58,'Trade Log'!$E$4:$E$503,"LONG")) -> 0 | E58: =IF($A58="","",SUMIFS('Trade Log'!$Q$4:$Q$503,'Trade Log'!$L$4:$L$503,$A58,'Trade Log'!$E$4:$E$503,"SHORT")) -> 0 | F58: =IF($A58="","",$D58+$E58) -> 0 | G58: =IF($A58="","",SUMIFS('Trade Log'!$Y$4:$Y$503,'Trade Log'!$L$4:$L$503,$A58)) -> 0 | H58: =IF($A58="","",IF($C58=0,"",$F58-$G58)) | I58: =IF($A58="","",$I57+IF($H58="",0,$H58)) -> 23918.552 | J58: =IF($A58="","",Config!$B$4+$I58) -> 1023918.6 | K58: =IF($A58="","",MAX($J$4:$J58)) -> 1023918.6 | L58: =IF($A58="","",$J58-$K58) -> 0 | M58: =IF(OR($A58="",$K58=0),"",$L58/$K58) -> 0 | N58: =IF($A58="","",SUMIFS('Trade Log'!$K$4:$K$503,'Trade Log'!$H$4:$H$503,$A58)) -> 0 | O58: =IF(OR($A58="",$H58="",Config!$B$4=0),"",$H58/Config!$B$4) | P58: =IF($A58="","",SUM($H$39:$H58)) -> 0 | Q58: =IF($A58="","",IFERROR((AVERAGE($O$39:$O58)-Config!$B$7/Config!$B$6)/STDEV($O$39:$O58)*SQRT(Config!$B$6),"")) | R58: =IF($A58="","",IFERROR((AVERAGE($O$4:$O58)-Config!$B$7/Config!$B$6)/STDEV($O$4:$O58)*SQRT(Config!$B$6),"")) | S58: =IF($H58="",$S57,IF($H58>0,$S57+1,0)) -> 1 | T58: =IF($H58="",$T57,IF($H58<0,$T57+1,0)) -> 0
A59: =IF($A58="","",$A58+1) -> 46290 | B59: =IF($A59="","",TEXT($A59,"ddd")) -> Fri | C59: =IF($A59="","",COUNTIFS('Trade Log'!$L$4:$L$503,$A59)) -> 0 | D59: =IF($A59="","",SUMIFS('Trade Log'!$Q$4:$Q$503,'Trade Log'!$L$4:$L$503,$A59,'Trade Log'!$E$4:$E$503,"LONG")) -> 0 | E59: =IF($A59="","",SUMIFS('Trade Log'!$Q$4:$Q$503,'Trade Log'!$L$4:$L$503,$A59,'Trade Log'!$E$4:$E$503,"SHORT")) -> 0 | F59: =IF($A59="","",$D59+$E59) -> 0 | G59: =IF($A59="","",SUMIFS('Trade Log'!$Y$4:$Y$503,'Trade Log'!$L$4:$L$503,$A59)) -> 0 | H59: =IF($A59="","",IF($C59=0,"",$F59-$G59)) | I59: =IF($A59="","",$I58+IF($H59="",0,$H59)) -> 23918.552 | J59: =IF($A59="","",Config!$B$4+$I59) -> 1023918.6 | K59: =IF($A59="","",MAX($J$4:$J59)) -> 1023918.6 | L59: =IF($A59="","",$J59-$K59) -> 0 | M59: =IF(OR($A59="",$K59=0),"",$L59/$K59) -> 0 | N59: =IF($A59="","",SUMIFS('Trade Log'!$K$4:$K$503,'Trade Log'!$H$4:$H$503,$A59)) -> 0 | O59: =IF(OR($A59="",$H59="",Config!$B$4=0),"",$H59/Config!$B$4) | P59: =IF($A59="","",SUM($H$40:$H59)) -> 0 | Q59: =IF($A59="","",IFERROR((AVERAGE($O$40:$O59)-Config!$B$7/Config!$B$6)/STDEV($O$40:$O59)*SQRT(Config!$B$6),"")) | R59: =IF($A59="","",IFERROR((AVERAGE($O$4:$O59)-Config!$B$7/Config!$B$6)/STDEV($O$4:$O59)*SQRT(Config!$B$6),"")) | S59: =IF($H59="",$S58,IF($H59>0,$S58+1,0)) -> 1 | T59: =IF($H59="",$T58,IF($H59<0,$T58+1,0)) -> 0
A60: =IF($A59="","",$A59+1) -> 46291 | B60: =IF($A60="","",TEXT($A60,"ddd")) -> Sat | C60: =IF($A60="","",COUNTIFS('Trade Log'!$L$4:$L$503,$A60)) -> 0 | D60: =IF($A60="","",SUMIFS('Trade Log'!$Q$4:$Q$503,'Trade Log'!$L$4:$L$503,$A60,'Trade Log'!$E$4:$E$503,"LONG")) -> 0 | E60: =IF($A60="","",SUMIFS('Trade Log'!$Q$4:$Q$503,'Trade Log'!$L$4:$L$503,$A60,'Trade Log'!$E$4:$E$503,"SHORT")) -> 0 | F60: =IF($A60="","",$D60+$E60) -> 0 | G60: =IF($A60="","",SUMIFS('Trade Log'!$Y$4:$Y$503,'Trade Log'!$L$4:$L$503,$A60)) -> 0 | H60: =IF($A60="","",IF($C60=0,"",$F60-$G60)) | I60: =IF($A60="","",$I59+IF($H60="",0,$H60)) -> 23918.552 | J60: =IF($A60="","",Config!$B$4+$I60) -> 1023918.6 | K60: =IF($A60="","",MAX($J$4:$J60)) -> 1023918.6 | L60: =IF($A60="","",$J60-$K60) -> 0 | M60: =IF(OR($A60="",$K60=0),"",$L60/$K60) -> 0 | N60: =IF($A60="","",SUMIFS('Trade Log'!$K$4:$K$503,'Trade Log'!$H$4:$H$503,$A60)) -> 0 | O60: =IF(OR($A60="",$H60="",Config!$B$4=0),"",$H60/Config!$B$4) | P60: =IF($A60="","",SUM($H$41:$H60)) -> 0 | Q60: =IF($A60="","",IFERROR((AVERAGE($O$41:$O60)-Config!$B$7/Config!$B$6)/STDEV($O$41:$O60)*SQRT(Config!$B$6),"")) | R60: =IF($A60="","",IFERROR((AVERAGE($O$4:$O60)-Config!$B$7/Config!$B$6)/STDEV($O$4:$O60)*SQRT(Config!$B$6),"")) | S60: =IF($H60="",$S59,IF($H60>0,$S59+1,0)) -> 1 | T60: =IF($H60="",$T59,IF($H60<0,$T59+1,0)) -> 0
A61: =IF($A60="","",$A60+1) -> 46292 | B61: =IF($A61="","",TEXT($A61,"ddd")) -> Sun | C61: =IF($A61="","",COUNTIFS('Trade Log'!$L$4:$L$503,$A61)) -> 0 | D61: =IF($A61="","",SUMIFS('Trade Log'!$Q$4:$Q$503,'Trade Log'!$L$4:$L$503,$A61,'Trade Log'!$E$4:$E$503,"LONG")) -> 0 | E61: =IF($A61="","",SUMIFS('Trade Log'!$Q$4:$Q$503,'Trade Log'!$L$4:$L$503,$A61,'Trade Log'!$E$4:$E$503,"SHORT")) -> 0 | F61: =IF($A61="","",$D61+$E61) -> 0 | G61: =IF($A61="","",SUMIFS('Trade Log'!$Y$4:$Y$503,'Trade Log'!$L$4:$L$503,$A61)) -> 0 | H61: =IF($A61="","",IF($C61=0,"",$F61-$G61)) | I61: =IF($A61="","",$I60+IF($H61="",0,$H61)) -> 23918.552 | J61: =IF($A61="","",Config!$B$4+$I61) -> 1023918.6 | K61: =IF($A61="","",MAX($J$4:$J61)) -> 1023918.6 | L61: =IF($A61="","",$J61-$K61) -> 0 | M61: =IF(OR($A61="",$K61=0),"",$L61/$K61) -> 0 | N61: =IF($A61="","",SUMIFS('Trade Log'!$K$4:$K$503,'Trade Log'!$H$4:$H$503,$A61)) -> 0 | O61: =IF(OR($A61="",$H61="",Config!$B$4=0),"",$H61/Config!$B$4) | P61: =IF($A61="","",SUM($H$42:$H61)) -> 0 | Q61: =IF($A61="","",IFERROR((AVERAGE($O$42:$O61)-Config!$B$7/Config!$B$6)/STDEV($O$42:$O61)*SQRT(Config!$B$6),"")) | R61: =IF($A61="","",IFERROR((AVERAGE($O$4:$O61)-Config!$B$7/Config!$B$6)/STDEV($O$4:$O61)*SQRT(Config!$B$6),"")) | S61: =IF($H61="",$S60,IF($H61>0,$S60+1,0)) -> 1 | T61: =IF($H61="",$T60,IF($H61<0,$T60+1,0)) -> 0
A62: =IF($A61="","",$A61+1) -> 46293 | B62: =IF($A62="","",TEXT($A62,"ddd")) -> Mon | C62: =IF($A62="","",COUNTIFS('Trade Log'!$L$4:$L$503,$A62)) -> 0 | D62: =IF($A62="","",SUMIFS('Trade Log'!$Q$4:$Q$503,'Trade Log'!$L$4:$L$503,$A62,'Trade Log'!$E$4:$E$503,"LONG")) -> 0 | E62: =IF($A62="","",SUMIFS('Trade Log'!$Q$4:$Q$503,'Trade Log'!$L$4:$L$503,$A62,'Trade Log'!$E$4:$E$503,"SHORT")) -> 0 | F62: =IF($A62="","",$D62+$E62) -> 0 | G62: =IF($A62="","",SUMIFS('Trade Log'!$Y$4:$Y$503,'Trade Log'!$L$4:$L$503,$A62)) -> 0 | H62: =IF($A62="","",IF($C62=0,"",$F62-$G62)) | I62: =IF($A62="","",$I61+IF($H62="",0,$H62)) -> 23918.552 | J62: =IF($A62="","",Config!$B$4+$I62) -> 1023918.6 | K62: =IF($A62="","",MAX($J$4:$J62)) -> 1023918.6 | L62: =IF($A62="","",$J62-$K62) -> 0 | M62: =IF(OR($A62="",$K62=0),"",$L62/$K62) -> 0 | N62: =IF($A62="","",SUMIFS('Trade Log'!$K$4:$K$503,'Trade Log'!$H$4:$H$503,$A62)) -> 0 | O62: =IF(OR($A62="",$H62="",Config!$B$4=0),"",$H62/Config!$B$4) | P62: =IF($A62="","",SUM($H$43:$H62)) -> 0 | Q62: =IF($A62="","",IFERROR((AVERAGE($O$43:$O62)-Config!$B$7/Config!$B$6)/STDEV($O$43:$O62)*SQRT(Config!$B$6),"")) | R62: =IF($A62="","",IFERROR((AVERAGE($O$4:$O62)-Config!$B$7/Config!$B$6)/STDEV($O$4:$O62)*SQRT(Config!$B$6),"")) | S62: =IF($H62="",$S61,IF($H62>0,$S61+1,0)) -> 1 | T62: =IF($H62="",$T61,IF($H62<0,$T61+1,0)) -> 0
A63: =IF($A62="","",$A62+1) -> 46294 | B63: =IF($A63="","",TEXT($A63,"ddd")) -> Tue | C63: =IF($A63="","",COUNTIFS('Trade Log'!$L$4:$L$503,$A63)) -> 0 | D63: =IF($A63="","",SUMIFS('Trade Log'!$Q$4:$Q$503,'Trade Log'!$L$4:$L$503,$A63,'Trade Log'!$E$4:$E$503,"LONG")) -> 0 | E63: =IF($A63="","",SUMIFS('Trade Log'!$Q$4:$Q$503,'Trade Log'!$L$4:$L$503,$A63,'Trade Log'!$E$4:$E$503,"SHORT")) -> 0 | F63: =IF($A63="","",$D63+$E63) -> 0 | G63: =IF($A63="","",SUMIFS('Trade Log'!$Y$4:$Y$503,'Trade Log'!$L$4:$L$503,$A63)) -> 0 | H63: =IF($A63="","",IF($C63=0,"",$F63-$G63)) | I63: =IF($A63="","",$I62+IF($H63="",0,$H63)) -> 23918.552 | J63: =IF($A63="","",Config!$B$4+$I63) -> 1023918.6 | K63: =IF($A63="","",MAX($J$4:$J63)) -> 1023918.6 | L63: =IF($A63="","",$J63-$K63) -> 0 | M63: =IF(OR($A63="",$K63=0),"",$L63/$K63) -> 0 | N63: =IF($A63="","",SUMIFS('Trade Log'!$K$4:$K$503,'Trade Log'!$H$4:$H$503,$A63)) -> 0 | O63: =IF(OR($A63="",$H63="",Config!$B$4=0),"",$H63/Config!$B$4) | P63: =IF($A63="","",SUM($H$44:$H63)) -> 0 | Q63: =IF($A63="","",IFERROR((AVERAGE($O$44:$O63)-Config!$B$7/Config!$B$6)/STDEV($O$44:$O63)*SQRT(Config!$B$6),"")) | R63: =IF($A63="","",IFERROR((AVERAGE($O$4:$O63)-Config!$B$7/Config!$B$6)/STDEV($O$4:$O63)*SQRT(Config!$B$6),"")) | S63: =IF($H63="",$S62,IF($H63>0,$S62+1,0)) -> 1 | T63: =IF($H63="",$T62,IF($H63<0,$T62+1,0)) -> 0
A64: =IF($A63="","",$A63+1) -> 46295 | B64: =IF($A64="","",TEXT($A64,"ddd")) -> Wed | C64: =IF($A64="","",COUNTIFS('Trade Log'!$L$4:$L$503,$A64)) -> 0 | D64: =IF($A64="","",SUMIFS('Trade Log'!$Q$4:$Q$503,'Trade Log'!$L$4:$L$503,$A64,'Trade Log'!$E$4:$E$503,"LONG")) -> 0 | E64: =IF($A64="","",SUMIFS('Trade Log'!$Q$4:$Q$503,'Trade Log'!$L$4:$L$503,$A64,'Trade Log'!$E$4:$E$503,"SHORT")) -> 0 | F64: =IF($A64="","",$D64+$E64) -> 0 | G64: =IF($A64="","",SUMIFS('Trade Log'!$Y$4:$Y$503,'Trade Log'!$L$4:$L$503,$A64)) -> 0 | H64: =IF($A64="","",IF($C64=0,"",$F64-$G64)) | I64: =IF($A64="","",$I63+IF($H64="",0,$H64)) -> 23918.552 | J64: =IF($A64="","",Config!$B$4+$I64) -> 1023918.6 | K64: =IF($A64="","",MAX($J$4:$J64)) -> 1023918.6 | L64: =IF($A64="","",$J64-$K64) -> 0 | M64: =IF(OR($A64="",$K64=0),"",$L64/$K64) -> 0 | N64: =IF($A64="","",SUMIFS('Trade Log'!$K$4:$K$503,'Trade Log'!$H$4:$H$503,$A64)) -> 0 | O64: =IF(OR($A64="",$H64="",Config!$B$4=0),"",$H64/Config!$B$4) | P64: =IF($A64="","",SUM($H$45:$H64)) -> 0 | Q64: =IF($A64="","",IFERROR((AVERAGE($O$45:$O64)-Config!$B$7/Config!$B$6)/STDEV($O$45:$O64)*SQRT(Config!$B$6),"")) | R64: =IF($A64="","",IFERROR((AVERAGE($O$5:$O64)-Config!$B$7/Config!$B$6)/STDEV($O$5:$O64)*SQRT(Config!$B$6),"")) | S64: =IF($H64="",$S63,IF($H64>0,$S63+1,0)) -> 1 | T64: =IF($H64="",$T63,IF($H64<0,$T63+1,0)) -> 0
A65: =IF($A64="","",$A64+1) -> 46296 | B65: =IF($A65="","",TEXT($A65,"ddd")) -> Thu | C65: =IF($A65="","",COUNTIFS('Trade Log'!$L$4:$L$503,$A65)) -> 0 | D65: =IF($A65="","",SUMIFS('Trade Log'!$Q$4:$Q$503,'Trade Log'!$L$4:$L$503,$A65,'Trade Log'!$E$4:$E$503,"LONG")) -> 0 | E65: =IF($A65="","",SUMIFS('Trade Log'!$Q$4:$Q$503,'Trade Log'!$L$4:$L$503,$A65,'Trade Log'!$E$4:$E$503,"SHORT")) -> 0 | F65: =IF($A65="","",$D65+$E65) -> 0 | G65: =IF($A65="","",SUMIFS('Trade Log'!$Y$4:$Y$503,'Trade Log'!$L$4:$L$503,$A65)) -> 0 | H65: =IF($A65="","",IF($C65=0,"",$F65-$G65)) | I65: =IF($A65="","",$I64+IF($H65="",0,$H65)) -> 23918.552 | J65: =IF($A65="","",Config!$B$4+$I65) -> 1023918.6 | K65: =IF($A65="","",MAX($J$4:$J65)) -> 1023918.6 | L65: =IF($A65="","",$J65-$K65) -> 0 | M65: =IF(OR($A65="",$K65=0),"",$L65/$K65) -> 0 | N65: =IF($A65="","",SUMIFS('Trade Log'!$K$4:$K$503,'Trade Log'!$H$4:$H$503,$A65)) -> 0 | O65: =IF(OR($A65="",$H65="",Config!$B$4=0),"",$H65/Config!$B$4) | P65: =IF($A65="","",SUM($H$46:$H65)) -> 0 | Q65: =IF($A65="","",IFERROR((AVERAGE($O$46:$O65)-Config!$B$7/Config!$B$6)/STDEV($O$46:$O65)*SQRT(Config!$B$6),"")) | R65: =IF($A65="","",IFERROR((AVERAGE($O$6:$O65)-Config!$B$7/Config!$B$6)/STDEV($O$6:$O65)*SQRT(Config!$B$6),"")) | S65: =IF($H65="",$S64,IF($H65>0,$S64+1,0)) -> 1 | T65: =IF($H65="",$T64,IF($H65<0,$T64+1,0)) -> 0
A66: =IF($A65="","",$A65+1) -> 46297 | B66: =IF($A66="","",TEXT($A66,"ddd")) -> Fri | C66: =IF($A66="","",COUNTIFS('Trade Log'!$L$4:$L$503,$A66)) -> 0 | D66: =IF($A66="","",SUMIFS('Trade Log'!$Q$4:$Q$503,'Trade Log'!$L$4:$L$503,$A66,'Trade Log'!$E$4:$E$503,"LONG")) -> 0 | E66: =IF($A66="","",SUMIFS('Trade Log'!$Q$4:$Q$503,'Trade Log'!$L$4:$L$503,$A66,'Trade Log'!$E$4:$E$503,"SHORT")) -> 0 | F66: =IF($A66="","",$D66+$E66) -> 0 | G66: =IF($A66="","",SUMIFS('Trade Log'!$Y$4:$Y$503,'Trade Log'!$L$4:$L$503,$A66)) -> 0 | H66: =IF($A66="","",IF($C66=0,"",$F66-$G66)) | I66: =IF($A66="","",$I65+IF($H66="",0,$H66)) -> 23918.552 | J66: =IF($A66="","",Config!$B$4+$I66) -> 1023918.6 | K66: =IF($A66="","",MAX($J$4:$J66)) -> 1023918.6 | L66: =IF($A66="","",$J66-$K66) -> 0 | M66: =IF(OR($A66="",$K66=0),"",$L66/$K66) -> 0 | N66: =IF($A66="","",SUMIFS('Trade Log'!$K$4:$K$503,'Trade Log'!$H$4:$H$503,$A66)) -> 0 | O66: =IF(OR($A66="",$H66="",Config!$B$4=0),"",$H66/Config!$B$4) | P66: =IF($A66="","",SUM($H$47:$H66)) -> 0 | Q66: =IF($A66="","",IFERROR((AVERAGE($O$47:$O66)-Config!$B$7/Config!$B$6)/STDEV($O$47:$O66)*SQRT(Config!$B$6),"")) | R66: =IF($A66="","",IFERROR((AVERAGE($O$7:$O66)-Config!$B$7/Config!$B$6)/STDEV($O$7:$O66)*SQRT(Config!$B$6),"")) | S66: =IF($H66="",$S65,IF($H66>0,$S65+1,0)) -> 1 | T66: =IF($H66="",$T65,IF($H66<0,$T65+1,0)) -> 0
A67: =IF($A66="","",$A66+1) -> 46298 | B67: =IF($A67="","",TEXT($A67,"ddd")) -> Sat | C67: =IF($A67="","",COUNTIFS('Trade Log'!$L$4:$L$503,$A67)) -> 0 | D67: =IF($A67="","",SUMIFS('Trade Log'!$Q$4:$Q$503,'Trade Log'!$L$4:$L$503,$A67,'Trade Log'!$E$4:$E$503,"LONG")) -> 0 | E67: =IF($A67="","",SUMIFS('Trade Log'!$Q$4:$Q$503,'Trade Log'!$L$4:$L$503,$A67,'Trade Log'!$E$4:$E$503,"SHORT")) -> 0 | F67: =IF($A67="","",$D67+$E67) -> 0 | G67: =IF($A67="","",SUMIFS('Trade Log'!$Y$4:$Y$503,'Trade Log'!$L$4:$L$503,$A67)) -> 0 | H67: =IF($A67="","",IF($C67=0,"",$F67-$G67)) | I67: =IF($A67="","",$I66+IF($H67="",0,$H67)) -> 23918.552 | J67: =IF($A67="","",Config!$B$4+$I67) -> 1023918.6 | K67: =IF($A67="","",MAX($J$4:$J67)) -> 1023918.6 | L67: =IF($A67="","",$J67-$K67) -> 0 | M67: =IF(OR($A67="",$K67=0),"",$L67/$K67) -> 0 | N67: =IF($A67="","",SUMIFS('Trade Log'!$K$4:$K$503,'Trade Log'!$H$4:$H$503,$A67)) -> 0 | O67: =IF(OR($A67="",$H67="",Config!$B$4=0),"",$H67/Config!$B$4) | P67: =IF($A67="","",SUM($H$48:$H67)) -> 0 | Q67: =IF($A67="","",IFERROR((AVERAGE($O$48:$O67)-Config!$B$7/Config!$B$6)/STDEV($O$48:$O67)*SQRT(Config!$B$6),"")) | R67: =IF($A67="","",IFERROR((AVERAGE($O$8:$O67)-Config!$B$7/Config!$B$6)/STDEV($O$8:$O67)*SQRT(Config!$B$6),"")) | S67: =IF($H67="",$S66,IF($H67>0,$S66+1,0)) -> 1 | T67: =IF($H67="",$T66,IF($H67<0,$T66+1,0)) -> 0
A68: =IF($A67="","",$A67+1) -> 46299 | B68: =IF($A68="","",TEXT($A68,"ddd")) -> Sun | C68: =IF($A68="","",COUNTIFS('Trade Log'!$L$4:$L$503,$A68)) -> 0 | D68: =IF($A68="","",SUMIFS('Trade Log'!$Q$4:$Q$503,'Trade Log'!$L$4:$L$503,$A68,'Trade Log'!$E$4:$E$503,"LONG")) -> 0 | E68: =IF($A68="","",SUMIFS('Trade Log'!$Q$4:$Q$503,'Trade Log'!$L$4:$L$503,$A68,'Trade Log'!$E$4:$E$503,"SHORT")) -> 0 | F68: =IF($A68="","",$D68+$E68) -> 0 | G68: =IF($A68="","",SUMIFS('Trade Log'!$Y$4:$Y$503,'Trade Log'!$L$4:$L$503,$A68)) -> 0 | H68: =IF($A68="","",IF($C68=0,"",$F68-$G68)) | I68: =IF($A68="","",$I67+IF($H68="",0,$H68)) -> 23918.552 | J68: =IF($A68="","",Config!$B$4+$I68) -> 1023918.6 | K68: =IF($A68="","",MAX($J$4:$J68)) -> 1023918.6 | L68: =IF($A68="","",$J68-$K68) -> 0 | M68: =IF(OR($A68="",$K68=0),"",$L68/$K68) -> 0 | N68: =IF($A68="","",SUMIFS('Trade Log'!$K$4:$K$503,'Trade Log'!$H$4:$H$503,$A68)) -> 0 | O68: =IF(OR($A68="",$H68="",Config!$B$4=0),"",$H68/Config!$B$4) | P68: =IF($A68="","",SUM($H$49:$H68)) -> 0 | Q68: =IF($A68="","",IFERROR((AVERAGE($O$49:$O68)-Config!$B$7/Config!$B$6)/STDEV($O$49:$O68)*SQRT(Config!$B$6),"")) | R68: =IF($A68="","",IFERROR((AVERAGE($O$9:$O68)-Config!$B$7/Config!$B$6)/STDEV($O$9:$O68)*SQRT(Config!$B$6),"")) | S68: =IF($H68="",$S67,IF($H68>0,$S67+1,0)) -> 1 | T68: =IF($H68="",$T67,IF($H68<0,$T67+1,0)) -> 0
A69: =IF($A68="","",$A68+1) -> 46300 | B69: =IF($A69="","",TEXT($A69,"ddd")) -> Mon | C69: =IF($A69="","",COUNTIFS('Trade Log'!$L$4:$L$503,$A69)) -> 0 | D69: =IF($A69="","",SUMIFS('Trade Log'!$Q$4:$Q$503,'Trade Log'!$L$4:$L$503,$A69,'Trade Log'!$E$4:$E$503,"LONG")) -> 0 | E69: =IF($A69="","",SUMIFS('Trade Log'!$Q$4:$Q$503,'Trade Log'!$L$4:$L$503,$A69,'Trade Log'!$E$4:$E$503,"SHORT")) -> 0 | F69: =IF($A69="","",$D69+$E69) -> 0 | G69: =IF($A69="","",SUMIFS('Trade Log'!$Y$4:$Y$503,'Trade Log'!$L$4:$L$503,$A69)) -> 0 | H69: =IF($A69="","",IF($C69=0,"",$F69-$G69)) | I69: =IF($A69="","",$I68+IF($H69="",0,$H69)) -> 23918.552 | J69: =IF($A69="","",Config!$B$4+$I69) -> 1023918.6 | K69: =IF($A69="","",MAX($J$4:$J69)) -> 1023918.6 | L69: =IF($A69="","",$J69-$K69) -> 0 | M69: =IF(OR($A69="",$K69=0),"",$L69/$K69) -> 0 | N69: =IF($A69="","",SUMIFS('Trade Log'!$K$4:$K$503,'Trade Log'!$H$4:$H$503,$A69)) -> 0 | O69: =IF(OR($A69="",$H69="",Config!$B$4=0),"",$H69/Config!$B$4) | P69: =IF($A69="","",SUM($H$50:$H69)) -> 0 | Q69: =IF($A69="","",IFERROR((AVERAGE($O$50:$O69)-Config!$B$7/Config!$B$6)/STDEV($O$50:$O69)*SQRT(Config!$B$6),"")) | R69: =IF($A69="","",IFERROR((AVERAGE($O$10:$O69)-Config!$B$7/Config!$B$6)/STDEV($O$10:$O69)*SQRT(Config!$B$6),"")) | S69: =IF($H69="",$S68,IF($H69>0,$S68+1,0)) -> 1 | T69: =IF($H69="",$T68,IF($H69<0,$T68+1,0)) -> 0
A70: =IF($A69="","",$A69+1) -> 46301 | B70: =IF($A70="","",TEXT($A70,"ddd")) -> Tue | C70: =IF($A70="","",COUNTIFS('Trade Log'!$L$4:$L$503,$A70)) -> 0 | D70: =IF($A70="","",SUMIFS('Trade Log'!$Q$4:$Q$503,'Trade Log'!$L$4:$L$503,$A70,'Trade Log'!$E$4:$E$503,"LONG")) -> 0 | E70: =IF($A70="","",SUMIFS('Trade Log'!$Q$4:$Q$503,'Trade Log'!$L$4:$L$503,$A70,'Trade Log'!$E$4:$E$503,"SHORT")) -> 0 | F70: =IF($A70="","",$D70+$E70) -> 0 | G70: =IF($A70="","",SUMIFS('Trade Log'!$Y$4:$Y$503,'Trade Log'!$L$4:$L$503,$A70)) -> 0 | H70: =IF($A70="","",IF($C70=0,"",$F70-$G70)) | I70: =IF($A70="","",$I69+IF($H70="",0,$H70)) -> 23918.552 | J70: =IF($A70="","",Config!$B$4+$I70) -> 1023918.6 | K70: =IF($A70="","",MAX($J$4:$J70)) -> 1023918.6 | L70: =IF($A70="","",$J70-$K70) -> 0 | M70: =IF(OR($A70="",$K70=0),"",$L70/$K70) -> 0 | N70: =IF($A70="","",SUMIFS('Trade Log'!$K$4:$K$503,'Trade Log'!$H$4:$H$503,$A70)) -> 0 | O70: =IF(OR($A70="",$H70="",Config!$B$4=0),"",$H70/Config!$B$4) | P70: =IF($A70="","",SUM($H$51:$H70)) -> 0 | Q70: =IF($A70="","",IFERROR((AVERAGE($O$51:$O70)-Config!$B$7/Config!$B$6)/STDEV($O$51:$O70)*SQRT(Config!$B$6),"")) | R70: =IF($A70="","",IFERROR((AVERAGE($O$11:$O70)-Config!$B$7/Config!$B$6)/STDEV($O$11:$O70)*SQRT(Config!$B$6),"")) | S70: =IF($H70="",$S69,IF($H70>0,$S69+1,0)) -> 1 | T70: =IF($H70="",$T69,IF($H70<0,$T69+1,0)) -> 0
A71: =IF($A70="","",$A70+1) -> 46302 | B71: =IF($A71="","",TEXT($A71,"ddd")) -> Wed | C71: =IF($A71="","",COUNTIFS('Trade Log'!$L$4:$L$503,$A71)) -> 0 | D71: =IF($A71="","",SUMIFS('Trade Log'!$Q$4:$Q$503,'Trade Log'!$L$4:$L$503,$A71,'Trade Log'!$E$4:$E$503,"LONG")) -> 0 | E71: =IF($A71="","",SUMIFS('Trade Log'!$Q$4:$Q$503,'Trade Log'!$L$4:$L$503,$A71,'Trade Log'!$E$4:$E$503,"SHORT")) -> 0 | F71: =IF($A71="","",$D71+$E71) -> 0 | G71: =IF($A71="","",SUMIFS('Trade Log'!$Y$4:$Y$503,'Trade Log'!$L$4:$L$503,$A71)) -> 0 | H71: =IF($A71="","",IF($C71=0,"",$F71-$G71)) | I71: =IF($A71="","",$I70+IF($H71="",0,$H71)) -> 23918.552 | J71: =IF($A71="","",Config!$B$4+$I71) -> 1023918.6 | K71: =IF($A71="","",MAX($J$4:$J71)) -> 1023918.6 | L71: =IF($A71="","",$J71-$K71) -> 0 | M71: =IF(OR($A71="",$K71=0),"",$L71/$K71) -> 0 | N71: =IF($A71="","",SUMIFS('Trade Log'!$K$4:$K$503,'Trade Log'!$H$4:$H$503,$A71)) -> 0 | O71: =IF(OR($A71="",$H71="",Config!$B$4=0),"",$H71/Config!$B$4) | P71: =IF($A71="","",SUM($H$52:$H71)) -> 0 | Q71: =IF($A71="","",IFERROR((AVERAGE($O$52:$O71)-Config!$B$7/Config!$B$6)/STDEV($O$52:$O71)*SQRT(Config!$B$6),"")) | R71: =IF($A71="","",IFERROR((AVERAGE($O$12:$O71)-Config!$B$7/Config!$B$6)/STDEV($O$12:$O71)*SQRT(Config!$B$6),"")) | S71: =IF($H71="",$S70,IF($H71>0,$S70+1,0)) -> 1 | T71: =IF($H71="",$T70,IF($H71<0,$T70+1,0)) -> 0
A72: =IF($A71="","",$A71+1) -> 46303 | B72: =IF($A72="","",TEXT($A72,"ddd")) -> Thu | C72: =IF($A72="","",COUNTIFS('Trade Log'!$L$4:$L$503,$A72)) -> 0 | D72: =IF($A72="","",SUMIFS('Trade Log'!$Q$4:$Q$503,'Trade Log'!$L$4:$L$503,$A72,'Trade Log'!$E$4:$E$503,"LONG")) -> 0 | E72: =IF($A72="","",SUMIFS('Trade Log'!$Q$4:$Q$503,'Trade Log'!$L$4:$L$503,$A72,'Trade Log'!$E$4:$E$503,"SHORT")) -> 0 | F72: =IF($A72="","",$D72+$E72) -> 0 | G72: =IF($A72="","",SUMIFS('Trade Log'!$Y$4:$Y$503,'Trade Log'!$L$4:$L$503,$A72)) -> 0 | H72: =IF($A72="","",IF($C72=0,"",$F72-$G72)) | I72: =IF($A72="","",$I71+IF($H72="",0,$H72)) -> 23918.552 | J72: =IF($A72="","",Config!$B$4+$I72) -> 1023918.6 | K72: =IF($A72="","",MAX($J$4:$J72)) -> 1023918.6 | L72: =IF($A72="","",$J72-$K72) -> 0 | M72: =IF(OR($A72="",$K72=0),"",$L72/$K72) -> 0 | N72: =IF($A72="","",SUMIFS('Trade Log'!$K$4:$K$503,'Trade Log'!$H$4:$H$503,$A72)) -> 0 | O72: =IF(OR($A72="",$H72="",Config!$B$4=0),"",$H72/Config!$B$4) | P72: =IF($A72="","",SUM($H$53:$H72)) -> 0 | Q72: =IF($A72="","",IFERROR((AVERAGE($O$53:$O72)-Config!$B$7/Config!$B$6)/STDEV($O$53:$O72)*SQRT(Config!$B$6),"")) | R72: =IF($A72="","",IFERROR((AVERAGE($O$13:$O72)-Config!$B$7/Config!$B$6)/STDEV($O$13:$O72)*SQRT(Config!$B$6),"")) | S72: =IF($H72="",$S71,IF($H72>0,$S71+1,0)) -> 1 | T72: =IF($H72="",$T71,IF($H72<0,$T71+1,0)) -> 0
A73: =IF($A72="","",$A72+1) -> 46304 | B73: =IF($A73="","",TEXT($A73,"ddd")) -> Fri | C73: =IF($A73="","",COUNTIFS('Trade Log'!$L$4:$L$503,$A73)) -> 0 | D73: =IF($A73="","",SUMIFS('Trade Log'!$Q$4:$Q$503,'Trade Log'!$L$4:$L$503,$A73,'Trade Log'!$E$4:$E$503,"LONG")) -> 0 | E73: =IF($A73="","",SUMIFS('Trade Log'!$Q$4:$Q$503,'Trade Log'!$L$4:$L$503,$A73,'Trade Log'!$E$4:$E$503,"SHORT")) -> 0 | F73: =IF($A73="","",$D73+$E73) -> 0 | G73: =IF($A73="","",SUMIFS('Trade Log'!$Y$4:$Y$503,'Trade Log'!$L$4:$L$503,$A73)) -> 0 | H73: =IF($A73="","",IF($C73=0,"",$F73-$G73)) | I73: =IF($A73="","",$I72+IF($H73="",0,$H73)) -> 23918.552 | J73: =IF($A73="","",Config!$B$4+$I73) -> 1023918.6 | K73: =IF($A73="","",MAX($J$4:$J73)) -> 1023918.6 | L73: =IF($A73="","",$J73-$K73) -> 0 | M73: =IF(OR($A73="",$K73=0),"",$L73/$K73) -> 0 | N73: =IF($A73="","",SUMIFS('Trade Log'!$K$4:$K$503,'Trade Log'!$H$4:$H$503,$A73)) -> 0 | O73: =IF(OR($A73="",$H73="",Config!$B$4=0),"",$H73/Config!$B$4) | P73: =IF($A73="","",SUM($H$54:$H73)) -> 0 | Q73: =IF($A73="","",IFERROR((AVERAGE($O$54:$O73)-Config!$B$7/Config!$B$6)/STDEV($O$54:$O73)*SQRT(Config!$B$6),"")) | R73: =IF($A73="","",IFERROR((AVERAGE($O$14:$O73)-Config!$B$7/Config!$B$6)/STDEV($O$14:$O73)*SQRT(Config!$B$6),"")) | S73: =IF($H73="",$S72,IF($H73>0,$S72+1,0)) -> 1 | T73: =IF($H73="",$T72,IF($H73<0,$T72+1,0)) -> 0
A74: =IF($A73="","",$A73+1) -> 46305 | B74: =IF($A74="","",TEXT($A74,"ddd")) -> Sat | C74: =IF($A74="","",COUNTIFS('Trade Log'!$L$4:$L$503,$A74)) -> 0 | D74: =IF($A74="","",SUMIFS('Trade Log'!$Q$4:$Q$503,'Trade Log'!$L$4:$L$503,$A74,'Trade Log'!$E$4:$E$503,"LONG")) -> 0 | E74: =IF($A74="","",SUMIFS('Trade Log'!$Q$4:$Q$503,'Trade Log'!$L$4:$L$503,$A74,'Trade Log'!$E$4:$E$503,"SHORT")) -> 0 | F74: =IF($A74="","",$D74+$E74) -> 0 | G74: =IF($A74="","",SUMIFS('Trade Log'!$Y$4:$Y$503,'Trade Log'!$L$4:$L$503,$A74)) -> 0 | H74: =IF($A74="","",IF($C74=0,"",$F74-$G74)) | I74: =IF($A74="","",$I73+IF($H74="",0,$H74)) -> 23918.552 | J74: =IF($A74="","",Config!$B$4+$I74) -> 1023918.6 | K74: =IF($A74="","",MAX($J$4:$J74)) -> 1023918.6 | L74: =IF($A74="","",$J74-$K74) -> 0 | M74: =IF(OR($A74="",$K74=0),"",$L74/$K74) -> 0 | N74: =IF($A74="","",SUMIFS('Trade Log'!$K$4:$K$503,'Trade Log'!$H$4:$H$503,$A74)) -> 0 | O74: =IF(OR($A74="",$H74="",Config!$B$4=0),"",$H74/Config!$B$4) | P74: =IF($A74="","",SUM($H$55:$H74)) -> 0 | Q74: =IF($A74="","",IFERROR((AVERAGE($O$55:$O74)-Config!$B$7/Config!$B$6)/STDEV($O$55:$O74)*SQRT(Config!$B$6),"")) | R74: =IF($A74="","",IFERROR((AVERAGE($O$15:$O74)-Config!$B$7/Config!$B$6)/STDEV($O$15:$O74)*SQRT(Config!$B$6),"")) | S74: =IF($H74="",$S73,IF($H74>0,$S73+1,0)) -> 1 | T74: =IF($H74="",$T73,IF($H74<0,$T73+1,0)) -> 0
A75: =IF($A74="","",$A74+1) -> 46306 | B75: =IF($A75="","",TEXT($A75,"ddd")) -> Sun | C75: =IF($A75="","",COUNTIFS('Trade Log'!$L$4:$L$503,$A75)) -> 0 | D75: =IF($A75="","",SUMIFS('Trade Log'!$Q$4:$Q$503,'Trade Log'!$L$4:$L$503,$A75,'Trade Log'!$E$4:$E$503,"LONG")) -> 0 | E75: =IF($A75="","",SUMIFS('Trade Log'!$Q$4:$Q$503,'Trade Log'!$L$4:$L$503,$A75,'Trade Log'!$E$4:$E$503,"SHORT")) -> 0 | F75: =IF($A75="","",$D75+$E75) -> 0 | G75: =IF($A75="","",SUMIFS('Trade Log'!$Y$4:$Y$503,'Trade Log'!$L$4:$L$503,$A75)) -> 0 | H75: =IF($A75="","",IF($C75=0,"",$F75-$G75)) | I75: =IF($A75="","",$I74+IF($H75="",0,$H75)) -> 23918.552 | J75: =IF($A75="","",Config!$B$4+$I75) -> 1023918.6 | K75: =IF($A75="","",MAX($J$4:$J75)) -> 1023918.6 | L75: =IF($A75="","",$J75-$K75) -> 0 | M75: =IF(OR($A75="",$K75=0),"",$L75/$K75) -> 0 | N75: =IF($A75="","",SUMIFS('Trade Log'!$K$4:$K$503,'Trade Log'!$H$4:$H$503,$A75)) -> 0 | O75: =IF(OR($A75="",$H75="",Config!$B$4=0),"",$H75/Config!$B$4) | P75: =IF($A75="","",SUM($H$56:$H75)) -> 0 | Q75: =IF($A75="","",IFERROR((AVERAGE($O$56:$O75)-Config!$B$7/Config!$B$6)/STDEV($O$56:$O75)*SQRT(Config!$B$6),"")) | R75: =IF($A75="","",IFERROR((AVERAGE($O$16:$O75)-Config!$B$7/Config!$B$6)/STDEV($O$16:$O75)*SQRT(Config!$B$6),"")) | S75: =IF($H75="",$S74,IF($H75>0,$S74+1,0)) -> 1 | T75: =IF($H75="",$T74,IF($H75<0,$T74+1,0)) -> 0
A76: =IF($A75="","",$A75+1) -> 46307 | B76: =IF($A76="","",TEXT($A76,"ddd")) -> Mon | C76: =IF($A76="","",COUNTIFS('Trade Log'!$L$4:$L$503,$A76)) -> 0 | D76: =IF($A76="","",SUMIFS('Trade Log'!$Q$4:$Q$503,'Trade Log'!$L$4:$L$503,$A76,'Trade Log'!$E$4:$E$503,"LONG")) -> 0 | E76: =IF($A76="","",SUMIFS('Trade Log'!$Q$4:$Q$503,'Trade Log'!$L$4:$L$503,$A76,'Trade Log'!$E$4:$E$503,"SHORT")) -> 0 | F76: =IF($A76="","",$D76+$E76) -> 0 | G76: =IF($A76="","",SUMIFS('Trade Log'!$Y$4:$Y$503,'Trade Log'!$L$4:$L$503,$A76)) -> 0 | H76: =IF($A76="","",IF($C76=0,"",$F76-$G76)) | I76: =IF($A76="","",$I75+IF($H76="",0,$H76)) -> 23918.552 | J76: =IF($A76="","",Config!$B$4+$I76) -> 1023918.6 | K76: =IF($A76="","",MAX($J$4:$J76)) -> 1023918.6 | L76: =IF($A76="","",$J76-$K76) -> 0 | M76: =IF(OR($A76="",$K76=0),"",$L76/$K76) -> 0 | N76: =IF($A76="","",SUMIFS('Trade Log'!$K$4:$K$503,'Trade Log'!$H$4:$H$503,$A76)) -> 0 | O76: =IF(OR($A76="",$H76="",Config!$B$4=0),"",$H76/Config!$B$4) | P76: =IF($A76="","",SUM($H$57:$H76)) -> 0 | Q76: =IF($A76="","",IFERROR((AVERAGE($O$57:$O76)-Config!$B$7/Config!$B$6)/STDEV($O$57:$O76)*SQRT(Config!$B$6),"")) | R76: =IF($A76="","",IFERROR((AVERAGE($O$17:$O76)-Config!$B$7/Config!$B$6)/STDEV($O$17:$O76)*SQRT(Config!$B$6),"")) | S76: =IF($H76="",$S75,IF($H76>0,$S75+1,0)) -> 1 | T76: =IF($H76="",$T75,IF($H76<0,$T75+1,0)) -> 0
A77: =IF($A76="","",$A76+1) -> 46308 | B77: =IF($A77="","",TEXT($A77,"ddd")) -> Tue | C77: =IF($A77="","",COUNTIFS('Trade Log'!$L$4:$L$503,$A77)) -> 0 | D77: =IF($A77="","",SUMIFS('Trade Log'!$Q$4:$Q$503,'Trade Log'!$L$4:$L$503,$A77,'Trade Log'!$E$4:$E$503,"LONG")) -> 0 | E77: =IF($A77="","",SUMIFS('Trade Log'!$Q$4:$Q$503,'Trade Log'!$L$4:$L$503,$A77,'Trade Log'!$E$4:$E$503,"SHORT")) -> 0 | F77: =IF($A77="","",$D77+$E77) -> 0 | G77: =IF($A77="","",SUMIFS('Trade Log'!$Y$4:$Y$503,'Trade Log'!$L$4:$L$503,$A77)) -> 0 | H77: =IF($A77="","",IF($C77=0,"",$F77-$G77)) | I77: =IF($A77="","",$I76+IF($H77="",0,$H77)) -> 23918.552 | J77: =IF($A77="","",Config!$B$4+$I77) -> 1023918.6 | K77: =IF($A77="","",MAX($J$4:$J77)) -> 1023918.6 | L77: =IF($A77="","",$J77-$K77) -> 0 | M77: =IF(OR($A77="",$K77=0),"",$L77/$K77) -> 0 | N77: =IF($A77="","",SUMIFS('Trade Log'!$K$4:$K$503,'Trade Log'!$H$4:$H$503,$A77)) -> 0 | O77: =IF(OR($A77="",$H77="",Config!$B$4=0),"",$H77/Config!$B$4) | P77: =IF($A77="","",SUM($H$58:$H77)) -> 0 | Q77: =IF($A77="","",IFERROR((AVERAGE($O$58:$O77)-Config!$B$7/Config!$B$6)/STDEV($O$58:$O77)*SQRT(Config!$B$6),"")) | R77: =IF($A77="","",IFERROR((AVERAGE($O$18:$O77)-Config!$B$7/Config!$B$6)/STDEV($O$18:$O77)*SQRT(Config!$B$6),"")) | S77: =IF($H77="",$S76,IF($H77>0,$S76+1,0)) -> 1 | T77: =IF($H77="",$T76,IF($H77<0,$T76+1,0)) -> 0
A78: =IF($A77="","",$A77+1) -> 46309 | B78: =IF($A78="","",TEXT($A78,"ddd")) -> Wed | C78: =IF($A78="","",COUNTIFS('Trade Log'!$L$4:$L$503,$A78)) -> 0 | D78: =IF($A78="","",SUMIFS('Trade Log'!$Q$4:$Q$503,'Trade Log'!$L$4:$L$503,$A78,'Trade Log'!$E$4:$E$503,"LONG")) -> 0 | E78: =IF($A78="","",SUMIFS('Trade Log'!$Q$4:$Q$503,'Trade Log'!$L$4:$L$503,$A78,'Trade Log'!$E$4:$E$503,"SHORT")) -> 0 | F78: =IF($A78="","",$D78+$E78) -> 0 | G78: =IF($A78="","",SUMIFS('Trade Log'!$Y$4:$Y$503,'Trade Log'!$L$4:$L$503,$A78)) -> 0 | H78: =IF($A78="","",IF($C78=0,"",$F78-$G78)) | I78: =IF($A78="","",$I77+IF($H78="",0,$H78)) -> 23918.552 | J78: =IF($A78="","",Config!$B$4+$I78) -> 1023918.6 | K78: =IF($A78="","",MAX($J$4:$J78)) -> 1023918.6 | L78: =IF($A78="","",$J78-$K78) -> 0 | M78: =IF(OR($A78="",$K78=0),"",$L78/$K78) -> 0 | N78: =IF($A78="","",SUMIFS('Trade Log'!$K$4:$K$503,'Trade Log'!$H$4:$H$503,$A78)) -> 0 | O78: =IF(OR($A78="",$H78="",Config!$B$4=0),"",$H78/Config!$B$4) | P78: =IF($A78="","",SUM($H$59:$H78)) -> 0 | Q78: =IF($A78="","",IFERROR((AVERAGE($O$59:$O78)-Config!$B$7/Config!$B$6)/STDEV($O$59:$O78)*SQRT(Config!$B$6),"")) | R78: =IF($A78="","",IFERROR((AVERAGE($O$19:$O78)-Config!$B$7/Config!$B$6)/STDEV($O$19:$O78)*SQRT(Config!$B$6),"")) | S78: =IF($H78="",$S77,IF($H78>0,$S77+1,0)) -> 1 | T78: =IF($H78="",$T77,IF($H78<0,$T77+1,0)) -> 0
A79: =IF($A78="","",$A78+1) -> 46310 | B79: =IF($A79="","",TEXT($A79,"ddd")) -> Thu | C79: =IF($A79="","",COUNTIFS('Trade Log'!$L$4:$L$503,$A79)) -> 0 | D79: =IF($A79="","",SUMIFS('Trade Log'!$Q$4:$Q$503,'Trade Log'!$L$4:$L$503,$A79,'Trade Log'!$E$4:$E$503,"LONG")) -> 0 | E79: =IF($A79="","",SUMIFS('Trade Log'!$Q$4:$Q$503,'Trade Log'!$L$4:$L$503,$A79,'Trade Log'!$E$4:$E$503,"SHORT")) -> 0 | F79: =IF($A79="","",$D79+$E79) -> 0 | G79: =IF($A79="","",SUMIFS('Trade Log'!$Y$4:$Y$503,'Trade Log'!$L$4:$L$503,$A79)) -> 0 | H79: =IF($A79="","",IF($C79=0,"",$F79-$G79)) | I79: =IF($A79="","",$I78+IF($H79="",0,$H79)) -> 23918.552 | J79: =IF($A79="","",Config!$B$4+$I79) -> 1023918.6 | K79: =IF($A79="","",MAX($J$4:$J79)) -> 1023918.6 | L79: =IF($A79="","",$J79-$K79) -> 0 | M79: =IF(OR($A79="",$K79=0),"",$L79/$K79) -> 0 | N79: =IF($A79="","",SUMIFS('Trade Log'!$K$4:$K$503,'Trade Log'!$H$4:$H$503,$A79)) -> 0 | O79: =IF(OR($A79="",$H79="",Config!$B$4=0),"",$H79/Config!$B$4) | P79: =IF($A79="","",SUM($H$60:$H79)) -> 0 | Q79: =IF($A79="","",IFERROR((AVERAGE($O$60:$O79)-Config!$B$7/Config!$B$6)/STDEV($O$60:$O79)*SQRT(Config!$B$6),"")) | R79: =IF($A79="","",IFERROR((AVERAGE($O$20:$O79)-Config!$B$7/Config!$B$6)/STDEV($O$20:$O79)*SQRT(Config!$B$6),"")) | S79: =IF($H79="",$S78,IF($H79>0,$S78+1,0)) -> 1 | T79: =IF($H79="",$T78,IF($H79<0,$T78+1,0)) -> 0
A80: =IF($A79="","",$A79+1) -> 46311 | B80: =IF($A80="","",TEXT($A80,"ddd")) -> Fri | C80: =IF($A80="","",COUNTIFS('Trade Log'!$L$4:$L$503,$A80)) -> 0 | D80: =IF($A80="","",SUMIFS('Trade Log'!$Q$4:$Q$503,'Trade Log'!$L$4:$L$503,$A80,'Trade Log'!$E$4:$E$503,"LONG")) -> 0 | E80: =IF($A80="","",SUMIFS('Trade Log'!$Q$4:$Q$503,'Trade Log'!$L$4:$L$503,$A80,'Trade Log'!$E$4:$E$503,"SHORT")) -> 0 | F80: =IF($A80="","",$D80+$E80) -> 0 | G80: =IF($A80="","",SUMIFS('Trade Log'!$Y$4:$Y$503,'Trade Log'!$L$4:$L$503,$A80)) -> 0 | H80: =IF($A80="","",IF($C80=0,"",$F80-$G80)) | I80: =IF($A80="","",$I79+IF($H80="",0,$H80)) -> 23918.552 | J80: =IF($A80="","",Config!$B$4+$I80) -> 1023918.6 | K80: =IF($A80="","",MAX($J$4:$J80)) -> 1023918.6 | L80: =IF($A80="","",$J80-$K80) -> 0 | M80: =IF(OR($A80="",$K80=0),"",$L80/$K80) -> 0 | N80: =IF($A80="","",SUMIFS('Trade Log'!$K$4:$K$503,'Trade Log'!$H$4:$H$503,$A80)) -> 0 | O80: =IF(OR($A80="",$H80="",Config!$B$4=0),"",$H80/Config!$B$4) | P80: =IF($A80="","",SUM($H$61:$H80)) -> 0 | Q80: =IF($A80="","",IFERROR((AVERAGE($O$61:$O80)-Config!$B$7/Config!$B$6)/STDEV($O$61:$O80)*SQRT(Config!$B$6),"")) | R80: =IF($A80="","",IFERROR((AVERAGE($O$21:$O80)-Config!$B$7/Config!$B$6)/STDEV($O$21:$O80)*SQRT(Config!$B$6),"")) | S80: =IF($H80="",$S79,IF($H80>0,$S79+1,0)) -> 1 | T80: =IF($H80="",$T79,IF($H80<0,$T79+1,0)) -> 0
A81: =IF($A80="","",$A80+1) -> 46312 | B81: =IF($A81="","",TEXT($A81,"ddd")) -> Sat | C81: =IF($A81="","",COUNTIFS('Trade Log'!$L$4:$L$503,$A81)) -> 0 | D81: =IF($A81="","",SUMIFS('Trade Log'!$Q$4:$Q$503,'Trade Log'!$L$4:$L$503,$A81,'Trade Log'!$E$4:$E$503,"LONG")) -> 0 | E81: =IF($A81="","",SUMIFS('Trade Log'!$Q$4:$Q$503,'Trade Log'!$L$4:$L$503,$A81,'Trade Log'!$E$4:$E$503,"SHORT")) -> 0 | F81: =IF($A81="","",$D81+$E81) -> 0 | G81: =IF($A81="","",SUMIFS('Trade Log'!$Y$4:$Y$503,'Trade Log'!$L$4:$L$503,$A81)) -> 0 | H81: =IF($A81="","",IF($C81=0,"",$F81-$G81)) | I81: =IF($A81="","",$I80+IF($H81="",0,$H81)) -> 23918.552 | J81: =IF($A81="","",Config!$B$4+$I81) -> 1023918.6 | K81: =IF($A81="","",MAX($J$4:$J81)) -> 1023918.6 | L81: =IF($A81="","",$J81-$K81) -> 0 | M81: =IF(OR($A81="",$K81=0),"",$L81/$K81) -> 0 | N81: =IF($A81="","",SUMIFS('Trade Log'!$K$4:$K$503,'Trade Log'!$H$4:$H$503,$A81)) -> 0 | O81: =IF(OR($A81="",$H81="",Config!$B$4=0),"",$H81/Config!$B$4) | P81: =IF($A81="","",SUM($H$62:$H81)) -> 0 | Q81: =IF($A81="","",IFERROR((AVERAGE($O$62:$O81)-Config!$B$7/Config!$B$6)/STDEV($O$62:$O81)*SQRT(Config!$B$6),"")) | R81: =IF($A81="","",IFERROR((AVERAGE($O$22:$O81)-Config!$B$7/Config!$B$6)/STDEV($O$22:$O81)*SQRT(Config!$B$6),"")) | S81: =IF($H81="",$S80,IF($H81>0,$S80+1,0)) -> 1 | T81: =IF($H81="",$T80,IF($H81<0,$T80+1,0)) -> 0
A82: =IF($A81="","",$A81+1) -> 46313 | B82: =IF($A82="","",TEXT($A82,"ddd")) -> Sun | C82: =IF($A82="","",COUNTIFS('Trade Log'!$L$4:$L$503,$A82)) -> 0 | D82: =IF($A82="","",SUMIFS('Trade Log'!$Q$4:$Q$503,'Trade Log'!$L$4:$L$503,$A82,'Trade Log'!$E$4:$E$503,"LONG")) -> 0 | E82: =IF($A82="","",SUMIFS('Trade Log'!$Q$4:$Q$503,'Trade Log'!$L$4:$L$503,$A82,'Trade Log'!$E$4:$E$503,"SHORT")) -> 0 | F82: =IF($A82="","",$D82+$E82) -> 0 | G82: =IF($A82="","",SUMIFS('Trade Log'!$Y$4:$Y$503,'Trade Log'!$L$4:$L$503,$A82)) -> 0 | H82: =IF($A82="","",IF($C82=0,"",$F82-$G82)) | I82: =IF($A82="","",$I81+IF($H82="",0,$H82)) -> 23918.552 | J82: =IF($A82="","",Config!$B$4+$I82) -> 1023918.6 | K82: =IF($A82="","",MAX($J$4:$J82)) -> 1023918.6 | L82: =IF($A82="","",$J82-$K82) -> 0 | M82: =IF(OR($A82="",$K82=0),"",$L82/$K82) -> 0 | N82: =IF($A82="","",SUMIFS('Trade Log'!$K$4:$K$503,'Trade Log'!$H$4:$H$503,$A82)) -> 0 | O82: =IF(OR($A82="",$H82="",Config!$B$4=0),"",$H82/Config!$B$4) | P82: =IF($A82="","",SUM($H$63:$H82)) -> 0 | Q82: =IF($A82="","",IFERROR((AVERAGE($O$63:$O82)-Config!$B$7/Config!$B$6)/STDEV($O$63:$O82)*SQRT(Config!$B$6),"")) | R82: =IF($A82="","",IFERROR((AVERAGE($O$23:$O82)-Config!$B$7/Config!$B$6)/STDEV($O$23:$O82)*SQRT(Config!$B$6),"")) | S82: =IF($H82="",$S81,IF($H82>0,$S81+1,0)) -> 1 | T82: =IF($H82="",$T81,IF($H82<0,$T81+1,0)) -> 0
A83: =IF($A82="","",$A82+1) -> 46314 | B83: =IF($A83="","",TEXT($A83,"ddd")) -> Mon | C83: =IF($A83="","",COUNTIFS('Trade Log'!$L$4:$L$503,$A83)) -> 0 | D83: =IF($A83="","",SUMIFS('Trade Log'!$Q$4:$Q$503,'Trade Log'!$L$4:$L$503,$A83,'Trade Log'!$E$4:$E$503,"LONG")) -> 0 | E83: =IF($A83="","",SUMIFS('Trade Log'!$Q$4:$Q$503,'Trade Log'!$L$4:$L$503,$A83,'Trade Log'!$E$4:$E$503,"SHORT")) -> 0 | F83: =IF($A83="","",$D83+$E83) -> 0 | G83: =IF($A83="","",SUMIFS('Trade Log'!$Y$4:$Y$503,'Trade Log'!$L$4:$L$503,$A83)) -> 0 | H83: =IF($A83="","",IF($C83=0,"",$F83-$G83)) | I83: =IF($A83="","",$I82+IF($H83="",0,$H83)) -> 23918.552 | J83: =IF($A83="","",Config!$B$4+$I83) -> 1023918.6 | K83: =IF($A83="","",MAX($J$4:$J83)) -> 1023918.6 | L83: =IF($A83="","",$J83-$K83) -> 0 | M83: =IF(OR($A83="",$K83=0),"",$L83/$K83) -> 0 | N83: =IF($A83="","",SUMIFS('Trade Log'!$K$4:$K$503,'Trade Log'!$H$4:$H$503,$A83)) -> 0 | O83: =IF(OR($A83="",$H83="",Config!$B$4=0),"",$H83/Config!$B$4) | P83: =IF($A83="","",SUM($H$64:$H83)) -> 0 | Q83: =IF($A83="","",IFERROR((AVERAGE($O$64:$O83)-Config!$B$7/Config!$B$6)/STDEV($O$64:$O83)*SQRT(Config!$B$6),"")) | R83: =IF($A83="","",IFERROR((AVERAGE($O$24:$O83)-Config!$B$7/Config!$B$6)/STDEV($O$24:$O83)*SQRT(Config!$B$6),"")) | S83: =IF($H83="",$S82,IF($H83>0,$S82+1,0)) -> 1 | T83: =IF($H83="",$T82,IF($H83<0,$T82+1,0)) -> 0
A84: =IF($A83="","",$A83+1) -> 46315 | B84: =IF($A84="","",TEXT($A84,"ddd")) -> Tue | C84: =IF($A84="","",COUNTIFS('Trade Log'!$L$4:$L$503,$A84)) -> 0 | D84: =IF($A84="","",SUMIFS('Trade Log'!$Q$4:$Q$503,'Trade Log'!$L$4:$L$503,$A84,'Trade Log'!$E$4:$E$503,"LONG")) -> 0 | E84: =IF($A84="","",SUMIFS('Trade Log'!$Q$4:$Q$503,'Trade Log'!$L$4:$L$503,$A84,'Trade Log'!$E$4:$E$503,"SHORT")) -> 0 | F84: =IF($A84="","",$D84+$E84) -> 0 | G84: =IF($A84="","",SUMIFS('Trade Log'!$Y$4:$Y$503,'Trade Log'!$L$4:$L$503,$A84)) -> 0 | H84: =IF($A84="","",IF($C84=0,"",$F84-$G84)) | I84: =IF($A84="","",$I83+IF($H84="",0,$H84)) -> 23918.552 | J84: =IF($A84="","",Config!$B$4+$I84) -> 1023918.6 | K84: =IF($A84="","",MAX($J$4:$J84)) -> 1023918.6 | L84: =IF($A84="","",$J84-$K84) -> 0 | M84: =IF(OR($A84="",$K84=0),"",$L84/$K84) -> 0 | N84: =IF($A84="","",SUMIFS('Trade Log'!$K$4:$K$503,'Trade Log'!$H$4:$H$503,$A84)) -> 0 | O84: =IF(OR($A84="",$H84="",Config!$B$4=0),"",$H84/Config!$B$4) | P84: =IF($A84="","",SUM($H$65:$H84)) -> 0 | Q84: =IF($A84="","",IFERROR((AVERAGE($O$65:$O84)-Config!$B$7/Config!$B$6)/STDEV($O$65:$O84)*SQRT(Config!$B$6),"")) | R84: =IF($A84="","",IFERROR((AVERAGE($O$25:$O84)-Config!$B$7/Config!$B$6)/STDEV($O$25:$O84)*SQRT(Config!$B$6),"")) | S84: =IF($H84="",$S83,IF($H84>0,$S83+1,0)) -> 1 | T84: =IF($H84="",$T83,IF($H84<0,$T83+1,0)) -> 0
A85: =IF($A84="","",$A84+1) -> 46316 | B85: =IF($A85="","",TEXT($A85,"ddd")) -> Wed | C85: =IF($A85="","",COUNTIFS('Trade Log'!$L$4:$L$503,$A85)) -> 0 | D85: =IF($A85="","",SUMIFS('Trade Log'!$Q$4:$Q$503,'Trade Log'!$L$4:$L$503,$A85,'Trade Log'!$E$4:$E$503,"LONG")) -> 0 | E85: =IF($A85="","",SUMIFS('Trade Log'!$Q$4:$Q$503,'Trade Log'!$L$4:$L$503,$A85,'Trade Log'!$E$4:$E$503,"SHORT")) -> 0 | F85: =IF($A85="","",$D85+$E85) -> 0 | G85: =IF($A85="","",SUMIFS('Trade Log'!$Y$4:$Y$503,'Trade Log'!$L$4:$L$503,$A85)) -> 0 | H85: =IF($A85="","",IF($C85=0,"",$F85-$G85)) | I85: =IF($A85="","",$I84+IF($H85="",0,$H85)) -> 23918.552 | J85: =IF($A85="","",Config!$B$4+$I85) -> 1023918.6 | K85: =IF($A85="","",MAX($J$4:$J85)) -> 1023918.6 | L85: =IF($A85="","",$J85-$K85) -> 0 | M85: =IF(OR($A85="",$K85=0),"",$L85/$K85) -> 0 | N85: =IF($A85="","",SUMIFS('Trade Log'!$K$4:$K$503,'Trade Log'!$H$4:$H$503,$A85)) -> 0 | O85: =IF(OR($A85="",$H85="",Config!$B$4=0),"",$H85/Config!$B$4) | P85: =IF($A85="","",SUM($H$66:$H85)) -> 0 | Q85: =IF($A85="","",IFERROR((AVERAGE($O$66:$O85)-Config!$B$7/Config!$B$6)/STDEV($O$66:$O85)*SQRT(Config!$B$6),"")) | R85: =IF($A85="","",IFERROR((AVERAGE($O$26:$O85)-Config!$B$7/Config!$B$6)/STDEV($O$26:$O85)*SQRT(Config!$B$6),"")) | S85: =IF($H85="",$S84,IF($H85>0,$S84+1,0)) -> 1 | T85: =IF($H85="",$T84,IF($H85<0,$T84+1,0)) -> 0
A86: =IF($A85="","",$A85+1) -> 46317 | B86: =IF($A86="","",TEXT($A86,"ddd")) -> Thu | C86: =IF($A86="","",COUNTIFS('Trade Log'!$L$4:$L$503,$A86)) -> 0 | D86: =IF($A86="","",SUMIFS('Trade Log'!$Q$4:$Q$503,'Trade Log'!$L$4:$L$503,$A86,'Trade Log'!$E$4:$E$503,"LONG")) -> 0 | E86: =IF($A86="","",SUMIFS('Trade Log'!$Q$4:$Q$503,'Trade Log'!$L$4:$L$503,$A86,'Trade Log'!$E$4:$E$503,"SHORT")) -> 0 | F86: =IF($A86="","",$D86+$E86) -> 0 | G86: =IF($A86="","",SUMIFS('Trade Log'!$Y$4:$Y$503,'Trade Log'!$L$4:$L$503,$A86)) -> 0 | H86: =IF($A86="","",IF($C86=0,"",$F86-$G86)) | I86: =IF($A86="","",$I85+IF($H86="",0,$H86)) -> 23918.552 | J86: =IF($A86="","",Config!$B$4+$I86) -> 1023918.6 | K86: =IF($A86="","",MAX($J$4:$J86)) -> 1023918.6 | L86: =IF($A86="","",$J86-$K86) -> 0 | M86: =IF(OR($A86="",$K86=0),"",$L86/$K86) -> 0 | N86: =IF($A86="","",SUMIFS('Trade Log'!$K$4:$K$503,'Trade Log'!$H$4:$H$503,$A86)) -> 0 | O86: =IF(OR($A86="",$H86="",Config!$B$4=0),"",$H86/Config!$B$4) | P86: =IF($A86="","",SUM($H$67:$H86)) -> 0 | Q86: =IF($A86="","",IFERROR((AVERAGE($O$67:$O86)-Config!$B$7/Config!$B$6)/STDEV($O$67:$O86)*SQRT(Config!$B$6),"")) | R86: =IF($A86="","",IFERROR((AVERAGE($O$27:$O86)-Config!$B$7/Config!$B$6)/STDEV($O$27:$O86)*SQRT(Config!$B$6),"")) | S86: =IF($H86="",$S85,IF($H86>0,$S85+1,0)) -> 1 | T86: =IF($H86="",$T85,IF($H86<0,$T85+1,0)) -> 0
A87: =IF($A86="","",$A86+1) -> 46318 | B87: =IF($A87="","",TEXT($A87,"ddd")) -> Fri | C87: =IF($A87="","",COUNTIFS('Trade Log'!$L$4:$L$503,$A87)) -> 0 | D87: =IF($A87="","",SUMIFS('Trade Log'!$Q$4:$Q$503,'Trade Log'!$L$4:$L$503,$A87,'Trade Log'!$E$4:$E$503,"LONG")) -> 0 | E87: =IF($A87="","",SUMIFS('Trade Log'!$Q$4:$Q$503,'Trade Log'!$L$4:$L$503,$A87,'Trade Log'!$E$4:$E$503,"SHORT")) -> 0 | F87: =IF($A87="","",$D87+$E87) -> 0 | G87: =IF($A87="","",SUMIFS('Trade Log'!$Y$4:$Y$503,'Trade Log'!$L$4:$L$503,$A87)) -> 0 | H87: =IF($A87="","",IF($C87=0,"",$F87-$G87)) | I87: =IF($A87="","",$I86+IF($H87="",0,$H87)) -> 23918.552 | J87: =IF($A87="","",Config!$B$4+$I87) -> 1023918.6 | K87: =IF($A87="","",MAX($J$4:$J87)) -> 1023918.6 | L87: =IF($A87="","",$J87-$K87) -> 0 | M87: =IF(OR($A87="",$K87=0),"",$L87/$K87) -> 0 | N87: =IF($A87="","",SUMIFS('Trade Log'!$K$4:$K$503,'Trade Log'!$H$4:$H$503,$A87)) -> 0 | O87: =IF(OR($A87="",$H87="",Config!$B$4=0),"",$H87/Config!$B$4) | P87: =IF($A87="","",SUM($H$68:$H87)) -> 0 | Q87: =IF($A87="","",IFERROR((AVERAGE($O$68:$O87)-Config!$B$7/Config!$B$6)/STDEV($O$68:$O87)*SQRT(Config!$B$6),"")) | R87: =IF($A87="","",IFERROR((AVERAGE($O$28:$O87)-Config!$B$7/Config!$B$6)/STDEV($O$28:$O87)*SQRT(Config!$B$6),"")) | S87: =IF($H87="",$S86,IF($H87>0,$S86+1,0)) -> 1 | T87: =IF($H87="",$T86,IF($H87<0,$T86+1,0)) -> 0
A88: =IF($A87="","",$A87+1) -> 46319 | B88: =IF($A88="","",TEXT($A88,"ddd")) -> Sat | C88: =IF($A88="","",COUNTIFS('Trade Log'!$L$4:$L$503,$A88)) -> 0 | D88: =IF($A88="","",SUMIFS('Trade Log'!$Q$4:$Q$503,'Trade Log'!$L$4:$L$503,$A88,'Trade Log'!$E$4:$E$503,"LONG")) -> 0 | E88: =IF($A88="","",SUMIFS('Trade Log'!$Q$4:$Q$503,'Trade Log'!$L$4:$L$503,$A88,'Trade Log'!$E$4:$E$503,"SHORT")) -> 0 | F88: =IF($A88="","",$D88+$E88) -> 0 | G88: =IF($A88="","",SUMIFS('Trade Log'!$Y$4:$Y$503,'Trade Log'!$L$4:$L$503,$A88)) -> 0 | H88: =IF($A88="","",IF($C88=0,"",$F88-$G88)) | I88: =IF($A88="","",$I87+IF($H88="",0,$H88)) -> 23918.552 | J88: =IF($A88="","",Config!$B$4+$I88) -> 1023918.6 | K88: =IF($A88="","",MAX($J$4:$J88)) -> 1023918.6 | L88: =IF($A88="","",$J88-$K88) -> 0 | M88: =IF(OR($A88="",$K88=0),"",$L88/$K88) -> 0 | N88: =IF($A88="","",SUMIFS('Trade Log'!$K$4:$K$503,'Trade Log'!$H$4:$H$503,$A88)) -> 0 | O88: =IF(OR($A88="",$H88="",Config!$B$4=0),"",$H88/Config!$B$4) | P88: =IF($A88="","",SUM($H$69:$H88)) -> 0 | Q88: =IF($A88="","",IFERROR((AVERAGE($O$69:$O88)-Config!$B$7/Config!$B$6)/STDEV($O$69:$O88)*SQRT(Config!$B$6),"")) | R88: =IF($A88="","",IFERROR((AVERAGE($O$29:$O88)-Config!$B$7/Config!$B$6)/STDEV($O$29:$O88)*SQRT(Config!$B$6),"")) | S88: =IF($H88="",$S87,IF($H88>0,$S87+1,0)) -> 1 | T88: =IF($H88="",$T87,IF($H88<0,$T87+1,0)) -> 0
A89: =IF($A88="","",$A88+1) -> 46320 | B89: =IF($A89="","",TEXT($A89,"ddd")) -> Sun | C89: =IF($A89="","",COUNTIFS('Trade Log'!$L$4:$L$503,$A89)) -> 0 | D89: =IF($A89="","",SUMIFS('Trade Log'!$Q$4:$Q$503,'Trade Log'!$L$4:$L$503,$A89,'Trade Log'!$E$4:$E$503,"LONG")) -> 0 | E89: =IF($A89="","",SUMIFS('Trade Log'!$Q$4:$Q$503,'Trade Log'!$L$4:$L$503,$A89,'Trade Log'!$E$4:$E$503,"SHORT")) -> 0 | F89: =IF($A89="","",$D89+$E89) -> 0 | G89: =IF($A89="","",SUMIFS('Trade Log'!$Y$4:$Y$503,'Trade Log'!$L$4:$L$503,$A89)) -> 0 | H89: =IF($A89="","",IF($C89=0,"",$F89-$G89)) | I89: =IF($A89="","",$I88+IF($H89="",0,$H89)) -> 23918.552 | J89: =IF($A89="","",Config!$B$4+$I89) -> 1023918.6 | K89: =IF($A89="","",MAX($J$4:$J89)) -> 1023918.6 | L89: =IF($A89="","",$J89-$K89) -> 0 | M89: =IF(OR($A89="",$K89=0),"",$L89/$K89) -> 0 | N89: =IF($A89="","",SUMIFS('Trade Log'!$K$4:$K$503,'Trade Log'!$H$4:$H$503,$A89)) -> 0 | O89: =IF(OR($A89="",$H89="",Config!$B$4=0),"",$H89/Config!$B$4) | P89: =IF($A89="","",SUM($H$70:$H89)) -> 0 | Q89: =IF($A89="","",IFERROR((AVERAGE($O$70:$O89)-Config!$B$7/Config!$B$6)/STDEV($O$70:$O89)*SQRT(Config!$B$6),"")) | R89: =IF($A89="","",IFERROR((AVERAGE($O$30:$O89)-Config!$B$7/Config!$B$6)/STDEV($O$30:$O89)*SQRT(Config!$B$6),"")) | S89: =IF($H89="",$S88,IF($H89>0,$S88+1,0)) -> 1 | T89: =IF($H89="",$T88,IF($H89<0,$T88+1,0)) -> 0
A90: =IF($A89="","",$A89+1) -> 46321 | B90: =IF($A90="","",TEXT($A90,"ddd")) -> Mon | C90: =IF($A90="","",COUNTIFS('Trade Log'!$L$4:$L$503,$A90)) -> 0 | D90: =IF($A90="","",SUMIFS('Trade Log'!$Q$4:$Q$503,'Trade Log'!$L$4:$L$503,$A90,'Trade Log'!$E$4:$E$503,"LONG")) -> 0 | E90: =IF($A90="","",SUMIFS('Trade Log'!$Q$4:$Q$503,'Trade Log'!$L$4:$L$503,$A90,'Trade Log'!$E$4:$E$503,"SHORT")) -> 0 | F90: =IF($A90="","",$D90+$E90) -> 0 | G90: =IF($A90="","",SUMIFS('Trade Log'!$Y$4:$Y$503,'Trade Log'!$L$4:$L$503,$A90)) -> 0 | H90: =IF($A90="","",IF($C90=0,"",$F90-$G90)) | I90: =IF($A90="","",$I89+IF($H90="",0,$H90)) -> 23918.552 | J90: =IF($A90="","",Config!$B$4+$I90) -> 1023918.6 | K90: =IF($A90="","",MAX($J$4:$J90)) -> 1023918.6 | L90: =IF($A90="","",$J90-$K90) -> 0 | M90: =IF(OR($A90="",$K90=0),"",$L90/$K90) -> 0 | N90: =IF($A90="","",SUMIFS('Trade Log'!$K$4:$K$503,'Trade Log'!$H$4:$H$503,$A90)) -> 0 | O90: =IF(OR($A90="",$H90="",Config!$B$4=0),"",$H90/Config!$B$4) | P90: =IF($A90="","",SUM($H$71:$H90)) -> 0 | Q90: =IF($A90="","",IFERROR((AVERAGE($O$71:$O90)-Config!$B$7/Config!$B$6)/STDEV($O$71:$O90)*SQRT(Config!$B$6),"")) | R90: =IF($A90="","",IFERROR((AVERAGE($O$31:$O90)-Config!$B$7/Config!$B$6)/STDEV($O$31:$O90)*SQRT(Config!$B$6),"")) | S90: =IF($H90="",$S89,IF($H90>0,$S89+1,0)) -> 1 | T90: =IF($H90="",$T89,IF($H90<0,$T89+1,0)) -> 0
A91: =IF($A90="","",$A90+1) -> 46322 | B91: =IF($A91="","",TEXT($A91,"ddd")) -> Tue | C91: =IF($A91="","",COUNTIFS('Trade Log'!$L$4:$L$503,$A91)) -> 0 | D91: =IF($A91="","",SUMIFS('Trade Log'!$Q$4:$Q$503,'Trade Log'!$L$4:$L$503,$A91,'Trade Log'!$E$4:$E$503,"LONG")) -> 0 | E91: =IF($A91="","",SUMIFS('Trade Log'!$Q$4:$Q$503,'Trade Log'!$L$4:$L$503,$A91,'Trade Log'!$E$4:$E$503,"SHORT")) -> 0 | F91: =IF($A91="","",$D91+$E91) -> 0 | G91: =IF($A91="","",SUMIFS('Trade Log'!$Y$4:$Y$503,'Trade Log'!$L$4:$L$503,$A91)) -> 0 | H91: =IF($A91="","",IF($C91=0,"",$F91-$G91)) | I91: =IF($A91="","",$I90+IF($H91="",0,$H91)) -> 23918.552 | J91: =IF($A91="","",Config!$B$4+$I91) -> 1023918.6 | K91: =IF($A91="","",MAX($J$4:$J91)) -> 1023918.6 | L91: =IF($A91="","",$J91-$K91) -> 0 | M91: =IF(OR($A91="",$K91=0),"",$L91/$K91) -> 0 | N91: =IF($A91="","",SUMIFS('Trade Log'!$K$4:$K$503,'Trade Log'!$H$4:$H$503,$A91)) -> 0 | O91: =IF(OR($A91="",$H91="",Config!$B$4=0),"",$H91/Config!$B$4) | P91: =IF($A91="","",SUM($H$72:$H91)) -> 0 | Q91: =IF($A91="","",IFERROR((AVERAGE($O$72:$O91)-Config!$B$7/Config!$B$6)/STDEV($O$72:$O91)*SQRT(Config!$B$6),"")) | R91: =IF($A91="","",IFERROR((AVERAGE($O$32:$O91)-Config!$B$7/Config!$B$6)/STDEV($O$32:$O91)*SQRT(Config!$B$6),"")) | S91: =IF($H91="",$S90,IF($H91>0,$S90+1,0)) -> 1 | T91: =IF($H91="",$T90,IF($H91<0,$T90+1,0)) -> 0
A92: =IF($A91="","",$A91+1) -> 46323 | B92: =IF($A92="","",TEXT($A92,"ddd")) -> Wed | C92: =IF($A92="","",COUNTIFS('Trade Log'!$L$4:$L$503,$A92)) -> 0 | D92: =IF($A92="","",SUMIFS('Trade Log'!$Q$4:$Q$503,'Trade Log'!$L$4:$L$503,$A92,'Trade Log'!$E$4:$E$503,"LONG")) -> 0 | E92: =IF($A92="","",SUMIFS('Trade Log'!$Q$4:$Q$503,'Trade Log'!$L$4:$L$503,$A92,'Trade Log'!$E$4:$E$503,"SHORT")) -> 0 | F92: =IF($A92="","",$D92+$E92) -> 0 | G92: =IF($A92="","",SUMIFS('Trade Log'!$Y$4:$Y$503,'Trade Log'!$L$4:$L$503,$A92)) -> 0 | H92: =IF($A92="","",IF($C92=0,"",$F92-$G92)) | I92: =IF($A92="","",$I91+IF($H92="",0,$H92)) -> 23918.552 | J92: =IF($A92="","",Config!$B$4+$I92) -> 1023918.6 | K92: =IF($A92="","",MAX($J$4:$J92)) -> 1023918.6 | L92: =IF($A92="","",$J92-$K92) -> 0 | M92: =IF(OR($A92="",$K92=0),"",$L92/$K92) -> 0 | N92: =IF($A92="","",SUMIFS('Trade Log'!$K$4:$K$503,'Trade Log'!$H$4:$H$503,$A92)) -> 0 | O92: =IF(OR($A92="",$H92="",Config!$B$4=0),"",$H92/Config!$B$4) | P92: =IF($A92="","",SUM($H$73:$H92)) -> 0 | Q92: =IF($A92="","",IFERROR((AVERAGE($O$73:$O92)-Config!$B$7/Config!$B$6)/STDEV($O$73:$O92)*SQRT(Config!$B$6),"")) | R92: =IF($A92="","",IFERROR((AVERAGE($O$33:$O92)-Config!$B$7/Config!$B$6)/STDEV($O$33:$O92)*SQRT(Config!$B$6),"")) | S92: =IF($H92="",$S91,IF($H92>0,$S91+1,0)) -> 1 | T92: =IF($H92="",$T91,IF($H92<0,$T91+1,0)) -> 0
A93: =IF($A92="","",$A92+1) -> 46324 | B93: =IF($A93="","",TEXT($A93,"ddd")) -> Thu | C93: =IF($A93="","",COUNTIFS('Trade Log'!$L$4:$L$503,$A93)) -> 0 | D93: =IF($A93="","",SUMIFS('Trade Log'!$Q$4:$Q$503,'Trade Log'!$L$4:$L$503,$A93,'Trade Log'!$E$4:$E$503,"LONG")) -> 0 | E93: =IF($A93="","",SUMIFS('Trade Log'!$Q$4:$Q$503,'Trade Log'!$L$4:$L$503,$A93,'Trade Log'!$E$4:$E$503,"SHORT")) -> 0 | F93: =IF($A93="","",$D93+$E93) -> 0 | G93: =IF($A93="","",SUMIFS('Trade Log'!$Y$4:$Y$503,'Trade Log'!$L$4:$L$503,$A93)) -> 0 | H93: =IF($A93="","",IF($C93=0,"",$F93-$G93)) | I93: =IF($A93="","",$I92+IF($H93="",0,$H93)) -> 23918.552 | J93: =IF($A93="","",Config!$B$4+$I93) -> 1023918.6 | K93: =IF($A93="","",MAX($J$4:$J93)) -> 1023918.6 | L93: =IF($A93="","",$J93-$K93) -> 0 | M93: =IF(OR($A93="",$K93=0),"",$L93/$K93) -> 0 | N93: =IF($A93="","",SUMIFS('Trade Log'!$K$4:$K$503,'Trade Log'!$H$4:$H$503,$A93)) -> 0 | O93: =IF(OR($A93="",$H93="",Config!$B$4=0),"",$H93/Config!$B$4) | P93: =IF($A93="","",SUM($H$74:$H93)) -> 0 | Q93: =IF($A93="","",IFERROR((AVERAGE($O$74:$O93)-Config!$B$7/Config!$B$6)/STDEV($O$74:$O93)*SQRT(Config!$B$6),"")) | R93: =IF($A93="","",IFERROR((AVERAGE($O$34:$O93)-Config!$B$7/Config!$B$6)/STDEV($O$34:$O93)*SQRT(Config!$B$6),"")) | S93: =IF($H93="",$S92,IF($H93>0,$S92+1,0)) -> 1 | T93: =IF($H93="",$T92,IF($H93<0,$T92+1,0)) -> 0
A94: =IF($A93="","",$A93+1) -> 46325 | B94: =IF($A94="","",TEXT($A94,"ddd")) -> Fri | C94: =IF($A94="","",COUNTIFS('Trade Log'!$L$4:$L$503,$A94)) -> 0 | D94: =IF($A94="","",SUMIFS('Trade Log'!$Q$4:$Q$503,'Trade Log'!$L$4:$L$503,$A94,'Trade Log'!$E$4:$E$503,"LONG")) -> 0 | E94: =IF($A94="","",SUMIFS('Trade Log'!$Q$4:$Q$503,'Trade Log'!$L$4:$L$503,$A94,'Trade Log'!$E$4:$E$503,"SHORT")) -> 0 | F94: =IF($A94="","",$D94+$E94) -> 0 | G94: =IF($A94="","",SUMIFS('Trade Log'!$Y$4:$Y$503,'Trade Log'!$L$4:$L$503,$A94)) -> 0 | H94: =IF($A94="","",IF($C94=0,"",$F94-$G94)) | I94: =IF($A94="","",$I93+IF($H94="",0,$H94)) -> 23918.552 | J94: =IF($A94="","",Config!$B$4+$I94) -> 1023918.6 | K94: =IF($A94="","",MAX($J$4:$J94)) -> 1023918.6 | L94: =IF($A94="","",$J94-$K94) -> 0 | M94: =IF(OR($A94="",$K94=0),"",$L94/$K94) -> 0 | N94: =IF($A94="","",SUMIFS('Trade Log'!$K$4:$K$503,'Trade Log'!$H$4:$H$503,$A94)) -> 0 | O94: =IF(OR($A94="",$H94="",Config!$B$4=0),"",$H94/Config!$B$4) | P94: =IF($A94="","",SUM($H$75:$H94)) -> 0 | Q94: =IF($A94="","",IFERROR((AVERAGE($O$75:$O94)-Config!$B$7/Config!$B$6)/STDEV($O$75:$O94)*SQRT(Config!$B$6),"")) | R94: =IF($A94="","",IFERROR((AVERAGE($O$35:$O94)-Config!$B$7/Config!$B$6)/STDEV($O$35:$O94)*SQRT(Config!$B$6),"")) | S94: =IF($H94="",$S93,IF($H94>0,$S93+1,0)) -> 1 | T94: =IF($H94="",$T93,IF($H94<0,$T93+1,0)) -> 0
A95: =IF($A94="","",$A94+1) -> 46326 | B95: =IF($A95="","",TEXT($A95,"ddd")) -> Sat | C95: =IF($A95="","",COUNTIFS('Trade Log'!$L$4:$L$503,$A95)) -> 0 | D95: =IF($A95="","",SUMIFS('Trade Log'!$Q$4:$Q$503,'Trade Log'!$L$4:$L$503,$A95,'Trade Log'!$E$4:$E$503,"LONG")) -> 0 | E95: =IF($A95="","",SUMIFS('Trade Log'!$Q$4:$Q$503,'Trade Log'!$L$4:$L$503,$A95,'Trade Log'!$E$4:$E$503,"SHORT")) -> 0 | F95: =IF($A95="","",$D95+$E95) -> 0 | G95: =IF($A95="","",SUMIFS('Trade Log'!$Y$4:$Y$503,'Trade Log'!$L$4:$L$503,$A95)) -> 0 | H95: =IF($A95="","",IF($C95=0,"",$F95-$G95)) | I95: =IF($A95="","",$I94+IF($H95="",0,$H95)) -> 23918.552 | J95: =IF($A95="","",Config!$B$4+$I95) -> 1023918.6 | K95: =IF($A95="","",MAX($J$4:$J95)) -> 1023918.6 | L95: =IF($A95="","",$J95-$K95) -> 0 | M95: =IF(OR($A95="",$K95=0),"",$L95/$K95) -> 0 | N95: =IF($A95="","",SUMIFS('Trade Log'!$K$4:$K$503,'Trade Log'!$H$4:$H$503,$A95)) -> 0 | O95: =IF(OR($A95="",$H95="",Config!$B$4=0),"",$H95/Config!$B$4) | P95: =IF($A95="","",SUM($H$76:$H95)) -> 0 | Q95: =IF($A95="","",IFERROR((AVERAGE($O$76:$O95)-Config!$B$7/Config!$B$6)/STDEV($O$76:$O95)*SQRT(Config!$B$6),"")) | R95: =IF($A95="","",IFERROR((AVERAGE($O$36:$O95)-Config!$B$7/Config!$B$6)/STDEV($O$36:$O95)*SQRT(Config!$B$6),"")) | S95: =IF($H95="",$S94,IF($H95>0,$S94+1,0)) -> 1 | T95: =IF($H95="",$T94,IF($H95<0,$T94+1,0)) -> 0
A96: =IF($A95="","",$A95+1) -> 46327 | B96: =IF($A96="","",TEXT($A96,"ddd")) -> Sun | C96: =IF($A96="","",COUNTIFS('Trade Log'!$L$4:$L$503,$A96)) -> 0 | D96: =IF($A96="","",SUMIFS('Trade Log'!$Q$4:$Q$503,'Trade Log'!$L$4:$L$503,$A96,'Trade Log'!$E$4:$E$503,"LONG")) -> 0 | E96: =IF($A96="","",SUMIFS('Trade Log'!$Q$4:$Q$503,'Trade Log'!$L$4:$L$503,$A96,'Trade Log'!$E$4:$E$503,"SHORT")) -> 0 | F96: =IF($A96="","",$D96+$E96) -> 0 | G96: =IF($A96="","",SUMIFS('Trade Log'!$Y$4:$Y$503,'Trade Log'!$L$4:$L$503,$A96)) -> 0 | H96: =IF($A96="","",IF($C96=0,"",$F96-$G96)) | I96: =IF($A96="","",$I95+IF($H96="",0,$H96)) -> 23918.552 | J96: =IF($A96="","",Config!$B$4+$I96) -> 1023918.6 | K96: =IF($A96="","",MAX($J$4:$J96)) -> 1023918.6 | L96: =IF($A96="","",$J96-$K96) -> 0 | M96: =IF(OR($A96="",$K96=0),"",$L96/$K96) -> 0 | N96: =IF($A96="","",SUMIFS('Trade Log'!$K$4:$K$503,'Trade Log'!$H$4:$H$503,$A96)) -> 0 | O96: =IF(OR($A96="",$H96="",Config!$B$4=0),"",$H96/Config!$B$4) | P96: =IF($A96="","",SUM($H$77:$H96)) -> 0 | Q96: =IF($A96="","",IFERROR((AVERAGE($O$77:$O96)-Config!$B$7/Config!$B$6)/STDEV($O$77:$O96)*SQRT(Config!$B$6),"")) | R96: =IF($A96="","",IFERROR((AVERAGE($O$37:$O96)-Config!$B$7/Config!$B$6)/STDEV($O$37:$O96)*SQRT(Config!$B$6),"")) | S96: =IF($H96="",$S95,IF($H96>0,$S95+1,0)) -> 1 | T96: =IF($H96="",$T95,IF($H96<0,$T95+1,0)) -> 0
A97: =IF($A96="","",$A96+1) -> 46328 | B97: =IF($A97="","",TEXT($A97,"ddd")) -> Mon | C97: =IF($A97="","",COUNTIFS('Trade Log'!$L$4:$L$503,$A97)) -> 0 | D97: =IF($A97="","",SUMIFS('Trade Log'!$Q$4:$Q$503,'Trade Log'!$L$4:$L$503,$A97,'Trade Log'!$E$4:$E$503,"LONG")) -> 0 | E97: =IF($A97="","",SUMIFS('Trade Log'!$Q$4:$Q$503,'Trade Log'!$L$4:$L$503,$A97,'Trade Log'!$E$4:$E$503,"SHORT")) -> 0 | F97: =IF($A97="","",$D97+$E97) -> 0 | G97: =IF($A97="","",SUMIFS('Trade Log'!$Y$4:$Y$503,'Trade Log'!$L$4:$L$503,$A97)) -> 0 | H97: =IF($A97="","",IF($C97=0,"",$F97-$G97)) | I97: =IF($A97="","",$I96+IF($H97="",0,$H97)) -> 23918.552 | J97: =IF($A97="","",Config!$B$4+$I97) -> 1023918.6 | K97: =IF($A97="","",MAX($J$4:$J97)) -> 1023918.6 | L97: =IF($A97="","",$J97-$K97) -> 0 | M97: =IF(OR($A97="",$K97=0),"",$L97/$K97) -> 0 | N97: =IF($A97="","",SUMIFS('Trade Log'!$K$4:$K$503,'Trade Log'!$H$4:$H$503,$A97)) -> 0 | O97: =IF(OR($A97="",$H97="",Config!$B$4=0),"",$H97/Config!$B$4) | P97: =IF($A97="","",SUM($H$78:$H97)) -> 0 | Q97: =IF($A97="","",IFERROR((AVERAGE($O$78:$O97)-Config!$B$7/Config!$B$6)/STDEV($O$78:$O97)*SQRT(Config!$B$6),"")) | R97: =IF($A97="","",IFERROR((AVERAGE($O$38:$O97)-Config!$B$7/Config!$B$6)/STDEV($O$38:$O97)*SQRT(Config!$B$6),"")) | S97: =IF($H97="",$S96,IF($H97>0,$S96+1,0)) -> 1 | T97: =IF($H97="",$T96,IF($H97<0,$T96+1,0)) -> 0
A98: =IF($A97="","",$A97+1) -> 46329 | B98: =IF($A98="","",TEXT($A98,"ddd")) -> Tue | C98: =IF($A98="","",COUNTIFS('Trade Log'!$L$4:$L$503,$A98)) -> 0 | D98: =IF($A98="","",SUMIFS('Trade Log'!$Q$4:$Q$503,'Trade Log'!$L$4:$L$503,$A98,'Trade Log'!$E$4:$E$503,"LONG")) -> 0 | E98: =IF($A98="","",SUMIFS('Trade Log'!$Q$4:$Q$503,'Trade Log'!$L$4:$L$503,$A98,'Trade Log'!$E$4:$E$503,"SHORT")) -> 0 | F98: =IF($A98="","",$D98+$E98) -> 0 | G98: =IF($A98="","",SUMIFS('Trade Log'!$Y$4:$Y$503,'Trade Log'!$L$4:$L$503,$A98)) -> 0 | H98: =IF($A98="","",IF($C98=0,"",$F98-$G98)) | I98: =IF($A98="","",$I97+IF($H98="",0,$H98)) -> 23918.552 | J98: =IF($A98="","",Config!$B$4+$I98) -> 1023918.6 | K98: =IF($A98="","",MAX($J$4:$J98)) -> 1023918.6 | L98: =IF($A98="","",$J98-$K98) -> 0 | M98: =IF(OR($A98="",$K98=0),"",$L98/$K98) -> 0 | N98: =IF($A98="","",SUMIFS('Trade Log'!$K$4:$K$503,'Trade Log'!$H$4:$H$503,$A98)) -> 0 | O98: =IF(OR($A98="",$H98="",Config!$B$4=0),"",$H98/Config!$B$4) | P98: =IF($A98="","",SUM($H$79:$H98)) -> 0 | Q98: =IF($A98="","",IFERROR((AVERAGE($O$79:$O98)-Config!$B$7/Config!$B$6)/STDEV($O$79:$O98)*SQRT(Config!$B$6),"")) | R98: =IF($A98="","",IFERROR((AVERAGE($O$39:$O98)-Config!$B$7/Config!$B$6)/STDEV($O$39:$O98)*SQRT(Config!$B$6),"")) | S98: =IF($H98="",$S97,IF($H98>0,$S97+1,0)) -> 1 | T98: =IF($H98="",$T97,IF($H98<0,$T97+1,0)) -> 0
A99: =IF($A98="","",$A98+1) -> 46330 | B99: =IF($A99="","",TEXT($A99,"ddd")) -> Wed | C99: =IF($A99="","",COUNTIFS('Trade Log'!$L$4:$L$503,$A99)) -> 0 | D99: =IF($A99="","",SUMIFS('Trade Log'!$Q$4:$Q$503,'Trade Log'!$L$4:$L$503,$A99,'Trade Log'!$E$4:$E$503,"LONG")) -> 0 | E99: =IF($A99="","",SUMIFS('Trade Log'!$Q$4:$Q$503,'Trade Log'!$L$4:$L$503,$A99,'Trade Log'!$E$4:$E$503,"SHORT")) -> 0 | F99: =IF($A99="","",$D99+$E99) -> 0 | G99: =IF($A99="","",SUMIFS('Trade Log'!$Y$4:$Y$503,'Trade Log'!$L$4:$L$503,$A99)) -> 0 | H99: =IF($A99="","",IF($C99=0,"",$F99-$G99)) | I99: =IF($A99="","",$I98+IF($H99="",0,$H99)) -> 23918.552 | J99: =IF($A99="","",Config!$B$4+$I99) -> 1023918.6 | K99: =IF($A99="","",MAX($J$4:$J99)) -> 1023918.6 | L99: =IF($A99="","",$J99-$K99) -> 0 | M99: =IF(OR($A99="",$K99=0),"",$L99/$K99) -> 0 | N99: =IF($A99="","",SUMIFS('Trade Log'!$K$4:$K$503,'Trade Log'!$H$4:$H$503,$A99)) -> 0 | O99: =IF(OR($A99="",$H99="",Config!$B$4=0),"",$H99/Config!$B$4) | P99: =IF($A99="","",SUM($H$80:$H99)) -> 0 | Q99: =IF($A99="","",IFERROR((AVERAGE($O$80:$O99)-Config!$B$7/Config!$B$6)/STDEV($O$80:$O99)*SQRT(Config!$B$6),"")) | R99: =IF($A99="","",IFERROR((AVERAGE($O$40:$O99)-Config!$B$7/Config!$B$6)/STDEV($O$40:$O99)*SQRT(Config!$B$6),"")) | S99: =IF($H99="",$S98,IF($H99>0,$S98+1,0)) -> 1 | T99: =IF($H99="",$T98,IF($H99<0,$T98+1,0)) -> 0
A100: =IF($A99="","",$A99+1) -> 46331 | B100: =IF($A100="","",TEXT($A100,"ddd")) -> Thu | C100: =IF($A100="","",COUNTIFS('Trade Log'!$L$4:$L$503,$A100)) -> 0 | D100: =IF($A100="","",SUMIFS('Trade Log'!$Q$4:$Q$503,'Trade Log'!$L$4:$L$503,$A100,'Trade Log'!$E$4:$E$503,"LONG")) -> 0 | E100: =IF($A100="","",SUMIFS('Trade Log'!$Q$4:$Q$503,'Trade Log'!$L$4:$L$503,$A100,'Trade Log'!$E$4:$E$503,"SHORT")) -> 0 | F100: =IF($A100="","",$D100+$E100) -> 0 | G100: =IF($A100="","",SUMIFS('Trade Log'!$Y$4:$Y$503,'Trade Log'!$L$4:$L$503,$A100)) -> 0 | H100: =IF($A100="","",IF($C100=0,"",$F100-$G100)) | I100: =IF($A100="","",$I99+IF($H100="",0,$H100)) -> 23918.552 | J100: =IF($A100="","",Config!$B$4+$I100) -> 1023918.6 | K100: =IF($A100="","",MAX($J$4:$J100)) -> 1023918.6 | L100: =IF($A100="","",$J100-$K100) -> 0 | M100: =IF(OR($A100="",$K100=0),"",$L100/$K100) -> 0 | N100: =IF($A100="","",SUMIFS('Trade Log'!$K$4:$K$503,'Trade Log'!$H$4:$H$503,$A100)) -> 0 | O100: =IF(OR($A100="",$H100="",Config!$B$4=0),"",$H100/Config!$B$4) | P100: =IF($A100="","",SUM($H$81:$H100)) -> 0 | Q100: =IF($A100="","",IFERROR((AVERAGE($O$81:$O100)-Config!$B$7/Config!$B$6)/STDEV($O$81:$O100)*SQRT(Config!$B$6),"")) | R100: =IF($A100="","",IFERROR((AVERAGE($O$41:$O100)-Config!$B$7/Config!$B$6)/STDEV($O$41:$O100)*SQRT(Config!$B$6),"")) | S100: =IF($H100="",$S99,IF($H100>0,$S99+1,0)) -> 1 | T100: =IF($H100="",$T99,IF($H100<0,$T99+1,0)) -> 0
A101: =IF($A100="","",$A100+1) -> 46332 | B101: =IF($A101="","",TEXT($A101,"ddd")) -> Fri | C101: =IF($A101="","",COUNTIFS('Trade Log'!$L$4:$L$503,$A101)) -> 0 | D101: =IF($A101="","",SUMIFS('Trade Log'!$Q$4:$Q$503,'Trade Log'!$L$4:$L$503,$A101,'Trade Log'!$E$4:$E$503,"LONG")) -> 0 | E101: =IF($A101="","",SUMIFS('Trade Log'!$Q$4:$Q$503,'Trade Log'!$L$4:$L$503,$A101,'Trade Log'!$E$4:$E$503,"SHORT")) -> 0 | F101: =IF($A101="","",$D101+$E101) -> 0 | G101: =IF($A101="","",SUMIFS('Trade Log'!$Y$4:$Y$503,'Trade Log'!$L$4:$L$503,$A101)) -> 0 | H101: =IF($A101="","",IF($C101=0,"",$F101-$G101)) | I101: =IF($A101="","",$I100+IF($H101="",0,$H101)) -> 23918.552 | J101: =IF($A101="","",Config!$B$4+$I101) -> 1023918.6 | K101: =IF($A101="","",MAX($J$4:$J101)) -> 1023918.6 | L101: =IF($A101="","",$J101-$K101) -> 0 | M101: =IF(OR($A101="",$K101=0),"",$L101/$K101) -> 0 | N101: =IF($A101="","",SUMIFS('Trade Log'!$K$4:$K$503,'Trade Log'!$H$4:$H$503,$A101)) -> 0 | O101: =IF(OR($A101="",$H101="",Config!$B$4=0),"",$H101/Config!$B$4) | P101: =IF($A101="","",SUM($H$82:$H101)) -> 0 | Q101: =IF($A101="","",IFERROR((AVERAGE($O$82:$O101)-Config!$B$7/Config!$B$6)/STDEV($O$82:$O101)*SQRT(Config!$B$6),"")) | R101: =IF($A101="","",IFERROR((AVERAGE($O$42:$O101)-Config!$B$7/Config!$B$6)/STDEV($O$42:$O101)*SQRT(Config!$B$6),"")) | S101: =IF($H101="",$S100,IF($H101>0,$S100+1,0)) -> 1 | T101: =IF($H101="",$T100,IF($H101<0,$T100+1,0)) -> 0
A102: =IF($A101="","",$A101+1) -> 46333 | B102: =IF($A102="","",TEXT($A102,"ddd")) -> Sat | C102: =IF($A102="","",COUNTIFS('Trade Log'!$L$4:$L$503,$A102)) -> 0 | D102: =IF($A102="","",SUMIFS('Trade Log'!$Q$4:$Q$503,'Trade Log'!$L$4:$L$503,$A102,'Trade Log'!$E$4:$E$503,"LONG")) -> 0 | E102: =IF($A102="","",SUMIFS('Trade Log'!$Q$4:$Q$503,'Trade Log'!$L$4:$L$503,$A102,'Trade Log'!$E$4:$E$503,"SHORT")) -> 0 | F102: =IF($A102="","",$D102+$E102) -> 0 | G102: =IF($A102="","",SUMIFS('Trade Log'!$Y$4:$Y$503,'Trade Log'!$L$4:$L$503,$A102)) -> 0 | H102: =IF($A102="","",IF($C102=0,"",$F102-$G102)) | I102: =IF($A102="","",$I101+IF($H102="",0,$H102)) -> 23918.552 | J102: =IF($A102="","",Config!$B$4+$I102) -> 1023918.6 | K102: =IF($A102="","",MAX($J$4:$J102)) -> 1023918.6 | L102: =IF($A102="","",$J102-$K102) -> 0 | M102: =IF(OR($A102="",$K102=0),"",$L102/$K102) -> 0 | N102: =IF($A102="","",SUMIFS('Trade Log'!$K$4:$K$503,'Trade Log'!$H$4:$H$503,$A102)) -> 0 | O102: =IF(OR($A102="",$H102="",Config!$B$4=0),"",$H102/Config!$B$4) | P102: =IF($A102="","",SUM($H$83:$H102)) -> 0 | Q102: =IF($A102="","",IFERROR((AVERAGE($O$83:$O102)-Config!$B$7/Config!$B$6)/STDEV($O$83:$O102)*SQRT(Config!$B$6),"")) | R102: =IF($A102="","",IFERROR((AVERAGE($O$43:$O102)-Config!$B$7/Config!$B$6)/STDEV($O$43:$O102)*SQRT(Config!$B$6),"")) | S102: =IF($H102="",$S101,IF($H102>0,$S101+1,0)) -> 1 | T102: =IF($H102="",$T101,IF($H102<0,$T101+1,0)) -> 0
A103: =IF($A102="","",$A102+1) -> 46334 | B103: =IF($A103="","",TEXT($A103,"ddd")) -> Sun | C103: =IF($A103="","",COUNTIFS('Trade Log'!$L$4:$L$503,$A103)) -> 0 | D103: =IF($A103="","",SUMIFS('Trade Log'!$Q$4:$Q$503,'Trade Log'!$L$4:$L$503,$A103,'Trade Log'!$E$4:$E$503,"LONG")) -> 0 | E103: =IF($A103="","",SUMIFS('Trade Log'!$Q$4:$Q$503,'Trade Log'!$L$4:$L$503,$A103,'Trade Log'!$E$4:$E$503,"SHORT")) -> 0 | F103: =IF($A103="","",$D103+$E103) -> 0 | G103: =IF($A103="","",SUMIFS('Trade Log'!$Y$4:$Y$503,'Trade Log'!$L$4:$L$503,$A103)) -> 0 | H103: =IF($A103="","",IF($C103=0,"",$F103-$G103)) | I103: =IF($A103="","",$I102+IF($H103="",0,$H103)) -> 23918.552 | J103: =IF($A103="","",Config!$B$4+$I103) -> 1023918.6 | K103: =IF($A103="","",MAX($J$4:$J103)) -> 1023918.6 | L103: =IF($A103="","",$J103-$K103) -> 0 | M103: =IF(OR($A103="",$K103=0),"",$L103/$K103) -> 0 | N103: =IF($A103="","",SUMIFS('Trade Log'!$K$4:$K$503,'Trade Log'!$H$4:$H$503,$A103)) -> 0 | O103: =IF(OR($A103="",$H103="",Config!$B$4=0),"",$H103/Config!$B$4) | P103: =IF($A103="","",SUM($H$84:$H103)) -> 0 | Q103: =IF($A103="","",IFERROR((AVERAGE($O$84:$O103)-Config!$B$7/Config!$B$6)/STDEV($O$84:$O103)*SQRT(Config!$B$6),"")) | R103: =IF($A103="","",IFERROR((AVERAGE($O$44:$O103)-Config!$B$7/Config!$B$6)/STDEV($O$44:$O103)*SQRT(Config!$B$6),"")) | S103: =IF($H103="",$S102,IF($H103>0,$S102+1,0)) -> 1 | T103: =IF($H103="",$T102,IF($H103<0,$T102+1,0)) -> 0
A104: =IF($A103="","",$A103+1) -> 46335 | B104: =IF($A104="","",TEXT($A104,"ddd")) -> Mon | C104: =IF($A104="","",COUNTIFS('Trade Log'!$L$4:$L$503,$A104)) -> 0 | D104: =IF($A104="","",SUMIFS('Trade Log'!$Q$4:$Q$503,'Trade Log'!$L$4:$L$503,$A104,'Trade Log'!$E$4:$E$503,"LONG")) -> 0 | E104: =IF($A104="","",SUMIFS('Trade Log'!$Q$4:$Q$503,'Trade Log'!$L$4:$L$503,$A104,'Trade Log'!$E$4:$E$503,"SHORT")) -> 0 | F104: =IF($A104="","",$D104+$E104) -> 0 | G104: =IF($A104="","",SUMIFS('Trade Log'!$Y$4:$Y$503,'Trade Log'!$L$4:$L$503,$A104)) -> 0 | H104: =IF($A104="","",IF($C104=0,"",$F104-$G104)) | I104: =IF($A104="","",$I103+IF($H104="",0,$H104)) -> 23918.552 | J104: =IF($A104="","",Config!$B$4+$I104) -> 1023918.6 | K104: =IF($A104="","",MAX($J$4:$J104)) -> 1023918.6 | L104: =IF($A104="","",$J104-$K104) -> 0 | M104: =IF(OR($A104="",$K104=0),"",$L104/$K104) -> 0 | N104: =IF($A104="","",SUMIFS('Trade Log'!$K$4:$K$503,'Trade Log'!$H$4:$H$503,$A104)) -> 0 | O104: =IF(OR($A104="",$H104="",Config!$B$4=0),"",$H104/Config!$B$4) | P104: =IF($A104="","",SUM($H$85:$H104)) -> 0 | Q104: =IF($A104="","",IFERROR((AVERAGE($O$85:$O104)-Config!$B$7/Config!$B$6)/STDEV($O$85:$O104)*SQRT(Config!$B$6),"")) | R104: =IF($A104="","",IFERROR((AVERAGE($O$45:$O104)-Config!$B$7/Config!$B$6)/STDEV($O$45:$O104)*SQRT(Config!$B$6),"")) | S104: =IF($H104="",$S103,IF($H104>0,$S103+1,0)) -> 1 | T104: =IF($H104="",$T103,IF($H104<0,$T103+1,0)) -> 0
A105: =IF($A104="","",$A104+1) -> 46336 | B105: =IF($A105="","",TEXT($A105,"ddd")) -> Tue | C105: =IF($A105="","",COUNTIFS('Trade Log'!$L$4:$L$503,$A105)) -> 0 | D105: =IF($A105="","",SUMIFS('Trade Log'!$Q$4:$Q$503,'Trade Log'!$L$4:$L$503,$A105,'Trade Log'!$E$4:$E$503,"LONG")) -> 0 | E105: =IF($A105="","",SUMIFS('Trade Log'!$Q$4:$Q$503,'Trade Log'!$L$4:$L$503,$A105,'Trade Log'!$E$4:$E$503,"SHORT")) -> 0 | F105: =IF($A105="","",$D105+$E105) -> 0 | G105: =IF($A105="","",SUMIFS('Trade Log'!$Y$4:$Y$503,'Trade Log'!$L$4:$L$503,$A105)) -> 0 | H105: =IF($A105="","",IF($C105=0,"",$F105-$G105)) | I105: =IF($A105="","",$I104+IF($H105="",0,$H105)) -> 23918.552 | J105: =IF($A105="","",Config!$B$4+$I105) -> 1023918.6 | K105: =IF($A105="","",MAX($J$4:$J105)) -> 1023918.6 | L105: =IF($A105="","",$J105-$K105) -> 0 | M105: =IF(OR($A105="",$K105=0),"",$L105/$K105) -> 0 | N105: =IF($A105="","",SUMIFS('Trade Log'!$K$4:$K$503,'Trade Log'!$H$4:$H$503,$A105)) -> 0 | O105: =IF(OR($A105="",$H105="",Config!$B$4=0),"",$H105/Config!$B$4) | P105: =IF($A105="","",SUM($H$86:$H105)) -> 0 | Q105: =IF($A105="","",IFERROR((AVERAGE($O$86:$O105)-Config!$B$7/Config!$B$6)/STDEV($O$86:$O105)*SQRT(Config!$B$6),"")) | R105: =IF($A105="","",IFERROR((AVERAGE($O$46:$O105)-Config!$B$7/Config!$B$6)/STDEV($O$46:$O105)*SQRT(Config!$B$6),"")) | S105: =IF($H105="",$S104,IF($H105>0,$S104+1,0)) -> 1 | T105: =IF($H105="",$T104,IF($H105<0,$T104+1,0)) -> 0
A106: =IF($A105="","",$A105+1) -> 46337 | B106: =IF($A106="","",TEXT($A106,"ddd")) -> Wed | C106: =IF($A106="","",COUNTIFS('Trade Log'!$L$4:$L$503,$A106)) -> 0 | D106: =IF($A106="","",SUMIFS('Trade Log'!$Q$4:$Q$503,'Trade Log'!$L$4:$L$503,$A106,'Trade Log'!$E$4:$E$503,"LONG")) -> 0 | E106: =IF($A106="","",SUMIFS('Trade Log'!$Q$4:$Q$503,'Trade Log'!$L$4:$L$503,$A106,'Trade Log'!$E$4:$E$503,"SHORT")) -> 0 | F106: =IF($A106="","",$D106+$E106) -> 0 | G106: =IF($A106="","",SUMIFS('Trade Log'!$Y$4:$Y$503,'Trade Log'!$L$4:$L$503,$A106)) -> 0 | H106: =IF($A106="","",IF($C106=0,"",$F106-$G106)) | I106: =IF($A106="","",$I105+IF($H106="",0,$H106)) -> 23918.552 | J106: =IF($A106="","",Config!$B$4+$I106) -> 1023918.6 | K106: =IF($A106="","",MAX($J$4:$J106)) -> 1023918.6 | L106: =IF($A106="","",$J106-$K106) -> 0 | M106: =IF(OR($A106="",$K106=0),"",$L106/$K106) -> 0 | N106: =IF($A106="","",SUMIFS('Trade Log'!$K$4:$K$503,'Trade Log'!$H$4:$H$503,$A106)) -> 0 | O106: =IF(OR($A106="",$H106="",Config!$B$4=0),"",$H106/Config!$B$4) | P106: =IF($A106="","",SUM($H$87:$H106)) -> 0 | Q106: =IF($A106="","",IFERROR((AVERAGE($O$87:$O106)-Config!$B$7/Config!$B$6)/STDEV($O$87:$O106)*SQRT(Config!$B$6),"")) | R106: =IF($A106="","",IFERROR((AVERAGE($O$47:$O106)-Config!$B$7/Config!$B$6)/STDEV($O$47:$O106)*SQRT(Config!$B$6),"")) | S106: =IF($H106="",$S105,IF($H106>0,$S105+1,0)) -> 1 | T106: =IF($H106="",$T105,IF($H106<0,$T105+1,0)) -> 0
...

Sheet Company Stats
A1: Company-wise statistics
A2: Type or paste symbols into column A. In Google Sheets you can auto-fill A4 with: =SORT(UNIQUE(FILTER('Trade Log'!D4:D503,'Trade Log'!D4:D503<>"")))
A3: Symbol | B3: Legs | C3: Long | D3: Short | E3: Closed | F3: Turnover | G3: Long Net | H3: Short Net | I3: Gross P&L | J3: Costs | K3: Net P&L | L3: Winners | M3: Net Win Rate | N3: Avg Net / Leg | O3: Best Leg | P3: Worst Leg | Q3: Avg Net Ret % | R3: Avg Hold Days | S3: Avg Slip (bp) | T3: % of Net P&L | U3: Rank
A4: TVSSRICHAK | B4: =IF($A4="","",COUNTIFS('Trade Log'!$D$4:$D$503,$A4)) -> 2 | C4: =IF($A4="","",COUNTIFS('Trade Log'!$D$4:$D$503,$A4,'Trade Log'!$E$4:$E$503,"LONG")) -> 1 | D4: =IF($A4="","",COUNTIFS('Trade Log'!$D$4:$D$503,$A4,'Trade Log'!$E$4:$E$503,"SHORT")) -> 1 | E4: =IF($A4="","",COUNTIFS('Trade Log'!$D$4:$D$503,$A4,'Trade Log'!$N$4:$N$503,"<>")) -> 2 | F4: =IF($A4="","",SUMIFS('Trade Log'!$K$4:$K$503,'Trade Log'!$D$4:$D$503,$A4)) -> 519289.5 | G4: =IF($A4="","",SUMIFS('Trade Log'!$Z$4:$Z$503,'Trade Log'!$D$4:$D$503,$A4,'Trade Log'!$E$4:$E$503,"LONG")) -> 18831.363 | H4: =IF($A4="","",SUMIFS('Trade Log'!$Z$4:$Z$503,'Trade Log'!$D$4:$D$503,$A4,'Trade Log'!$E$4:$E$503,"SHORT")) -> 5087.1894 | I4: =IF($A4="","",SUMIFS('Trade Log'!$Q$4:$Q$503,'Trade Log'!$D$4:$D$503,$A4)) -> 24775.5 | J4: =IF($A4="","",SUMIFS('Trade Log'!$Y$4:$Y$503,'Trade Log'!$D$4:$D$503,$A4)) -> 856.94781 | K4: =IF($A4="","",SUMIFS('Trade Log'!$Z$4:$Z$503,'Trade Log'!$D$4:$D$503,$A4)) -> 23918.552 | L4: =IF($A4="","",COUNTIFS('Trade Log'!$D$4:$D$503,$A4,'Trade Log'!$Z$4:$Z$503,">0")) -> 2 | M4: =IF(OR($A4="",$E4=0),"",$L4/$E4) -> 1 | N4: =IF(OR($A4="",$E4=0),"",$K4/$E4) -> 11959.276 | O4: =IF($A4="","",IFERROR(_xlfn.MAXIFS('Trade Log'!$Z$4:$Z$503,'Trade Log'!$D$4:$D$503,$A4),"")) -> 18831.363 | P4: =IF($A4="","",IFERROR(_xlfn.MINIFS('Trade Log'!$Z$4:$Z$503,'Trade Log'!$D$4:$D$503,$A4),"")) -> 5087.1894 | Q4: =IF($A4="","",IFERROR(AVERAGEIFS('Trade Log'!$AA$4:$AA$503,'Trade Log'!$D$4:$D$503,$A4),"")) -> 0.047123166 | R4: =IF($A4="","",IFERROR(AVERAGEIFS('Trade Log'!$P$4:$P$503,'Trade Log'!$D$4:$D$503,$A4),"")) -> 0.5 | S4: =IF($A4="","",IFERROR(AVERAGEIFS('Trade Log'!$AC$4:$AC$503,'Trade Log'!$D$4:$D$503,$A4),"")) -> 17.5 | T4: =IF(OR($A4="",Summary!$B$13=0),"",$K4/Summary!$B$13) -> 1 | U4: =IF($A4="","",IFERROR(RANK($K4,$K$4:$K$153),"")) -> 1
B5: =IF($A5="","",COUNTIFS('Trade Log'!$D$4:$D$503,$A5)) | C5: =IF($A5="","",COUNTIFS('Trade Log'!$D$4:$D$503,$A5,'Trade Log'!$E$4:$E$503,"LONG")) | D5: =IF($A5="","",COUNTIFS('Trade Log'!$D$4:$D$503,$A5,'Trade Log'!$E$4:$E$503,"SHORT")) | E5: =IF($A5="","",COUNTIFS('Trade Log'!$D$4:$D$503,$A5,'Trade Log'!$N$4:$N$503,"<>")) | F5: =IF($A5="","",SUMIFS('Trade Log'!$K$4:$K$503,'Trade Log'!$D$4:$D$503,$A5)) | G5: =IF($A5="","",SUMIFS('Trade Log'!$Z$4:$Z$503,'Trade Log'!$D$4:$D$503,$A5,'Trade Log'!$E$4:$E$503,"LONG")) | H5: =IF($A5="","",SUMIFS('Trade Log'!$Z$4:$Z$503,'Trade Log'!$D$4:$D$503,$A5,'Trade Log'!$E$4:$E$503,"SHORT")) | I5: =IF($A5="","",SUMIFS('Trade Log'!$Q$4:$Q$503,'Trade Log'!$D$4:$D$503,$A5)) | J5: =IF($A5="","",SUMIFS('Trade Log'!$Y$4:$Y$503,'Trade Log'!$D$4:$D$503,$A5)) | K5: =IF($A5="","",SUMIFS('Trade Log'!$Z$4:$Z$503,'Trade Log'!$D$4:$D$503,$A5)) | L5: =IF($A5="","",COUNTIFS('Trade Log'!$D$4:$D$503,$A5,'Trade Log'!$Z$4:$Z$503,">0")) | M5: =IF(OR($A5="",$E5=0),"",$L5/$E5) | N5: =IF(OR($A5="",$E5=0),"",$K5/$E5) | O5: =IF($A5="","",IFERROR(_xlfn.MAXIFS('Trade Log'!$Z$4:$Z$503,'Trade Log'!$D$4:$D$503,$A5),"")) | P5: =IF($A5="","",IFERROR(_xlfn.MINIFS('Trade Log'!$Z$4:$Z$503,'Trade Log'!$D$4:$D$503,$A5),"")) | Q5: =IF($A5="","",IFERROR(AVERAGEIFS('Trade Log'!$AA$4:$AA$503,'Trade Log'!$D$4:$D$503,$A5),"")) | R5: =IF($A5="","",IFERROR(AVERAGEIFS('Trade Log'!$P$4:$P$503,'Trade Log'!$D$4:$D$503,$A5),"")) | S5: =IF($A5="","",IFERROR(AVERAGEIFS('Trade Log'!$AC$4:$AC$503,'Trade Log'!$D$4:$D$503,$A5),"")) | T5: =IF(OR($A5="",Summary!$B$13=0),"",$K5/Summary!$B$13) | U5: =IF($A5="","",IFERROR(RANK($K5,$K$4:$K$153),""))
B6: =IF($A6="","",COUNTIFS('Trade Log'!$D$4:$D$503,$A6)) | C6: =IF($A6="","",COUNTIFS('Trade Log'!$D$4:$D$503,$A6,'Trade Log'!$E$4:$E$503,"LONG")) | D6: =IF($A6="","",COUNTIFS('Trade Log'!$D$4:$D$503,$A6,'Trade Log'!$E$4:$E$503,"SHORT")) | E6: =IF($A6="","",COUNTIFS('Trade Log'!$D$4:$D$503,$A6,'Trade Log'!$N$4:$N$503,"<>")) | F6: =IF($A6="","",SUMIFS('Trade Log'!$K$4:$K$503,'Trade Log'!$D$4:$D$503,$A6)) | G6: =IF($A6="","",SUMIFS('Trade Log'!$Z$4:$Z$503,'Trade Log'!$D$4:$D$503,$A6,'Trade Log'!$E$4:$E$503,"LONG")) | H6: =IF($A6="","",SUMIFS('Trade Log'!$Z$4:$Z$503,'Trade Log'!$D$4:$D$503,$A6,'Trade Log'!$E$4:$E$503,"SHORT")) | I6: =IF($A6="","",SUMIFS('Trade Log'!$Q$4:$Q$503,'Trade Log'!$D$4:$D$503,$A6)) | J6: =IF($A6="","",SUMIFS('Trade Log'!$Y$4:$Y$503,'Trade Log'!$D$4:$D$503,$A6)) | K6: =IF($A6="","",SUMIFS('Trade Log'!$Z$4:$Z$503,'Trade Log'!$D$4:$D$503,$A6)) | L6: =IF($A6="","",COUNTIFS('Trade Log'!$D$4:$D$503,$A6,'Trade Log'!$Z$4:$Z$503,">0")) | M6: =IF(OR($A6="",$E6=0),"",$L6/$E6) | N6: =IF(OR($A6="",$E6=0),"",$K6/$E6) | O6: =IF($A6="","",IFERROR(_xlfn.MAXIFS('Trade Log'!$Z$4:$Z$503,'Trade Log'!$D$4:$D$503,$A6),"")) | P6: =IF($A6="","",IFERROR(_xlfn.MINIFS('Trade Log'!$Z$4:$Z$503,'Trade Log'!$D$4:$D$503,$A6),"")) | Q6: =IF($A6="","",IFERROR(AVERAGEIFS('Trade Log'!$AA$4:$AA$503,'Trade Log'!$D$4:$D$503,$A6),"")) | R6: =IF($A6="","",IFERROR(AVERAGEIFS('Trade Log'!$P$4:$P$503,'Trade Log'!$D$4:$D$503,$A6),"")) | S6: =IF($A6="","",IFERROR(AVERAGEIFS('Trade Log'!$AC$4:$AC$503,'Trade Log'!$D$4:$D$503,$A6),"")) | T6: =IF(OR($A6="",Summary!$B$13=0),"",$K6/Summary!$B$13) | U6: =IF($A6="","",IFERROR(RANK($K6,$K$4:$K$153),""))
B7: =IF($A7="","",COUNTIFS('Trade Log'!$D$4:$D$503,$A7)) | C7: =IF($A7="","",COUNTIFS('Trade Log'!$D$4:$D$503,$A7,'Trade Log'!$E$4:$E$503,"LONG")) | D7: =IF($A7="","",COUNTIFS('Trade Log'!$D$4:$D$503,$A7,'Trade Log'!$E$4:$E$503,"SHORT")) | E7: =IF($A7="","",COUNTIFS('Trade Log'!$D$4:$D$503,$A7,'Trade Log'!$N$4:$N$503,"<>")) | F7: =IF($A7="","",SUMIFS('Trade Log'!$K$4:$K$503,'Trade Log'!$D$4:$D$503,$A7)) | G7: =IF($A7="","",SUMIFS('Trade Log'!$Z$4:$Z$503,'Trade Log'!$D$4:$D$503,$A7,'Trade Log'!$E$4:$E$503,"LONG")) | H7: =IF($A7="","",SUMIFS('Trade Log'!$Z$4:$Z$503,'Trade Log'!$D$4:$D$503,$A7,'Trade Log'!$E$4:$E$503,"SHORT")) | I7: =IF($A7="","",SUMIFS('Trade Log'!$Q$4:$Q$503,'Trade Log'!$D$4:$D$503,$A7)) | J7: =IF($A7="","",SUMIFS('Trade Log'!$Y$4:$Y$503,'Trade Log'!$D$4:$D$503,$A7)) | K7: =IF($A7="","",SUMIFS('Trade Log'!$Z$4:$Z$503,'Trade Log'!$D$4:$D$503,$A7)) | L7: =IF($A7="","",COUNTIFS('Trade Log'!$D$4:$D$503,$A7,'Trade Log'!$Z$4:$Z$503,">0")) | M7: =IF(OR($A7="",$E7=0),"",$L7/$E7) | N7: =IF(OR($A7="",$E7=0),"",$K7/$E7) | O7: =IF($A7="","",IFERROR(_xlfn.MAXIFS('Trade Log'!$Z$4:$Z$503,'Trade Log'!$D$4:$D$503,$A7),"")) | P7: =IF($A7="","",IFERROR(_xlfn.MINIFS('Trade Log'!$Z$4:$Z$503,'Trade Log'!$D$4:$D$503,$A7),"")) | Q7: =IF($A7="","",IFERROR(AVERAGEIFS('Trade Log'!$AA$4:$AA$503,'Trade Log'!$D$4:$D$503,$A7),"")) | R7: =IF($A7="","",IFERROR(AVERAGEIFS('Trade Log'!$P$4:$P$503,'Trade Log'!$D$4:$D$503,$A7),"")) | S7: =IF($A7="","",IFERROR(AVERAGEIFS('Trade Log'!$AC$4:$AC$503,'Trade Log'!$D$4:$D$503,$A7),"")) | T7: =IF(OR($A7="",Summary!$B$13=0),"",$K7/Summary!$B$13) | U7: =IF($A7="","",IFERROR(RANK($K7,$K$4:$K$153),""))
B8: =IF($A8="","",COUNTIFS('Trade Log'!$D$4:$D$503,$A8)) | C8: =IF($A8="","",COUNTIFS('Trade Log'!$D$4:$D$503,$A8,'Trade Log'!$E$4:$E$503,"LONG")) | D8: =IF($A8="","",COUNTIFS('Trade Log'!$D$4:$D$503,$A8,'Trade Log'!$E$4:$E$503,"SHORT")) | E8: =IF($A8="","",COUNTIFS('Trade Log'!$D$4:$D$503,$A8,'Trade Log'!$N$4:$N$503,"<>")) | F8: =IF($A8="","",SUMIFS('Trade Log'!$K$4:$K$503,'Trade Log'!$D$4:$D$503,$A8)) | G8: =IF($A8="","",SUMIFS('Trade Log'!$Z$4:$Z$503,'Trade Log'!$D$4:$D$503,$A8,'Trade Log'!$E$4:$E$503,"LONG")) | H8: =IF($A8="","",SUMIFS('Trade Log'!$Z$4:$Z$503,'Trade Log'!$D$4:$D$503,$A8,'Trade Log'!$E$4:$E$503,"SHORT")) | I8: =IF($A8="","",SUMIFS('Trade Log'!$Q$4:$Q$503,'Trade Log'!$D$4:$D$503,$A8)) | J8: =IF($A8="","",SUMIFS('Trade Log'!$Y$4:$Y$503,'Trade Log'!$D$4:$D$503,$A8)) | K8: =IF($A8="","",SUMIFS('Trade Log'!$Z$4:$Z$503,'Trade Log'!$D$4:$D$503,$A8)) | L8: =IF($A8="","",COUNTIFS('Trade Log'!$D$4:$D$503,$A8,'Trade Log'!$Z$4:$Z$503,">0")) | M8: =IF(OR($A8="",$E8=0),"",$L8/$E8) | N8: =IF(OR($A8="",$E8=0),"",$K8/$E8) | O8: =IF($A8="","",IFERROR(_xlfn.MAXIFS('Trade Log'!$Z$4:$Z$503,'Trade Log'!$D$4:$D$503,$A8),"")) | P8: =IF($A8="","",IFERROR(_xlfn.MINIFS('Trade Log'!$Z$4:$Z$503,'Trade Log'!$D$4:$D$503,$A8),"")) | Q8: =IF($A8="","",IFERROR(AVERAGEIFS('Trade Log'!$AA$4:$AA$503,'Trade Log'!$D$4:$D$503,$A8),"")) | R8: =IF($A8="","",IFERROR(AVERAGEIFS('Trade Log'!$P$4:$P$503,'Trade Log'!$D$4:$D$503,$A8),"")) | S8: =IF($A8="","",IFERROR(AVERAGEIFS('Trade Log'!$AC$4:$AC$503,'Trade Log'!$D$4:$D$503,$A8),"")) | T8: =IF(OR($A8="",Summary!$B$13=0),"",$K8/Summary!$B$13) | U8: =IF($A8="","",IFERROR(RANK($K8,$K$4:$K$153),""))
B9: =IF($A9="","",COUNTIFS('Trade Log'!$D$4:$D$503,$A9)) | C9: =IF($A9="","",COUNTIFS('Trade Log'!$D$4:$D$503,$A9,'Trade Log'!$E$4:$E$503,"LONG")) | D9: =IF($A9="","",COUNTIFS('Trade Log'!$D$4:$D$503,$A9,'Trade Log'!$E$4:$E$503,"SHORT")) | E9: =IF($A9="","",COUNTIFS('Trade Log'!$D$4:$D$503,$A9,'Trade Log'!$N$4:$N$503,"<>")) | F9: =IF($A9="","",SUMIFS('Trade Log'!$K$4:$K$503,'Trade Log'!$D$4:$D$503,$A9)) | G9: =IF($A9="","",SUMIFS('Trade Log'!$Z$4:$Z$503,'Trade Log'!$D$4:$D$503,$A9,'Trade Log'!$E$4:$E$503,"LONG")) | H9: =IF($A9="","",SUMIFS('Trade Log'!$Z$4:$Z$503,'Trade Log'!$D$4:$D$503,$A9,'Trade Log'!$E$4:$E$503,"SHORT")) | I9: =IF($A9="","",SUMIFS('Trade Log'!$Q$4:$Q$503,'Trade Log'!$D$4:$D$503,$A9)) | J9: =IF($A9="","",SUMIFS('Trade Log'!$Y$4:$Y$503,'Trade Log'!$D$4:$D$503,$A9)) | K9: =IF($A9="","",SUMIFS('Trade Log'!$Z$4:$Z$503,'Trade Log'!$D$4:$D$503,$A9)) | L9: =IF($A9="","",COUNTIFS('Trade Log'!$D$4:$D$503,$A9,'Trade Log'!$Z$4:$Z$503,">0")) | M9: =IF(OR($A9="",$E9=0),"",$L9/$E9) | N9: =IF(OR($A9="",$E9=0),"",$K9/$E9) | O9: =IF($A9="","",IFERROR(_xlfn.MAXIFS('Trade Log'!$Z$4:$Z$503,'Trade Log'!$D$4:$D$503,$A9),"")) | P9: =IF($A9="","",IFERROR(_xlfn.MINIFS('Trade Log'!$Z$4:$Z$503,'Trade Log'!$D$4:$D$503,$A9),"")) | Q9: =IF($A9="","",IFERROR(AVERAGEIFS('Trade Log'!$AA$4:$AA$503,'Trade Log'!$D$4:$D$503,$A9),"")) | R9: =IF($A9="","",IFERROR(AVERAGEIFS('Trade Log'!$P$4:$P$503,'Trade Log'!$D$4:$D$503,$A9),"")) | S9: =IF($A9="","",IFERROR(AVERAGEIFS('Trade Log'!$AC$4:$AC$503,'Trade Log'!$D$4:$D$503,$A9),"")) | T9: =IF(OR($A9="",Summary!$B$13=0),"",$K9/Summary!$B$13) | U9: =IF($A9="","",IFERROR(RANK($K9,$K$4:$K$153),""))
B10: =IF($A10="","",COUNTIFS('Trade Log'!$D$4:$D$503,$A10)) | C10: =IF($A10="","",COUNTIFS('Trade Log'!$D$4:$D$503,$A10,'Trade Log'!$E$4:$E$503,"LONG")) | D10: =IF($A10="","",COUNTIFS('Trade Log'!$D$4:$D$503,$A10,'Trade Log'!$E$4:$E$503,"SHORT")) | E10: =IF($A10="","",COUNTIFS('Trade Log'!$D$4:$D$503,$A10,'Trade Log'!$N$4:$N$503,"<>")) | F10: =IF($A10="","",SUMIFS('Trade Log'!$K$4:$K$503,'Trade Log'!$D$4:$D$503,$A10)) | G10: =IF($A10="","",SUMIFS('Trade Log'!$Z$4:$Z$503,'Trade Log'!$D$4:$D$503,$A10,'Trade Log'!$E$4:$E$503,"LONG")) | H10: =IF($A10="","",SUMIFS('Trade Log'!$Z$4:$Z$503,'Trade Log'!$D$4:$D$503,$A10,'Trade Log'!$E$4:$E$503,"SHORT")) | I10: =IF($A10="","",SUMIFS('Trade Log'!$Q$4:$Q$503,'Trade Log'!$D$4:$D$503,$A10)) | J10: =IF($A10="","",SUMIFS('Trade Log'!$Y$4:$Y$503,'Trade Log'!$D$4:$D$503,$A10)) | K10: =IF($A10="","",SUMIFS('Trade Log'!$Z$4:$Z$503,'Trade Log'!$D$4:$D$503,$A10)) | L10: =IF($A10="","",COUNTIFS('Trade Log'!$D$4:$D$503,$A10,'Trade Log'!$Z$4:$Z$503,">0")) | M10: =IF(OR($A10="",$E10=0),"",$L10/$E10) | N10: =IF(OR($A10="",$E10=0),"",$K10/$E10) | O10: =IF($A10="","",IFERROR(_xlfn.MAXIFS('Trade Log'!$Z$4:$Z$503,'Trade Log'!$D$4:$D$503,$A10),"")) | P10: =IF($A10="","",IFERROR(_xlfn.MINIFS('Trade Log'!$Z$4:$Z$503,'Trade Log'!$D$4:$D$503,$A10),"")) | Q10: =IF($A10="","",IFERROR(AVERAGEIFS('Trade Log'!$AA$4:$AA$503,'Trade Log'!$D$4:$D$503,$A10),"")) | R10: =IF($A10="","",IFERROR(AVERAGEIFS('Trade Log'!$P$4:$P$503,'Trade Log'!$D$4:$D$503,$A10),"")) | S10: =IF($A10="","",IFERROR(AVERAGEIFS('Trade Log'!$AC$4:$AC$503,'Trade Log'!$D$4:$D$503,$A10),"")) | T10: =IF(OR($A10="",Summary!$B$13=0),"",$K10/Summary!$B$13) | U10: =IF($A10="","",IFERROR(RANK($K10,$K$4:$K$153),""))
B11: =IF($A11="","",COUNTIFS('Trade Log'!$D$4:$D$503,$A11)) | C11: =IF($A11="","",COUNTIFS('Trade Log'!$D$4:$D$503,$A11,'Trade Log'!$E$4:$E$503,"LONG")) | D11: =IF($A11="","",COUNTIFS('Trade Log'!$D$4:$D$503,$A11,'Trade Log'!$E$4:$E$503,"SHORT")) | E11: =IF($A11="","",COUNTIFS('Trade Log'!$D$4:$D$503,$A11,'Trade Log'!$N$4:$N$503,"<>")) | F11: =IF($A11="","",SUMIFS('Trade Log'!$K$4:$K$503,'Trade Log'!$D$4:$D$503,$A11)) | G11: =IF($A11="","",SUMIFS('Trade Log'!$Z$4:$Z$503,'Trade Log'!$D$4:$D$503,$A11,'Trade Log'!$E$4:$E$503,"LONG")) | H11: =IF($A11="","",SUMIFS('Trade Log'!$Z$4:$Z$503,'Trade Log'!$D$4:$D$503,$A11,'Trade Log'!$E$4:$E$503,"SHORT")) | I11: =IF($A11="","",SUMIFS('Trade Log'!$Q$4:$Q$503,'Trade Log'!$D$4:$D$503,$A11)) | J11: =IF($A11="","",SUMIFS('Trade Log'!$Y$4:$Y$503,'Trade Log'!$D$4:$D$503,$A11)) | K11: =IF($A11="","",SUMIFS('Trade Log'!$Z$4:$Z$503,'Trade Log'!$D$4:$D$503,$A11)) | L11: =IF($A11="","",COUNTIFS('Trade Log'!$D$4:$D$503,$A11,'Trade Log'!$Z$4:$Z$503,">0")) | M11: =IF(OR($A11="",$E11=0),"",$L11/$E11) | N11: =IF(OR($A11="",$E11=0),"",$K11/$E11) | O11: =IF($A11="","",IFERROR(_xlfn.MAXIFS('Trade Log'!$Z$4:$Z$503,'Trade Log'!$D$4:$D$503,$A11),"")) | P11: =IF($A11="","",IFERROR(_xlfn.MINIFS('Trade Log'!$Z$4:$Z$503,'Trade Log'!$D$4:$D$503,$A11),"")) | Q11: =IF($A11="","",IFERROR(AVERAGEIFS('Trade Log'!$AA$4:$AA$503,'Trade Log'!$D$4:$D$503,$A11),"")) | R11: =IF($A11="","",IFERROR(AVERAGEIFS('Trade Log'!$P$4:$P$503,'Trade Log'!$D$4:$D$503,$A11),"")) | S11: =IF($A11="","",IFERROR(AVERAGEIFS('Trade Log'!$AC$4:$AC$503,'Trade Log'!$D$4:$D$503,$A11),"")) | T11: =IF(OR($A11="",Summary!$B$13=0),"",$K11/Summary!$B$13) | U11: =IF($A11="","",IFERROR(RANK($K11,$K$4:$K$153),""))
B12: =IF($A12="","",COUNTIFS('Trade Log'!$D$4:$D$503,$A12)) | C12: =IF($A12="","",COUNTIFS('Trade Log'!$D$4:$D$503,$A12,'Trade Log'!$E$4:$E$503,"LONG")) | D12: =IF($A12="","",COUNTIFS('Trade Log'!$D$4:$D$503,$A12,'Trade Log'!$E$4:$E$503,"SHORT")) | E12: =IF($A12="","",COUNTIFS('Trade Log'!$D$4:$D$503,$A12,'Trade Log'!$N$4:$N$503,"<>")) | F12: =IF($A12="","",SUMIFS('Trade Log'!$K$4:$K$503,'Trade Log'!$D$4:$D$503,$A12)) | G12: =IF($A12="","",SUMIFS('Trade Log'!$Z$4:$Z$503,'Trade Log'!$D$4:$D$503,$A12,'Trade Log'!$E$4:$E$503,"LONG")) | H12: =IF($A12="","",SUMIFS('Trade Log'!$Z$4:$Z$503,'Trade Log'!$D$4:$D$503,$A12,'Trade Log'!$E$4:$E$503,"SHORT")) | I12: =IF($A12="","",SUMIFS('Trade Log'!$Q$4:$Q$503,'Trade Log'!$D$4:$D$503,$A12)) | J12: =IF($A12="","",SUMIFS('Trade Log'!$Y$4:$Y$503,'Trade Log'!$D$4:$D$503,$A12)) | K12: =IF($A12="","",SUMIFS('Trade Log'!$Z$4:$Z$503,'Trade Log'!$D$4:$D$503,$A12)) | L12: =IF($A12="","",COUNTIFS('Trade Log'!$D$4:$D$503,$A12,'Trade Log'!$Z$4:$Z$503,">0")) | M12: =IF(OR($A12="",$E12=0),"",$L12/$E12) | N12: =IF(OR($A12="",$E12=0),"",$K12/$E12) | O12: =IF($A12="","",IFERROR(_xlfn.MAXIFS('Trade Log'!$Z$4:$Z$503,'Trade Log'!$D$4:$D$503,$A12),"")) | P12: =IF($A12="","",IFERROR(_xlfn.MINIFS('Trade Log'!$Z$4:$Z$503,'Trade Log'!$D$4:$D$503,$A12),"")) | Q12: =IF($A12="","",IFERROR(AVERAGEIFS('Trade Log'!$AA$4:$AA$503,'Trade Log'!$D$4:$D$503,$A12),"")) | R12: =IF($A12="","",IFERROR(AVERAGEIFS('Trade Log'!$P$4:$P$503,'Trade Log'!$D$4:$D$503,$A12),"")) | S12: =IF($A12="","",IFERROR(AVERAGEIFS('Trade Log'!$AC$4:$AC$503,'Trade Log'!$D$4:$D$503,$A12),"")) | T12: =IF(OR($A12="",Summary!$B$13=0),"",$K12/Summary!$B$13) | U12: =IF($A12="","",IFERROR(RANK($K12,$K$4:$K$153),""))
B13: =IF($A13="","",COUNTIFS('Trade Log'!$D$4:$D$503,$A13)) | C13: =IF($A13="","",COUNTIFS('Trade Log'!$D$4:$D$503,$A13,'Trade Log'!$E$4:$E$503,"LONG")) | D13: =IF($A13="","",COUNTIFS('Trade Log'!$D$4:$D$503,$A13,'Trade Log'!$E$4:$E$503,"SHORT")) | E13: =IF($A13="","",COUNTIFS('Trade Log'!$D$4:$D$503,$A13,'Trade Log'!$N$4:$N$503,"<>")) | F13: =IF($A13="","",SUMIFS('Trade Log'!$K$4:$K$503,'Trade Log'!$D$4:$D$503,$A13)) | G13: =IF($A13="","",SUMIFS('Trade Log'!$Z$4:$Z$503,'Trade Log'!$D$4:$D$503,$A13,'Trade Log'!$E$4:$E$503,"LONG")) | H13: =IF($A13="","",SUMIFS('Trade Log'!$Z$4:$Z$503,'Trade Log'!$D$4:$D$503,$A13,'Trade Log'!$E$4:$E$503,"SHORT")) | I13: =IF($A13="","",SUMIFS('Trade Log'!$Q$4:$Q$503,'Trade Log'!$D$4:$D$503,$A13)) | J13: =IF($A13="","",SUMIFS('Trade Log'!$Y$4:$Y$503,'Trade Log'!$D$4:$D$503,$A13)) | K13: =IF($A13="","",SUMIFS('Trade Log'!$Z$4:$Z$503,'Trade Log'!$D$4:$D$503,$A13)) | L13: =IF($A13="","",COUNTIFS('Trade Log'!$D$4:$D$503,$A13,'Trade Log'!$Z$4:$Z$503,">0")) | M13: =IF(OR($A13="",$E13=0),"",$L13/$E13) | N13: =IF(OR($A13="",$E13=0),"",$K13/$E13) | O13: =IF($A13="","",IFERROR(_xlfn.MAXIFS('Trade Log'!$Z$4:$Z$503,'Trade Log'!$D$4:$D$503,$A13),"")) | P13: =IF($A13="","",IFERROR(_xlfn.MINIFS('Trade Log'!$Z$4:$Z$503,'Trade Log'!$D$4:$D$503,$A13),"")) | Q13: =IF($A13="","",IFERROR(AVERAGEIFS('Trade Log'!$AA$4:$AA$503,'Trade Log'!$D$4:$D$503,$A13),"")) | R13: =IF($A13="","",IFERROR(AVERAGEIFS('Trade Log'!$P$4:$P$503,'Trade Log'!$D$4:$D$503,$A13),"")) | S13: =IF($A13="","",IFERROR(AVERAGEIFS('Trade Log'!$AC$4:$AC$503,'Trade Log'!$D$4:$D$503,$A13),"")) | T13: =IF(OR($A13="",Summary!$B$13=0),"",$K13/Summary!$B$13) | U13: =IF($A13="","",IFERROR(RANK($K13,$K$4:$K$153),""))
B14: =IF($A14="","",COUNTIFS('Trade Log'!$D$4:$D$503,$A14)) | C14: =IF($A14="","",COUNTIFS('Trade Log'!$D$4:$D$503,$A14,'Trade Log'!$E$4:$E$503,"LONG")) | D14: =IF($A14="","",COUNTIFS('Trade Log'!$D$4:$D$503,$A14,'Trade Log'!$E$4:$E$503,"SHORT")) | E14: =IF($A14="","",COUNTIFS('Trade Log'!$D$4:$D$503,$A14,'Trade Log'!$N$4:$N$503,"<>")) | F14: =IF($A14="","",SUMIFS('Trade Log'!$K$4:$K$503,'Trade Log'!$D$4:$D$503,$A14)) | G14: =IF($A14="","",SUMIFS('Trade Log'!$Z$4:$Z$503,'Trade Log'!$D$4:$D$503,$A14,'Trade Log'!$E$4:$E$503,"LONG")) | H14: =IF($A14="","",SUMIFS('Trade Log'!$Z$4:$Z$503,'Trade Log'!$D$4:$D$503,$A14,'Trade Log'!$E$4:$E$503,"SHORT")) | I14: =IF($A14="","",SUMIFS('Trade Log'!$Q$4:$Q$503,'Trade Log'!$D$4:$D$503,$A14)) | J14: =IF($A14="","",SUMIFS('Trade Log'!$Y$4:$Y$503,'Trade Log'!$D$4:$D$503,$A14)) | K14: =IF($A14="","",SUMIFS('Trade Log'!$Z$4:$Z$503,'Trade Log'!$D$4:$D$503,$A14)) | L14: =IF($A14="","",COUNTIFS('Trade Log'!$D$4:$D$503,$A14,'Trade Log'!$Z$4:$Z$503,">0")) | M14: =IF(OR($A14="",$E14=0),"",$L14/$E14) | N14: =IF(OR($A14="",$E14=0),"",$K14/$E14) | O14: =IF($A14="","",IFERROR(_xlfn.MAXIFS('Trade Log'!$Z$4:$Z$503,'Trade Log'!$D$4:$D$503,$A14),"")) | P14: =IF($A14="","",IFERROR(_xlfn.MINIFS('Trade Log'!$Z$4:$Z$503,'Trade Log'!$D$4:$D$503,$A14),"")) | Q14: =IF($A14="","",IFERROR(AVERAGEIFS('Trade Log'!$AA$4:$AA$503,'Trade Log'!$D$4:$D$503,$A14),"")) | R14: =IF($A14="","",IFERROR(AVERAGEIFS('Trade Log'!$P$4:$P$503,'Trade Log'!$D$4:$D$503,$A14),"")) | S14: =IF($A14="","",IFERROR(AVERAGEIFS('Trade Log'!$AC$4:$AC$503,'Trade Log'!$D$4:$D$503,$A14),"")) | T14: =IF(OR($A14="",Summary!$B$13=0),"",$K14/Summary!$B$13) | U14: =IF($A14="","",IFERROR(RANK($K14,$K$4:$K$153),""))
B15: =IF($A15="","",COUNTIFS('Trade Log'!$D$4:$D$503,$A15)) | C15: =IF($A15="","",COUNTIFS('Trade Log'!$D$4:$D$503,$A15,'Trade Log'!$E$4:$E$503,"LONG")) | D15: =IF($A15="","",COUNTIFS('Trade Log'!$D$4:$D$503,$A15,'Trade Log'!$E$4:$E$503,"SHORT")) | E15: =IF($A15="","",COUNTIFS('Trade Log'!$D$4:$D$503,$A15,'Trade Log'!$N$4:$N$503,"<>")) | F15: =IF($A15="","",SUMIFS('Trade Log'!$K$4:$K$503,'Trade Log'!$D$4:$D$503,$A15)) | G15: =IF($A15="","",SUMIFS('Trade Log'!$Z$4:$Z$503,'Trade Log'!$D$4:$D$503,$A15,'Trade Log'!$E$4:$E$503,"LONG")) | H15: =IF($A15="","",SUMIFS('Trade Log'!$Z$4:$Z$503,'Trade Log'!$D$4:$D$503,$A15,'Trade Log'!$E$4:$E$503,"SHORT")) | I15: =IF($A15="","",SUMIFS('Trade Log'!$Q$4:$Q$503,'Trade Log'!$D$4:$D$503,$A15)) | J15: =IF($A15="","",SUMIFS('Trade Log'!$Y$4:$Y$503,'Trade Log'!$D$4:$D$503,$A15)) | K15: =IF($A15="","",SUMIFS('Trade Log'!$Z$4:$Z$503,'Trade Log'!$D$4:$D$503,$A15)) | L15: =IF($A15="","",COUNTIFS('Trade Log'!$D$4:$D$503,$A15,'Trade Log'!$Z$4:$Z$503,">0")) | M15: =IF(OR($A15="",$E15=0),"",$L15/$E15) | N15: =IF(OR($A15="",$E15=0),"",$K15/$E15) | O15: =IF($A15="","",IFERROR(_xlfn.MAXIFS('Trade Log'!$Z$4:$Z$503,'Trade Log'!$D$4:$D$503,$A15),"")) | P15: =IF($A15="","",IFERROR(_xlfn.MINIFS('Trade Log'!$Z$4:$Z$503,'Trade Log'!$D$4:$D$503,$A15),"")) | Q15: =IF($A15="","",IFERROR(AVERAGEIFS('Trade Log'!$AA$4:$AA$503,'Trade Log'!$D$4:$D$503,$A15),"")) | R15: =IF($A15="","",IFERROR(AVERAGEIFS('Trade Log'!$P$4:$P$503,'Trade Log'!$D$4:$D$503,$A15),"")) | S15: =IF($A15="","",IFERROR(AVERAGEIFS('Trade Log'!$AC$4:$AC$503,'Trade Log'!$D$4:$D$503,$A15),"")) | T15: =IF(OR($A15="",Summary!$B$13=0),"",$K15/Summary!$B$13) | U15: =IF($A15="","",IFERROR(RANK($K15,$K$4:$K$153),""))
B16: =IF($A16="","",COUNTIFS('Trade Log'!$D$4:$D$503,$A16)) | C16: =IF($A16="","",COUNTIFS('Trade Log'!$D$4:$D$503,$A16,'Trade Log'!$E$4:$E$503,"LONG")) | D16: =IF($A16="","",COUNTIFS('Trade Log'!$D$4:$D$503,$A16,'Trade Log'!$E$4:$E$503,"SHORT")) | E16: =IF($A16="","",COUNTIFS('Trade Log'!$D$4:$D$503,$A16,'Trade Log'!$N$4:$N$503,"<>")) | F16: =IF($A16="","",SUMIFS('Trade Log'!$K$4:$K$503,'Trade Log'!$D$4:$D$503,$A16)) | G16: =IF($A16="","",SUMIFS('Trade Log'!$Z$4:$Z$503,'Trade Log'!$D$4:$D$503,$A16,'Trade Log'!$E$4:$E$503,"LONG")) | H16: =IF($A16="","",SUMIFS('Trade Log'!$Z$4:$Z$503,'Trade Log'!$D$4:$D$503,$A16,'Trade Log'!$E$4:$E$503,"SHORT")) | I16: =IF($A16="","",SUMIFS('Trade Log'!$Q$4:$Q$503,'Trade Log'!$D$4:$D$503,$A16)) | J16: =IF($A16="","",SUMIFS('Trade Log'!$Y$4:$Y$503,'Trade Log'!$D$4:$D$503,$A16)) | K16: =IF($A16="","",SUMIFS('Trade Log'!$Z$4:$Z$503,'Trade Log'!$D$4:$D$503,$A16)) | L16: =IF($A16="","",COUNTIFS('Trade Log'!$D$4:$D$503,$A16,'Trade Log'!$Z$4:$Z$503,">0")) | M16: =IF(OR($A16="",$E16=0),"",$L16/$E16) | N16: =IF(OR($A16="",$E16=0),"",$K16/$E16) | O16: =IF($A16="","",IFERROR(_xlfn.MAXIFS('Trade Log'!$Z$4:$Z$503,'Trade Log'!$D$4:$D$503,$A16),"")) | P16: =IF($A16="","",IFERROR(_xlfn.MINIFS('Trade Log'!$Z$4:$Z$503,'Trade Log'!$D$4:$D$503,$A16),"")) | Q16: =IF($A16="","",IFERROR(AVERAGEIFS('Trade Log'!$AA$4:$AA$503,'Trade Log'!$D$4:$D$503,$A16),"")) | R16: =IF($A16="","",IFERROR(AVERAGEIFS('Trade Log'!$P$4:$P$503,'Trade Log'!$D$4:$D$503,$A16),"")) | S16: =IF($A16="","",IFERROR(AVERAGEIFS('Trade Log'!$AC$4:$AC$503,'Trade Log'!$D$4:$D$503,$A16),"")) | T16: =IF(OR($A16="",Summary!$B$13=0),"",$K16/Summary!$B$13) | U16: =IF($A16="","",IFERROR(RANK($K16,$K$4:$K$153),""))
