Workbook

Sheet Total PnL
A1: Total PnL
A2: Overall strategy performance -- set Base Capital below; everything else calculates automatically from Trade Log.
A3: Base Capital (₹) | B3: 1500000
A4: STRATEGY SNAPSHOT
B5: NET P&L (₹) | F5: NET P&L (%) | J5: WIN RATE | N5: PROFIT FACTOR
B6: =SUM('Trade Log'!$L$4:$L$503) | F6: =IF($B$3=0,"",$B$6/$B$3) | J6: =IFERROR($C$13/$C$12,"") | N6: =IFERROR(SUMIF('Trade Log'!$L$4:$L$503,">0")/ABS(SUMIF('Trade Log'!$L$4:$L$503,"<0")),"")
A10: DETAILED STATS
B11: Metric | C11: Value
B12: Total Trades | C12: =COUNT('Trade Log'!$L$4:$L$503)
B13: Winning Trades | C13: =COUNTIF('Trade Log'!$L$4:$L$503,">0")
B14: Losing Trades | C14: =COUNTIF('Trade Log'!$L$4:$L$503,"<0")
B15: Average Win (₹) | C15: =IFERROR(AVERAGEIF('Trade Log'!$L$4:$L$503,">0"),"")
B16: Average Loss (₹) | C16: =IFERROR(AVERAGEIF('Trade Log'!$L$4:$L$503,"<0"),"")
B17: Best Trade (₹) | C17: =IFERROR(MAX('Trade Log'!$L$4:$L$503),"")
B18: Worst Trade (₹) | C18: =IFERROR(MIN('Trade Log'!$L$4:$L$503),"")
B19: Gross P&L (₹) | C19: =SUM('Trade Log'!$I$4:$I$503)
B20: Gross P&L (%) | C20: =IF($B$3=0,"",$C$19/$B$3)

Sheet Trade Log
A1: Trade Log
A2: One row per position -- long and short trades are logged separately. Fill columns A-H, K and O; formulas compute I, J, L, M, N.
A3: Trade ID | B3: Symbol | C3: Position | D3: Entry Date | E3: Entry Price | F3: Qty | G3: Exit Date | H3: Exit Price | I3: Gross P&L | J3: Gross Return % | K3: Costs | L3: Net P&L | M3: Net Return % | N3: Status | O3: Return Bucket
A4: DHAN-221260819775809 | B4: BAJAJHIND | C4: LONG | D4: 46253 | E4: 20.2933 | F4: 14742 | G4: 46254 | H4: 20.9689 | I4: =IF(OR($B4="",$H4=""),"",IF($C4="LONG",($H4-$E4)*$F4,($E4-$H4)*$F4)) | J4: =IF(OR($B4="",$I4="",$E4=0,$F4=0),"",$I4/($E4*$F4)) | K4: 515.25 | L4: =IF(OR($B4="",$I4=""),"",$I4-IF($K4="",0,$K4)) | M4: =IF(OR($B4="",$L4="",$E4=0,$F4=0),"",$L4/($E4*$F4)) | N4: =IF($B4="","",IF($H4="","Open","Closed")) | O4: Untagged
A5: DHAN-23126082016509 | B5: BAJAJHIND | C5: SHORT | D5: 46254 | E5: 20.9605 | F5: 14742 | G5: 46254 | H5: 22.2519 | I5: =IF(OR($B5="",$H5=""),"",IF($C5="LONG",($H5-$E5)*$F5,($E5-$H5)*$F5)) | J5: =IF(OR($B5="",$I5="",$E5=0,$F5=0),"",$I5/($E5*$F5)) | K5: 451.6 | L5: =IF(OR($B5="",$I5=""),"",$I5-IF($K5="",0,$K5)) | M5: =IF(OR($B5="",$L5="",$E5=0,$F5=0),"",$L5/($E5*$F5)) | N5: =IF($B5="","",IF($H5="","Open","Closed")) | O5: Untagged
A6: DHAN-221260819775909 | B6: GOPAL | C6: LONG | D6: 46253 | E6: 289.4016 | F6: 1038 | G6: 46254 | H6: 281.1859 | I6: =IF(OR($B6="",$H6=""),"",IF($C6="LONG",($H6-$E6)*$F6,($E6-$H6)*$F6)) | J6: =IF(OR($B6="",$I6="",$E6=0,$F6=0),"",$I6/($E6*$F6)) | K6: 610.31 | L6: =IF(OR($B6="",$I6=""),"",$I6-IF($K6="",0,$K6)) | M6: =IF(OR($B6="",$L6="",$E6=0,$F6=0),"",$L6/($E6*$F6)) | N6: =IF($B6="","",IF($H6="","Open","Closed")) | O6: Untagged
A7: DHAN-22126082044409 | B7: GOPAL | C7: SHORT | D7: 46254 | E7: 281.1067 | F7: 1038 | G7: 46254 | H7: 282.9361 | I7: =IF(OR($B7="",$H7=""),"",IF($C7="LONG",($H7-$E7)*$F7,($E7-$H7)*$F7)) | J7: =IF(OR($B7="",$I7="",$E7=0,$F7=0),"",$I7/($E7*$F7)) | K7: 346.76 | L7: =IF(OR($B7="",$I7=""),"",$I7-IF($K7="",0,$K7)) | M7: =IF(OR($B7="",$L7="",$E7=0,$F7=0),"",$L7/($E7*$F7)) | N7: =IF($B7="","",IF($H7="","Open","Closed")) | O7: Untagged
A8: DHAN-321260819763709 | B8: NILKAMAL | C8: LONG | D8: 46253 | E8: 2031.8572 | F8: 147 | G8: 46254 | H8: 2020.8687 | I8: =IF(OR($B8="",$H8=""),"",IF($C8="LONG",($H8-$E8)*$F8,($E8-$H8)*$F8)) | J8: =IF(OR($B8="",$I8="",$E8=0,$F8=0),"",$I8/($E8*$F8)) | K8: 514.19 | L8: =IF(OR($B8="",$I8=""),"",$I8-IF($K8="",0,$K8)) | M8: =IF(OR($B8="",$L8="",$E8=0,$F8=0),"",$L8/($E8*$F8)) | N8: =IF($B8="","",IF($H8="","Open","Closed")) | O8: Untagged
A9: DHAN-321260820468709 | B9: NILKAMAL | C9: SHORT | D9: 46254 | E9: 2019.2572 | F9: 147 | G9: 46254 | H9: 2037.9993 | I9: =IF(OR($B9="",$H9=""),"",IF($C9="LONG",($H9-$E9)*$F9,($E9-$H9)*$F9)) | J9: =IF(OR($B9="",$I9="",$E9=0,$F9=0),"",$I9/($E9*$F9)) | K9: 427.19 | L9: =IF(OR($B9="",$I9=""),"",$I9-IF($K9="",0,$K9)) | M9: =IF(OR($B9="",$L9="",$E9=0,$F9=0),"",$L9/($E9*$F9)) | N9: =IF($B9="","",IF($H9="","Open","Closed")) | O9: Untagged
A10: DHAN-321260819763909 | B10: ORIENTHOT | C10: LONG | D10: 46253 | E10: 139.6107 | F10: 2137 | G10: 46254 | H10: 134.2087 | I10: =IF(OR($B10="",$H10=""),"",IF($C10="LONG",($H10-$E10)*$F10,($E10-$H10)*$F10)) | J10: =IF(OR($B10="",$I10="",$E10=0,$F10=0),"",$I10/($E10*$F10)) | K10: 595.38 | L10: =IF(OR($B10="",$I10=""),"",$I10-IF($K10="",0,$K10)) | M10: =IF(OR($B10="",$L10="",$E10=0,$F10=0),"",$L10/($E10*$F10)) | N10: =IF($B10="","",IF($H10="","Open","Closed")) | O10: Untagged
A11: DHAN-22126082044709 | B11: ORIENTHOT | C11: SHORT | D11: 46254 | E11: 134.1808 | F11: 2137 | G11: 46254 | H11: 134.9144 | I11: =IF(OR($B11="",$H11=""),"",IF($C11="LONG",($H11-$E11)*$F11,($E11-$H11)*$F11)) | J11: =IF(OR($B11="",$I11="",$E11=0,$F11=0),"",$I11/($E11*$F11)) | K11: 341.04 | L11: =IF(OR($B11="",$I11=""),"",$I11-IF($K11="",0,$K11)) | M11: =IF(OR($B11="",$L11="",$E11=0,$F11=0),"",$L11/($E11*$F11)) | N11: =IF($B11="","",IF($H11="","Open","Closed")) | O11: Untagged
A12: DHAN-321260819764209 | B12: ZAGGLE | C12: LONG | D12: 46253 | E12: 186.67 | F12: 1609 | G12: 46254 | H12: 190.697 | I12: =IF(OR($B12="",$H12=""),"",IF($C12="LONG",($H12-$E12)*$F12,($E12-$H12)*$F12)) | J12: =IF(OR($B12="",$I12="",$E12=0,$F12=0),"",$I12/($E12*$F12)) | K12: 526.36 | L12: =IF(OR($B12="",$I12=""),"",$I12-IF($K12="",0,$K12)) | M12: =IF(OR($B12="",$L12="",$E12=0,$F12=0),"",$L12/($E12*$F12)) | N12: =IF($B12="","",IF($H12="","Open","Closed")) | O12: Untagged
A13: DHAN-22126082044909 | B13: ZAGGLE | C13: SHORT | D13: 46254 | E13: 190.82 | F13: 1609 | G13: 46254 | H13: 197.6402 | I13: =IF(OR($B13="",$H13=""),"",IF($C13="LONG",($H13-$E13)*$F13,($E13-$H13)*$F13)) | J13: =IF(OR($B13="",$I13="",$E13=0,$F13=0),"",$I13/($E13*$F13)) | K13: 444.79 | L13: =IF(OR($B13="",$I13=""),"",$I13-IF($K13="",0,$K13)) | M13: =IF(OR($B13="",$L13="",$E13=0,$F13=0),"",$L13/($E13*$F13)) | N13: =IF($B13="","",IF($H13="","Open","Closed")) | O13: Untagged
A14: DHAN-34126082075909 | B14: BANARISUG | C14: LONG | D14: 46254 | E14: 4243.582 | F14: 39 | G14: 46255 | H14: 4030.5 | I14: =IF(OR($B14="",$H14=""),"",IF($C14="LONG",($H14-$E14)*$F14,($E14-$H14)*$F14)) | J14: =IF(OR($B14="",$I14="",$E14=0,$F14=0),"",$I14/($E14*$F14)) | K14: 367.34 | L14: =IF(OR($B14="",$I14=""),"",$I14-IF($K14="",0,$K14)) | M14: =IF(OR($B14="",$L14="",$E14=0,$F14=0),"",$L14/($E14*$F14)) | N14: =IF($B14="","",IF($H14="","Open","Closed")) | O14: Untagged
A15: DHAN-23126082147609 | B15: BANARISUG | C15: SHORT | D15: 46255 | E15: 4030.5103 | F15: 39 | G15: 46255 | H15: 4029.782 | I15: =IF(OR($B15="",$H15=""),"",IF($C15="LONG",($H15-$E15)*$F15,($E15-$H15)*$F15)) | J15: =IF(OR($B15="",$I15="",$E15=0,$F15=0),"",$I15/($E15*$F15)) | K15: 197.25 | L15: =IF(OR($B15="",$I15=""),"",$I15-IF($K15="",0,$K15)) | M15: =IF(OR($B15="",$L15="",$E15=0,$F15=0),"",$L15/($E15*$F15)) | N15: =IF($B15="","",IF($H15="","Open","Closed")) | O15: Untagged
... A254: DHAN-221260930623409 | B254: DPABHUSHAN | C254: LONG | D254: 46295 | E254: 1772 | F254: 105 | G254: 46296 | H254: 1775.08 | I254: =IF(OR($B254="",$H254=""),"",IF($C254="LONG",($H254-$E254)*$F254,($E254-$H254)*$F254)) | J254: =IF(OR($B254="",$I254="",$E254=0,$F254=0),"",$I254/($E254*$F254)) | K254: 235.89 | L254: =IF(OR($B254="",$I254=""),"",$I254-IF($K254="",0,$K254)) | M254: =IF(OR($B254="",$L254="",$E254=0,$F254=0),"",$L254/($E254*$F254)) | N254: =IF($B254="","",IF($H254="","Open","Closed")) | O254: 5-10
I255: =IF(OR($B255="",$H255=""),"",IF($C255="LONG",($H255-$E255)*$F255,($E255-$H255)*$F255)) | J255: =IF(OR($B255="",$I255="",$E255=0,$F255=0),"",$I255/($E255*$F255)) | L255: =IF(OR($B255="",$I255=""),"",$I255-IF($K255="",0,$K255)) | M255: =IF(OR($B255="",$L255="",$E255=0,$F255=0),"",$L255/($E255*$F255)) | N255: =IF($B255="","",IF($H255="","Open","Closed"))
I256: =IF(OR($B256="",$H256=""),"",IF($C256="LONG",($H256-$E256)*$F256,($E256-$H256)*$F256)) | J256: =IF(OR($B256="",$I256="",$E256=0,$F256=0),"",$I256/($E256*$F256)) | L256: =IF(OR($B256="",$I256=""),"",$I256-IF($K256="",0,$K256)) | M256: =IF(OR($B256="",$L256="",$E256=0,$F256=0),"",$L256/($E256*$F256)) | N256: =IF($B256="","",IF($H256="","Open","Closed"))
I257: =IF(OR($B257="",$H257=""),"",IF($C257="LONG",($H257-$E257)*$F257,($E257-$H257)*$F257)) | J257: =IF(OR($B257="",$I257="",$E257=0,$F257=0),"",$I257/($E257*$F257)) | L257: =IF(OR($B257="",$I257=""),"",$I257-IF($K257="",0,$K257)) | M257: =IF(OR($B257="",$L257="",$E257=0,$F257=0),"",$L257/($E257*$F257)) | N257: =IF($B257="","",IF($H257="","Open","Closed"))
I258: =IF(OR($B258="",$H258=""),"",IF($C258="LONG",($H258-$E258)*$F258,($E258-$H258)*$F258)) | J258: =IF(OR($B258="",$I258="",$E258=0,$F258=0),"",$I258/($E258*$F258)) | L258: =IF(OR($B258="",$I258=""),"",$I258-IF($K258="",0,$K258)) | M258: =IF(OR($B258="",$L258="",$E258=0,$F258=0),"",$L258/($E258*$F258)) | N258: =IF($B258="","",IF($H258="","Open","Closed"))
I259: =IF(OR($B259="",$H259=""),"",IF($C259="LONG",($H259-$E259)*$F259,($E259-$H259)*$F259)) | J259: =IF(OR($B259="",$I259="",$E259=0,$F259=0),"",$I259/($E259*$F259)) | L259: =IF(OR($B259="",$I259=""),"",$I259-IF($K259="",0,$K259)) | M259: =IF(OR($B259="",$L259="",$E259=0,$F259=0),"",$L259/($E259*$F259)) | N259: =IF($B259="","",IF($H259="","Open","Closed"))
I260: =IF(OR($B260="",$H260=""),"",IF($C260="LONG",($H260-$E260)*$F260,($E260-$H260)*$F260)) | J260: =IF(OR($B260="",$I260="",$E260=0,$F260=0),"",$I260/($E260*$F260)) | L260: =IF(OR($B260="",$I260=""),"",$I260-IF($K260="",0,$K260)) | M260: =IF(OR($B260="",$L260="",$E260=0,$F260=0),"",$L260/($E260*$F260)) | N260: =IF($B260="","",IF($H260="","Open","Closed"))
I261: =IF(OR($B261="",$H261=""),"",IF($C261="LONG",($H261-$E261)*$F261,($E261-$H261)*$F261)) | J261: =IF(OR($B261="",$I261="",$E261=0,$F261=0),"",$I261/($E261*$F261)) | L261: =IF(OR($B261="",$I261=""),"",$I261-IF($K261="",0,$K261)) | M261: =IF(OR($B261="",$L261="",$E261=0,$F261=0),"",$L261/($E261*$F261)) | N261: =IF($B261="","",IF($H261="","Open","Closed"))
I262: =IF(OR($B262="",$H262=""),"",IF($C262="LONG",($H262-$E262)*$F262,($E262-$H262)*$F262)) | J262: =IF(OR($B262="",$I262="",$E262=0,$F262=0),"",$I262/($E262*$F262)) | L262: =IF(OR($B262="",$I262=""),"",$I262-IF($K262="",0,$K262)) | M262: =IF(OR($B262="",$L262="",$E262=0,$F262=0),"",$L262/($E262*$F262)) | N262: =IF($B262="","",IF($H262="","Open","Closed"))
I263: =IF(OR($B263="",$H263=""),"",IF($C263="LONG",($H263-$E263)*$F263,($E263-$H263)*$F263)) | J263: =IF(OR($B263="",$I263="",$E263=0,$F263=0),"",$I263/($E263*$F263)) | L263: =IF(OR($B263="",$I263=""),"",$I263-IF($K263="",0,$K263)) | M263: =IF(OR($B263="",$L263="",$E263=0,$F263=0),"",$L263/($E263*$F263)) | N263: =IF($B263="","",IF($H263="","Open","Closed"))
I264: =IF(OR($B264="",$H264=""),"",IF($C264="LONG",($H264-$E264)*$F264,($E264-$H264)*$F264)) | J264: =IF(OR($B264="",$I264="",$E264=0,$F264=0),"",$I264/($E264*$F264)) | L264: =IF(OR($B264="",$I264=""),"",$I264-IF($K264="",0,$K264)) | M264: =IF(OR($B264="",$L264="",$E264=0,$F264=0),"",$L264/($E264*$F264)) | N264: =IF($B264="","",IF($H264="","Open","Closed"))
I265: =IF(OR($B265="",$H265=""),"",IF($C265="LONG",($H265-$E265)*$F265,($E265-$H265)*$F265)) | J265: =IF(OR($B265="",$I265="",$E265=0,$F265=0),"",$I265/($E265*$F265)) | L265: =IF(OR($B265="",$I265=""),"",$I265-IF($K265="",0,$K265)) | M265: =IF(OR($B265="",$L265="",$E265=0,$F265=0),"",$L265/($E265*$F265)) | N265: =IF($B265="","",IF($H265="","Open","Closed"))
I266: =IF(OR($B266="",$H266=""),"",IF($C266="LONG",($H266-$E266)*$F266,($E266-$H266)*$F266)) | J266: =IF(OR($B266="",$I266="",$E266=0,$F266=0),"",$I266/($E266*$F266)) | L266: =IF(OR($B266="",$I266=""),"",$I266-IF($K266="",0,$K266)) | M266: =IF(OR($B266="",$L266="",$E266=0,$F266=0),"",$L266/($E266*$F266)) | N266: =IF($B266="","",IF($H266="","Open","Closed"))
... I503: =IF(OR($B503="",$H503=""),"",IF($C503="LONG",($H503-$E503)*$F503,($E503-$H503)*$F503)) | J503: =IF(OR($B503="",$I503="",$E503=0,$F503=0),"",$I503/($E503*$F503)) | L503: =IF(OR($B503="",$I503=""),"",$I503-IF($K503="",0,$K503)) | M503: =IF(OR($B503="",$L503="",$E503=0,$F503=0),"",$L503/($E503*$F503)) | N503: =IF($B503="","",IF($H503="","Open","Closed"))

Sheet Day Wise PnL
A1: Day Wise PnL
A2: One row per calendar date, attributed by Exit Date -- continues forward automatically from the first date in A4.
A3: Date | B3: Long Gross P&L | C3: Short Gross P&L | D3: Total Gross P&L | E3: Long Net P&L | F3: Short Net P&L | G3: Total Net P&L
A4: 46253 | B4: =IF($A4="","",SUMIFS('Trade Log'!$I$4:$I$503,'Trade Log'!$G$4:$G$503,$A4,'Trade Log'!$C$4:$C$503,"LONG")) | C4: =IF($A4="","",SUMIFS('Trade Log'!$I$4:$I$503,'Trade Log'!$G$4:$G$503,$A4,'Trade Log'!$C$4:$C$503,"SHORT")) | D4: =IF($A4="","",$B4+$C4) | E4: =IF($A4="","",SUMIFS('Trade Log'!$L$4:$L$503,'Trade Log'!$G$4:$G$503,$A4,'Trade Log'!$C$4:$C$503,"LONG")) | F4: =IF($A4="","",SUMIFS('Trade Log'!$L$4:$L$503,'Trade Log'!$G$4:$G$503,$A4,'Trade Log'!$C$4:$C$503,"SHORT")) | G4: =IF($A4="","",$E4+$F4)
A5: =IF(A4="","",A4+1) | B5: =IF($A5="","",SUMIFS('Trade Log'!$I$4:$I$503,'Trade Log'!$G$4:$G$503,$A5,'Trade Log'!$C$4:$C$503,"LONG")) | C5: =IF($A5="","",SUMIFS('Trade Log'!$I$4:$I$503,'Trade Log'!$G$4:$G$503,$A5,'Trade Log'!$C$4:$C$503,"SHORT")) | D5: =IF($A5="","",$B5+$C5) | E5: =IF($A5="","",SUMIFS('Trade Log'!$L$4:$L$503,'Trade Log'!$G$4:$G$503,$A5,'Trade Log'!$C$4:$C$503,"LONG")) | F5: =IF($A5="","",SUMIFS('Trade Log'!$L$4:$L$503,'Trade Log'!$G$4:$G$503,$A5,'Trade Log'!$C$4:$C$503,"SHORT")) | G5: =IF($A5="","",$E5+$F5)
A6: =IF(A5="","",A5+1) | B6: =IF($A6="","",SUMIFS('Trade Log'!$I$4:$I$503,'Trade Log'!$G$4:$G$503,$A6,'Trade Log'!$C$4:$C$503,"LONG")) | C6: =IF($A6="","",SUMIFS('Trade Log'!$I$4:$I$503,'Trade Log'!$G$4:$G$503,$A6,'Trade Log'!$C$4:$C$503,"SHORT")) | D6: =IF($A6="","",$B6+$C6) | E6: =IF($A6="","",SUMIFS('Trade Log'!$L$4:$L$503,'Trade Log'!$G$4:$G$503,$A6,'Trade Log'!$C$4:$C$503,"LONG")) | F6: =IF($A6="","",SUMIFS('Trade Log'!$L$4:$L$503,'Trade Log'!$G$4:$G$503,$A6,'Trade Log'!$C$4:$C$503,"SHORT")) | G6: =IF($A6="","",$E6+$F6)
A7: =IF(A6="","",A6+1) | B7: =IF($A7="","",SUMIFS('Trade Log'!$I$4:$I$503,'Trade Log'!$G$4:$G$503,$A7,'Trade Log'!$C$4:$C$503,"LONG")) | C7: =IF($A7="","",SUMIFS('Trade Log'!$I$4:$I$503,'Trade Log'!$G$4:$G$503,$A7,'Trade Log'!$C$4:$C$503,"SHORT")) | D7: =IF($A7="","",$B7+$C7) | E7: =IF($A7="","",SUMIFS('Trade Log'!$L$4:$L$503,'Trade Log'!$G$4:$G$503,$A7,'Trade Log'!$C$4:$C$503,"LONG")) | F7: =IF($A7="","",SUMIFS('Trade Log'!$L$4:$L$503,'Trade Log'!$G$4:$G$503,$A7,'Trade Log'!$C$4:$C$503,"SHORT")) | G7: =IF($A7="","",$E7+$F7)
A8: =IF(A7="","",A7+1) | B8: =IF($A8="","",SUMIFS('Trade Log'!$I$4:$I$503,'Trade Log'!$G$4:$G$503,$A8,'Trade Log'!$C$4:$C$503,"LONG")) | C8: =IF($A8="","",SUMIFS('Trade Log'!$I$4:$I$503,'Trade Log'!$G$4:$G$503,$A8,'Trade Log'!$C$4:$C$503,"SHORT")) | D8: =IF($A8="","",$B8+$C8) | E8: =IF($A8="","",SUMIFS('Trade Log'!$L$4:$L$503,'Trade Log'!$G$4:$G$503,$A8,'Trade Log'!$C$4:$C$503,"LONG")) | F8: =IF($A8="","",SUMIFS('Trade Log'!$L$4:$L$503,'Trade Log'!$G$4:$G$503,$A8,'Trade Log'!$C$4:$C$503,"SHORT")) | G8: =IF($A8="","",$E8+$F8)
A9: =IF(A8="","",A8+1) | B9: =IF($A9="","",SUMIFS('Trade Log'!$I$4:$I$503,'Trade Log'!$G$4:$G$503,$A9,'Trade Log'!$C$4:$C$503,"LONG")) | C9: =IF($A9="","",SUMIFS('Trade Log'!$I$4:$I$503,'Trade Log'!$G$4:$G$503,$A9,'Trade Log'!$C$4:$C$503,"SHORT")) | D9: =IF($A9="","",$B9+$C9) | E9: =IF($A9="","",SUMIFS('Trade Log'!$L$4:$L$503,'Trade Log'!$G$4:$G$503,$A9,'Trade Log'!$C$4:$C$503,"LONG")) | F9: =IF($A9="","",SUMIFS('Trade Log'!$L$4:$L$503,'Trade Log'!$G$4:$G$503,$A9,'Trade Log'!$C$4:$C$503,"SHORT")) | G9: =IF($A9="","",$E9+$F9)
A10: =IF(A9="","",A9+1) | B10: =IF($A10="","",SUMIFS('Trade Log'!$I$4:$I$503,'Trade Log'!$G$4:$G$503,$A10,'Trade Log'!$C$4:$C$503,"LONG")) | C10: =IF($A10="","",SUMIFS('Trade Log'!$I$4:$I$503,'Trade Log'!$G$4:$G$503,$A10,'Trade Log'!$C$4:$C$503,"SHORT")) | D10: =IF($A10="","",$B10+$C10) | E10: =IF($A10="","",SUMIFS('Trade Log'!$L$4:$L$503,'Trade Log'!$G$4:$G$503,$A10,'Trade Log'!$C$4:$C$503,"LONG")) | F10: =IF($A10="","",SUMIFS('Trade Log'!$L$4:$L$503,'Trade Log'!$G$4:$G$503,$A10,'Trade Log'!$C$4:$C$503,"SHORT")) | G10: =IF($A10="","",$E10+$F10)
A11: =IF(A10="","",A10+1) | B11: =IF($A11="","",SUMIFS('Trade Log'!$I$4:$I$503,'Trade Log'!$G$4:$G$503,$A11,'Trade Log'!$C$4:$C$503,"LONG")) | C11: =IF($A11="","",SUMIFS('Trade Log'!$I$4:$I$503,'Trade Log'!$G$4:$G$503,$A11,'Trade Log'!$C$4:$C$503,"SHORT")) | D11: =IF($A11="","",$B11+$C11) | E11: =IF($A11="","",SUMIFS('Trade Log'!$L$4:$L$503,'Trade Log'!$G$4:$G$503,$A11,'Trade Log'!$C$4:$C$503,"LONG")) | F11: =IF($A11="","",SUMIFS('Trade Log'!$L$4:$L$503,'Trade Log'!$G$4:$G$503,$A11,'Trade Log'!$C$4:$C$503,"SHORT")) | G11: =IF($A11="","",$E11+$F11)
A12: =IF(A11="","",A11+1) | B12: =IF($A12="","",SUMIFS('Trade Log'!$I$4:$I$503,'Trade Log'!$G$4:$G$503,$A12,'Trade Log'!$C$4:$C$503,"LONG")) | C12: =IF($A12="","",SUMIFS('Trade Log'!$I$4:$I$503,'Trade Log'!$G$4:$G$503,$A12,'Trade Log'!$C$4:$C$503,"SHORT")) | D12: =IF($A12="","",$B12+$C12) | E12: =IF($A12="","",SUMIFS('Trade Log'!$L$4:$L$503,'Trade Log'!$G$4:$G$503,$A12,'Trade Log'!$C$4:$C$503,"LONG")) | F12: =IF($A12="","",SUMIFS('Trade Log'!$L$4:$L$503,'Trade Log'!$G$4:$G$503,$A12,'Trade Log'!$C$4:$C$503,"SHORT")) | G12: =IF($A12="","",$E12+$F12)
A13: =IF(A12="","",A12+1) | B13: =IF($A13="","",SUMIFS('Trade Log'!$I$4:$I$503,'Trade Log'!$G$4:$G$503,$A13,'Trade Log'!$C$4:$C$503,"LONG")) | C13: =IF($A13="","",SUMIFS('Trade Log'!$I$4:$I$503,'Trade Log'!$G$4:$G$503,$A13,'Trade Log'!$C$4:$C$503,"SHORT")) | D13: =IF($A13="","",$B13+$C13) | E13: =IF($A13="","",SUMIFS('Trade Log'!$L$4:$L$503,'Trade Log'!$G$4:$G$503,$A13,'Trade Log'!$C$4:$C$503,"LONG")) | F13: =IF($A13="","",SUMIFS('Trade Log'!$L$4:$L$503,'Trade Log'!$G$4:$G$503,$A13,'Trade Log'!$C$4:$C$503,"SHORT")) | G13: =IF($A13="","",$E13+$F13)
A14: =IF(A13="","",A13+1) | B14: =IF($A14="","",SUMIFS('Trade Log'!$I$4:$I$503,'Trade Log'!$G$4:$G$503,$A14,'Trade Log'!$C$4:$C$503,"LONG")) | C14: =IF($A14="","",SUMIFS('Trade Log'!$I$4:$I$503,'Trade Log'!$G$4:$G$503,$A14,'Trade Log'!$C$4:$C$503,"SHORT")) | D14: =IF($A14="","",$B14+$C14) | E14: =IF($A14="","",SUMIFS('Trade Log'!$L$4:$L$503,'Trade Log'!$G$4:$G$503,$A14,'Trade Log'!$C$4:$C$503,"LONG")) | F14: =IF($A14="","",SUMIFS('Trade Log'!$L$4:$L$503,'Trade Log'!$G$4:$G$503,$A14,'Trade Log'!$C$4:$C$503,"SHORT")) | G14: =IF($A14="","",$E14+$F14)
A15: =IF(A14="","",A14+1) | B15: =IF($A15="","",SUMIFS('Trade Log'!$I$4:$I$503,'Trade Log'!$G$4:$G$503,$A15,'Trade Log'!$C$4:$C$503,"LONG")) | C15: =IF($A15="","",SUMIFS('Trade Log'!$I$4:$I$503,'Trade Log'!$G$4:$G$503,$A15,'Trade Log'!$C$4:$C$503,"SHORT")) | D15: =IF($A15="","",$B15+$C15) | E15: =IF($A15="","",SUMIFS('Trade Log'!$L$4:$L$503,'Trade Log'!$G$4:$G$503,$A15,'Trade Log'!$C$4:$C$503,"LONG")) | F15: =IF($A15="","",SUMIFS('Trade Log'!$L$4:$L$503,'Trade Log'!$G$4:$G$503,$A15,'Trade Log'!$C$4:$C$503,"SHORT")) | G15: =IF($A15="","",$E15+$F15)
A16: =IF(A15="","",A15+1) | B16: =IF($A16="","",SUMIFS('Trade Log'!$I$4:$I$503,'Trade Log'!$G$4:$G$503,$A16,'Trade Log'!$C$4:$C$503,"LONG")) | C16: =IF($A16="","",SUMIFS('Trade Log'!$I$4:$I$503,'Trade Log'!$G$4:$G$503,$A16,'Trade Log'!$C$4:$C$503,"SHORT")) | D16: =IF($A16="","",$B16+$C16) | E16: =IF($A16="","",SUMIFS('Trade Log'!$L$4:$L$503,'Trade Log'!$G$4:$G$503,$A16,'Trade Log'!$C$4:$C$503,"LONG")) | F16: =IF($A16="","",SUMIFS('Trade Log'!$L$4:$L$503,'Trade Log'!$G$4:$G$503,$A16,'Trade Log'!$C$4:$C$503,"SHORT")) | G16: =IF($A16="","",$E16+$F16)
... A403: =IF(A402="","",A402+1) | B403: =IF($A403="","",SUMIFS('Trade Log'!$I$4:$I$503,'Trade Log'!$G$4:$G$503,$A403,'Trade Log'!$C$4:$C$503,"LONG")) | C403: =IF($A403="","",SUMIFS('Trade Log'!$I$4:$I$503,'Trade Log'!$G$4:$G$503,$A403,'Trade Log'!$C$4:$C$503,"SHORT")) | D403: =IF($A403="","",$B403+$C403) | E403: =IF($A403="","",SUMIFS('Trade Log'!$L$4:$L$503,'Trade Log'!$G$4:$G$503,$A403,'Trade Log'!$C$4:$C$503,"LONG")) | F403: =IF($A403="","",SUMIFS('Trade Log'!$L$4:$L$503,'Trade Log'!$G$4:$G$503,$A403,'Trade Log'!$C$4:$C$503,"SHORT")) | G403: =IF($A403="","",$E403+$F403)

Sheet Position Type Stats
A1: Position Type Stats
A2: Long vs. short performance, computed straight from Trade Log.
A3: Position | B3: Trades | C3: Wins | D3: Losses | E3: Win Rate | F3: Gross P&L | G3: Net P&L | H3: Avg Net P&L / Trade | I3: Best Trade | J3: Worst Trade | K3: Profit Factor
A4: LONG | B4: =COUNTIF('Trade Log'!$C$4:$C$503,$A4) | C4: =COUNTIFS('Trade Log'!$C$4:$C$503,$A4,'Trade Log'!$L$4:$L$503,">0") | D4: =COUNTIFS('Trade Log'!$C$4:$C$503,$A4,'Trade Log'!$L$4:$L$503,"<0") | E4: =IFERROR($C4/$B4,"") | F4: =SUMIF('Trade Log'!$C$4:$C$503,$A4,'Trade Log'!$I$4:$I$503) | G4: =SUMIF('Trade Log'!$C$4:$C$503,$A4,'Trade Log'!$L$4:$L$503) | H4: =IFERROR($G4/$B4,"") | I4: =IFERROR(_xlfn.MAXIFS('Trade Log'!$L$4:$L$503,'Trade Log'!$C$4:$C$503,$A4),"") | J4: =IFERROR(_xlfn.MINIFS('Trade Log'!$L$4:$L$503,'Trade Log'!$C$4:$C$503,$A4),"") | K4: =IFERROR(SUMIFS('Trade Log'!$L$4:$L$503,'Trade Log'!$C$4:$C$503,$A4,'Trade Log'!$L$4:$L$503,">0")/ABS(SUMIFS('Trade Log'!$L$4:$L$503,'Trade Log'!$C$4:$C$503,$A4,'Trade Log'!$L$4:$L$503,"<0")),"")
A5: SHORT | B5: =COUNTIF('Trade Log'!$C$4:$C$503,$A5) | C5: =COUNTIFS('Trade Log'!$C$4:$C$503,$A5,'Trade Log'!$L$4:$L$503,">0") | D5: =COUNTIFS('Trade Log'!$C$4:$C$503,$A5,'Trade Log'!$L$4:$L$503,"<0") | E5: =IFERROR($C5/$B5,"") | F5: =SUMIF('Trade Log'!$C$4:$C$503,$A5,'Trade Log'!$I$4:$I$503) | G5: =SUMIF('Trade Log'!$C$4:$C$503,$A5,'Trade Log'!$L$4:$L$503) | H5: =IFERROR($G5/$B5,"") | I5: =IFERROR(_xlfn.MAXIFS('Trade Log'!$L$4:$L$503,'Trade Log'!$C$4:$C$503,$A5),"") | J5: =IFERROR(_xlfn.MINIFS('Trade Log'!$L$4:$L$503,'Trade Log'!$C$4:$C$503,$A5),"") | K5: =IFERROR(SUMIFS('Trade Log'!$L$4:$L$503,'Trade Log'!$C$4:$C$503,$A5,'Trade Log'!$L$4:$L$503,">0")/ABS(SUMIFS('Trade Log'!$L$4:$L$503,'Trade Log'!$C$4:$C$503,$A5,'Trade Log'!$L$4:$L$503,"<0")),"")
A6: TOTAL | B6: =SUM(B4:B5) | C6: =SUM(C4:C5) | D6: =SUM(D4:D5) | E6: =IFERROR(C6/B6,"") | F6: =SUM(F4:F5) | G6: =SUM(G4:G5) | H6: =IFERROR(G6/B6,"") | K6: =IFERROR(SUMIF('Trade Log'!$L$4:$L$503,">0")/ABS(SUMIF('Trade Log'!$L$4:$L$503,"<0")),"")

Sheet Bucket Stats
A1: Bucket Stats
A2: Performance by entry-signal return bucket (5-10% / 10-15% / 15-20%), computed straight from Trade Log. Untagged = entered before the return-bucketed exit schedule shipped (2026-09-26).
A3: Bucket | B3: Trades | C3: Wins | D3: Losses | E3: Win Rate | F3: Gross P&L | G3: Net P&L | H3: Avg Net P&L / Trade | I3: Best Trade | J3: Worst Trade | K3: Profit Factor
A4: 5-10 | B4: =COUNTIF('Trade Log'!$O$4:$O$503,$A4) | C4: =COUNTIFS('Trade Log'!$O$4:$O$503,$A4,'Trade Log'!$L$4:$L$503,">0") | D4: =COUNTIFS('Trade Log'!$O$4:$O$503,$A4,'Trade Log'!$L$4:$L$503,"<0") | E4: =IFERROR($C4/$B4,"") | F4: =SUMIF('Trade Log'!$O$4:$O$503,$A4,'Trade Log'!$I$4:$I$503) | G4: =SUMIF('Trade Log'!$O$4:$O$503,$A4,'Trade Log'!$L$4:$L$503) | H4: =IFERROR($G4/$B4,"") | I4: =IFERROR(_xlfn.MAXIFS('Trade Log'!$L$4:$L$503,'Trade Log'!$O$4:$O$503,$A4),"") | J4: =IFERROR(_xlfn.MINIFS('Trade Log'!$L$4:$L$503,'Trade Log'!$O$4:$O$503,$A4),"") | K4: =IFERROR(SUMIFS('Trade Log'!$L$4:$L$503,'Trade Log'!$O$4:$O$503,$A4,'Trade Log'!$L$4:$L$503,">0")/ABS(SUMIFS('Trade Log'!$L$4:$L$503,'Trade Log'!$O$4:$O$503,$A4,'Trade Log'!$L$4:$L$503,"<0")),"")
A5: 10-15 | B5: =COUNTIF('Trade Log'!$O$4:$O$503,$A5) | C5: =COUNTIFS('Trade Log'!$O$4:$O$503,$A5,'Trade Log'!$L$4:$L$503,">0") | D5: =COUNTIFS('Trade Log'!$O$4:$O$503,$A5,'Trade Log'!$L$4:$L$503,"<0") | E5: =IFERROR($C5/$B5,"") | F5: =SUMIF('Trade Log'!$O$4:$O$503,$A5,'Trade Log'!$I$4:$I$503) | G5: =SUMIF('Trade Log'!$O$4:$O$503,$A5,'Trade Log'!$L$4:$L$503) | H5: =IFERROR($G5/$B5,"") | I5: =IFERROR(_xlfn.MAXIFS('Trade Log'!$L$4:$L$503,'Trade Log'!$O$4:$O$503,$A5),"") | J5: =IFERROR(_xlfn.MINIFS('Trade Log'!$L$4:$L$503,'Trade Log'!$O$4:$O$503,$A5),"") | K5: =IFERROR(SUMIFS('Trade Log'!$L$4:$L$503,'Trade Log'!$O$4:$O$503,$A5,'Trade Log'!$L$4:$L$503,">0")/ABS(SUMIFS('Trade Log'!$L$4:$L$503,'Trade Log'!$O$4:$O$503,$A5,'Trade Log'!$L$4:$L$503,"<0")),"")
A6: 15-20 | B6: =COUNTIF('Trade Log'!$O$4:$O$503,$A6) | C6: =COUNTIFS('Trade Log'!$O$4:$O$503,$A6,'Trade Log'!$L$4:$L$503,">0") | D6: =COUNTIFS('Trade Log'!$O$4:$O$503,$A6,'Trade Log'!$L$4:$L$503,"<0") | E6: =IFERROR($C6/$B6,"") | F6: =SUMIF('Trade Log'!$O$4:$O$503,$A6,'Trade Log'!$I$4:$I$503) | G6: =SUMIF('Trade Log'!$O$4:$O$503,$A6,'Trade Log'!$L$4:$L$503) | H6: =IFERROR($G6/$B6,"") | I6: =IFERROR(_xlfn.MAXIFS('Trade Log'!$L$4:$L$503,'Trade Log'!$O$4:$O$503,$A6),"") | J6: =IFERROR(_xlfn.MINIFS('Trade Log'!$L$4:$L$503,'Trade Log'!$O$4:$O$503,$A6),"") | K6: =IFERROR(SUMIFS('Trade Log'!$L$4:$L$503,'Trade Log'!$O$4:$O$503,$A6,'Trade Log'!$L$4:$L$503,">0")/ABS(SUMIFS('Trade Log'!$L$4:$L$503,'Trade Log'!$O$4:$O$503,$A6,'Trade Log'!$L$4:$L$503,"<0")),"")
A7: Untagged | B7: =COUNTIF('Trade Log'!$O$4:$O$503,$A7) | C7: =COUNTIFS('Trade Log'!$O$4:$O$503,$A7,'Trade Log'!$L$4:$L$503,">0") | D7: =COUNTIFS('Trade Log'!$O$4:$O$503,$A7,'Trade Log'!$L$4:$L$503,"<0") | E7: =IFERROR($C7/$B7,"") | F7: =SUMIF('Trade Log'!$O$4:$O$503,$A7,'Trade Log'!$I$4:$I$503) | G7: =SUMIF('Trade Log'!$O$4:$O$503,$A7,'Trade Log'!$L$4:$L$503) | H7: =IFERROR($G7/$B7,"") | I7: =IFERROR(_xlfn.MAXIFS('Trade Log'!$L$4:$L$503,'Trade Log'!$O$4:$O$503,$A7),"") | J7: =IFERROR(_xlfn.MINIFS('Trade Log'!$L$4:$L$503,'Trade Log'!$O$4:$O$503,$A7),"") | K7: =IFERROR(SUMIFS('Trade Log'!$L$4:$L$503,'Trade Log'!$O$4:$O$503,$A7,'Trade Log'!$L$4:$L$503,">0")/ABS(SUMIFS('Trade Log'!$L$4:$L$503,'Trade Log'!$O$4:$O$503,$A7,'Trade Log'!$L$4:$L$503,"<0")),"")
A8: TOTAL | B8: =SUM(B4:B7) | C8: =SUM(C4:C7) | D8: =SUM(D4:D7) | E8: =IFERROR(C8/B8,"") | F8: =SUM(F4:F7) | G8: =SUM(G4:G7) | H8: =IFERROR(G8/B8,"") | K8: =IFERROR(SUMIF('Trade Log'!$L$4:$L$503,">0")/ABS(SUMIF('Trade Log'!$L$4:$L$503,"<0")),"")

Sheet Company Stats
A1: Company Stats
A2: Per-symbol performance across every logged trade, computed straight from Trade Log.
A3: Symbol | B3: Trades | C3: Wins | D3: Losses | E3: Win Rate | F3: Gross P&L | G3: Net P&L | H3: Avg Net P&L / Trade | I3: Best Trade | J3: Worst Trade
A4: ALEMBICLTD | B4: =COUNTIF('Trade Log'!$B$4:$B$503,$A4) | C4: =COUNTIFS('Trade Log'!$B$4:$B$503,$A4,'Trade Log'!$L$4:$L$503,">0") | D4: =COUNTIFS('Trade Log'!$B$4:$B$503,$A4,'Trade Log'!$L$4:$L$503,"<0") | E4: =IFERROR($C4/$B4,"") | F4: =SUMIF('Trade Log'!$B$4:$B$503,$A4,'Trade Log'!$I$4:$I$503) | G4: =SUMIF('Trade Log'!$B$4:$B$503,$A4,'Trade Log'!$L$4:$L$503) | H4: =IFERROR($G4/$B4,"") | I4: =IFERROR(_xlfn.MAXIFS('Trade Log'!$L$4:$L$503,'Trade Log'!$B$4:$B$503,$A4),"") | J4: =IFERROR(_xlfn.MINIFS('Trade Log'!$L$4:$L$503,'Trade Log'!$B$4:$B$503,$A4),"")
A5: ANTELOPUS | B5: =COUNTIF('Trade Log'!$B$4:$B$503,$A5) | C5: =COUNTIFS('Trade Log'!$B$4:$B$503,$A5,'Trade Log'!$L$4:$L$503,">0") | D5: =COUNTIFS('Trade Log'!$B$4:$B$503,$A5,'Trade Log'!$L$4:$L$503,"<0") | E5: =IFERROR($C5/$B5,"") | F5: =SUMIF('Trade Log'!$B$4:$B$503,$A5,'Trade Log'!$I$4:$I$503) | G5: =SUMIF('Trade Log'!$B$4:$B$503,$A5,'Trade Log'!$L$4:$L$503) | H5: =IFERROR($G5/$B5,"") | I5: =IFERROR(_xlfn.MAXIFS('Trade Log'!$L$4:$L$503,'Trade Log'!$B$4:$B$503,$A5),"") | J5: =IFERROR(_xlfn.MINIFS('Trade Log'!$L$4:$L$503,'Trade Log'!$B$4:$B$503,$A5),"")
A6: ARVSMART | B6: =COUNTIF('Trade Log'!$B$4:$B$503,$A6) | C6: =COUNTIFS('Trade Log'!$B$4:$B$503,$A6,'Trade Log'!$L$4:$L$503,">0") | D6: =COUNTIFS('Trade Log'!$B$4:$B$503,$A6,'Trade Log'!$L$4:$L$503,"<0") | E6: =IFERROR($C6/$B6,"") | F6: =SUMIF('Trade Log'!$B$4:$B$503,$A6,'Trade Log'!$I$4:$I$503) | G6: =SUMIF('Trade Log'!$B$4:$B$503,$A6,'Trade Log'!$L$4:$L$503) | H6: =IFERROR($G6/$B6,"") | I6: =IFERROR(_xlfn.MAXIFS('Trade Log'!$L$4:$L$503,'Trade Log'!$B$4:$B$503,$A6),"") | J6: =IFERROR(_xlfn.MINIFS('Trade Log'!$L$4:$L$503,'Trade Log'!$B$4:$B$503,$A6),"")
A7: ASHIANA | B7: =COUNTIF('Trade Log'!$B$4:$B$503,$A7) | C7: =COUNTIFS('Trade Log'!$B$4:$B$503,$A7,'Trade Log'!$L$4:$L$503,">0") | D7: =COUNTIFS('Trade Log'!$B$4:$B$503,$A7,'Trade Log'!$L$4:$L$503,"<0") | E7: =IFERROR($C7/$B7,"") | F7: =SUMIF('Trade Log'!$B$4:$B$503,$A7,'Trade Log'!$I$4:$I$503) | G7: =SUMIF('Trade Log'!$B$4:$B$503,$A7,'Trade Log'!$L$4:$L$503) | H7: =IFERROR($G7/$B7,"") | I7: =IFERROR(_xlfn.MAXIFS('Trade Log'!$L$4:$L$503,'Trade Log'!$B$4:$B$503,$A7),"") | J7: =IFERROR(_xlfn.MINIFS('Trade Log'!$L$4:$L$503,'Trade Log'!$B$4:$B$503,$A7),"")
A8: ASHOKA | B8: =COUNTIF('Trade Log'!$B$4:$B$503,$A8) | C8: =COUNTIFS('Trade Log'!$B$4:$B$503,$A8,'Trade Log'!$L$4:$L$503,">0") | D8: =COUNTIFS('Trade Log'!$B$4:$B$503,$A8,'Trade Log'!$L$4:$L$503,"<0") | E8: =IFERROR($C8/$B8,"") | F8: =SUMIF('Trade Log'!$B$4:$B$503,$A8,'Trade Log'!$I$4:$I$503) | G8: =SUMIF('Trade Log'!$B$4:$B$503,$A8,'Trade Log'!$L$4:$L$503) | H8: =IFERROR($G8/$B8,"") | I8: =IFERROR(_xlfn.MAXIFS('Trade Log'!$L$4:$L$503,'Trade Log'!$B$4:$B$503,$A8),"") | J8: =IFERROR(_xlfn.MINIFS('Trade Log'!$L$4:$L$503,'Trade Log'!$B$4:$B$503,$A8),"")
A9: ASTEC | B9: =COUNTIF('Trade Log'!$B$4:$B$503,$A9) | C9: =COUNTIFS('Trade Log'!$B$4:$B$503,$A9,'Trade Log'!$L$4:$L$503,">0") | D9: =COUNTIFS('Trade Log'!$B$4:$B$503,$A9,'Trade Log'!$L$4:$L$503,"<0") | E9: =IFERROR($C9/$B9,"") | F9: =SUMIF('Trade Log'!$B$4:$B$503,$A9,'Trade Log'!$I$4:$I$503) | G9: =SUMIF('Trade Log'!$B$4:$B$503,$A9,'Trade Log'!$L$4:$L$503) | H9: =IFERROR($G9/$B9,"") | I9: =IFERROR(_xlfn.MAXIFS('Trade Log'!$L$4:$L$503,'Trade Log'!$B$4:$B$503,$A9),"") | J9: =IFERROR(_xlfn.MINIFS('Trade Log'!$L$4:$L$503,'Trade Log'!$B$4:$B$503,$A9),"")
A10: AVANTEL | B10: =COUNTIF('Trade Log'!$B$4:$B$503,$A10) | C10: =COUNTIFS('Trade Log'!$B$4:$B$503,$A10,'Trade Log'!$L$4:$L$503,">0") | D10: =COUNTIFS('Trade Log'!$B$4:$B$503,$A10,'Trade Log'!$L$4:$L$503,"<0") | E10: =IFERROR($C10/$B10,"") | F10: =SUMIF('Trade Log'!$B$4:$B$503,$A10,'Trade Log'!$I$4:$I$503) | G10: =SUMIF('Trade Log'!$B$4:$B$503,$A10,'Trade Log'!$L$4:$L$503) | H10: =IFERROR($G10/$B10,"") | I10: =IFERROR(_xlfn.MAXIFS('Trade Log'!$L$4:$L$503,'Trade Log'!$B$4:$B$503,$A10),"") | J10: =IFERROR(_xlfn.MINIFS('Trade Log'!$L$4:$L$503,'Trade Log'!$B$4:$B$503,$A10),"")
A11: AWFIS | B11: =COUNTIF('Trade Log'!$B$4:$B$503,$A11) | C11: =COUNTIFS('Trade Log'!$B$4:$B$503,$A11,'Trade Log'!$L$4:$L$503,">0") | D11: =COUNTIFS('Trade Log'!$B$4:$B$503,$A11,'Trade Log'!$L$4:$L$503,"<0") | E11: =IFERROR($C11/$B11,"") | F11: =SUMIF('Trade Log'!$B$4:$B$503,$A11,'Trade Log'!$I$4:$I$503) | G11: =SUMIF('Trade Log'!$B$4:$B$503,$A11,'Trade Log'!$L$4:$L$503) | H11: =IFERROR($G11/$B11,"") | I11: =IFERROR(_xlfn.MAXIFS('Trade Log'!$L$4:$L$503,'Trade Log'!$B$4:$B$503,$A11),"") | J11: =IFERROR(_xlfn.MINIFS('Trade Log'!$L$4:$L$503,'Trade Log'!$B$4:$B$503,$A11),"")
A12: BAJAJHIND | B12: =COUNTIF('Trade Log'!$B$4:$B$503,$A12) | C12: =COUNTIFS('Trade Log'!$B$4:$B$503,$A12,'Trade Log'!$L$4:$L$503,">0") | D12: =COUNTIFS('Trade Log'!$B$4:$B$503,$A12,'Trade Log'!$L$4:$L$503,"<0") | E12: =IFERROR($C12/$B12,"") | F12: =SUMIF('Trade Log'!$B$4:$B$503,$A12,'Trade Log'!$I$4:$I$503) | G12: =SUMIF('Trade Log'!$B$4:$B$503,$A12,'Trade Log'!$L$4:$L$503) | H12: =IFERROR($G12/$B12,"") | I12: =IFERROR(_xlfn.MAXIFS('Trade Log'!$L$4:$L$503,'Trade Log'!$B$4:$B$503,$A12),"") | J12: =IFERROR(_xlfn.MINIFS('Trade Log'!$L$4:$L$503,'Trade Log'!$B$4:$B$503,$A12),"")
A13: BANARISUG | B13: =COUNTIF('Trade Log'!$B$4:$B$503,$A13) | C13: =COUNTIFS('Trade Log'!$B$4:$B$503,$A13,'Trade Log'!$L$4:$L$503,">0") | D13: =COUNTIFS('Trade Log'!$B$4:$B$503,$A13,'Trade Log'!$L$4:$L$503,"<0") | E13: =IFERROR($C13/$B13,"") | F13: =SUMIF('Trade Log'!$B$4:$B$503,$A13,'Trade Log'!$I$4:$I$503) | G13: =SUMIF('Trade Log'!$B$4:$B$503,$A13,'Trade Log'!$L$4:$L$503) | H13: =IFERROR($G13/$B13,"") | I13: =IFERROR(_xlfn.MAXIFS('Trade Log'!$L$4:$L$503,'Trade Log'!$B$4:$B$503,$A13),"") | J13: =IFERROR(_xlfn.MINIFS('Trade Log'!$L$4:$L$503,'Trade Log'!$B$4:$B$503,$A13),"")
A14: BCG | B14: =COUNTIF('Trade Log'!$B$4:$B$503,$A14) | C14: =COUNTIFS('Trade Log'!$B$4:$B$503,$A14,'Trade Log'!$L$4:$L$503,">0") | D14: =COUNTIFS('Trade Log'!$B$4:$B$503,$A14,'Trade Log'!$L$4:$L$503,"<0") | E14: =IFERROR($C14/$B14,"") | F14: =SUMIF('Trade Log'!$B$4:$B$503,$A14,'Trade Log'!$I$4:$I$503) | G14: =SUMIF('Trade Log'!$B$4:$B$503,$A14,'Trade Log'!$L$4:$L$503) | H14: =IFERROR($G14/$B14,"") | I14: =IFERROR(_xlfn.MAXIFS('Trade Log'!$L$4:$L$503,'Trade Log'!$B$4:$B$503,$A14),"") | J14: =IFERROR(_xlfn.MINIFS('Trade Log'!$L$4:$L$503,'Trade Log'!$B$4:$B$503,$A14),"")
A15: BFUTILITIE | B15: =COUNTIF('Trade Log'!$B$4:$B$503,$A15) | C15: =COUNTIFS('Trade Log'!$B$4:$B$503,$A15,'Trade Log'!$L$4:$L$503,">0") | D15: =COUNTIFS('Trade Log'!$B$4:$B$503,$A15,'Trade Log'!$L$4:$L$503,"<0") | E15: =IFERROR($C15/$B15,"") | F15: =SUMIF('Trade Log'!$B$4:$B$503,$A15,'Trade Log'!$I$4:$I$503) | G15: =SUMIF('Trade Log'!$B$4:$B$503,$A15,'Trade Log'!$L$4:$L$503) | H15: =IFERROR($G15/$B15,"") | I15: =IFERROR(_xlfn.MAXIFS('Trade Log'!$L$4:$L$503,'Trade Log'!$B$4:$B$503,$A15),"") | J15: =IFERROR(_xlfn.MINIFS('Trade Log'!$L$4:$L$503,'Trade Log'!$B$4:$B$503,$A15),"")
... A120: ZOTA | B120: =COUNTIF('Trade Log'!$B$4:$B$503,$A120) | C120: =COUNTIFS('Trade Log'!$B$4:$B$503,$A120,'Trade Log'!$L$4:$L$503,">0") | D120: =COUNTIFS('Trade Log'!$B$4:$B$503,$A120,'Trade Log'!$L$4:$L$503,"<0") | E120: =IFERROR($C120/$B120,"") | F120: =SUMIF('Trade Log'!$B$4:$B$503,$A120,'Trade Log'!$I$4:$I$503) | G120: =SUMIF('Trade Log'!$B$4:$B$503,$A120,'Trade Log'!$L$4:$L$503) | H120: =IFERROR($G120/$B120,"") | I120: =IFERROR(_xlfn.MAXIFS('Trade Log'!$L$4:$L$503,'Trade Log'!$B$4:$B$503,$A120),"") | J120: =IFERROR(_xlfn.MINIFS('Trade Log'!$L$4:$L$503,'Trade Log'!$B$4:$B$503,$A120),"")
A121: TOTAL | B121: =SUM(B4:B120) | C121: =SUM(C4:C120) | D121: =SUM(D4:D120) | E121: =IFERROR(C121/B121,"") | F121: =SUM(F4:F120) | G121: =SUM(G4:G120) | H121: =IFERROR(G121/B121,"")

Sheet Charges
A1: Charges
A2: Real per-trade charge breakdown from Dhan's trade-book, by category -- synced from Trade Log.
A3: Trade ID | B3: Symbol | C3: Position | D3: Exit Date | E3: Brokerage | F3: STT | G3: Exchange | H3: SEBI | I3: Stamp | J3: GST | K3: DP | L3: Pledge/Unpledge | M3: MTF Interest | N3: Total Charges
A4: DHAN-221260819775809 | B4: BAJAJHIND | C4: LONG | D4: 46254 | E4: 40 | F4: 299.12 | G4: 18.67 | H4: 0.61 | I4: 44.87 | J4: 10.67 | K4: 14.75 | L4: 35.4 | M4: 51.16 | N4: =SUM(E4:M4)
A5: DHAN-23126082016509 | B5: BAJAJHIND | C5: SHORT | D5: 46254 | E5: 20 | F5: 394.33 | G5: 19.55 | H5: 0.64 | I5: 9.84 | J5: 7.24 | K5: 0 | L5: 0 | M5: 0 | N5: =SUM(E5:M5)
A6: DHAN-221260819775909 | B6: GOPAL | C6: LONG | D6: 46254 | E6: 40 | F6: 373.36 | G6: 18.18 | H6: 0.59 | I6: 45.53 | J6: 10.58 | K6: 14.75 | L6: 35.4 | M6: 71.92 | N6: =SUM(E6:M6)
A7: DHAN-22126082044409 | B7: GOPAL | C7: SHORT | D7: 46254 | E7: 20 | F7: 292.45 | G7: 17.97 | H7: 0.59 | I7: 8.81 | J7: 6.94 | K7: 0 | L7: 0 | M7: 0 | N7: =SUM(E7:M7)
A8: DHAN-321260819763709 | B8: NILKAMAL | C8: LONG | D8: 46254 | E8: 40 | F8: 298.68 | G8: 18.29 | H8: 0.6 | I8: 44.8 | J8: 10.6 | K8: 14.75 | L8: 35.4 | M8: 51.07 | N8: =SUM(E8:M8)
A9: DHAN-321260820468709 | B9: NILKAMAL | C9: SHORT | D9: 46254 | E9: 20 | F9: 372.29 | G9: 18.31 | H9: 0.6 | I9: 8.99 | J9: 7 | K9: 0 | L9: 0 | M9: 0 | N9: =SUM(E9:M9)
A10: DHAN-321260819763909 | B10: ORIENTHOT | C10: LONG | D10: 46254 | E10: 40 | F10: 370.17 | G10: 17.96 | H10: 0.59 | I10: 44.75 | J10: 10.54 | K10: 14.75 | L10: 35.4 | M10: 61.22 | N10: =SUM(E10:M10)
A11: DHAN-22126082044709 | B11: ORIENTHOT | C11: SHORT | D11: 46254 | E11: 20 | F11: 287.28 | G11: 17.65 | H11: 0.57 | I11: 8.65 | J11: 6.88 | K11: 0 | L11: 0 | M11: 0 | N11: =SUM(E11:M11)
A12: DHAN-321260819764209 | B12: ZAGGLE | C12: LONG | D12: 46254 | E12: 40 | F12: 300.35 | G12: 18.64 | H12: 0.61 | I12: 45.05 | J12: 10.66 | K12: 14.75 | L12: 35.4 | M12: 60.9 | N12: =SUM(E12:M12)
A13: DHAN-22126082044909 | B13: ZAGGLE | C13: SHORT | D13: 46254 | E13: 20 | F13: 388.27 | G13: 19.19 | H13: 0.62 | I13: 9.54 | J13: 7.17 | K13: 0 | L13: 0 | M13: 0 | N13: =SUM(E13:M13)
A14: DHAN-34126082075909 | B14: BANARISUG | C14: LONG | D14: 46255 | E14: 40 | F14: 204.8 | G14: 9.91 | H14: 0.32 | I14: 24.82 | J14: 9.04 | K14: 14.75 | L14: 35.4 | M14: 28.3 | N14: =SUM(E14:M14)
A15: DHAN-23126082147609 | B15: BANARISUG | C15: SHORT | D15: 46255 | E15: 20 | F15: 157.18 | G15: 9.65 | H15: 0.31 | I15: 4.71 | J15: 5.39 | K15: 0 | L15: 0 | M15: 0 | N15: =SUM(E15:M15)
... A254: DHAN-221260930623409 | B254: DPABHUSHAN | C254: LONG | D254: 46296 | E254: 0 | F254: 186.06 | G254: 5.71 | H254: 0.19 | I254: 28.12 | J254: 1.06 | K254: 14.75 | L254: 0 | M254: 0 | N254: =SUM(E254:M254)
A255: TOTAL | E255: =SUM(E4:E254) | F255: =SUM(F4:F254) | G255: =SUM(G4:G254) | H255: =SUM(H4:H254) | I255: =SUM(I4:I254) | J255: =SUM(J4:J254) | K255: =SUM(K4:K254) | L255: =SUM(L4:L254) | ... N255: =SUM(N4:N254)

Sheet Monthly & Weekly PnL
A1: Monthly & Weekly PnL
A2: Month-wise and week-wise performance, attributed by Exit Date -- computed straight from Trade Log.
A3: MONTHLY PnL
A4: Period | B4: Trades | C4: Wins | D4: Losses | E4: Win Rate | F4: Gross P&L | G4: Net P&L | H4: Avg Net P&L / Trade | I4: Best Trade | J4: Worst Trade | K4: Profit Factor
A5: 2026-08 | B5: =COUNTIFS('Trade Log'!$G$4:$G$503,">="&DATE(2026,8,1),'Trade Log'!$G$4:$G$503,"<"&DATE(2026,9,1)) | C5: =COUNTIFS('Trade Log'!$G$4:$G$503,">="&DATE(2026,8,1),'Trade Log'!$G$4:$G$503,"<"&DATE(2026,9,1),'Trade Log'!$L$4:$L$503,">0") | D5: =COUNTIFS('Trade Log'!$G$4:$G$503,">="&DATE(2026,8,1),'Trade Log'!$G$4:$G$503,"<"&DATE(2026,9,1),'Trade Log'!$L$4:$L$503,"<0") | E5: =IFERROR($C5/$B5,"") | F5: =SUMIFS('Trade Log'!$I$4:$I$503,'Trade Log'!$G$4:$G$503,">="&DATE(2026,8,1),'Trade Log'!$G$4:$G$503,"<"&DATE(2026,9,1)) | G5: =SUMIFS('Trade Log'!$L$4:$L$503,'Trade Log'!$G$4:$G$503,">="&DATE(2026,8,1),'Trade Log'!$G$4:$G$503,"<"&DATE(2026,9,1)) | H5: =IFERROR($G5/$B5,"") | I5: =IFERROR(_xlfn.MAXIFS('Trade Log'!$L$4:$L$503,'Trade Log'!$G$4:$G$503,">="&DATE(2026,8,1),'Trade Log'!$G$4:$G$503,"<"&DATE(2026,9,1)),"") | J5: =IFERROR(_xlfn.MINIFS('Trade Log'!$L$4:$L$503,'Trade Log'!$G$4:$G$503,">="&DATE(2026,8,1),'Trade Log'!$G$4:$G$503,"<"&DATE(2026,9,1)),"") | K5: =IFERROR(SUMIFS('Trade Log'!$L$4:$L$503,'Trade Log'!$G$4:$G$503,">="&DATE(2026,8,1),'Trade Log'!$G$4:$G$503,"<"&DATE(2026,9,1),'Trade Log'!$L$4:$L$503,">0")/ABS(SUMIFS('Trade Log'!$L$4:$L$503,'Trade Log'!$G$4:$G$503,">="&DATE(2026,8,1),'Trade Log'!$G$4:$G$503,"<"&DATE(2026,9,1),'Trade Log'!$L$4:$L$503,"<0")),"")
A6: 2026-09 | B6: =COUNTIFS('Trade Log'!$G$4:$G$503,">="&DATE(2026,9,1),'Trade Log'!$G$4:$G$503,"<"&DATE(2026,10,1)) | C6: =COUNTIFS('Trade Log'!$G$4:$G$503,">="&DATE(2026,9,1),'Trade Log'!$G$4:$G$503,"<"&DATE(2026,10,1),'Trade Log'!$L$4:$L$503,">0") | D6: =COUNTIFS('Trade Log'!$G$4:$G$503,">="&DATE(2026,9,1),'Trade Log'!$G$4:$G$503,"<"&DATE(2026,10,1),'Trade Log'!$L$4:$L$503,"<0") | E6: =IFERROR($C6/$B6,"") | F6: =SUMIFS('Trade Log'!$I$4:$I$503,'Trade Log'!$G$4:$G$503,">="&DATE(2026,9,1),'Trade Log'!$G$4:$G$503,"<"&DATE(2026,10,1)) | G6: =SUMIFS('Trade Log'!$L$4:$L$503,'Trade Log'!$G$4:$G$503,">="&DATE(2026,9,1),'Trade Log'!$G$4:$G$503,"<"&DATE(2026,10,1)) | H6: =IFERROR($G6/$B6,"") | I6: =IFERROR(_xlfn.MAXIFS('Trade Log'!$L$4:$L$503,'Trade Log'!$G$4:$G$503,">="&DATE(2026,9,1),'Trade Log'!$G$4:$G$503,"<"&DATE(2026,10,1)),"") | J6: =IFERROR(_xlfn.MINIFS('Trade Log'!$L$4:$L$503,'Trade Log'!$G$4:$G$503,">="&DATE(2026,9,1),'Trade Log'!$G$4:$G$503,"<"&DATE(2026,10,1)),"") | K6: =IFERROR(SUMIFS('Trade Log'!$L$4:$L$503,'Trade Log'!$G$4:$G$503,">="&DATE(2026,9,1),'Trade Log'!$G$4:$G$503,"<"&DATE(2026,10,1),'Trade Log'!$L$4:$L$503,">0")/ABS(SUMIFS('Trade Log'!$L$4:$L$503,'Trade Log'!$G$4:$G$503,">="&DATE(2026,9,1),'Trade Log'!$G$4:$G$503,"<"&DATE(2026,10,1),'Trade Log'!$L$4:$L$503,"<0")),"")
A7: 2026-10 | B7: =COUNTIFS('Trade Log'!$G$4:$G$503,">="&DATE(2026,10,1),'Trade Log'!$G$4:$G$503,"<"&DATE(2026,11,1)) | C7: =COUNTIFS('Trade Log'!$G$4:$G$503,">="&DATE(2026,10,1),'Trade Log'!$G$4:$G$503,"<"&DATE(2026,11,1),'Trade Log'!$L$4:$L$503,">0") | D7: =COUNTIFS('Trade Log'!$G$4:$G$503,">="&DATE(2026,10,1),'Trade Log'!$G$4:$G$503,"<"&DATE(2026,11,1),'Trade Log'!$L$4:$L$503,"<0") | E7: =IFERROR($C7/$B7,"") | F7: =SUMIFS('Trade Log'!$I$4:$I$503,'Trade Log'!$G$4:$G$503,">="&DATE(2026,10,1),'Trade Log'!$G$4:$G$503,"<"&DATE(2026,11,1)) | G7: =SUMIFS('Trade Log'!$L$4:$L$503,'Trade Log'!$G$4:$G$503,">="&DATE(2026,10,1),'Trade Log'!$G$4:$G$503,"<"&DATE(2026,11,1)) | H7: =IFERROR($G7/$B7,"") | I7: =IFERROR(_xlfn.MAXIFS('Trade Log'!$L$4:$L$503,'Trade Log'!$G$4:$G$503,">="&DATE(2026,10,1),'Trade Log'!$G$4:$G$503,"<"&DATE(2026,11,1)),"") | J7: =IFERROR(_xlfn.MINIFS('Trade Log'!$L$4:$L$503,'Trade Log'!$G$4:$G$503,">="&DATE(2026,10,1),'Trade Log'!$G$4:$G$503,"<"&DATE(2026,11,1)),"") | K7: =IFERROR(SUMIFS('Trade Log'!$L$4:$L$503,'Trade Log'!$G$4:$G$503,">="&DATE(2026,10,1),'Trade Log'!$G$4:$G$503,"<"&DATE(2026,11,1),'Trade Log'!$L$4:$L$503,">0")/ABS(SUMIFS('Trade Log'!$L$4:$L$503,'Trade Log'!$G$4:$G$503,">="&DATE(2026,10,1),'Trade Log'!$G$4:$G$503,"<"&DATE(2026,11,1),'Trade Log'!$L$4:$L$503,"<0")),"")
A8: TOTAL | B8: =SUM(B5:B7) | C8: =SUM(C5:C7) | D8: =SUM(D5:D7) | E8: =IFERROR(C8/B8,"") | F8: =SUM(F5:F7) | G8: =SUM(G5:G7) | H8: =IFERROR(G8/B8,"") | K8: =IFERROR(SUMIF('Trade Log'!$L$4:$L$503,">0")/ABS(SUMIF('Trade Log'!$L$4:$L$503,"<0")),"")
A10: WEEKLY PnL
A11: Period | B11: Trades | C11: Wins | D11: Losses | E11: Win Rate | F11: Gross P&L | G11: Net P&L | H11: Avg Net P&L / Trade | I11: Best Trade | J11: Worst Trade | K11: Profit Factor
A12: 46251 | B12: =COUNTIFS('Trade Log'!$G$4:$G$503,">="&DATE(2026,8,17),'Trade Log'!$G$4:$G$503,"<"&DATE(2026,8,24)) | C12: =COUNTIFS('Trade Log'!$G$4:$G$503,">="&DATE(2026,8,17),'Trade Log'!$G$4:$G$503,"<"&DATE(2026,8,24),'Trade Log'!$L$4:$L$503,">0") | D12: =COUNTIFS('Trade Log'!$G$4:$G$503,">="&DATE(2026,8,17),'Trade Log'!$G$4:$G$503,"<"&DATE(2026,8,24),'Trade Log'!$L$4:$L$503,"<0") | E12: =IFERROR($C12/$B12,"") | F12: =SUMIFS('Trade Log'!$I$4:$I$503,'Trade Log'!$G$4:$G$503,">="&DATE(2026,8,17),'Trade Log'!$G$4:$G$503,"<"&DATE(2026,8,24)) | G12: =SUMIFS('Trade Log'!$L$4:$L$503,'Trade Log'!$G$4:$G$503,">="&DATE(2026,8,17),'Trade Log'!$G$4:$G$503,"<"&DATE(2026,8,24)) | H12: =IFERROR($G12/$B12,"") | I12: =IFERROR(_xlfn.MAXIFS('Trade Log'!$L$4:$L$503,'Trade Log'!$G$4:$G$503,">="&DATE(2026,8,17),'Trade Log'!$G$4:$G$503,"<"&DATE(2026,8,24)),"") | J12: =IFERROR(_xlfn.MINIFS('Trade Log'!$L$4:$L$503,'Trade Log'!$G$4:$G$503,">="&DATE(2026,8,17),'Trade Log'!$G$4:$G$503,"<"&DATE(2026,8,24)),"") | K12: =IFERROR(SUMIFS('Trade Log'!$L$4:$L$503,'Trade Log'!$G$4:$G$503,">="&DATE(2026,8,17),'Trade Log'!$G$4:$G$503,"<"&DATE(2026,8,24),'Trade Log'!$L$4:$L$503,">0")/ABS(SUMIFS('Trade Log'!$L$4:$L$503,'Trade Log'!$G$4:$G$503,">="&DATE(2026,8,17),'Trade Log'!$G$4:$G$503,"<"&DATE(2026,8,24),'Trade Log'!$L$4:$L$503,"<0")),"")
A13: 46258 | B13: =COUNTIFS('Trade Log'!$G$4:$G$503,">="&DATE(2026,8,24),'Trade Log'!$G$4:$G$503,"<"&DATE(2026,8,31)) | C13: =COUNTIFS('Trade Log'!$G$4:$G$503,">="&DATE(2026,8,24),'Trade Log'!$G$4:$G$503,"<"&DATE(2026,8,31),'Trade Log'!$L$4:$L$503,">0") | D13: =COUNTIFS('Trade Log'!$G$4:$G$503,">="&DATE(2026,8,24),'Trade Log'!$G$4:$G$503,"<"&DATE(2026,8,31),'Trade Log'!$L$4:$L$503,"<0") | E13: =IFERROR($C13/$B13,"") | F13: =SUMIFS('Trade Log'!$I$4:$I$503,'Trade Log'!$G$4:$G$503,">="&DATE(2026,8,24),'Trade Log'!$G$4:$G$503,"<"&DATE(2026,8,31)) | G13: =SUMIFS('Trade Log'!$L$4:$L$503,'Trade Log'!$G$4:$G$503,">="&DATE(2026,8,24),'Trade Log'!$G$4:$G$503,"<"&DATE(2026,8,31)) | H13: =IFERROR($G13/$B13,"") | I13: =IFERROR(_xlfn.MAXIFS('Trade Log'!$L$4:$L$503,'Trade Log'!$G$4:$G$503,">="&DATE(2026,8,24),'Trade Log'!$G$4:$G$503,"<"&DATE(2026,8,31)),"") | J13: =IFERROR(_xlfn.MINIFS('Trade Log'!$L$4:$L$503,'Trade Log'!$G$4:$G$503,">="&DATE(2026,8,24),'Trade Log'!$G$4:$G$503,"<"&DATE(2026,8,31)),"") | K13: =IFERROR(SUMIFS('Trade Log'!$L$4:$L$503,'Trade Log'!$G$4:$G$503,">="&DATE(2026,8,24),'Trade Log'!$G$4:$G$503,"<"&DATE(2026,8,31),'Trade Log'!$L$4:$L$503,">0")/ABS(SUMIFS('Trade Log'!$L$4:$L$503,'Trade Log'!$G$4:$G$503,">="&DATE(2026,8,24),'Trade Log'!$G$4:$G$503,"<"&DATE(2026,8,31),'Trade Log'!$L$4:$L$503,"<0")),"")
A14: 46265 | B14: =COUNTIFS('Trade Log'!$G$4:$G$503,">="&DATE(2026,8,31),'Trade Log'!$G$4:$G$503,"<"&DATE(2026,9,7)) | C14: =COUNTIFS('Trade Log'!$G$4:$G$503,">="&DATE(2026,8,31),'Trade Log'!$G$4:$G$503,"<"&DATE(2026,9,7),'Trade Log'!$L$4:$L$503,">0") | D14: =COUNTIFS('Trade Log'!$G$4:$G$503,">="&DATE(2026,8,31),'Trade Log'!$G$4:$G$503,"<"&DATE(2026,9,7),'Trade Log'!$L$4:$L$503,"<0") | E14: =IFERROR($C14/$B14,"") | F14: =SUMIFS('Trade Log'!$I$4:$I$503,'Trade Log'!$G$4:$G$503,">="&DATE(2026,8,31),'Trade Log'!$G$4:$G$503,"<"&DATE(2026,9,7)) | G14: =SUMIFS('Trade Log'!$L$4:$L$503,'Trade Log'!$G$4:$G$503,">="&DATE(2026,8,31),'Trade Log'!$G$4:$G$503,"<"&DATE(2026,9,7)) | H14: =IFERROR($G14/$B14,"") | I14: =IFERROR(_xlfn.MAXIFS('Trade Log'!$L$4:$L$503,'Trade Log'!$G$4:$G$503,">="&DATE(2026,8,31),'Trade Log'!$G$4:$G$503,"<"&DATE(2026,9,7)),"") | J14: =IFERROR(_xlfn.MINIFS('Trade Log'!$L$4:$L$503,'Trade Log'!$G$4:$G$503,">="&DATE(2026,8,31),'Trade Log'!$G$4:$G$503,"<"&DATE(2026,9,7)),"") | K14: =IFERROR(SUMIFS('Trade Log'!$L$4:$L$503,'Trade Log'!$G$4:$G$503,">="&DATE(2026,8,31),'Trade Log'!$G$4:$G$503,"<"&DATE(2026,9,7),'Trade Log'!$L$4:$L$503,">0")/ABS(SUMIFS('Trade Log'!$L$4:$L$503,'Trade Log'!$G$4:$G$503,">="&DATE(2026,8,31),'Trade Log'!$G$4:$G$503,"<"&DATE(2026,9,7),'Trade Log'!$L$4:$L$503,"<0")),"")
A15: 46272 | B15: =COUNTIFS('Trade Log'!$G$4:$G$503,">="&DATE(2026,9,7),'Trade Log'!$G$4:$G$503,"<"&DATE(2026,9,14)) | C15: =COUNTIFS('Trade Log'!$G$4:$G$503,">="&DATE(2026,9,7),'Trade Log'!$G$4:$G$503,"<"&DATE(2026,9,14),'Trade Log'!$L$4:$L$503,">0") | D15: =COUNTIFS('Trade Log'!$G$4:$G$503,">="&DATE(2026,9,7),'Trade Log'!$G$4:$G$503,"<"&DATE(2026,9,14),'Trade Log'!$L$4:$L$503,"<0") | E15: =IFERROR($C15/$B15,"") | F15: =SUMIFS('Trade Log'!$I$4:$I$503,'Trade Log'!$G$4:$G$503,">="&DATE(2026,9,7),'Trade Log'!$G$4:$G$503,"<"&DATE(2026,9,14)) | G15: =SUMIFS('Trade Log'!$L$4:$L$503,'Trade Log'!$G$4:$G$503,">="&DATE(2026,9,7),'Trade Log'!$G$4:$G$503,"<"&DATE(2026,9,14)) | H15: =IFERROR($G15/$B15,"") | I15: =IFERROR(_xlfn.MAXIFS('Trade Log'!$L$4:$L$503,'Trade Log'!$G$4:$G$503,">="&DATE(2026,9,7),'Trade Log'!$G$4:$G$503,"<"&DATE(2026,9,14)),"") | J15: =IFERROR(_xlfn.MINIFS('Trade Log'!$L$4:$L$503,'Trade Log'!$G$4:$G$503,">="&DATE(2026,9,7),'Trade Log'!$G$4:$G$503,"<"&DATE(2026,9,14)),"") | K15: =IFERROR(SUMIFS('Trade Log'!$L$4:$L$503,'Trade Log'!$G$4:$G$503,">="&DATE(2026,9,7),'Trade Log'!$G$4:$G$503,"<"&DATE(2026,9,14),'Trade Log'!$L$4:$L$503,">0")/ABS(SUMIFS('Trade Log'!$L$4:$L$503,'Trade Log'!$G$4:$G$503,">="&DATE(2026,9,7),'Trade Log'!$G$4:$G$503,"<"&DATE(2026,9,14),'Trade Log'!$L$4:$L$503,"<0")),"")
A16: 46279 | B16: =COUNTIFS('Trade Log'!$G$4:$G$503,">="&DATE(2026,9,14),'Trade Log'!$G$4:$G$503,"<"&DATE(2026,9,21)) | C16: =COUNTIFS('Trade Log'!$G$4:$G$503,">="&DATE(2026,9,14),'Trade Log'!$G$4:$G$503,"<"&DATE(2026,9,21),'Trade Log'!$L$4:$L$503,">0") | D16: =COUNTIFS('Trade Log'!$G$4:$G$503,">="&DATE(2026,9,14),'Trade Log'!$G$4:$G$503,"<"&DATE(2026,9,21),'Trade Log'!$L$4:$L$503,"<0") | E16: =IFERROR($C16/$B16,"") | F16: =SUMIFS('Trade Log'!$I$4:$I$503,'Trade Log'!$G$4:$G$503,">="&DATE(2026,9,14),'Trade Log'!$G$4:$G$503,"<"&DATE(2026,9,21)) | G16: =SUMIFS('Trade Log'!$L$4:$L$503,'Trade Log'!$G$4:$G$503,">="&DATE(2026,9,14),'Trade Log'!$G$4:$G$503,"<"&DATE(2026,9,21)) | H16: =IFERROR($G16/$B16,"") | I16: =IFERROR(_xlfn.MAXIFS('Trade Log'!$L$4:$L$503,'Trade Log'!$G$4:$G$503,">="&DATE(2026,9,14),'Trade Log'!$G$4:$G$503,"<"&DATE(2026,9,21)),"") | J16: =IFERROR(_xlfn.MINIFS('Trade Log'!$L$4:$L$503,'Trade Log'!$G$4:$G$503,">="&DATE(2026,9,14),'Trade Log'!$G$4:$G$503,"<"&DATE(2026,9,21)),"") | K16: =IFERROR(SUMIFS('Trade Log'!$L$4:$L$503,'Trade Log'!$G$4:$G$503,">="&DATE(2026,9,14),'Trade Log'!$G$4:$G$503,"<"&DATE(2026,9,21),'Trade Log'!$L$4:$L$503,">0")/ABS(SUMIFS('Trade Log'!$L$4:$L$503,'Trade Log'!$G$4:$G$503,">="&DATE(2026,9,14),'Trade Log'!$G$4:$G$503,"<"&DATE(2026,9,21),'Trade Log'!$L$4:$L$503,"<0")),"")
A17: 46286 | B17: =COUNTIFS('Trade Log'!$G$4:$G$503,">="&DATE(2026,9,21),'Trade Log'!$G$4:$G$503,"<"&DATE(2026,9,28)) | C17: =COUNTIFS('Trade Log'!$G$4:$G$503,">="&DATE(2026,9,21),'Trade Log'!$G$4:$G$503,"<"&DATE(2026,9,28),'Trade Log'!$L$4:$L$503,">0") | D17: =COUNTIFS('Trade Log'!$G$4:$G$503,">="&DATE(2026,9,21),'Trade Log'!$G$4:$G$503,"<"&DATE(2026,9,28),'Trade Log'!$L$4:$L$503,"<0") | E17: =IFERROR($C17/$B17,"") | F17: =SUMIFS('Trade Log'!$I$4:$I$503,'Trade Log'!$G$4:$G$503,">="&DATE(2026,9,21),'Trade Log'!$G$4:$G$503,"<"&DATE(2026,9,28)) | G17: =SUMIFS('Trade Log'!$L$4:$L$503,'Trade Log'!$G$4:$G$503,">="&DATE(2026,9,21),'Trade Log'!$G$4:$G$503,"<"&DATE(2026,9,28)) | H17: =IFERROR($G17/$B17,"") | I17: =IFERROR(_xlfn.MAXIFS('Trade Log'!$L$4:$L$503,'Trade Log'!$G$4:$G$503,">="&DATE(2026,9,21),'Trade Log'!$G$4:$G$503,"<"&DATE(2026,9,28)),"") | J17: =IFERROR(_xlfn.MINIFS('Trade Log'!$L$4:$L$503,'Trade Log'!$G$4:$G$503,">="&DATE(2026,9,21),'Trade Log'!$G$4:$G$503,"<"&DATE(2026,9,28)),"") | K17: =IFERROR(SUMIFS('Trade Log'!$L$4:$L$503,'Trade Log'!$G$4:$G$503,">="&DATE(2026,9,21),'Trade Log'!$G$4:$G$503,"<"&DATE(2026,9,28),'Trade Log'!$L$4:$L$503,">0")/ABS(SUMIFS('Trade Log'!$L$4:$L$503,'Trade Log'!$G$4:$G$503,">="&DATE(2026,9,21),'Trade Log'!$G$4:$G$503,"<"&DATE(2026,9,28),'Trade Log'!$L$4:$L$503,"<0")),"")
A18: 46293 | B18: =COUNTIFS('Trade Log'!$G$4:$G$503,">="&DATE(2026,9,28),'Trade Log'!$G$4:$G$503,"<"&DATE(2026,10,5)) | C18: =COUNTIFS('Trade Log'!$G$4:$G$503,">="&DATE(2026,9,28),'Trade Log'!$G$4:$G$503,"<"&DATE(2026,10,5),'Trade Log'!$L$4:$L$503,">0") | D18: =COUNTIFS('Trade Log'!$G$4:$G$503,">="&DATE(2026,9,28),'Trade Log'!$G$4:$G$503,"<"&DATE(2026,10,5),'Trade Log'!$L$4:$L$503,"<0") | E18: =IFERROR($C18/$B18,"") | F18: =SUMIFS('Trade Log'!$I$4:$I$503,'Trade Log'!$G$4:$G$503,">="&DATE(2026,9,28),'Trade Log'!$G$4:$G$503,"<"&DATE(2026,10,5)) | G18: =SUMIFS('Trade Log'!$L$4:$L$503,'Trade Log'!$G$4:$G$503,">="&DATE(2026,9,28),'Trade Log'!$G$4:$G$503,"<"&DATE(2026,10,5)) | H18: =IFERROR($G18/$B18,"") | I18: =IFERROR(_xlfn.MAXIFS('Trade Log'!$L$4:$L$503,'Trade Log'!$G$4:$G$503,">="&DATE(2026,9,28),'Trade Log'!$G$4:$G$503,"<"&DATE(2026,10,5)),"") | J18: =IFERROR(_xlfn.MINIFS('Trade Log'!$L$4:$L$503,'Trade Log'!$G$4:$G$503,">="&DATE(2026,9,28),'Trade Log'!$G$4:$G$503,"<"&DATE(2026,10,5)),"") | K18: =IFERROR(SUMIFS('Trade Log'!$L$4:$L$503,'Trade Log'!$G$4:$G$503,">="&DATE(2026,9,28),'Trade Log'!$G$4:$G$503,"<"&DATE(2026,10,5),'Trade Log'!$L$4:$L$503,">0")/ABS(SUMIFS('Trade Log'!$L$4:$L$503,'Trade Log'!$G$4:$G$503,">="&DATE(2026,9,28),'Trade Log'!$G$4:$G$503,"<"&DATE(2026,10,5),'Trade Log'!$L$4:$L$503,"<0")),"")
A19: TOTAL | B19: =SUM(B12:B18) | C19: =SUM(C12:C18) | D19: =SUM(D12:D18) | E19: =IFERROR(C19/B19,"") | F19: =SUM(F12:F18) | G19: =SUM(G12:G18) | H19: =IFERROR(G19/B19,"") | K19: =IFERROR(SUMIF('Trade Log'!$L$4:$L$503,">0")/ABS(SUMIF('Trade Log'!$L$4:$L$503,"<0")),"")
